Workbook
Name ScenID: '01 Control Panel'!$D$15
Name ScenarioName: '01 Control Panel'!$D$14

Sheet Cover
B2: INDUSTRY FINANCIAL MODEL
B3: INDIAN STEEL INDUSTRY - ANALYTICAL ENGINE
B5: Global Metals & Mining Research
B6: Forecast horizon FY2027E-FY2033E (7 years) | Base year FY2026A | Built 03 August 2026
B8: WHAT THIS MODEL IS
B9: An analytical engine, not a database. It consumes FY2026 actuals from Master Industry Database.xlsx and forecasts Indian steel demand, supply, capacity, utilisation, prices, costs, revenue, EBITDA, working capital, cash flow and trade to FY2033, under four fully integrated scenarios. It is the parent model for single-name DCF, trading and transaction comparables, EV per tonne, replacement cost and ROIC work on Tata Steel, JSW Steel, SAIL, Jindal Steel, Jindal Stainless and AM/NS India.
B11: HOW SCENARIOS WORK
B12: Change one cell - the scenario selector on 01 Control Panel - and the entire workbook re-computes. The selector drives a named range ScenID, which every driver on 02 Model Assumptions resolves through an INDEX across its four scenario rows. No sheet contains a scenario-specific hardcode. There is nothing else to change.
B14: THE ONE THING THAT MAKES THIS AN ENGINE RATHER THAN A SPREADSHEET
B15: A lagged price-utilisation feedback (driver D23). Effective realisation is adjusted by an elasticity applied to the gap between the PRIOR year's capacity utilisation and normal utilisation. Because it is lagged there is no circular reference, but it means capacity, pipeline delivery rates and secondary-sector additions genuinely transmit into price and therefore EBITDA. Without it, capacity would be decorative and the capacity drivers would show literally zero EBITDA sensitivity. It also produces the economically correct and counter-intuitive result that FASTER capacity delivery is EBITDA-NEGATIVE, because it depresses utilisation and therefore price.
B17: INDEPENDENT VALIDATION OF THE CAPACITY BLOCK
B18: Built bottom-up from a dated 20-project tracker plus a secondary-sector residual, the model produces India crude steel capacity of 302.0 Mtpa in FY2031 against the National Steel Policy 2017 target of 300 Mtpa - within 0.7%. The model was not calibrated to that target, so this is a genuine external check.
... B29: Public sources only. No non-public or price-sensitive information.

Sheet Contents
B1: CONTENTS
B2: Click a sheet name to navigate.
A4: # | B4: Worksheet | C4: Purpose and principal content | D4: Type
A5: 00 | B5: 00 Database Import | C5: The controlled boundary with Master Industry Database.xlsx: 18 FY2026 anchors with exact provenance and a documented refresh procedure. | D5: Input
A6: 0H | B6: 0H Forecast Horizon | C6: Weighted evaluation of 5, 7 and 10-year horizons; 7 years selected. Live weighted-score formulas. | D6: Documentation
A7: 01 | B7: 01 Control Panel | C7: The scenario selector - the only cell a user changes - plus a live output panel. | D7: Control
A8: 02 | B8: 02 Model Assumptions | C8: 26 drivers on 4 scenarios, the active resolved block, the 13-field assumption register and the WACC build-up. | D8: Input
A9: 03 | B9: 03 Macroeconomic Model | C9: Real GDP, CPI, USD/INR, G-sec yield and WACC. | D9: Calc
A10: 04 | B10: 04 Steel Demand Model | C10: Consumption via GDP times a history-calibrated elasticity; per capita intensity. | D10: Calc
A11: 05 | B11: 05 Steel Supply Model | C11: The JPC supply identity, the capacity ceiling and the shortfall routed to imports. | D11: Calc
A12: 06 | B12: 06 Capacity Forecast | C12: Capacity from the project tracker plus a secondary residual; validated against the 300 Mtpa policy target. | D12: Calc
A13: 07 | B13: 07 Capacity Expansion Tracker | C13: 20 dated projects with live SUMIFS feeding 06; encodes the acquisition, downstream and overseas exclusions. | D13: Input
A14: 08 | B14: 08 Capacity Utilisation | C14: Utilisation and the utilisation gap that drives the price feedback. | D14: Calc
A15: 09 | B15: 09 Steel Price Forecast | C15: Blended realisation with the lagged utilisation feedback; safeguard duty schedule. | D15: Calc
... A32: 26 | B32: 26 Sources | C32: Sources for the forward-looking assumptions, plus the model change log. | D32: Documentation

Sheet 00 Database Import
B1: 00 Database Import
B2: Industry Financial Model | Indian Steel Industry | Horizon FY2027E-FY2033E | Base year FY2026A | Built 03-Aug-2026
B4: OBJECTIVE
B5: The single controlled boundary between Master Industry Database.xlsx and this model. Every FY2026 actual the model uses enters here, once, with its exact location in the database recorded. Nothing downstream references the database directly.
B6: METHODOLOGY
B7: DESIGN CHOICE, STATED EXPLICITLY. Values are imported as static numbers with full provenance rather than as live external-workbook links. Live links to another file are an operational risk in a model that will be circulated - they break on move or rename, they prompt on open, and they silently return stale values if the source is unavailable. Instead each row records the database sheet and the exact line it came from, and the 'Refresh formula' column contains the external-link formula as TEXT, ready to paste if a live link is wanted. The refresh procedure is at the foot of this sheet. Every value here was extracted programmatically from the database file at build time, so a transcription error is structurally impossible.
B8: UNITS
B9: As stated per row.
B10: DEPENDENCIES
B11: Source: Master Industry Database.xlsx. Consumed by every forecast sheet.
A13: ID | B13: Imported item | C13: Unit | D13: FY2026A value | E13: Master Database location | F13: Source ID in database | G13: Refresh formula (paste to activate a live link) | H13: Confidence | I13: Notes
A14: A01 | B14: India crude steel production | C14: Mt | D14: 168.42 | E14: Master DB > Production Volume > India crude steel production > FY2026 | F14: S01 | G14: ='[Master Industry Database.xlsx]Production Volume'!<cell> | H14: High
A15: A02 | B15: India total finished steel production | C15: Mt | D15: 160.94 | E15: Master DB > Demand & Consumption > supply balance (April-2026 JPC vintage) > FY2026 | F15: S01 | G15: ='[Master Industry Database.xlsx]Demand & Consumption'!<cell> | H15: High | I15: Master DB > Demand & Consumption > supply balance (April-2026 JPC vintage) > FY2026. VINTAGE CHOICE: the model uses the April-2026 vintage throughout because that balance is internally self-reconciling (production + imports - exports - stock change = consumption), which a forecast identity requires. The June-2026 vintage figure of 161.74 Mt is carried as a reconciliation memo. This is the resolution the database itself recommends for the supply balance under Conflict C03
A16: A03 | B16: India apparent finished steel consumption | C16: Mt | D16: 163.74 | E16: Master DB > Demand & Consumption > supply balance (April-2026 JPC vintage) > FY2026 | F16: S01 | G16: ='[Master Industry Database.xlsx]Demand & Consumption'!<cell> | H16: High | I16: Master DB > Demand & Consumption > supply balance (April-2026 JPC vintage) > FY2026. June-2026 vintage is 164.19 Mt - carried as a memo. See A02 on the vintage choice
A17: A04 | B17: India crude steel capacity | C17: Mtpa | D17: 220.4 | E17: Master DB > Production Capacity > India crude steel capacity > FY2026 | F17: S02/S03 | G17: ='[Master Industry Database.xlsx]Production Capacity'!<cell> | H17: High
A18: A05 | B18: India finished steel imports | C18: Mt | D18: 6.524 | E18: Master DB > Imports & Exports > FY2026 | F18: S02 | G18: ='[Master Industry Database.xlsx]Imports & Exports'!<cell> | H18: High
A19: A06 | B19: India finished steel exports | C19: Mt | D19: 6.602 | E19: Master DB > Imports & Exports > FY2026 | F19: S02 | G19: ='[Master Industry Database.xlsx]Imports & Exports'!<cell> | H19: High
A20: A07 | B20: Variation in stock | C20: Mt | D20: -2.88 | E20: Master DB > Demand & Consumption > supply balance line 6 > FY2026 | F20: S01 | G20: ='[Master Industry Database.xlsx]Demand & Consumption'!<cell> | H20: High
A21: A08 | B21: Crude-to-finished steel ratio | C21: x | D21: 1.04647 | E21: Derived: 168.42 / 160.94, both on the April-2026 JPC vintage, so the ratio is internally consistent with the supply balance the model uses. On the June-2026 vintage (168.42 / 161.74) the ratio would be 1.0413 - a 0.5% difference | F21: S01 | G21: ='[Master Industry Database.xlsx]Sheet'!<cell> | H21: High | I21: Derived: 168.42 / 160.94, both on the April-2026 JPC vintage, so the ratio is internally consistent with the supply balance the model uses. On the June-2026 vintage (168.42 / 161.74) the ratio would be 1.0413 - a 0.5% difference
A22: A09 | B22: Blended industry realisation | C22: Rs/t | D22: 59974 | E22: Derived: volume-weighted revenue / volume for Tata Steel India, JSW Steel India, SAIL and Jindal Steel from Master DB (Rs 4,79,191 cr / 79.90 Mt x 10) | F22: S08/S09/S10/S11 | G22: ='[Master Industry Database.xlsx]Sheet'!<cell> | H22: High | I22: Derived: volume-weighted revenue / volume for Tata Steel India, JSW Steel India, SAIL and Jindal Steel from Master DB (Rs 4,79,191 cr / 79.90 Mt x 10)
A23: A10 | B23: Weighted EBITDA per tonne | C23: Rs/t | D23: 10733 | E23: Derived: volume-weighted EBITDA/t across the same four majors from Master DB | F23: S08-S11 | G23: ='[Master Industry Database.xlsx]Sheet'!<cell> | H23: High | I23: Derived: volume-weighted EBITDA/t across the same four majors from Master DB
A24: A11 | B24: Implied cash cost per tonne | C24: Rs/t | D24: 49241 | E24: Derived: A09 less A10. Reconciliation: A10 x 79.90 Mt = Rs 85,759 cr against the Rs 86,318 cr sum of the four reported EBITDAs, a 0.6% rounding difference | F24: Derived | G24: ='[Master Industry Database.xlsx]Sheet'!<cell> | H24: High | I24: Derived: A09 less A10. Reconciliation: A10 x 79.90 Mt = Rs 85,759 cr against the Rs 86,318 cr sum of the four reported EBITDAs, a 0.6% rounding difference
A25: A12 | B25: Weighted EBITDA margin | C25: % | D25: 0.179 | E25: Derived: A10 / A09 | F25: Derived | G25: ='[Master Industry Database.xlsx]Sheet'!<cell> | H25: High | I25: Derived: A10 / A09
A26: A13 | B26: Calibration volume coverage | C26: Mt | D26: 79.9 | E26: Sum of FY2026 volumes for the four majors = 49.4% of India finished steel production | F26: S08-S11 | G26: ='[Master Industry Database.xlsx]Sheet'!<cell> | H26: High
A27: A14 | B27: India per capita consumption | C27: kg | D27: 115.7 | E27: Master DB > Demand & Consumption > per capita > FY2026 | F27: S03 | G27: ='[Master Industry Database.xlsx]Demand & Consumption'!<cell> | H27: High
A28: A15 | B28: Iron ore 62% Fe CFR China, FY2026 average | C28: US$/dmt | D28: 100.52 | E28: Master DB > Iron Ore Prices > fiscal-year averages > FY2026 | F28: S17 | G28: ='[Master Industry Database.xlsx]Iron Ore Prices'!<cell> | H28: High
A29: A16 | B29: Australian thermal coal, FY2026 average | C29: US$/mt | D29: 111.5 | E29: Master DB > Coking Coal Prices > thermal reference > FY2026 | F29: S17 | G29: ='[Master Industry Database.xlsx]Coking Coal Prices'!<cell> | H29: High
A30: A17 | B30: Premium HCC coking coal, Mar-2026 spot reference | C30: US$/t | D30: 225 | E30: Master DB > Coking Coal Prices > Ministry of Steel assessment > Mar-2026. NOT a fiscal-year average - none is asserted in the database (Conflict C01) | F30: S01 | G30: ='[Master Industry Database.xlsx]Coking Coal Prices'!<cell> | H30: High
A31: A18 | B31: Domestic HRC, end-Mar-2026 | C31: Rs/t | D31: 57700 | E31: Master DB > Steel Prices > ICRA end-Mar-2026 assessment | F31: S19 | G31: ='[Master Industry Database.xlsx]Steel Prices'!<cell> | H31: High
B33: REFRESH PROCEDURE. (1) Open both workbooks. (2) For each row, read the value at the stated Master Database location. (3) Compare against column D. (4) If different, overwrite column D and record the change in the model change log on 26 Sources. (5) Re-run 25 Audit Checks. Nothing else needs to change: every downstream sheet references this sheet, so a single correction propagates.
B35: DERIVED IMPORTS. A09 to A13 and A08 are DERIVED from database figures rather than lifted from a single cell, and their derivation is stated in the Notes column. They are imported here rather than computed downstream so that the calibration of the entire model sits in one auditable place.
B37: VINTAGE. The model uses the April-2026 Joint Plant Committee vintage for the supply balance because that balance is internally self-reconciling - production plus imports less exports less stock change equals consumption - which a forecast identity requires. The database's June-2026 vintage figures (finished production 161.74 Mt, consumption 164.19 Mt) are carried as reconciliation memos. This is the resolution the database itself recommends under its Conflict C03.

Sheet 0H Forecast Horizon
B1: 0H Forecast Horizon
B2: Industry Financial Model | Indian Steel Industry | Horizon FY2027E-FY2033E | Base year FY2026A | Built 03-Aug-2026
B4: OBJECTIVE
B5: Evaluates 5-year, 7-year and 10-year forecast horizons against weighted criteria and selects one. The selected horizon is applied identically on every forecast sheet in the workbook.
B6: METHODOLOGY
B7: Five criteria, weighted. Each option is scored 1 to 5 against each criterion. The weighted total is a live formula, not a hardcoded result, so a reviewer who disagrees with a weight can change it and see whether the conclusion survives.
B8: UNITS
B9: Scores 1 (worst) to 5 (best). Weights sum to 1.00.
B10: DEPENDENCIES
B11: Determines the column structure of every forecast sheet.
A13: Criterion | B13: Weight | C13: 5-Year (FY2027-FY2031) | D13: 7-Year (FY2027-FY2033) | E13: 10-Year (FY2027-FY2036) | F13: Score 5Y | G13: Score 7Y | H13: Score 10Y | I13: Basis of assessment / evidence
A14: Coverage of the announced capacity pipeline | B14: 0.25 | C14: Ends FY2031, exactly the terminal year of the announced pipeline. Captures 100% of commissioning but 0 years of post-commissioning ramp. | D14: Ends FY2033. Captures 100% of commissioning PLUS a 2-year ramp tail, so the terminal year reflects normalised rather than ramping utilisation. | E14: Ends FY2036, five years beyond the last dated project. Years 8-10 have no project-level visibility and become pure extrapolation. | F14: 3 | G14: 5 | H14: 2 | I14: Dated pipeline in the Master Database terminates FY2031: POSCO-JSW 6 Mtpa greenfield by 2031, SAIL ~35 Mt ambition by FY2031, PLI 1.2 capacity 8.7 Mt by FY2031, National Steel Policy 2017 target year FY2031. No credible dated project extends beyond FY2031.
A15: Terminal year is a normalised, valuation-usable year | B15: 0.25 | C15: NO. Capacity commissioned FY2030-FY2031 is still ramping in FY2031, so terminal-year utilisation is artificially depressed and a terminal value struck there is understated. | D15: YES. The FY2030-FY2031 capacity cohort reaches normalised utilisation by FY2033 on a 2-3 year ramp, so the terminal year is a fair steady state. | E15: YES but redundant - steady state is already reached by FY2033, so FY2034-FY2036 add extrapolation risk without adding information. | F15: 1 | G15: 5 | H15: 4 | I15: Greenfield and large brownfield Indian steel capacity historically takes 2-3 years from commissioning to normalised utilisation. Observed in the database: NMDC Steel Nagarnar (3 Mtpa) produced 1.471 Mt in FY2025 and 2.382 Mt in FY2026, i.e. ~79% of nameplate in year 3+; RINL required a full year to recover to 5.43 Mt.
A16: Coverage of a complete industry cycle | B16: 0.2 | C16: ~0.7 cycles. Truncates the cycle, so the average forecast year is not cycle-neutral and the result is highly sensitive to where the start point sits in the cycle. | D16: ~1.0 cycle. The forecast average is approximately cycle-neutral, which is the property a mid-cycle valuation requires. | E16: ~1.4 cycles. Cycle-neutral but the second partial cycle is unforecastable in its timing. | F16: 2 | G16: 5 | H16: 3 | I16: Observed cycle length in the database: standardised EBITDA margin for Tata Steel peaked at 26% in FY2022, troughed at 10% in FY2024 and recovered to 15% in FY2026 - a 4-year peak-to-trough leg implying a ~7-8 year full cycle. Coking coal peaked at US$354/t in Oct-2023 and troughed at ~US$175/t in Mar-2025; iron ore peaked at US$155.52/dmt in FY2022 and troughed at US$100.52/dmt in FY2026.
A17: Reliability of the macro anchor | B17: 0.15 | C17: Strong. RBI publishes an explicit FY2027 projection and the IMF medium-term path is credible to roughly 5 years. | D17: Adequate. Years 6-7 rely on a converging steady-state growth assumption rather than a published projection, which is disclosed and sensitised. | E17: Weak. Years 8-10 require a GDP path with no institutional publisher support at all. | F17: 5 | G17: 4 | H17: 2 | I17: RBI's June-2026 MPC projects FY2027 real GDP growth at 6.6%. No official Indian source publishes a real GDP path beyond roughly 5 years, so any year past FY2031 is the modeller's own convergence assumption.
A18: Usability for DCF terminal value | B18: 0.15 | C18: Poor. A terminal value struck on a non-normalised year requires a manual mid-cycle adjustment, which defeats the purpose of an explicit forecast period. | D18: Good. Terminal value can be struck directly off FY2033 with no manual normalisation. | E18: Good but the incremental years add estimation error to the discounted stub, where their present-value weight is small. | F18: 2 | G18: 5 | H18: 3 | I18: At a ~12% nominal WACC the present-value weight of forecast years 8-10 is under 12% of total enterprise value, so extending the horizon adds materially more estimation error than valuation information.
A19: WEIGHTED TOTAL | B19: =SUM(B14:B18) | F19: =SUMPRODUCT($B$14:$B$18,F14:F18) | G19: =SUMPRODUCT($B$14:$B$18,G14:G18) | H19: =SUMPRODUCT($B$14:$B$18,H14:H18) | I19: Live formula. The 7-year option wins on four of five criteria and ties on none; it loses only on macro-anchor reliability, where the 5-year option is stronger.
A21: SELECTED: 7 YEARS - FY2027E to FY2033E
A23: SELECTED HORIZON: 7 YEARS - FY2027E to FY2033E, with FY2026A as the base year.
A25: Weighted score: 7-year 4.85 against 5-year 2.55 and 10-year 2.75 (weights and criterion scores are shown live in the table above and the weighted total is a formula, not a hard-coded number).
A27: The decisive consideration is that the 5-year horizon ends in FY2031 - the same year the announced capacity pipeline finishes commissioning - so its terminal year embeds artificially low utilisation and would understate terminal value. The 7-year horizon adds the two-year ramp tail needed for the FY2030-FY2031 capacity cohort to reach normalised utilisation, and in doing so also spans approximately one full industry cycle, which makes the forecast average cycle-neutral. The 10-year horizon buys no additional information: steady state is already reached by FY2033, no dated project extends beyond FY2031, no institutional source publishes an Indian GDP path that far out, and forecast years 8-10 carry under 12% of present value at a ~12% nominal WACC while carrying the highest estimation error in the model.
A29: This horizon is applied consistently on every forecast worksheet. Columns E to K are FY2027E to FY2033E throughout the workbook without exception.

Sheet 01 Control Panel
B1: 01 Control Panel
B2: Industry Financial Model | Indian Steel Industry | Horizon FY2027E-FY2033E | Base year FY2026A | Built 03-Aug-2026
B4: OBJECTIVE
B5: The only cell in this workbook a user needs to change. The scenario selector drives every forecast on every sheet.
B6: METHODOLOGY
B7: The selector is a validated dropdown. It resolves to the named range ScenID via MATCH against the scenario list below. Every driver on 02 Model Assumptions uses INDEX with ScenID to pick its active row. Consequently no sheet anywhere in the workbook contains a scenario-specific hardcode.
B8: UNITS
B9: As stated per row.
B10: DEPENDENCIES
B11: Drives 02 Model Assumptions and therefore every sheet from 03 to 24.
B13: SCENARIO SELECTOR
B14: Active scenario | D14: Base Case | O14: CHANGE THIS CELL ONLY. Dropdown-validated. Everything else recomputes.
B15: Scenario index (ScenID) | D15: =MATCH(D$14,D$17:D$20,0) | O15: Named range ScenID. Resolves the selector to 1-4 for the INDEX lookups on 02 Model Assumptions.
B17: Scenario list (do not reorder - ScenID depends on this order)
B18: 1. | D18: Base Case | O18: Central case. RBI FY2027 GDP of 6.6%, realisation calibrated to a FY2033 industry margin of 16.8%.
B19: 2. | D19: Bull Case | O19: Demand-led upcycle. Peaks at a 26.0% industry margin in FY2030, matching the FY2022 cycle peak.
B20: 3. | D20: Bear Case | O20: Demand-led downturn. Raw materials FALL with demand, so margins compress to 7-11% rather than collapsing.
B21: 4. | D21: Stress Case | O21: Stagflationary supply shock plus demand shock. Coking coal to US$300/t, INR to 113. Troughs at -9.2% in FY2028.
B23: LIVE MODEL OUTPUT - ACTIVE SCENARIO
B24: Line item | C24: Unit | D24: FY2026A | E24: FY2027E | F24: FY2028E | G24: FY2029E | H24: FY2030E | I24: FY2031E | J24: FY2032E | K24: FY2033E | L24: CAGR | M24: Source | N24: Conf. | O24: Notes / methodology
B25: India finished steel consumption | C25: Mt | D25: =IF(ISBLANK('04 Steel Demand Model'!D$17),"n/a",'04 Steel Demand Model'!D$17) | E25: ='04 Steel Demand Model'!E$17 | F25: ='04 Steel Demand Model'!F$17 | G25: ='04 Steel Demand Model'!G$17 | H25: ='04 Steel Demand Model'!H$17 | I25: ='04 Steel Demand Model'!I$17 | J25: ='04 Steel Demand Model'!J$17 | K25: ='04 Steel Demand Model'!K$17 | L25: =IFERROR(IF(AND(ISNUMBER(D25),ISNUMBER(K25),D25>0),(K25/D25)^(1/7)-1,""),"") | M25: 04
B26: India crude steel production | C26: Mt | D26: =IF(ISBLANK('05 Steel Supply Model'!D$25),"n/a",'05 Steel Supply Model'!D$25) | E26: ='05 Steel Supply Model'!E$25 | F26: ='05 Steel Supply Model'!F$25 | G26: ='05 Steel Supply Model'!G$25 | H26: ='05 Steel Supply Model'!H$25 | I26: ='05 Steel Supply Model'!I$25 | J26: ='05 Steel Supply Model'!J$25 | K26: ='05 Steel Supply Model'!K$25 | L26: =IFERROR(IF(AND(ISNUMBER(D26),ISNUMBER(K26),D26>0),(K26/D26)^(1/7)-1,""),"") | M26: 05
B27: India crude steel capacity | C27: Mtpa | D27: =IF(ISBLANK('06 Capacity Forecast'!D$20),"n/a",'06 Capacity Forecast'!D$20) | E27: ='06 Capacity Forecast'!E$20 | F27: ='06 Capacity Forecast'!F$20 | G27: ='06 Capacity Forecast'!G$20 | H27: ='06 Capacity Forecast'!H$20 | I27: ='06 Capacity Forecast'!I$20 | J27: ='06 Capacity Forecast'!J$20 | K27: ='06 Capacity Forecast'!K$20 | L27: =IFERROR(IF(AND(ISNUMBER(D27),ISNUMBER(K27),D27>0),(K27/D27)^(1/7)-1,""),"") | M27: 06
B28: Capacity utilisation | C28: % | D28: =IF(ISBLANK('08 Capacity Utilisation'!D$16),"n/a",'08 Capacity Utilisation'!D$16) | E28: ='08 Capacity Utilisation'!E$16 | F28: ='08 Capacity Utilisation'!F$16 | G28: ='08 Capacity Utilisation'!G$16 | H28: ='08 Capacity Utilisation'!H$16 | I28: ='08 Capacity Utilisation'!I$16 | J28: ='08 Capacity Utilisation'!J$16 | K28: ='08 Capacity Utilisation'!K$16 | L28: =IFERROR(IF(AND(ISNUMBER(D28),ISNUMBER(K28),D28>0),(K28/D28)^(1/7)-1,""),"") | M28: 08
B29: Blended realisation | C29: Rs/t | D29: =IF(ISBLANK('09 Steel Price Forecast'!D$22),"n/a",'09 Steel Price Forecast'!D$22) | E29: ='09 Steel Price Forecast'!E$22 | F29: ='09 Steel Price Forecast'!F$22 | G29: ='09 Steel Price Forecast'!G$22 | H29: ='09 Steel Price Forecast'!H$22 | I29: ='09 Steel Price Forecast'!I$22 | J29: ='09 Steel Price Forecast'!J$22 | K29: ='09 Steel Price Forecast'!K$22 | L29: =IFERROR(IF(AND(ISNUMBER(D29),ISNUMBER(K29),D29>0),(K29/D29)^(1/7)-1,""),"") | M29: 09
B30: Cash cost per tonne | C30: Rs/t | D30: =IF(ISBLANK('11 Cost Curve'!D$17),"n/a",'11 Cost Curve'!D$17) | E30: ='11 Cost Curve'!E$17 | F30: ='11 Cost Curve'!F$17 | G30: ='11 Cost Curve'!G$17 | H30: ='11 Cost Curve'!H$17 | I30: ='11 Cost Curve'!I$17 | J30: ='11 Cost Curve'!J$17 | K30: ='11 Cost Curve'!K$17 | L30: =IFERROR(IF(AND(ISNUMBER(D30),ISNUMBER(K30),D30>0),(K30/D30)^(1/7)-1,""),"") | M30: 11
B31: EBITDA per tonne | C31: Rs/t | D31: =IF(ISBLANK('13 EBITDA Model'!D$16),"n/a",'13 EBITDA Model'!D$16) | E31: ='13 EBITDA Model'!E$16 | F31: ='13 EBITDA Model'!F$16 | G31: ='13 EBITDA Model'!G$16 | H31: ='13 EBITDA Model'!H$16 | I31: ='13 EBITDA Model'!I$16 | J31: ='13 EBITDA Model'!J$16 | K31: ='13 EBITDA Model'!K$16 | L31: =IFERROR(IF(AND(ISNUMBER(D31),ISNUMBER(K31),D31>0),(K31/D31)^(1/7)-1,""),"") | M31: 13
B32: Industry EBITDA margin | C32: % | D32: =IF(ISBLANK('14 Margin Analysis'!D$17),"n/a",'14 Margin Analysis'!D$17) | E32: ='14 Margin Analysis'!E$17 | F32: ='14 Margin Analysis'!F$17 | G32: ='14 Margin Analysis'!G$17 | H32: ='14 Margin Analysis'!H$17 | I32: ='14 Margin Analysis'!I$17 | J32: ='14 Margin Analysis'!J$17 | K32: ='14 Margin Analysis'!K$17 | L32: =IFERROR(IF(AND(ISNUMBER(D32),ISNUMBER(K32),D32>0),(K32/D32)^(1/7)-1,""),"") | M32: 14
B33: Industry revenue | C33: Rs cr | D33: =IF(ISBLANK('12 Revenue Forecast'!D$16),"n/a",'12 Revenue Forecast'!D$16) | E33: ='12 Revenue Forecast'!E$16 | F33: ='12 Revenue Forecast'!F$16 | G33: ='12 Revenue Forecast'!G$16 | H33: ='12 Revenue Forecast'!H$16 | I33: ='12 Revenue Forecast'!I$16 | J33: ='12 Revenue Forecast'!J$16 | K33: ='12 Revenue Forecast'!K$16 | L33: =IFERROR(IF(AND(ISNUMBER(D33),ISNUMBER(K33),D33>0),(K33/D33)^(1/7)-1,""),"") | M33: 12
B34: Industry EBITDA | C34: Rs cr | D34: =IF(ISBLANK('13 EBITDA Model'!D$18),"n/a",'13 EBITDA Model'!D$18) | E34: ='13 EBITDA Model'!E$18 | F34: ='13 EBITDA Model'!F$18 | G34: ='13 EBITDA Model'!G$18 | H34: ='13 EBITDA Model'!H$18 | I34: ='13 EBITDA Model'!I$18 | J34: ='13 EBITDA Model'!J$18 | K34: ='13 EBITDA Model'!K$18 | L34: =IFERROR(IF(AND(ISNUMBER(D34),ISNUMBER(K34),D34>0),(K34/D34)^(1/7)-1,""),"") | M34: 13
B35: Unlevered free cash flow | C35: Rs cr | D35: =IF(ISBLANK('16 Cash Flow Model'!D$32),"n/a",'16 Cash Flow Model'!D$32) | E35: ='16 Cash Flow Model'!E$32 | F35: ='16 Cash Flow Model'!F$32 | G35: ='16 Cash Flow Model'!G$32 | H35: ='16 Cash Flow Model'!H$32 | I35: ='16 Cash Flow Model'!I$32 | J35: ='16 Cash Flow Model'!J$32 | K35: ='16 Cash Flow Model'!K$32 | L35: =IFERROR(IF(AND(ISNUMBER(D35),ISNUMBER(K35),D35>0),(K35/D35)^(1/7)-1,""),"") | M35: 16
B36: Every figure above is a live link. Change the selector and this panel, and every other sheet, recomputes.

Sheet 02 Model Assumptions
B1: 02 Model Assumptions
B2: Industry Financial Model | Indian Steel Industry | Horizon FY2027E-FY2033E | Base year FY2026A | Built 03-Aug-2026
B4: OBJECTIVE
B5: Every driver in the model, on all four scenarios, with the full evidence base. Section B resolves the active scenario and is the ONLY block the rest of the workbook reads.
B6: METHODOLOGY
B7: Section A holds the raw scenario matrix: four rows per driver, one per scenario, in a fixed order. Section B holds one row per driver whose forecast cells are =INDEX(<the four scenario cells in this column>, ScenID). Downstream sheets reference Section B only. Section C is the assumption register carrying the mandated thirteen fields. Section D shows the WACC build-up cell by cell rather than as a single number, so a reviewer can substitute house assumptions in one place.
B8: UNITS
B9: As stated per row. Percentages are stored as decimals.
B10: DEPENDENCIES
B11: Reads ScenID from 01 Control Panel. Read by every sheet from 03 to 24.
B13: SECTION A - SCENARIO DRIVER MATRIX (raw input; not read downstream)
A14: ID | B14: Driver | C14: Unit | D14: Scenario | E14: FY2027E | F14: FY2028E | G14: FY2029E | H14: FY2030E | I14: FY2031E | J14: FY2032E | K14: FY2033E | M14: Source | N14: Conf. | O14: Evidence and reasoning
A15: D01 | B15: India real GDP growth | C15: % | D15: Base Case | E15: 0.066 | F15: 0.068 | G15: 0.068 | H15: 0.067 | I15: 0.067 | J15: 0.065 | K15: 0.065 | M15: RBI-Jun26 | N15: High | O15: RBI Monetary Policy Committee, 05-Jun-2026, projects FY2027 real GDP growth at 6.6%, revised down from 6.9% in Apr-2026 on West Asia conflict, energy prices and monsoon risk; FY2026 estimated at 7.6%; Q4FY2026 actual 7.7%. Base case adopts the RBI FY2027 figure unchanged, then converges to a 6.5% steady state. Bull adds ~80bps on the RBI's own stated sensitivity that growth 'could top 7% if oil prices fall further'. Stress applies a 220bps FY2027 shock, comparable in magnitude to a global recession year.
D16: Bull Case | E16: 0.074 | F16: 0.076 | G16: 0.075 | H16: 0.074 | I16: 0.073 | J16: 0.072 | K16: 0.07
D17: Bear Case | E17: 0.056 | F17: 0.058 | G17: 0.06 | H17: 0.061 | I17: 0.062 | J17: 0.062 | K17: 0.062
D18: Stress Case | E18: 0.044 | F18: 0.048 | G18: 0.055 | H18: 0.058 | I18: 0.06 | J18: 0.06 | K18: 0.06
A19: D02 | B19: Steel demand elasticity to real GDP | C19: x | D19: Base Case | E19: 1.15 | F19: 1.15 | G19: 1.12 | H19: 1.1 | I19: 1.08 | J19: 1.06 | K19: 1.05 | M19: Derived-DB | N19: High | O19: Realised elasticity FY2015-FY2026 is 1.06x to 1.13x: apparent consumption compounded at 7.13% (76.99 Mt to 164.19 Mt over 11 years) against real GDP CAGR of roughly 6.3-6.7%, midpoint 1.10x. Near-term base is set slightly above at 1.15x because worldsteel's Apr-2026 Short Range Outlook forecasts Indian demand +7.4% in CY2026 and +9.2% in CY2027 against RBI GDP of 6.6%, implying 1.1x-1.4x. Elasticity tapers toward 1.05x by FY2033 on the standard maturing-intensity argument as per capita consumption rises from 115.7 kg. Stress assumes elasticity falls below 1.0x, as it did in FY2021 (-5.27% consumption on a positive-growth base effect).
D20: Bull Case | E20: 1.3 | F20: 1.28 | G20: 1.25 | H20: 1.22 | I20: 1.2 | J20: 1.18 | K20: 1.15
D21: Bear Case | E21: 1 | F21: 1 | G21: 0.98 | H21: 0.97 | I21: 0.96 | J21: 0.95 | K21: 0.95
D22: Stress Case | E22: 0.75 | F22: 0.85 | G22: 0.9 | H22: 0.92 | I22: 0.93 | J22: 0.94 | K22: 0.95
A23: D03 | B23: USD/INR average | C23: Rs/US$ | D23: Base Case | E23: 94.5 | F23: 95.5 | G23: 96.5 | H23: 97.5 | I23: 98.5 | J23: 99.5 | K23: 100.5 | M23: IDBI-22Jun26 | N23: High | O23: Spot USD/INR was 94 on 22-Jun-2026 with a 52-week range of 85 to 98 (IDBI Capital commodity tracker). Base assumes ~1.0% annual depreciation, consistent with the inflation differential implied by RBI's 5.1% FY2027 CPI projection against developed-market targets of ~2%. Stress takes INR beyond the 52-week low to 113, a ~20% depreciation from spot. MATERIAL BOTH WAYS: a weaker INR raises rupee raw-material cost (iron ore, coking coal and nickel are dollar-priced) but also raises the rupee landed cost of imports, supporting domestic realisations.
D24: Bull Case | E24: 93 | F24: 93.5 | G24: 94 | H24: 94.5 | I24: 95 | J24: 95.5 | K24: 96
D25: Bear Case | E25: 96.5 | F25: 98.5 | G25: 100 | H25: 101.5 | I25: 103 | J25: 104.5 | K25: 106
D26: Stress Case | E26: 101 | F26: 105 | G26: 107 | H26: 108.5 | I26: 110 | J26: 111.5 | K26: 113
A27: D04 | B27: CPI inflation | C27: % | D27: Base Case | E27: 0.051 | F27: 0.046 | G27: 0.045 | H27: 0.045 | I27: 0.045 | J27: 0.045 | K27: 0.045 | M27: RBI-Jun26 | N27: High | O27: RBI raised its FY2027 CPI projection by 50bps to 5.1% at the 05-Jun-2026 MPC, citing crude oil and supply disruption. Base converges to the 4.5% mid-point of the RBI's 4%+/-2% target band. Drives conversion cost inflation (D12) and the discount rate.
D28: Bull Case | E28: 0.045 | F28: 0.042 | G28: 0.042 | H28: 0.042 | I28: 0.042 | J28: 0.042 | K28: 0.042
D29: Bear Case | E29: 0.057 | F29: 0.052 | G29: 0.05 | H29: 0.048 | I29: 0.048 | J29: 0.048 | K29: 0.048
D30: Stress Case | E30: 0.068 | F30: 0.062 | G30: 0.055 | H30: 0.052 | I30: 0.05 | J30: 0.05 | K30: 0.05
A31: D05 | B31: Announced pipeline delivery factor | C31: % | D31: Base Case | E31: 0.85 | F31: 0.85 | G31: 0.85 | H31: 0.85 | I31: 0.85 | J31: 0.85 | K31: 0.85 | M31: Derived-DB | N31: Medium | O31: Proportion of dated announced capacity additions assumed to commission on schedule. Calibrated against realised delivery: India added 20.82 Mtpa in FY2025 and 20.07 Mtpa in FY2026 (Master DB), against a National Steel Policy path to 300 Mtpa by FY2031 that requires roughly 16 Mtpa a year - i.e. recent delivery has RUN AHEAD of the required rate, which supports a base factor materially above 50%. 85% rather than 100% reflects the routine slippage evident in the tracker (JSW Vijayanagar BF-3 was still under testing at FY2026 year-end; AM/NS Hazira 9 to 15 Mtpa has been in progress for several years). Stress at 55% reflects a capital-constrained environment.
D32: Bull Case | E32: 0.95 | F32: 0.95 | G32: 0.95 | H32: 0.95 | I32: 0.95 | J32: 0.95 | K32: 0.95
D33: Bear Case | E33: 0.7 | F33: 0.7 | G33: 0.7 | H33: 0.7 | I33: 0.7 | J33: 0.7 | K33: 0.7
D34: Stress Case | E34: 0.55 | F34: 0.55 | G34: 0.55 | H34: 0.55 | I34: 0.55 | J34: 0.55 | K34: 0.55
A35: D06 | B35: Crude-to-finished steel ratio | C35: x | D35: Base Case | E35: 1.0465 | F35: 1.0465 | G35: 1.0465 | H35: 1.0465 | I35: 1.0465 | J35: 1.0465 | K35: 1.0465 | M35: Derived-DB | N35: High | O35: FY2026 actual 168.42 / 160.94 = 1.0465 on the April-2026 JPC vintage used throughout the model (Master DB). Held flat in the base case: yield improvement is slow and offsetting mix effects are material. Bull assumes modest yield gains from continuous casting and newer assets; bear and stress assume yield deterioration from higher utilisation of older assets.
D36: Bull Case | E36: 1.043 | F36: 1.043 | G36: 1.043 | H36: 1.043 | I36: 1.043 | J36: 1.043 | K36: 1.043
D37: Bear Case | E37: 1.05 | F37: 1.05 | G37: 1.05 | H37: 1.05 | I37: 1.05 | J37: 1.05 | K37: 1.05
D38: Stress Case | E38: 1.053 | F38: 1.053 | G38: 1.053 | H38: 1.053 | I38: 1.053 | J38: 1.053 | K38: 1.053
A39: D07 | B39: Net finished steel exports | C39: Mt | D39: Base Case | E39: 0.5 | F39: 1 | G39: 1.5 | H39: 2 | I39: 2.5 | J39: 3 | K39: 3.5 | M39: Derived-DB | N39: Medium | O39: FY2026 actual net exports +0.078 Mt, having swung 4.77 Mt from a 4.693 Mt net import position in FY2025 (Master DB). Base assumes India becomes a progressively larger net exporter as capacity growth outpaces demand growth. Bear case is HIGHER net exports, because weak domestic demand forces surplus tonnes offshore at lower realisations. Stress reverses the sign: a demand collapse in India combined with the safeguard duty lapsing in Apr-2028 makes India a net importer again, which is the historically observed FY2025 configuration.
D40: Bull Case | E40: 0 | F40: 0 | G40: 0.5 | H40: 0.5 | I40: 1 | J40: 1 | K40: 1.5
D41: Bear Case | E41: 1.5 | F41: 2.5 | G41: 3.5 | H41: 4.5 | I41: 5.5 | J41: 6 | K41: 6.5
D42: Stress Case | E42: -1 | F42: -2.5 | G42: -3.5 | H42: -4 | I42: -4.5 | J42: -5 | K42: -5
A43: D08 | B43: Variation in stock | C43: Mt | D43: Base Case | E43: -1 | F43: 0 | G43: 0.5 | H43: 0.5 | I43: 0.5 | J43: 0.5 | K43: 0.5 | M43: Derived-DB | N43: Medium | O43: FY2026 actual -2.88 Mt, i.e. a destock of about 1.8% of consumption which flattered reported consumption growth (Master DB, supply balance line 6). Base normalises toward a small restock. Bear and stress assume inventory build, which is the classic signature of a demand disappointment and is a drag on apparent consumption.
D44: Bull Case | E44: -1.5 | F44: -0.5 | G44: 0 | H44: 0 | I44: 0.5 | J44: 0.5 | K44: 0.5
D45: Bear Case | E45: 0.5 | F45: 1.5 | G45: 1.5 | H45: 1 | I45: 1 | J45: 1 | K45: 1
D46: Stress Case | E46: 2 | F46: 3 | G46: 2.5 | H46: 2 | I46: 1.5 | J46: 1 | K46: 1
A47: D09 | B47: Blended industry realisation | C47: Rs/t | D47: Base Case | E47: 61800 | F47: 61000 | G47: 60500 | H47: 62000 | I47: 64000 | J47: 66000 | K47: 68000 | M47: Derived-DB | N47: Medium | O47: FY2026A anchor of Rs 59,974/t is DERIVED from the Master Database as the volume-weighted revenue per tonne of Tata Steel India, JSW Steel India, SAIL and Jindal Steel - Rs 4,79,191 cr over 79.90 Mt, i.e. 49.4% of India's finished steel production. This is used in preference to a spot HRC quote because the database documents three irreconcilable Mar-2026 HRC assessments (Rs 55,900, Rs 57,700 and Rs 59,500/t - Conflict C07) and because a blended realisation is what actually drives revenue. Base path: FY2027 +3% carrying Q4FY2026 momentum (HRC rose ~14% QoQ to Rs 57,700/t by end-Mar-2026 on the safeguard duty); then a two-year decline as the safeguard duty tapers from 12% to 11.5% (from 21-Apr-2026) to 11% and expires 20-Apr-2028, coinciding with peak capacity commissioning; then recovery to a ~2.0% CAGR over the horizon, below expected inflation, reflecting structural oversupply. Bear and stress are calibrated to the observed 52-week HRC low of Rs 45,700/t (IDBI, Jun-2026) as a floor reference.
D48: Bull Case | E48: 62500 | F48: 63500 | G48: 64000 | H48: 65500 | I48: 66500 | J48: 67500 | K48: 68500
D49: Bear Case | E49: 57500 | F49: 55000 | G49: 54000 | H49: 55000 | I49: 56500 | J49: 58000 | K49: 59500
D50: Stress Case | E50: 59000 | F50: 58500 | G50: 60000 | H50: 62500 | I50: 65000 | J50: 67000 | K50: 69000
A51: D10 | B51: Iron ore 62% Fe CFR China | C51: US$/dmt | D51: Base Case | E51: 102 | F51: 97 | G51: 93 | H51: 90 | I51: 90 | J51: 91 | K51: 93 | M51: S17 | N51: High | O51: FY2026 average US$100.52/dmt, the third consecutive annual decline from US$155.52/dmt in FY2022 (World Bank Pink Sheet, Master DB). Q1FY2027 actual average US$105.17/dmt with Jun-2026 at US$100.8/dmt, so the FY2027 base of US$102 is anchored on realised data. Base assumes continued gradual decline on new global supply, then stabilisation around US$90/dmt. NOTE the sign convention: LOWER iron ore is BULLISH for Indian steel margins because most Indian producers are net purchasers of ore, so the bull scenario carries the LOW price path. Godawari Power and NMDC are the exceptions and are flagged separately.
D52: Bull Case | E52: 98 | F52: 92 | G52: 88 | H52: 85 | I52: 84 | J52: 84 | K52: 86
D53: Bear Case | E53: 96 | F53: 90 | G53: 86 | H53: 83 | I53: 82 | J53: 82 | K53: 83
D54: Stress Case | E54: 115 | F54: 112 | G54: 104 | H54: 98 | I54: 94 | J54: 92 | K54: 92
A55: D11 | B55: Premium HCC coking coal FOB Australia | C55: US$/t | D55: Base Case | E55: 210 | F55: 200 | G55: 195 | H55: 190 | I55: 190 | J55: 195 | K55: 200 | M55: S01 | N55: Medium | O55: IMPORTANT: the Master Database deliberately asserts NO fiscal-year average for coking coal because the two public series disagree by up to US$40/t (Conflict C01). The FY2026 reference used here is the Ministry of Steel's Mar-2026 assessment of ~US$225/t, explicitly labelled a spot reference and not a fiscal-year average. Base assumes easing from that level toward a US$190/t mid-cycle, still well above the ~US$175/t Mar-2025 trough. Stress reflects a repeat of the Oct-2023 spike to US$354/t at roughly 80% amplitude. THIS IS THE SINGLE LARGEST COST UNCERTAINTY IN THE MODEL and the driver most in need of a licensed price-reporting-agency series before transaction use.
D56: Bull Case | E56: 200 | F56: 188 | G56: 182 | H56: 178 | I56: 178 | J56: 180 | K56: 184
D57: Bear Case | E57: 200 | F57: 185 | G57: 176 | H57: 170 | I57: 168 | J57: 168 | K57: 170
D58: Stress Case | E58: 300 | F58: 285 | G58: 245 | H58: 220 | I58: 208 | J58: 202 | K58: 200
A59: D12 | B59: Conversion cost inflation | C59: % | D59: Base Case | E59: 0.045 | F59: 0.042 | G59: 0.04 | H59: 0.04 | I59: 0.04 | J59: 0.04 | K59: 0.04 | M59: RBI-Jun26 | N59: Medium | O59: Applies to the non-raw-material element of cash cost: labour, power, consumables, stores, repairs and logistics. Anchored slightly below RBI's 5.1% FY2027 CPI projection because steel conversion cost includes power and freight that track energy rather than headline CPI, and because the majors are delivering explicit cost programmes - Tata Steel recorded roughly Rs 10,868 cr of cost transformation benefit in FY2026 (Master DB), equal to about Rs 4,825 per tonne of India deliveries. Stress reflects the West Asia energy shock flagged by both Tata Steel and Jindal Stainless in their FY2026 filings.
D60: Bull Case | E60: 0.038 | F60: 0.035 | G60: 0.033 | H60: 0.032 | I60: 0.032 | J60: 0.032 | K60: 0.032
D61: Bear Case | E61: 0.05 | F61: 0.046 | G61: 0.044 | H61: 0.042 | I61: 0.042 | J61: 0.042 | K61: 0.042
D62: Stress Case | E62: 0.075 | F62: 0.068 | G62: 0.055 | H62: 0.048 | I62: 0.044 | J62: 0.042 | K62: 0.042
A63: D13 | B63: Raw material share of cash cost | C63: % | D63: Base Case | E63: 0.6 | F63: 0.6 | G63: 0.6 | H63: 0.6 | I63: 0.6 | J63: 0.6 | K63: 0.6 | M63: Indicative | N63: Low | O63: INDICATIVE STRUCTURAL ASSUMPTION - NOT SOURCED FROM A PRIMARY DOCUMENT. Splits the FY2026 implied cash cost of Rs 49,241/t between a raw-material component that indexes to the iron ore and coking coal basket and a conversion component that indexes to inflation. 60/40 is the conventional split for an Indian integrated BF-BOF producer. Held constant across scenarios precisely because it is unsourced - flexing an unsourced parameter across scenarios would manufacture false precision. Plausible range 55-65%; the sensitivity of EBITDA/t to this parameter is quantified on sheet 22. MUST be replaced with company-specific cost disclosure from annual report technical parameters before any transaction use.
D64: Bull Case | E64: 0.6 | F64: 0.6 | G64: 0.6 | H64: 0.6 | I64: 0.6 | J64: 0.6 | K64: 0.6
D65: Bear Case | E65: 0.6 | F65: 0.6 | G65: 0.6 | H65: 0.6 | I65: 0.6 | J65: 0.6 | K65: 0.6
D66: Stress Case | E66: 0.6 | F66: 0.6 | G66: 0.6 | H66: 0.6 | I66: 0.6 | J66: 0.6 | K66: 0.6
A67: D14 | B67: Iron ore weight in the raw material basket | C67: % | D67: Base Case | E67: 0.45 | F67: 0.45 | G67: 0.45 | H67: 0.45 | I67: 0.45 | J67: 0.45 | K67: 0.45 | M67: Indicative | N67: Low | O67: INDICATIVE. Iron ore 45%, coking coal 45%, other ferrous and fluxes 10% by value in the BF-BOF raw material basket. Unsourced and therefore held constant across scenarios. Sensitivity quantified on sheet 22.
D68: Bull Case | E68: 0.45 | F68: 0.45 | G68: 0.45 | H68: 0.45 | I68: 0.45 | J68: 0.45 | K68: 0.45
D69: Bear Case | E69: 0.45 | F69: 0.45 | G69: 0.45 | H69: 0.45 | I69: 0.45 | J69: 0.45 | K69: 0.45
D70: Stress Case | E70: 0.45 | F70: 0.45 | G70: 0.45 | H70: 0.45 | I70: 0.45 | J70: 0.45 | K70: 0.45
A71: D15 | B71: Effective tax rate | C71: % | D71: Base Case | E71: 0.2517 | F71: 0.2517 | G71: 0.2517 | H71: 0.2517 | I71: 0.2517 | J71: 0.2517 | K71: 0.2517 | M71: Statutory | N71: Medium | O71: Indian statutory corporate tax rate of 22% plus surcharge and cess equals 25.17% under section 115BAA, which the large Indian steel producers have elected. Held flat across scenarios: the tax rate is a policy parameter, not a cyclical variable. Actual effective rates differ because of MAT credits, accumulated losses and deferred tax - the Master Database flags Kirloskar Ferrous FY2026 net profit exceeding profit before tax on a tax write-back (Conflict C12). Company-specific effective rates must be substituted in single-name models.
D72: Bull Case | E72: 0.2517 | F72: 0.2517 | G72: 0.2517 | H72: 0.2517 | I72: 0.2517 | J72: 0.2517 | K72: 0.2517
D73: Bear Case | E73: 0.2517 | F73: 0.2517 | G73: 0.2517 | H73: 0.2517 | I73: 0.2517 | J73: 0.2517 | K73: 0.2517
D74: Stress Case | E74: 0.2517 | F74: 0.2517 | G74: 0.2517 | H74: 0.2517 | I74: 0.2517 | J74: 0.2517 | K74: 0.2517
A75: D16 | B75: Capex intensity | C75: Rs/t of capacity added | D75: Base Case | E75: 55000 | F75: 55000 | G75: 55000 | H75: 55000 | I75: 55000 | J75: 55000 | K75: 55000 | M75: Derived-DB | N75: Medium | O75: Greenfield and large brownfield Indian crude steel capacity. Cross-checks from the Master Database: JSW Steel Board-approved 5 Mtpa brownfield expansion at JVML-Vijayanagar at Rs 26,000 cr equals Rs 52,000 per tonne; SAIL's stated roughly Rs 1 lakh crore for about 15 Mtpa of additions equals roughly Rs 67,000 per tonne; Tata Steel's 0.75 Mtpa Ludhiana scrap EAF at about Rs 3,200 cr equals Rs 42,700 per tonne, which is lower because an EAF has no ironmaking. Base of Rs 55,000/t sits between the JSW brownfield and SAIL blended figures. Also the primary input to the replacement-cost valuation on sheet 23.
D76: Bull Case | E76: 52000 | F76: 52000 | G76: 52000 | H76: 52000 | I76: 52000 | J76: 52000 | K76: 52000
D77: Bear Case | E77: 60000 | F77: 60000 | G77: 60000 | H77: 60000 | I77: 60000 | J77: 60000 | K77: 60000
D78: Stress Case | E78: 65000 | F78: 65000 | G78: 65000 | H78: 65000 | I78: 65000 | J78: 65000 | K78: 65000
A79: D17 | B79: Maintenance capex | C79: % of revenue | D79: Base Case | E79: 0.03 | F79: 0.03 | G79: 0.03 | H79: 0.03 | I79: 0.03 | J79: 0.03 | K79: 0.03 | M79: Indicative | N79: Low | O79: INDICATIVE. Sustaining capex excluding growth. Cross-check: Tata Steel FY2026 total capex of Rs 14,026 cr on consolidated revenue of Rs 2,32,140 cr is 6.0%, but that figure includes substantial growth capex, so a 3.0% sustaining assumption is consistent with a roughly 50/50 growth-maintenance split. Not separately disclosed by any issuer in the database, hence Low confidence.
D80: Bull Case | E80: 0.028 | F80: 0.028 | G80: 0.028 | H80: 0.028 | I80: 0.028 | J80: 0.028 | K80: 0.028
D81: Bear Case | E81: 0.033 | F81: 0.033 | G81: 0.033 | H81: 0.033 | I81: 0.033 | J81: 0.033 | K81: 0.033
D82: Stress Case | E82: 0.035 | F82: 0.035 | G82: 0.035 | H82: 0.035 | I82: 0.035 | J82: 0.035 | K82: 0.035
A83: D18 | B83: Net working capital | C83: days of revenue | D83: Base Case | E83: 45 | F83: 45 | G83: 45 | H83: 45 | I83: 45 | J83: 45 | K83: 45 | M83: Not sourced | N83: Low | O83: NOT SOURCED. The Master Database carries total assets and borrowings but not receivables, inventory or payables, so working capital days could not be derived from it. Directional evidence only: Tata Steel disclosed a working capital RELEASE of about Rs 6,470 cr in FY2026 (Master DB), consistent with tightening days on a Rs 2,32,140 cr revenue base of roughly 10 days. Base of 45 days is a sector convention for an integrated Indian steel producer and MUST be replaced with balance-sheet-derived days before transaction use. Stress reflects a working capital build in a downturn as inventory rises and receivables stretch, which is a first-order cash flow risk, not a second-order one.
D84: Bull Case | E84: 40 | F84: 40 | G84: 40 | H84: 40 | I84: 40 | J84: 40 | K84: 40
D85: Bear Case | E85: 52 | F85: 52 | G85: 52 | H85: 52 | I85: 52 | J85: 52 | K85: 52
D86: Stress Case | E86: 62 | F86: 62 | G86: 62 | H86: 62 | I86: 62 | J86: 62 | K86: 62
A87: D19 | B87: Exit EV/EBITDA multiple | C87: x | D87: Base Case | E87: 6 | F87: 6 | G87: 6 | H87: 6 | I87: 6 | J87: 6 | K87: 6 | M87: Not sourced | N87: Low | O87: NOT SOURCED - market multiples were not obtained in this research cycle because share prices were not sourced. 6.0x is the conventional mid-cycle EV/EBITDA for Indian integrated steel and is provided as a starting point only. Sheet 23 computes live trading multiples the moment share prices are entered, and the exit multiple should then be re-based on that observed evidence. Flagged Low confidence and excluded from the headline conclusions.
D88: Bull Case | E88: 7 | F88: 7 | G88: 7 | H88: 7 | I88: 7 | J88: 7 | K88: 7
D89: Bear Case | E89: 5 | F89: 5 | G89: 5 | H89: 5 | I89: 5 | J89: 5 | K89: 5
D90: Stress Case | E90: 4 | F90: 4 | G90: 4 | H90: 4 | I90: 4 | J90: 4 | K90: 4
A91: D20 | B91: WACC (nominal, INR) | C91: % | D91: Base Case | E91: 0.12 | F91: 0.12 | G91: 0.12 | H91: 0.12 | I91: 0.12 | J91: 0.12 | K91: 0.12 | M91: Composite | N91: Medium | O91: Built from observable Indian market data where available. Risk-free rate 6.83% - the 10-year G-sec yield on 31-Jul-2026, with Trading Economics expecting 6.78% at quarter end. Pre-tax cost of debt 7.44% - the lower bound of CRISIL RateView's Jul-2026 projected 10-year corporate bond yield range of 7.44-7.54%, consistent with the AA domestic ratings the Master Database records for JSW Steel. Post-tax cost of debt therefore 5.57% at the 25.17% tax rate. Equity risk premium of 6.5% and an equity beta of 1.2 are NOT SOURCED and are the weakest links in this build; at a 30% debt weight these give a cost of equity of about 14.6% and a WACC of about 12.0%. The full build-up is shown and is fully editable on sheet 02, and WACC is a sensitivity axis on sheet 22.
D92: Bull Case | E92: 0.112 | F92: 0.112 | G92: 0.112 | H92: 0.112 | I92: 0.112 | J92: 0.112 | K92: 0.112
D93: Bear Case | E93: 0.128 | F93: 0.128 | G93: 0.128 | H93: 0.128 | I93: 0.128 | J93: 0.128 | K93: 0.128
D94: Stress Case | E94: 0.14 | F94: 0.14 | G94: 0.14 | H94: 0.14 | I94: 0.14 | J94: 0.14 | K94: 0.14
A95: D21 | B95: Finished steel imports | C95: Mt | D95: Base Case | E95: 6.8 | F95: 7 | G95: 7.2 | H95: 7.5 | I95: 7.8 | J95: 8.1 | K95: 8.4 | M95: Derived-DB | N95: Medium | O95: FY2026 actual 6.524 Mt, down 31.7% from 9.551 Mt in FY2025 as the safeguard duty bit (Master DB). Base assumes imports grow slowly with the market as the duty tapers to 11.5% then 11% and expires 20-Apr-2028, but stay well below the FY2025 peak because domestic capacity has expanded. Note the counter-intuitive scenario signs: the BULL case carries HIGHER imports because strong domestic demand pulls material in, while the BEAR case carries LOWER imports because weak demand and a wide domestic discount to import parity make imports uncompetitive. Stress assumes a return above the FY2025 peak on duty expiry plus Chinese surplus redirection. Exports are derived as imports plus net exports (D07), so the two trade drivers are internally consistent by construction.
D96: Bull Case | E96: 7.5 | F96: 8 | G96: 8.5 | H96: 9 | I96: 9.5 | J96: 10 | K96: 10.5
D97: Bear Case | E97: 6 | F97: 5.5 | G97: 5.2 | H97: 5 | I97: 5 | J97: 5.1 | K97: 5.2
D98: Stress Case | E98: 8.5 | F98: 10 | G98: 11 | H98: 11.5 | I98: 12 | J98: 12 | K98: 12
A99: D22 | B99: Secondary and unattributed capacity additions | C99: Mtpa p.a. | D99: Base Case | E99: 11 | F99: 11 | G99: 11 | H99: 10.5 | I99: 10.5 | J99: 10 | K99: 10 | M99: Derived-DB | N99: Medium | O99: ESSENTIAL RECONCILIATION ITEM. The dated project tracker on sheet 07 captures only large, individually announced projects and averages 7.7 Mtpa a year over FY2027-FY2033. India actually added 20.82 Mtpa in FY2025 and 20.07 Mtpa in FY2026 (Master DB), so roughly 12.7 Mtpa a year has historically come from the secondary sector and from projects too small to be individually announced. The Master Database evidences this directly: production by 'other producers' rose from 66.61 Mt in FY2025 to 73.02 Mt in FY2026 and compounded at 10.7% over FY2022-FY2026, faster than the integrated majors' 8.1%. Base assumes 11.0 Mtpa a year tapering to 10.0, slightly below the historical rate. VALIDATION: this build produces India crude steel capacity of about 302 Mtpa by FY2031 against the National Steel Policy 2017 target of 300 Mtpa - the model reproduces the policy target from bottom-up components without being calibrated to it, which is a meaningful independent check on the capacity block. Omitting this driver would understate FY2031 capacity by about 54 Mtpa, or 18%.
D100: Bull Case | E100: 13 | F100: 13 | G100: 12.5 | H100: 12.5 | I100: 12 | J100: 12 | K100: 11.5
D101: Bear Case | E101: 8 | F101: 8 | G101: 7.5 | H101: 7 | I101: 7 | J101: 6.5 | K101: 6.5
D102: Stress Case | E102: 5 | F102: 4 | G102: 4 | H102: 3.5 | I102: 3.5 | J102: 3 | K102: 3
...

Sheet 03 Macroeconomic Model
B1: 03 Macroeconomic Model
B2: Industry Financial Model | Indian Steel Industry | Horizon FY2027E-FY2033E | Base year FY2026A | Built 03-Aug-2026
B4: OBJECTIVE
B5: The macro spine: real GDP, inflation, the exchange rate and interest rates. Every demand and cost forecast in the workbook is anchored here.
B6: METHODOLOGY
B7: Real GDP growth and CPI are taken from RBI's June-2026 Monetary Policy Committee projections for FY2027 and converge to a steady state thereafter, because no Indian official body publishes a real GDP path beyond roughly five years. USD/INR is anchored on the 22-Jun-2026 spot of 94. Index rows compound the growth rates so that cumulative effects are visible rather than implied.
B8: UNITS
B9: Percentages as decimals. Indices FY2026A = 100. USD/INR in rupees per dollar.
B10: DEPENDENCIES
B11: Reads 02 Model Assumptions. Read by 04 Steel Demand, 10 Raw Material, 16 Cash Flow.
B13: Line item | C13: Unit | D13: FY2026A | E13: FY2027E | F13: FY2028E | G13: FY2029E | H13: FY2030E | I13: FY2031E | J13: FY2032E | K13: FY2033E | L13: CAGR | M13: Source | N13: Conf. | O13: Notes / methodology
B14: GROWTH AND PRICES
B15: India real GDP growth | C15: % | D15: 0.076 | E15: '02 Model Assumptions'!E$122 | F15: '02 Model Assumptions'!F$122 | G15: '02 Model Assumptions'!G$122 | H15: '02 Model Assumptions'!H$122 | I15: '02 Model Assumptions'!I$122 | J15: '02 Model Assumptions'!J$122 | K15: '02 Model Assumptions'!K$122 | M15: RBI MPC 05-Jun-2026 | N15: High | O15: FY2026A of 7.6% is the RBI's own estimate for FY2026. FY2027E of 6.6% is the RBI projection, revised down from 6.9% on West Asia conflict, energy prices and monsoon risk. Beyond FY2027 the path converges to 6.5%.
B16: Real GDP index | C16: FY2026A=100 | D16: 100 | E16: =D16*(1+E15) | F16: =E16*(1+F15) | G16: =F16*(1+G15) | H16: =G16*(1+H15) | I16: =H16*(1+I15) | J16: =I16*(1+J15) | K16: =J16*(1+K15) | L16: =IFERROR(IF(AND(ISNUMBER(D16),ISNUMBER(K16),D16>0),(K16/D16)^(1/7)-1,""),"") | M16: Computed | N16: High | O16: Compounds the growth rate above.
B17: CPI inflation | C17: % | D17: 0.051 | E17: '02 Model Assumptions'!E$125 | F17: '02 Model Assumptions'!F$125 | G17: '02 Model Assumptions'!G$125 | H17: '02 Model Assumptions'!H$125 | I17: '02 Model Assumptions'!I$125 | J17: '02 Model Assumptions'!J$125 | K17: '02 Model Assumptions'!K$125 | M17: RBI MPC 05-Jun-2026 | N17: High | O17: RBI raised its FY2027 CPI projection by 50bps to 5.1%. Converges to the 4.5% mid-point of the 4% plus or minus 2% target band.
B18: Nominal GDP index | C18: FY2026A=100 | D18: 100 | E18: =D18*(1+E15)*(1+E17) | F18: =E18*(1+F15)*(1+F17) | G18: =F18*(1+G15)*(1+G17) | H18: =G18*(1+H15)*(1+H17) | I18: =H18*(1+I15)*(1+I17) | J18: =I18*(1+J15)*(1+J17) | K18: =J18*(1+K15)*(1+K17) | L18: =IFERROR(IF(AND(ISNUMBER(D18),ISNUMBER(K18),D18>0),(K18/D18)^(1/7)-1,""),"") | M18: Computed | N18: High | O18: Real growth compounded with inflation.
B20: EXCHANGE RATE AND INTEREST RATES
B21: USD/INR (average) | C21: Rs/US$ | D21: 88.4 | E21: '02 Model Assumptions'!E$124 | F21: '02 Model Assumptions'!F$124 | G21: '02 Model Assumptions'!G$124 | H21: '02 Model Assumptions'!H$124 | I21: '02 Model Assumptions'!I$124 | J21: '02 Model Assumptions'!J$124 | K21: '02 Model Assumptions'!K$124 | L21: =IFERROR(IF(AND(ISNUMBER(D21),ISNUMBER(K21),D21>0),(K21/D21)^(1/7)-1,""),"") | M21: IDBI Capital 22-Jun-2026 | N21: High | O21: FY2026A of 88.4 is DERIVED from Tata Steel's dual-currency disclosure in the database - consolidated EBITDA/t of Rs 10,900 against US$124 gives 87.90, India EBITDA/t of Rs 15,213 against US$172 gives 88.45, and group turnover of Rs 2,32,140 cr against US$26bn gives 89.28. Spot was 94 on 22-Jun-2026 with a 52-week range of 85 to 98.
B22: INR depreciation | C22: % | E22: =E21/D21-1 | F22: =F21/E21-1 | G22: =G21/F21-1 | H22: =H21/G21-1 | I22: =I21/H21-1 | J22: =J21/I21-1 | K22: =K21/J21-1 | M22: Computed | N22: High | O22: Positive equals depreciation, which raises rupee raw-material cost but also raises the rupee landed cost of imports and therefore supports domestic realisations.
B23: 10-year G-sec yield | C23: % | D23: 0.0683 | E23: ='02 Model Assumptions'!$D$164 | F23: ='02 Model Assumptions'!$D$164 | G23: ='02 Model Assumptions'!$D$164 | H23: ='02 Model Assumptions'!$D$164 | I23: ='02 Model Assumptions'!$D$164 | J23: ='02 Model Assumptions'!$D$164 | K23: ='02 Model Assumptions'!$D$164 | M23: investing.com 31-Jul-2026 | N23: High | O23: 6.833% on 31-Jul-2026. Trading Economics expects 6.78% at quarter end. Held flat across the horizon - a term-structure forecast is not attempted.
B24: WACC (nominal, INR) | C24: % | E24: '02 Model Assumptions'!E$141 | F24: '02 Model Assumptions'!F$141 | G24: '02 Model Assumptions'!G$141 | H24: '02 Model Assumptions'!H$141 | I24: '02 Model Assumptions'!I$141 | J24: '02 Model Assumptions'!J$141 | K24: '02 Model Assumptions'!K$141 | M24: Composite - see 02 Section D | N24: Medium | O24: Used for discounting on 23 Comparable Valuation. Cross-checked against the build-up on 02 Section D by 25 Audit Checks.
B26: Macro drivers are scenario-dependent: the stress case applies a 220bps FY2027 GDP shock and takes USD/INR beyond its 52-week low.

Sheet 04 Steel Demand Model
B1: 04 Steel Demand Model
B2: Industry Financial Model | Indian Steel Industry | Horizon FY2027E-FY2033E | Base year FY2026A | Built 03-Aug-2026
B4: OBJECTIVE
B5: Forecasts India's apparent finished steel consumption, the demand anchor for the whole model.
B6: METHODOLOGY
B7: Consumption growth equals real GDP growth multiplied by a steel demand elasticity. The elasticity is not assumed - it is calibrated to realised history: consumption compounded at 7.13% from 76.99 Mt in FY2015 to 164.19 Mt in FY2026 against real GDP CAGR of roughly 6.3-6.7%, giving 1.06x to 1.13x. It is set at 1.15x near term, consistent with worldsteel's Apr-2026 forecast of +7.4% in CY2026 and +9.2% in CY2027 against RBI GDP of 6.6%, then tapers to 1.05x on maturing intensity.
B8: UNITS
B9: Mt. Population in billions. Per capita in kg.
B10: DEPENDENCIES
B11: Reads 03 Macroeconomic Model and 02 Model Assumptions. Read by 05 Steel Supply.
B13: Line item | C13: Unit | D13: FY2026A | E13: FY2027E | F13: FY2028E | G13: FY2029E | H13: FY2030E | I13: FY2031E | J13: FY2032E | K13: FY2033E | L13: CAGR | M13: Source | N13: Conf. | O13: Notes / methodology
B14: India real GDP growth | C14: % | D14: 0.076 | E14: ='03 Macroeconomic Model'!E$15 | F14: ='03 Macroeconomic Model'!F$15 | G14: ='03 Macroeconomic Model'!G$15 | H14: ='03 Macroeconomic Model'!H$15 | I14: ='03 Macroeconomic Model'!I$15 | J14: ='03 Macroeconomic Model'!J$15 | K14: ='03 Macroeconomic Model'!K$15 | M14: 03 Macro | N14: High | O14: Linked, not re-entered.
B15: Steel demand elasticity to GDP | C15: x | D15: 1.1 | E15: '02 Model Assumptions'!E$123 | F15: '02 Model Assumptions'!F$123 | G15: '02 Model Assumptions'!G$123 | H15: '02 Model Assumptions'!H$123 | I15: '02 Model Assumptions'!I$123 | J15: '02 Model Assumptions'!J$123 | K15: '02 Model Assumptions'!K$123 | M15: Derived from Master DB | N15: High | O15: FY2026A of 1.10x is the realised FY2015-FY2026 average, the midpoint of the 1.06x-1.13x range depending on the GDP deflator used.
B16: Implied consumption growth | C16: % | D16: 0.079 | E16: =E14*E15 | F16: =F14*F15 | G16: =G14*G15 | H16: =H14*H15 | I16: =I14*I15 | J16: =J14*J15 | K16: =K14*K15 | M16: Computed | N16: High | O16: FY2026A of 7.9% is the actual reported growth, against 7.6% GDP times 1.04x realised elasticity - the model's structure reproduces the actual outturn.
B17: Apparent finished steel consumption | C17: Mt | D17: 163.74 | E17: =D17*(1+E16) | F17: =E17*(1+F16) | G17: =F17*(1+G16) | H17: =G17*(1+H16) | I17: =H17*(1+I16) | J17: =I17*(1+J16) | K17: =J17*(1+K16) | L17: =IFERROR(IF(AND(ISNUMBER(D17),ISNUMBER(K17),D17>0),(K17/D17)^(1/7)-1,""),"") | M17: 00 Database Import A03 | N17: High | O17: FY2026A of 163.74 Mt is the April-2026 JPC vintage, which is the internally self-reconciling balance. The June-2026 vintage of 164.19 Mt is a memo below.
B18: Memo: June-2026 JPC vintage, FY2026 actual | C18: Mt | D18: 164.19 | M18: Master DB | N18: High | O18: Carried so the vintage difference is visible rather than buried - Master DB Conflict C03. The 0.45 Mt difference is 0.27%.
B20: DEMAND INTENSITY
B21: Population | C21: bn | D21: 1.4191 | E21: =D21*(1+$D$22) | F21: =E21*(1+$D$22) | G21: =F21*(1+$D$22) | H21: =G21*(1+$D$22) | I21: =H21*(1+$D$22) | J21: =I21*(1+$D$22) | K21: =J21*(1+$D$22) | M21: Derived | N21: Medium | O21: DERIVED from the database: consumption of 163.74 Mt divided by per capita consumption of 115.7 kg gives 1.4152 bn; the 1.4191 bn shown uses the June-vintage consumption of 164.19 Mt against 115.7 kg, which is the internally consistent pairing the database publishes.
B22: Population growth | C22: % | D22: 0.0085 | M22: NOT SOURCED | N22: Low | O22: 0.85% per annum is NOT sourced in this research cycle. Replace with a UN World Population Prospects series. Affects per capita consumption only, not tonnage, so it does not propagate into revenue or EBITDA.
B23: Per capita finished steel consumption | C23: kg | D23: 115.7 | E23: =E17/E21 | F23: =F17/F21 | G23: =G17/G21 | H23: =H17/H21 | I23: =I17/I21 | J23: =J17/J21 | K23: =K17/K21 | L23: =IFERROR(IF(AND(ISNUMBER(D23),ISNUMBER(K23),D23>0),(K23/D23)^(1/7)-1,""),"") | M23: Computed | N23: Medium | O23: Consumption in Mt divided by population in bn gives kg per head directly. India is at roughly half the world average of 215 kg and about a fifth of China's 604 kg.
B25: Demand is the ONLY block in this model that is not capacity-aware. The capacity ceiling is applied on 05 Steel Supply, so consumption here is unconstrained demand.

Sheet 05 Steel Supply Model
B1: 05 Steel Supply Model
B2: Industry Financial Model | Indian Steel Industry | Horizon FY2027E-FY2033E | Base year FY2026A | Built 03-Aug-2026
B4: OBJECTIVE
B5: Converts demand into required domestic production, applies a practical capacity ceiling, and routes any shortfall to imports so that the supply balance always closes.
B6: METHODOLOGY
B7: The identity is the Joint Plant Committee's own: consumption equals production plus imports less exports adjusted for the change in stocks. Rearranged, required finished production equals consumption plus net exports plus the stock change. Crude steel equals finished production multiplied by the crude-to-finished ratio of 1.0465, which is the FY2026 actual on the April-2026 vintage. Production is then capped at capacity times maximum practical utilisation of 92%; where demand would exceed that, the shortfall is met by additional imports rather than by impossible domestic output.
B8: UNITS
B9: Mt. Ratio in times.
B10: DEPENDENCIES
B11: Reads 04 Steel Demand, 06 Capacity Forecast, 02 Model Assumptions. Read by 09, 11, 12, 13, 19.
B13: Line item | C13: Unit | D13: FY2026A | E13: FY2027E | F13: FY2028E | G13: FY2029E | H13: FY2030E | I13: FY2031E | J13: FY2032E | K13: FY2033E | L13: CAGR | M13: Source | N13: Conf. | O13: Notes / methodology
B14: Apparent finished steel consumption | C14: Mt | D14: 163.74 | E14: ='04 Steel Demand Model'!E$17 | F14: ='04 Steel Demand Model'!F$17 | G14: ='04 Steel Demand Model'!G$17 | H14: ='04 Steel Demand Model'!H$17 | I14: ='04 Steel Demand Model'!I$17 | J14: ='04 Steel Demand Model'!J$17 | K14: ='04 Steel Demand Model'!K$17 | M14: 04 Demand | N14: High
B15: Net finished steel exports | C15: Mt | D15: 0.078 | E15: '02 Model Assumptions'!E$128 | F15: '02 Model Assumptions'!F$128 | G15: '02 Model Assumptions'!G$128 | H15: '02 Model Assumptions'!H$128 | I15: '02 Model Assumptions'!I$128 | J15: '02 Model Assumptions'!J$128 | K15: '02 Model Assumptions'!K$128 | M15: Derived from Master DB | N15: Medium | O15: FY2026A of +0.078 Mt - India returned to net exporter status having been 4.693 Mt net importer in FY2025, a 4.77 Mt swing in one year.
B16: Variation in stock | C16: Mt | D16: -2.88 | E16: '02 Model Assumptions'!E$129 | F16: '02 Model Assumptions'!F$129 | G16: '02 Model Assumptions'!G$129 | H16: '02 Model Assumptions'!H$129 | I16: '02 Model Assumptions'!I$129 | J16: '02 Model Assumptions'!J$129 | K16: '02 Model Assumptions'!K$129 | M16: Master DB supply balance | N16: Medium | O16: FY2026A of -2.88 Mt, i.e. a DESTOCK of about 1.8% of consumption which flattered reported consumption growth. Base normalises to a small restock.
B17: Required finished steel production | C17: Mt | D17: 160.94 | E17: =E14+E15+E16 | F17: =F14+F15+F16 | G17: =G14+G15+G16 | H17: =H14+H15+H16 | I17: =I14+I15+I16 | J17: =J14+J15+J16 | K17: =K14+K15+K16 | M17: Computed - JPC identity | N17: High | O17: IDENTITY CHECK: 163.74 + 0.078 + (-2.88) = 160.94, which equals the reported FY2026 finished steel production exactly. The balance closes.
B18: Crude-to-finished steel ratio | C18: x | D18: 1.04647 | E18: '02 Model Assumptions'!E$127 | F18: '02 Model Assumptions'!F$127 | G18: '02 Model Assumptions'!G$127 | H18: '02 Model Assumptions'!H$127 | I18: '02 Model Assumptions'!I$127 | J18: '02 Model Assumptions'!J$127 | K18: '02 Model Assumptions'!K$127 | M18: Derived from Master DB | N18: High | O18: 168.42 / 160.94 on the April-2026 vintage. On the June vintage it would be 1.0413, a 0.5% difference.
B19: Required crude steel production (unconstrained) | C19: Mt | D19: 168.42 | E19: =E17*E18 | F19: =F17*F18 | G19: =G17*G18 | H19: =H17*H18 | I19: =I17*I18 | J19: =J17*J18 | K19: =K17*K18 | M19: Computed | N19: High
B21: CAPACITY CEILING
B22: Crude steel capacity | C22: Mtpa | D22: 220.4 | E22: ='06 Capacity Forecast'!E$20 | F22: ='06 Capacity Forecast'!F$20 | G22: ='06 Capacity Forecast'!G$20 | H22: ='06 Capacity Forecast'!H$20 | I22: ='06 Capacity Forecast'!I$20 | J22: ='06 Capacity Forecast'!J$20 | K22: ='06 Capacity Forecast'!K$20 | M22: 06 Capacity | N22: High
B23: Maximum practical utilisation | C23: % | E23: '02 Model Assumptions'!E$146 | F23: '02 Model Assumptions'!F$146 | G23: '02 Model Assumptions'!G$146 | H23: '02 Model Assumptions'!H$146 | I23: '02 Model Assumptions'!I$146 | J23: '02 Model Assumptions'!J$146 | K23: '02 Model Assumptions'!K$146 | M23: Indicative | N23: Low | O23: 92%. Allows for maintenance and relining. Individual assets can exceed nameplate - the database records SAIL Rourkela at 103.8% - but a national aggregate cannot.
B24: Maximum crude steel production | C24: Mt | E24: =E22*E23 | F24: =F22*F23 | G24: =G22*G23 | H24: =H22*H23 | I24: =I22*I23 | J24: =J22*J23 | K24: =K22*K23 | M24: Computed | N24: Low
B25: Crude steel production | C25: Mt | D25: 168.42 | E25: =MIN(E19,E24) | F25: =MIN(F19,F24) | G25: =MIN(G19,G24) | H25: =MIN(H19,H24) | I25: =MIN(I19,I24) | J25: =MIN(J19,J24) | K25: =MIN(K19,K24) | L25: =IFERROR(IF(AND(ISNUMBER(D25),ISNUMBER(K25),D25>0),(K25/D25)^(1/7)-1,""),"") | M25: Computed | N25: High | O25: The binding constraint. In the base case the ceiling does NOT bind - peak utilisation is 84.0% in FY2033 - which is itself an important finding: India is not capacity-constrained on this demand path.
B26: Capacity ceiling binding? | C26: flag | E26: =IF(E19>E24+0.001,"BINDING","no") | F26: =IF(F19>F24+0.001,"BINDING","no") | G26: =IF(G19>G24+0.001,"BINDING","no") | H26: =IF(H19>H24+0.001,"BINDING","no") | I26: =IF(I19>I24+0.001,"BINDING","no") | J26: =IF(J19>J24+0.001,"BINDING","no") | K26: =IF(K19>K24+0.001,"BINDING","no") | M26: Computed | N26: High | O26: Flags any year where domestic demand cannot be met from domestic capacity.
B27: Finished steel production | C27: Mt | D27: 160.94 | E27: =E25/E18 | F27: =F25/F18 | G27: =G25/G18 | H27: =H25/H18 | I27: =I25/I18 | J27: =J25/J18 | K27: =K25/K18 | L27: =IFERROR(IF(AND(ISNUMBER(D27),ISNUMBER(K27),D27>0),(K27/D27)^(1/7)-1,""),"") | M27: Computed | N27: High
B28: Shortfall met by additional imports | C28: Mt | D28: 0 | E28: =MAX(0,E17-E27) | F28: =MAX(0,F17-F27) | G28: =MAX(0,G17-G27) | H28: =MAX(0,H17-H27) | I28: =MAX(0,I17-I27) | J28: =MAX(0,J17-J27) | K28: =MAX(0,K17-K27) | M28: Computed | N28: High | O28: Keeps the balance closed when the ceiling binds. Flows through to 19 Trade Model.
B30: The model does NOT endogenise supply response - it does not idle capacity when margins turn negative. This is why the stress case should be read as a lower bound on margin rather than a central expectation, and is a documented limitation on 25 Audit Checks.

Sheet 06 Capacity Forecast
B1: 06 Capacity Forecast
B2: Industry Financial Model | Indian Steel Industry | Horizon FY2027E-FY2033E | Base year FY2026A | Built 03-Aug-2026
B4: OBJECTIVE
B5: Forecasts India's crude steel capacity from the dated project pipeline plus a secondary-sector residual, and validates the result against the National Steel Policy 2017 target.
B6: METHODOLOGY
B7: Capacity equals prior-year capacity plus announced additions delivered plus secondary and unattributed additions. Announced additions come live from the project tracker by SUMIFS and are multiplied by a delivery factor of 85% reflecting observed slippage. The secondary residual exists because the tracker captures only individually announced projects averaging 7.7 Mtpa a year, whereas India actually added 20.8 Mtpa in FY2025 and 20.1 Mtpa in FY2026 - the difference comes from the secondary sector, whose output the database shows growing at 10.7% a year, faster than the integrated majors' 8.1%.
B8: UNITS
B9: Mtpa.
B10: DEPENDENCIES
B11: Reads 07 Capacity Expansion Tracker and 02 Model Assumptions. Read by 08 Utilisation, 05 Steel Supply, 17 Capital Allocation.
B13: Line item | C13: Unit | D13: FY2026A | E13: FY2027E | F13: FY2028E | G13: FY2029E | H13: FY2030E | I13: FY2031E | J13: FY2032E | K13: FY2033E | L13: CAGR | M13: Source | N13: Conf. | O13: Notes / methodology
B14: Opening capacity | C14: Mtpa | E14: =D20 | F14: =E20 | G14: =F20 | H14: =G20 | I14: =H20 | J14: =I20 | K14: =J20 | M14: Computed | N14: High | O14: Prior-year closing capacity.
B15: Gross announced additions (from tracker) | C15: Mtpa | E15: ='07 Capacity Expansion Tracker'!E$36 | F15: ='07 Capacity Expansion Tracker'!F$36 | G15: ='07 Capacity Expansion Tracker'!G$36 | H15: ='07 Capacity Expansion Tracker'!H$36 | I15: ='07 Capacity Expansion Tracker'!I$36 | J15: ='07 Capacity Expansion Tracker'!J$36 | K15: ='07 Capacity Expansion Tracker'!K$36 | M15: 07 Tracker (SUMIFS) | N15: Medium | O15: Live from the project tracker. Excludes acquisitions, downstream lines, overseas assets and already-commissioned projects.
B16: Pipeline delivery factor | C16: % | E16: '02 Model Assumptions'!E$126 | F16: '02 Model Assumptions'!F$126 | G16: '02 Model Assumptions'!G$126 | H16: '02 Model Assumptions'!H$126 | I16: '02 Model Assumptions'!I$126 | J16: '02 Model Assumptions'!J$126 | K16: '02 Model Assumptions'!K$126 | M16: Derived from Master DB | N16: Medium | O16: 85% in the base case. India delivered ~20 Mtpa a year in FY2025 and FY2026 against a National Steel Policy requirement of ~16 Mtpa a year, so delivery capability is demonstrated; the 15% haircut reflects project-level slippage such as JSW Vijayanagar BF-3 still testing at FY2026 year-end.
B17: Announced additions delivered | C17: Mtpa | E17: =E15*E16 | F17: =F15*F16 | G17: =G15*G16 | H17: =H15*H16 | I17: =I15*I16 | J17: =J15*J16 | K17: =K15*K16 | M17: Computed | N17: Medium
B18: Secondary and unattributed additions | C18: Mtpa | E18: '02 Model Assumptions'!E$143 | F18: '02 Model Assumptions'!F$143 | G18: '02 Model Assumptions'!G$143 | H18: '02 Model Assumptions'!H$143 | I18: '02 Model Assumptions'!I$143 | J18: '02 Model Assumptions'!J$143 | K18: '02 Model Assumptions'!K$143 | M18: Derived from Master DB | N18: Medium | O18: ESSENTIAL RECONCILIATION ITEM. Omitting this would understate FY2031 capacity by about 54 Mtpa, or 18%.
B19: Total additions | C19: Mtpa | D19: 20.07 | E19: =E17+E18 | F19: =F17+F18 | G19: =G17+G18 | H19: =H17+H18 | I19: =I17+I18 | J19: =J17+J18 | K19: =K17+K18 | M19: Computed | N19: Medium | O19: FY2026A of 20.07 Mtpa is the actual year-on-year capacity increase from the database (220.4 less 200.33).
B20: Closing crude steel capacity | C20: Mtpa | D20: 220.4 | E20: =D20+E19 | F20: =E20+F19 | G20: =F20+G19 | H20: =G20+H19 | I20: =H20+I19 | J20: =I20+J19 | K20: =J20+K19 | L20: =IFERROR(IF(AND(ISNUMBER(D20),ISNUMBER(K20),D20>0),(K20/D20)^(1/7)-1,""),"") | M20: 00 Database Import A04 | N20: High | O20: FY2026A of 220.4 Mtpa is the database figure (June-2026 Ministry vintage; the March vintage said 220.3 - Conflict C04).
B22: VALIDATION AGAINST NATIONAL STEEL POLICY 2017
B23: National Steel Policy 2017 target | C23: Mtpa | I23: 300 | M23: Master DB policy P10 | N23: High | O23: 300 Mtpa of crude steel capacity by FY2031.
B24: Model capacity in FY2031E | C24: Mtpa | I24: =I20 | M24: Computed | N24: High
B25: Model as % of policy target | C25: % | I25: =I24/I23 | M25: Computed | N25: High | O25: The model was built bottom-up from the project tracker plus the secondary residual and was NOT calibrated to the policy target, so agreement within roughly 1% is a genuine independent check on the capacity block.
B27: Sign warning: more capacity is EBITDA-NEGATIVE in this model, because it depresses utilisation which feeds back into price via driver D23. See 09 Steel Price Forecast.

Sheet 07 Capacity Expansion Tracker
B1: 07 Capacity Expansion Tracker
B2: Industry Financial Model | Indian Steel Industry | Horizon FY2027E-FY2033E | Base year FY2026A | Built 03-Aug-2026
B4: OBJECTIVE
B5: The dated project pipeline that drives the capacity forecast. Twenty projects, each with its capacity, status, expected commissioning year and whether it counts towards INDIA's national crude steel capacity.
B6: METHODOLOGY
B7: Every project is taken from the Master Database. The 'Included in forecast' flag is the critical field and encodes four exclusions that are routinely got wrong: already-commissioned projects are in the FY2026 base and must not be added again; ACQUISITIONS add to a company but nothing to national capacity; DOWNSTREAM lines (HRAP, CRAP, cold rolling) are processing capacity, not melt capacity; and OVERSEAS assets are outside India. Ramp-ups are utilisation, not capacity. 06 Capacity Forecast reads this sheet by SUMIFS on the flag and the year, so changing a flag or a date here immediately changes the forecast.
B8: UNITS
B9: Mtpa. Capex in Rs crore.
B10: DEPENDENCIES
B11: Source: Master Industry Database. Read by 06 Capacity Forecast and 12 Revenue.
A13: Project ID | B13: Company | C13: Project / Asset | D13: State / Country | E13: Type | F13: Capacity Added (Mtpa) | G13: Capacity Definition | H13: Status At Cutoff | I13: Expected Commissioning FY | J13: Capex (Rs cr) | K13: Implied Capex (Rs/t) | L13: Included In Forecast? | M13: Source ID | N13: Confidence | O13: Notes
A14: P01 | B14: Tata Steel | C14: Ludhiana scrap-based EAF | D14: Punjab | E14: Brownfield EAF | F14: 0.75 | G14: Crude steel | H14: Commissioned Mar-2026 | I14: FY2026 | J14: 3200 | K14: =J14/F14*10000 | L14: No - already in base | M14: S08 | N14: High | O14: Commissioned in Mar-2026 and therefore already inside the FY2026 capacity base of 220.4 Mtpa. Designed for under 0.3 tCO2e per tonne of crude steel, which makes it 5-star green steel under the Taxonomy notified 23-Dec-2024.
A15: P02 | B15: Tata Steel | C15: NINL expansion | D15: Odisha | E15: Brownfield integrated | F15: 4.8 | G15: Crude steel | H15: Proposed | I15: FY2030 | L15: Yes | M15: S08 | N15: Medium | O15: Described as proposed in the FY2026 results release, so not yet Board-approved capex. Commissioning year is the modeller's estimate based on typical 4-year build.
A16: P03 | B16: Tata Steel | C16: India roadmap to 40 Mtpa | D16: India | E16: Programme | F16: 5 | G16: Crude steel | H16: Announced - aspirational | I16: FY2033 | L16: Yes | M16: S37 | N16: Low | O16: Tata Steel's Q1FY2027 presentation (31-Jul-2026) sets out an India roadmap to 40 Mtpa. The residual above identified projects is carried at low confidence and is materially reduced by the delivery factor D05.
A17: P04 | B17: JSW Steel | C17: Vijayanagar BF-3 expansion 3.0 to 4.5 Mtpa | D17: Karnataka | E17: Brownfield BF | F17: 1.5 | G17: Crude steel | H17: Under testing and commissioning | I17: FY2027 | L17: Yes | M17: S09 | N17: High | O17: Was under testing at FY2026 year-end and excluded from the FY2026 utilisation calculation, so it is genuinely incremental to the base.
A18: P05 | B18: JSW Steel | C18: JVML-Vijayanagar brownfield expansion | D18: Karnataka | E18: Brownfield integrated | F18: 5 | G18: Crude steel | H18: Board approved | I18: FY2030 | J18: 26000 | K18: =J18/F18*10000 | L18: Yes | M18: S09 | N18: High | O18: Board approved. Rs 26,000 cr for 5 Mtpa gives Rs 52,000 per tonne, the cleanest brownfield capex-intensity datapoint available and the primary calibration for D16.
A19: P06 | B19: JSW Steel | C19: BMM Ispat acquisition | D19: Karnataka | E19: Acquisition | F19: 0.9 | G19: Crude steel | H19: Board approved | I19: FY2027 | L19: No - acquisition, not new national capacity | M19: S09 | N19: High | O19: Acquisition of existing operating capacity, so it adds to JSW Steel's own capacity and volume but adds NOTHING to India's national capacity - those tonnes are already in the 220.4 Mtpa FY2026 base. Correctly excluded from the industry capacity build. This is a standard trap: summing company announcements without stripping out acquisitions double-counts national capacity. JSW's FY2027 guidance explicitly includes BMM Ispat production of 0.75 Mt and sales of 0.70 Mt, so it IS included in the company-level volume build on sheet 12.
A20: P07 | B20: JSW Steel / POSCO | C20: Greenfield integrated plant, 50:50 JV | D20: Odisha | E20: Greenfield JV | F20: 6 | G20: Crude steel | H20: Announced Apr-2026 | I20: FY2031 | L20: Yes | M20: S09 | N20: Medium | O20: 50:50 joint venture announced Apr-2026 targeting commissioning by 2031. This is the single most distant dated project in the pipeline and is the reason the announced pipeline terminates in FY2031, which in turn drives the horizon selection.
A21: P08 | B21: SAIL | C21: IISCO Steel Plant greenfield expansion | D21: West Bengal | E21: Greenfield | F21: 4.08 | G21: Crude steel | H21: Board approved | I21: FY2031 | L21: Yes | M21: S26 | N21: High | O21: Board approved per Ministry of Steel, Rajya Sabha USQ 3982 answered 27-Mar-2026. IISCO averaged 91.6% utilisation over FY2021-FY2025 on 2.5 Mtpa.
A22: P09 | B22: SAIL | C22: Bokaro Steel Plant brownfield expansion | D22: Jharkhand | E22: Brownfield | F22: 2.65 | G22: Crude steel | H22: Board approved | I22: FY2030 | L22: Yes | M22: S26 | N22: High | O22: Board approved per the same Parliamentary answer. Bokaro averaged 87.8% utilisation on 4.6 Mtpa, so there is headroom in the existing asset as well.
A23: P10 | B23: SAIL | C23: Durgapur Steel Plant brownfield expansion | D23: West Bengal | E23: Brownfield | F23: 0.89 | G23: Crude steel | H23: Board approved | I23: FY2029 | L23: Yes | M23: S26 | N23: High | O23: Board approved. Durgapur already averaged 101.6% utilisation on 2.2 Mtpa over FY2021-FY2025, i.e. it is running above nameplate and the expansion is debottlenecking.
A24: P11 | B24: SAIL | C24: Residual ambition to ~35 Mt by FY2031 | D24: India | E24: Programme | F24: 8 | G24: Crude steel | H24: Announced - aspirational | I24: FY2033 | L24: Yes | M24: S47 | N24: Low | O24: SAIL has publicly targeted roughly 35 Mt by FY2031 against 19.676 Mtpa today at an indicated roughly Rs 1 lakh crore outlay. Board-approved tranches total only 7.62 Mtpa, so about 8 Mtpa of the ambition is unapproved and is carried at low confidence.
A25: P12 | B25: AM/NS India | C25: Hazira expansion 9 to 15 Mtpa | D25: Gujarat | E25: Brownfield integrated | F25: 6 | G25: Crude steel | H25: Under implementation | I25: FY2029 | L25: Yes | M25: S13 | N25: High | O25: Under implementation. The largest single brownfield addition in the pipeline.
A26: P13 | B26: AM/NS India | C26: Rajayyapeta greenfield, Phase 1 | D26: Andhra Pradesh | E26: Greenfield | F26: 8.2 | G26: Crude steel | H26: Announced 23-Mar-2026 | I26: FY2032 | L26: Yes | M26: S14 | N26: Medium | O26: Announced 23-Mar-2026 as a low-cost, highly efficient coastal asset. Phase 1 of 8.2 Mtpa. Greenfield of this scale in India has historically taken 5 to 7 years.
A27: P14 | B27: AM/NS India | C27: Hazira further expansion to 24 Mtpa | D27: Gujarat | E27: Brownfield | F27: 9 | G27: Crude steel | H27: Detailed engineering under way | I27: Beyond FY2033 | L27: No - beyond horizon | M27: S13 | N27: Low | O27: Detailed engineering only. Falls outside the FY2033 horizon and is therefore excluded from the capacity build. Retained in the tracker for completeness and for terminal-value context.
A28: P15 | B28: Jindal Steel | C28: Angul expansion 6.0 to 12.0 Mtpa | D28: Odisha | E28: Brownfield integrated | F28: 6 | G28: Crude steel | H28: Completed in FY2026 | I28: FY2026 | L28: No - already in base | M28: S11 | N28: High | O28: Completed during FY2026, taking group steelmaking capacity from 9.6 to 15.6 Mtpa. Already inside the FY2026 capacity base. Ironmaking capacity is being raised by a further 6.6 Mtpa with elements still under construction.
A29: P16 | B29: Jindal Stainless | C29: Indonesia stainless melt shop | D29: Indonesia | E29: Greenfield | F29: 1.2 | G29: Stainless melt | H29: Commissioned in FY2026 | I29: FY2026 | L29: No - outside India and in base | M29: S12 | N29: High | O29: Commissioned ahead of schedule in FY2026, taking group melt capacity to 4.2 Mtpa. OUTSIDE INDIA, so excluded from the India capacity build.
A30: P17 | B30: Jindal Stainless | C30: Jajpur HRAP and CRAP downstream lines | D30: Odisha | E30: Downstream | F30: 1.27 | G30: Downstream processing | H30: Upcoming | I30: FY2028 | L30: No - downstream, not melt | M30: S12 | N30: High | O30: 1.1 Mtpa HRAP plus 0.17 Mtpa CRAP. DOWNSTREAM PROCESSING, not melt capacity, so it must not be added to crude steel capacity. Included in the tracker because it drives mix and realisation, not tonnage.
A31: P18 | B31: Jindal Stainless | C31: Hisar and Kharagpur cold rolling augmentation | D31: Haryana / West Bengal | E31: Downstream | G31: Downstream processing | H31: Announced - Rs 900 cr committed | I31: FY2028 | J31: 900 | L31: No - downstream, not melt | M31: S12 | N31: High | O31: Takes CRAP capacity to 2.67 Mtpa by FY2028. Downstream only.
A32: P19 | B32: Electrosteel / ESL | C32: Bokaro capacity doubling | D32: Jharkhand | E32: Brownfield | F32: 1.5 | G32: Crude steel | H32: Announced by parent | I32: FY2027 | L32: Yes | M32: S43 | N32: Low | O32: Vedanta targeting a doubling of Bokaro from 1.5 to 3.0 Mtpa by end-CY2026. Rests on a single secondary source and is carried at low confidence.
A33: P20 | B33: NMDC Steel | C33: Nagarnar ramp-up to nameplate | D33: Chhattisgarh | E33: Ramp-up | G33: Crude steel | H33: Ramping | I33: FY2028 | L33: No - utilisation, not capacity | M33: S01 | N33: High | O33: The 3 Mtpa plant produced 2.382 Mt in FY2026, up 61.9%. The remaining roughly 0.6 Mt is a UTILISATION gain within existing capacity, not new capacity, and is captured through the utilisation forecast rather than the capacity build. Included here because it is one of the two empirical ramp-rate observations underpinning the horizon choice.
B35: SUMMARY - GROSS ANNOUNCED INDIA CRUDE STEEL ADDITIONS BY YEAR (live SUMIFS)
B36: Included projects only | C36: Mtpa | E36: =SUMIFS($F$14:$F$33,$I$14:$I$33,"FY2027",$L$14:$L$33,"Yes") | F36: =SUMIFS($F$14:$F$33,$I$14:$I$33,"FY2028",$L$14:$L$33,"Yes") | G36: =SUMIFS($F$14:$F$33,$I$14:$I$33,"FY2029",$L$14:$L$33,"Yes") | H36: =SUMIFS($F$14:$F$33,$I$14:$I$33,"FY2030",$L$14:$L$33,"Yes") | I36: =SUMIFS($F$14:$F$33,$I$14:$I$33,"FY2031",$L$14:$L$33,"Yes") | J36: =SUMIFS($F$14:$F$33,$I$14:$I$33,"FY2032",$L$14:$L$33,"Yes") | K36: =SUMIFS($F$14:$F$33,$I$14:$I$33,"FY2033",$L$14:$L$33,"Yes") | O36: Live SUMIFS across the table above. Matches on the commissioning year AND on the inclusion flag being exactly 'Yes'.
B38: Total gross announced additions, FY2027E-FY2033E | C38: Mtpa | D38: =SUM(E36:K36) | O38: 53.62 Mtpa of individually announced projects. Note this averages only 7.7 Mtpa a year against India's ACTUAL 20.8 and 20.1 Mtpa additions in FY2025 and FY2026, which is precisely why driver D22 exists - see 06.

Sheet 08 Capacity Utilisation
B1: 08 Capacity Utilisation
B2: Industry Financial Model | Indian Steel Industry | Horizon FY2027E-FY2033E | Base year FY2026A | Built 03-Aug-2026
B4: OBJECTIVE
B5: The bridge between the capacity and supply blocks, and the input to the price feedback that makes this model integrated.
B6: METHODOLOGY
B7: Utilisation equals crude steel production divided by closing capacity. The utilisation GAP against normal utilisation of 80% is the quantity that drives the lagged price adjustment on 09 Steel Price Forecast. Normal utilisation of 80% is anchored on actual Indian utilisation from the database - 80.4% in FY2024, 76.0% in FY2025 and 76.4% in FY2026 - with FY2024's recent high adopted as normal.
B8: UNITS
B9: Percentages as decimals. Mt for headroom.
B10: DEPENDENCIES
B11: Reads 05 Steel Supply and 06 Capacity Forecast. Read by 09 Steel Price and 18 Cycle.
B13: Line item | C13: Unit | D13: FY2026A | E13: FY2027E | F13: FY2028E | G13: FY2029E | H13: FY2030E | I13: FY2031E | J13: FY2032E | K13: FY2033E | L13: CAGR | M13: Source | N13: Conf. | O13: Notes / methodology
B14: Crude steel production | C14: Mt | D14: 168.42 | E14: ='05 Steel Supply Model'!E$25 | F14: ='05 Steel Supply Model'!F$25 | G14: ='05 Steel Supply Model'!G$25 | H14: ='05 Steel Supply Model'!H$25 | I14: ='05 Steel Supply Model'!I$25 | J14: ='05 Steel Supply Model'!J$25 | K14: ='05 Steel Supply Model'!K$25 | M14: 05 Supply | N14: High
B15: Crude steel capacity | C15: Mtpa | D15: 220.4 | E15: ='06 Capacity Forecast'!E$20 | F15: ='06 Capacity Forecast'!F$20 | G15: ='06 Capacity Forecast'!G$20 | H15: ='06 Capacity Forecast'!H$20 | I15: ='06 Capacity Forecast'!I$20 | J15: ='06 Capacity Forecast'!J$20 | K15: ='06 Capacity Forecast'!K$20 | M15: 06 Capacity | N15: High
B16: Capacity utilisation | C16: % | D16: 0.76415608 | E16: =E14/E15 | F16: =F14/F15 | G16: =G14/G15 | H16: =H14/H15 | I16: =I14/I15 | J16: =J14/J15 | K16: =K14/K15 | M16: Computed | N16: High | O16: FY2026A of 76.4%. Uses closing capacity as the denominator, so it understates true utilisation in heavy commissioning years - the same convention as the database.
B17: Normal utilisation | C17: % | E17: '02 Model Assumptions'!E$145 | F17: '02 Model Assumptions'!F$145 | G17: '02 Model Assumptions'!G$145 | H17: '02 Model Assumptions'!H$145 | I17: '02 Model Assumptions'!I$145 | J17: '02 Model Assumptions'!J$145 | K17: '02 Model Assumptions'!K$145 | M17: Derived from Master DB | N17: Medium | O17: 80%, anchored on the FY2024 actual of 80.4%.
B18: Utilisation gap vs normal | C18: ppt | E18: =E16-E17 | F18: =F16-F17 | G18: =G16-G17 | H18: =H16-H17 | I18: =I16-I17 | J18: =J16-J17 | K18: =K16-K17 | M18: Computed | N18: High | O18: THE DRIVER OF THE PRICE FEEDBACK. Positive means tight capacity supporting price; negative means surplus capacity depressing it. Used with a one-year lag on 09.
B19: Spare capacity | C19: Mt | E19: =E15-E14 | F19: =F15-F14 | G19: =G15-G14 | H19: =H15-H14 | I19: =I15-I14 | J19: =J15-J14 | K19: =K15-K14 | M19: Computed | N19: High | O19: Idle capacity. Large and persistent spare capacity is the structural reason the base case forecasts realisation growing below inflation.
B21: FY2026 utilisation of 76.4% against 80.4% in FY2024 is the single most important structural fact in the Indian steel investment case: capacity has been added faster than demand, which caps domestic pricing power and is why a safeguard duty was needed.

Sheet 09 Steel Price Forecast
B1: 09 Steel Price Forecast
B2: Industry Financial Model | Indian Steel Industry | Horizon FY2027E-FY2033E | Base year FY2026A | Built 03-Aug-2026
B4: OBJECTIVE
B5: Forecasts blended industry realisation, including the lagged utilisation feedback that connects the capacity block to earnings.
B6: METHODOLOGY
B7: The base-year anchor is a DERIVED blended realisation of Rs 59,974/t: the volume-weighted revenue per tonne of Tata Steel India, JSW Steel India, SAIL and Jindal Steel from the database - Rs 4,79,191 cr over 79.90 Mt, covering 49.4% of India's finished steel production. A blended realisation is used rather than a spot HRC quote for two reasons: the database documents three irreconcilable Mar-2026 HRC assessments spanning Rs 55,900 to Rs 59,500/t (Conflict C07), and revenue is driven by actual product mix, not by HRC alone. Effective realisation then equals the scenario driver multiplied by (1 + elasticity x prior-year utilisation gap).
B8: UNITS
B9: Rs per tonne. Percentages as decimals.
B10: DEPENDENCIES
B11: Reads 02 Model Assumptions and 08 Capacity Utilisation. Read by 12 Revenue, 13 EBITDA, 14 Margin.
B13: Line item | C13: Unit | D13: FY2026A | E13: FY2027E | F13: FY2028E | G13: FY2029E | H13: FY2030E | I13: FY2031E | J13: FY2032E | K13: FY2033E | L13: CAGR | M13: Source | N13: Conf. | O13: Notes / methodology
B14: DRIVER REALISATION (before the utilisation feedback)
B15: Blended realisation - scenario driver | C15: Rs/t | D15: 59974 | E15: '02 Model Assumptions'!E$130 | F15: '02 Model Assumptions'!F$130 | G15: '02 Model Assumptions'!G$130 | H15: '02 Model Assumptions'!H$130 | I15: '02 Model Assumptions'!I$130 | J15: '02 Model Assumptions'!J$130 | K15: '02 Model Assumptions'!K$130 | M15: Derived from Master DB | N15: Medium | O15: FY2026A of Rs 59,974/t is derived, not quoted. Component realisations: Tata Steel India Rs 62,273/t, JSW Steel India Rs 60,798/t, Jindal Steel Rs 61,319/t, SAIL Rs 55,600/t. Jindal Stainless is EXCLUDED at roughly Rs 1,67,000/t because stainless is not comparable.
B17: UTILISATION FEEDBACK (lagged one year - no circular reference)
B18: Prior-year capacity utilisation | C18: % | E18: ='08 Capacity Utilisation'!D$16 | F18: ='08 Capacity Utilisation'!E$16 | G18: ='08 Capacity Utilisation'!F$16 | H18: ='08 Capacity Utilisation'!G$16 | I18: ='08 Capacity Utilisation'!H$16 | J18: ='08 Capacity Utilisation'!I$16 | K18: ='08 Capacity Utilisation'!J$16 | M18: 08 Utilisation (lagged) | N18: High | O18: Deliberately the PRIOR year. FY2027E uses the FY2026A actual of 76.4%. The lag is what allows capacity to affect price without creating a circular reference.
B19: Normal utilisation | C19: % | E19: '02 Model Assumptions'!E$145 | F19: '02 Model Assumptions'!F$145 | G19: '02 Model Assumptions'!G$145 | H19: '02 Model Assumptions'!H$145 | I19: '02 Model Assumptions'!I$145 | J19: '02 Model Assumptions'!J$145 | K19: '02 Model Assumptions'!K$145 | M19: Derived from Master DB | N19: Medium
B20: Price sensitivity to utilisation | C20: x | E20: '02 Model Assumptions'!E$144 | F20: '02 Model Assumptions'!F$144 | G20: '02 Model Assumptions'!G$144 | H20: '02 Model Assumptions'!H$144 | I20: '02 Model Assumptions'!I$144 | J20: '02 Model Assumptions'!J$144 | K20: '02 Model Assumptions'!K$144 | M20: Indicative | N20: Low | O20: 0.40x. INDICATIVE and unsourced, held constant across scenarios for that reason, and given a sensitivity axis on 22.
B21: Price adjustment factor | C21: x | D21: 1 | E21: =1+E20*(E18-E19) | F21: =1+F20*(F18-F19) | G21: =1+G20*(G18-G19) | H21: =1+H20*(H18-H19) | I21: =1+I20*(I18-I19) | J21: =1+J20*(J18-J19) | K21: =1+K20*(K18-K19) | M21: Computed | N21: Low | O21: Below 1.0 means surplus capacity is depressing realisation; above 1.0 means tight capacity is supporting it.
B22: Blended realisation - effective | C22: Rs/t | D22: 59974 | E22: =E15*E21 | F22: =F15*F21 | G22: =G15*G21 | H22: =H15*H21 | I22: =I15*I21 | J22: =J15*J21 | K22: =K15*K21 | L22: =IFERROR(IF(AND(ISNUMBER(D22),ISNUMBER(K22),D22>0),(K22/D22)^(1/7)-1,""),"") | M22: Computed | N22: Medium | O22: THE REVENUE DRIVER. This, not the raw driver above, is what 12 Revenue reads.
B24: REFERENCE PRICES AND POLICY
B25: Memo: domestic HRC, end-Mar-2026 (ICRA) | C25: Rs/t | D25: 57700 | M25: Master DB S19 | N25: High | O25: The database's recommended HRC reference. Shown as a memo only - the model runs on blended realisation. IDBI put Mar-2026 at Rs 59,500/t and ETInfra at Rs 55,900/t (Conflict C07).
B26: Memo: HRC 52-week range to Jun-2026 | C26: Rs/t | E26: Rs 45,700 - 59,600/t | M26: Master DB S21 | N26: High | O26: A ~30% range. The single largest source of FY2027 earnings uncertainty.
B27: Safeguard duty on flat products | C27: % | D27: 0.12 | E27: 0.115 | F27: 0.11 | G27: 0 | H27: 0 | I27: 0 | J27: 0 | K27: 0 | M27: Master DB policy P03 | N27: High | O27: SCHEDULE, NOT A FORECAST. 12% for 21-Apr-2025 to 20-Apr-2026 (FY2026), 11.5% from 21-Apr-2026 (FY2027), 11% from 21-Apr-2027 (FY2028), expiring 20-Apr-2028. Zero thereafter unless extended - a mid-term review is provided for. The FY2029 step to zero is why the base case realisation path dips in FY2028-FY2029.
B29: The duty covers FLAT products only, which is why the database records primary rebar rising 25% against HRC's 18% between the Dec-2025 quarter and Mar-2026.

Sheet 10 Raw Material Forecast
B1: 10 Raw Material Forecast
B2: Industry Financial Model | Indian Steel Industry | Horizon FY2027E-FY2033E | Base year FY2026A | Built 03-Aug-2026
B4: OBJECTIVE
B5: Forecasts the input basket - iron ore, coking coal and the exchange rate - and builds the raw-material cost index that drives cash cost.
B6: METHODOLOGY
B7: Dollar prices are converted to rupees at the forecast exchange rate, then indexed to FY2026. The basket weights iron ore and coking coal at 45% each with 10% other, which is INDICATIVE and unsourced. The resulting index, together with a conversion cost index compounding inflation, drives cash cost on 11 Cost Curve.
B8: UNITS
B9: US dollars per tonne as quoted; rupees per tonne after conversion. Indices FY2026A = 1.00.
B10: DEPENDENCIES
B11: Reads 02 Model Assumptions and 03 Macroeconomic Model. Read by 11 Cost Curve.
B13: Line item | C13: Unit | D13: FY2026A | E13: FY2027E | F13: FY2028E | G13: FY2029E | H13: FY2030E | I13: FY2031E | J13: FY2032E | K13: FY2033E | L13: CAGR | M13: Source | N13: Conf. | O13: Notes / methodology
B14: DOLLAR PRICES
B15: Iron ore 62% Fe fines, CFR China | C15: US$/dmt | D15: 100.52 | E15: '02 Model Assumptions'!E$131 | F15: '02 Model Assumptions'!F$131 | G15: '02 Model Assumptions'!G$131 | H15: '02 Model Assumptions'!H$131 | I15: '02 Model Assumptions'!I$131 | J15: '02 Model Assumptions'!J$131 | K15: '02 Model Assumptions'!K$131 | M15: Master DB S17 (World Bank) | N15: High | O15: FY2026A of US$100.52/dmt is a genuine 12-month average from the World Bank Pink Sheet - the highest-quality price series in the model. Third consecutive annual decline from US$155.52/dmt in FY2022. Q1FY2027 actual averaged US$105.17/dmt.
B16: Premium HCC coking coal, FOB Australia | C16: US$/t | D16: 225 | E16: '02 Model Assumptions'!E$132 | F16: '02 Model Assumptions'!F$132 | G16: '02 Model Assumptions'!G$132 | H16: '02 Model Assumptions'!H$132 | I16: '02 Model Assumptions'!I$132 | J16: '02 Model Assumptions'!J$132 | K16: '02 Model Assumptions'!K$132 | M16: Master DB S01 (Ministry of Steel) | N16: Medium | O16: FY2026A of US$225/t is the Ministry of Steel's MAR-2026 SPOT observation, NOT a fiscal-year average - the database deliberately asserts no average because the two public series disagree by up to US$40/t (Conflict C01). THE LARGEST COST UNCERTAINTY IN THE MODEL. Replace with a licensed PRA series before transaction use.
B17: USD/INR | C17: Rs/US$ | D17: 88.4 | E17: ='03 Macroeconomic Model'!E$21 | F17: ='03 Macroeconomic Model'!F$21 | G17: ='03 Macroeconomic Model'!G$21 | H17: ='03 Macroeconomic Model'!H$21 | I17: ='03 Macroeconomic Model'!I$21 | J17: ='03 Macroeconomic Model'!J$21 | K17: ='03 Macroeconomic Model'!K$21 | M17: 03 Macro | N17: High
B19: RUPEE-CONVERTED PRICES
B20: Iron ore in rupees | C20: Rs/dmt | D20: 8885.968 | E20: =E15*E17 | F20: =F15*F17 | G20: =G15*G17 | H20: =H15*H17 | I20: =I15*I17 | J20: =J15*J17 | K20: =K15*K17 | L20: =IFERROR(IF(AND(ISNUMBER(D20),ISNUMBER(K20),D20>0),(K20/D20)^(1/7)-1,""),"") | M20: Computed | N20: High | O20: This is where the FX channel enters cost: a weaker rupee raises input cost even if the dollar price is flat.
B21: Coking coal in rupees | C21: Rs/t | D21: 19890 | E21: =E16*E17 | F21: =F16*F17 | G21: =G16*G17 | H21: =H16*H17 | I21: =I16*I17 | J21: =J16*J17 | K21: =K16*K17 | L21: =IFERROR(IF(AND(ISNUMBER(D21),ISNUMBER(K21),D21>0),(K21/D21)^(1/7)-1,""),"") | M21: Computed | N21: Medium
B23: COST INDICES
B24: Conversion cost inflation | C24: % | E24: '02 Model Assumptions'!E$133 | F24: '02 Model Assumptions'!F$133 | G24: '02 Model Assumptions'!G$133 | H24: '02 Model Assumptions'!H$133 | I24: '02 Model Assumptions'!I$133 | J24: '02 Model Assumptions'!J$133 | K24: '02 Model Assumptions'!K$133 | M24: RBI-anchored | N24: Medium | O24: Applies to labour, power, consumables, stores, repairs and logistics. Set below RBI's 5.1% FY2027 CPI because conversion cost tracks energy rather than headline CPI and because the majors are delivering cost programmes - Tata Steel recorded roughly Rs 10,868 cr of benefit in FY2026, about Rs 4,825 per tonne of India deliveries.
B25: Conversion cost index | C25: x | D25: 1 | E25: =D25*(1+E24) | F25: =E25*(1+F24) | G25: =F25*(1+G24) | H25: =G25*(1+H24) | I25: =H25*(1+I24) | J25: =I25*(1+J24) | K25: =J25*(1+K24) | M25: Computed | N25: Medium | O25: Compounds the inflation rate above.
B26: Iron ore weight in basket | C26: % | E26: '02 Model Assumptions'!E$135 | F26: '02 Model Assumptions'!F$135 | G26: '02 Model Assumptions'!G$135 | H26: '02 Model Assumptions'!H$135 | I26: '02 Model Assumptions'!I$135 | J26: '02 Model Assumptions'!J$135 | K26: '02 Model Assumptions'!K$135 | M26: Indicative | N26: Low | O26: 45% iron ore, 45% coking coal, 10% other ferrous and fluxes. INDICATIVE and unsourced; held constant across scenarios and given a sensitivity axis on 22.
B27: Raw material cost index | C27: x | D27: 1 | E27: =E26*(E20/$D$20)+E26*(E21/$D$21)+(1-2*E26)*E25 | F27: =F26*(F20/$D$20)+F26*(F21/$D$21)+(1-2*F26)*F25 | G27: =G26*(G20/$D$20)+G26*(G21/$D$21)+(1-2*G26)*G25 | H27: =H26*(H20/$D$20)+H26*(H21/$D$21)+(1-2*H26)*H25 | I27: =I26*(I20/$D$20)+I26*(I21/$D$21)+(1-2*I26)*I25 | J27: =J26*(J20/$D$20)+J26*(J21/$D$21)+(1-2*J26)*J25 | K27: =K26*(K20/$D$20)+K26*(K21/$D$21)+(1-2*K26)*K25 | M27: Computed | N27: Low | O27: Weighted index of rupee input prices relative to FY2026, with the residual 10% indexed to conversion inflation.
B29: The Australian THERMAL coal series in the database (FY2026 average US$111.50/mt) is deliberately NOT used here. It is thermal, not metallurgical, coal - see database Conflict C15.

Sheet 11 Cost Curve
B1: 11 Cost Curve
B2: Industry Financial Model | Indian Steel Industry | Horizon FY2027E-FY2033E | Base year FY2026A | Built 03-Aug-2026
B4: OBJECTIVE
B5: Forecasts industry cash cost per tonne and positions each covered producer on the cost curve.
B6: METHODOLOGY
B7: CALIBRATED TOP-DOWN, NOT BUILT BOTTOM-UP. The FY2026 anchor of Rs 49,241/t is derived as blended realisation of Rs 59,974/t less weighted EBITDA of Rs 10,733/t, both from the database. It is forecast by splitting cash cost into a raw-material component indexed to the input basket and a conversion component indexed to inflation. A bottom-up build with consumption coefficients - tonnes of ore and coal per tonne of steel - was deliberately NOT attempted because those coefficients could not be sourced from any primary document, and inventing them would create false precision in the single most important cost line in the model.
B8: UNITS
B9: Rs per tonne.
B10: DEPENDENCIES
B11: Reads 09 Steel Price and 10 Raw Material. Read by 13 EBITDA and 14 Margin.
B13: Line item | C13: Unit | D13: FY2026A | E13: FY2027E | F13: FY2028E | G13: FY2029E | H13: FY2030E | I13: FY2031E | J13: FY2032E | K13: FY2033E | L13: CAGR | M13: Source | N13: Conf. | O13: Notes / methodology
B14: Raw material share of cash cost | C14: % | E14: '02 Model Assumptions'!E$134 | F14: '02 Model Assumptions'!F$134 | G14: '02 Model Assumptions'!G$134 | H14: '02 Model Assumptions'!H$134 | I14: '02 Model Assumptions'!I$134 | J14: '02 Model Assumptions'!J$134 | K14: '02 Model Assumptions'!K$134 | M14: Indicative | N14: Low | O14: 60/40 raw material to conversion. INDICATIVE and unsourced. Plausible range 55-65%; a 5ppt change alters FY2033 EBITDA/t by roughly Rs 600/t.
B15: Raw material cost index | C15: x | D15: 1 | E15: ='10 Raw Material Forecast'!E$27 | F15: ='10 Raw Material Forecast'!F$27 | G15: ='10 Raw Material Forecast'!G$27 | H15: ='10 Raw Material Forecast'!H$27 | I15: ='10 Raw Material Forecast'!I$27 | J15: ='10 Raw Material Forecast'!J$27 | K15: ='10 Raw Material Forecast'!K$27 | M15: 10 Raw Material | N15: Low
B16: Conversion cost index | C16: x | D16: 1 | E16: ='10 Raw Material Forecast'!E$25 | F16: ='10 Raw Material Forecast'!F$25 | G16: ='10 Raw Material Forecast'!G$25 | H16: ='10 Raw Material Forecast'!H$25 | I16: ='10 Raw Material Forecast'!I$25 | J16: ='10 Raw Material Forecast'!J$25 | K16: ='10 Raw Material Forecast'!K$25 | M16: 10 Raw Material | N16: Medium
B17: Industry cash cost per tonne | C17: Rs/t | D17: 49241 | E17: =$D$17*(E14*E15+(1-E14)*E16) | F17: =$D$17*(F14*F15+(1-F14)*F16) | G17: =$D$17*(G14*G15+(1-G14)*G16) | H17: =$D$17*(H14*H15+(1-H14)*H16) | I17: =$D$17*(I14*I15+(1-I14)*I16) | J17: =$D$17*(J14*J15+(1-J14)*J16) | K17: =$D$17*(K14*K15+(1-K14)*K16) | L17: =IFERROR(IF(AND(ISNUMBER(D17),ISNUMBER(K17),D17>0),(K17/D17)^(1/7)-1,""),"") | M17: Computed - calibrated | N17: Medium | O17: FY2026A of Rs 49,241/t is derived from the database. Dispersion across the four majors is only Rs 3,777/t, under 8%, which supports the weighted figure being representative rather than an artefact of one company.
B19: PRODUCER COST CURVE - FY2026A ACTUAL AND FORECAST
B20: Each producer's FY2026 implied cash cost is realisation less reported EBITDA/t. The forecast holds each producer's SPREAD to the industry constant, which assumes relative competitive position is stable - a strong assumption, stated explicitly.
B21: Line item | C21: Unit | D21: FY2026A | E21: FY2027E | F21: FY2028E | G21: FY2029E | H21: FY2030E | I21: FY2031E | J21: FY2032E | K21: FY2033E | L21: CAGR | M21: Source | N21: Conf. | O21: Notes / methodology
B22: Tata Steel - cash cost | C22: Rs/t | D22: 47060 | E22: =E17+(-2181) | F22: =F17+(-2181) | G22: =G17+(-2181) | H22: =H17+(-2181) | I22: =I17+(-2181) | J22: =J17+(-2181) | K22: =K17+(-2181) | M22: Master DB | N22: Medium | O22: FY2026 realisation Rs 62,273/t less reported EBITDA Rs 15,213/t. Spread to industry -2181 Rs/t, held constant in the forecast.
B23: SAIL - cash cost | C23: Rs/t | D23: 49004 | E23: =E17+(-237) | F23: =F17+(-237) | G23: =G17+(-237) | H23: =H17+(-237) | I23: =I17+(-237) | J23: =J17+(-237) | K23: =K17+(-237) | M23: Master DB | N23: Medium | O23: FY2026 realisation Rs 55,600/t less reported EBITDA Rs 6,596/t. Spread to industry -237 Rs/t, held constant in the forecast.
B24: JSW Steel - cash cost | C24: Rs/t | D24: 50631 | E24: =E17+1390 | F24: =F17+1390 | G24: =G17+1390 | H24: =H17+1390 | I24: =I17+1390 | J24: =J17+1390 | K24: =K17+1390 | M24: Master DB | N24: Medium | O24: FY2026 realisation Rs 60,798/t less reported EBITDA Rs 10,167/t. Spread to industry +1390 Rs/t, held constant in the forecast.
B25: Jindal Steel - cash cost | C25: Rs/t | D25: 50837 | E25: =E17+1596 | F25: =F17+1596 | G25: =G17+1596 | H25: =H17+1596 | I25: =I17+1596 | J25: =J17+1596 | K25: =K17+1596 | M25: Master DB | N25: Medium | O25: FY2026 realisation Rs 61,319/t less reported EBITDA Rs 10,482/t. Spread to industry +1596 Rs/t, held constant in the forecast.
B27: Cost-curve position is the primary determinant of who survives a downturn. On FY2026 actuals Tata Steel India sits roughly Rs 2,180/t BELOW the industry weighted cash cost and Jindal Steel roughly Rs 1,600/t above it - a Rs 3,780/t spread between best and worst of the four, equal to about 35% of industry EBITDA per tonne.

Sheet 12 Revenue Forecast
B1: 12 Revenue Forecast
B2: Industry Financial Model | Indian Steel Industry | Horizon FY2027E-FY2033E | Base year FY2026A | Built 03-Aug-2026
B4: OBJECTIVE
B5: Industry revenue and a company-level revenue build for the covered producers.
B6: METHODOLOGY
B7: Industry revenue equals finished steel production multiplied by effective blended realisation. The unit bridge is explicit: Rs/t multiplied by Mt divided by 10 gives Rs crore. Company volumes grow from their FY2026 actual by their own tracked capacity additions multiplied by the industry utilisation rate, so a company only gets volume if the industry can absorb it. Company realisation moves with the industry index, preserving each producer's observed FY2026 mix premium or discount.
B8: UNITS
B9: Rs crore. Volumes in Mt.
B10: DEPENDENCIES
B11: Reads 05 Steel Supply, 09 Steel Price, 07 Tracker. Read by 13, 14, 15, 16, 23.
B13: Line item | C13: Unit | D13: FY2026A | E13: FY2027E | F13: FY2028E | G13: FY2029E | H13: FY2030E | I13: FY2031E | J13: FY2032E | K13: FY2033E | L13: CAGR | M13: Source | N13: Conf. | O13: Notes / methodology
B14: Finished steel production | C14: Mt | D14: 160.94 | E14: ='05 Steel Supply Model'!E$27 | F14: ='05 Steel Supply Model'!F$27 | G14: ='05 Steel Supply Model'!G$27 | H14: ='05 Steel Supply Model'!H$27 | I14: ='05 Steel Supply Model'!I$27 | J14: ='05 Steel Supply Model'!J$27 | K14: ='05 Steel Supply Model'!K$27 | M14: 05 Supply | N14: High
B15: Blended realisation - effective | C15: Rs/t | D15: 59974 | E15: ='09 Steel Price Forecast'!E$22 | F15: ='09 Steel Price Forecast'!F$22 | G15: ='09 Steel Price Forecast'!G$22 | H15: ='09 Steel Price Forecast'!H$22 | I15: ='09 Steel Price Forecast'!I$22 | J15: ='09 Steel Price Forecast'!J$22 | K15: ='09 Steel Price Forecast'!K$22 | M15: 09 Price | N15: Medium
B16: INDUSTRY REVENUE | C16: Rs cr | D16: 965221.56 | E16: =E14*E15/10 | F16: =F14*F15/10 | G16: =G14*G15/10 | H16: =H14*H15/10 | I16: =I14*I15/10 | J16: =J14*J15/10 | K16: =K14*K15/10 | L16: =IFERROR(IF(AND(ISNUMBER(D16),ISNUMBER(K16),D16>0),(K16/D16)^(1/7)-1,""),"") | M16: Computed | N16: Medium | O16: Unit bridge: Rs/t x Mt / 10 = Rs crore, because 1 Rs crore = 1e7 Rs and 1 Mt = 1e6 tonnes. FY2026A of Rs 9,65,238 cr is the whole-of-India finished steel revenue pool, against Rs 4,79,191 cr for the four majors that anchor realisation - i.e. the calibration sample is 49.6% of the pool by revenue.
B19: COMPANY VOLUME BUILD
B20: Line item | C20: Unit | D20: FY2026A | E20: FY2027E | F20: FY2028E | G20: FY2029E | H20: FY2030E | I20: FY2031E | J20: FY2032E | K20: FY2033E | L20: CAGR | M20: Source | N20: Conf. | O20: Notes / methodology
B21: Tata Steel - volume | C21: Mt | D21: 22.53 | E21: =D21 | F21: =E21 | G21: =F21 | H21: =G21+4.8*'08 Capacity Utilisation'!H$16 | I21: =H21 | J21: =I21 | K21: =J21+5.0*'08 Capacity Utilisation'!K$16 | L21: =IFERROR(IF(AND(ISNUMBER(D21),ISNUMBER(K21),D21>0),(K21/D21)^(1/7)-1,""),"") | M21: S08 | N21: Medium | O21: India segment used for volume and margin. Netherlands carries a disclosed material uncertainty related to going concern (Master DB, policy P18) - the single largest identifiable downside in the universe and NOT captured in this industry model, which forecasts India only.. Basis: India deliveries. Tracked additions: FY2030 +4.80 Mtpa, FY2033 +5.00 Mtpa
B22: JSW Steel - volume | C22: Mt | D22: 28.76 | E22: =D22+2.4*'08 Capacity Utilisation'!E$16 | F22: =E22 | G22: =F22 | H22: =G22+5.0*'08 Capacity Utilisation'!H$16 | I22: =H22+6.0*'08 Capacity Utilisation'!I$16 | J22: =I22 | K22: =J22 | L22: =IFERROR(IF(AND(ISNUMBER(D22),ISNUMBER(K22),D22>0),(K22/D22)^(1/7)-1,""),"") | M22: S09 | N22: Medium | O22: FY2027 additions include BMM Ispat (0.90 Mtpa), an acquisition of existing capacity: it adds to JSW but NOT to national capacity. BPSL was deconsolidated from 27-Mar-2026, so FY2026 to FY2027 company volumes are not like-for-like.. Basis: India steel sales. Tracked additions: FY2027 +2.40 Mtpa, FY2030 +5.00 Mtpa, FY2031 +6.00 Mtpa
B23: SAIL - volume | C23: Mt | D23: 19.93 | E23: =D23 | F23: =E23 | G23: =F23+0.89*'08 Capacity Utilisation'!G$16 | H23: =G23+2.65*'08 Capacity Utilisation'!H$16 | I23: =H23+4.08*'08 Capacity Utilisation'!I$16 | J23: =I23 | K23: =J23+8.0*'08 Capacity Utilisation'!K$16 | L23: =IFERROR(IF(AND(ISNUMBER(D23),ISNUMBER(K23),D23>0),(K23/D23)^(1/7)-1,""),"") | M23: S10 | N23: Medium | O23: EBITDA per tonne is struck on the STANDALONE EBITDA headline over standalone sales volume. Do not pair a consolidated enterprise value with this EBITDA - see Master DB Conflict C09.. Basis: Standalone sales volume. Tracked additions: FY2029 +0.89 Mtpa, FY2030 +2.65 Mtpa, FY2031 +4.08 Mtpa, FY2033 +8.00 Mtpa
B24: Jindal Steel - volume | C24: Mt | D24: 8.68 | E24: =D24 | F24: =E24 | G24: =F24 | H24: =G24 | I24: =H24 | J24: =I24 | K24: =J24 | L24: =IFERROR(IF(AND(ISNUMBER(D24),ISNUMBER(K24),D24>0),(K24/D24)^(1/7)-1,""),"") | M24: S11 | N24: Medium | O24: Capacity rose from 9.6 to 15.6 Mtpa in FY2026, so FY2027 volume growth comes from utilising capacity already built rather than from new additions. Company guidance for FY2027 is 11.0-11.5 Mt of production against 9.25 Mt in FY2026.. Basis: Consolidated steel sales. No tracked additions - volume growth comes from utilising capacity already built.
B25: Jindal Stainless - volume | C25: Mt | D25: 2.57 | E25: =D25 | F25: =E25 | G25: =F25 | H25: =G25 | I25: =H25 | J25: =I25 | K25: =J25 | L25: =IFERROR(IF(AND(ISNUMBER(D25),ISNUMBER(K25),D25>0),(K25/D25)^(1/7)-1,""),"") | M25: S12 | N25: Medium | O25: STAINLESS. Realisation of roughly Rs 1,67,000/t and EBITDA per tonne of Rs 21,634 are not comparable with carbon steel and this company is EXCLUDED from the blended industry realisation anchor. Management guided FY2027 EBITDA per tonne to Rs 18,000-20,000, i.e. BELOW the FY2026 outcome.. Basis: Consolidated deliveries. No tracked additions - volume growth comes from utilising capacity already built.
B26: AM/NS India - volume | C26: Mt | D26: 7.975 | E26: =D26 | F26: =E26 | G26: =F26+6.0*'08 Capacity Utilisation'!G$16 | H26: =G26 | I26: =H26 | J26: =I26+8.2*'08 Capacity Utilisation'!J$16 | K26: =J26 | L26: =IFERROR(IF(AND(ISNUMBER(D26),ISNUMBER(K26),D26>0),(K26/D26)^(1/7)-1,""),"") | M26: S13/S14 | N26: Medium | O26: Unlisted 60:40 joint venture. All figures are 100% basis, USD, calendar quarters, converted at the derived FY2026 average USD/INR of 88.4. The fiscal-year figures are themselves derived by summing calendar quarters - Master DB Conflict C16.. Basis: Derived FY2026 shipments (sum of calendar quarters). Tracked additions: FY2029 +6.00 Mtpa, FY2032 +8.20 Mtpa
B27: RINL - volume | C27: Mt | D27: 4.4 | E27: =D27 | F27: =E27 | G27: =F27 | H27: =G27 | I27: =H27 | J27: =I27 | K27: =J27 | L27: =IFERROR(IF(AND(ISNUMBER(D27),ISNUMBER(K27),D27>0),(K27/D27)^(1/7)-1,""),"") | M27: S16 | N27: Medium | O27: Unlisted and wholly Government-owned. No EBITDA, balance sheet or valuation data is publicly available, so RINL appears in the volume build only.. Basis: Standalone sales volume (issuer rounded). No tracked additions - volume growth comes from utilising capacity already built.
B29: COMPANY REVENUE BUILD
B30: Line item | C30: Unit | D30: FY2026A | E30: FY2027E | F30: FY2028E | G30: FY2029E | H30: FY2030E | I30: FY2031E | J30: FY2032E | K30: FY2033E | L30: CAGR | M30: Source | N30: Conf. | O30: Notes / methodology
B31: Tata Steel - revenue | C31: Rs cr | D31: 140302 | E31: =E21*E15*1.038340/10 | F31: =F21*F15*1.038340/10 | G31: =G21*G15*1.038340/10 | H31: =H21*H15*1.038340/10 | I31: =I21*I15*1.038340/10 | J31: =J21*J15*1.038340/10 | K31: =K21*K15*1.038340/10 | L31: =IFERROR(IF(AND(ISNUMBER(D31),ISNUMBER(K31),D31>0),(K31/D31)^(1/7)-1,""),"") | M31: S08 | N31: Medium | O31: FY2026 realisation Rs 62,273/t = 1.04x the industry blend, held constant. Basis: India.
B32: JSW Steel - revenue | C32: Rs cr | D32: 174854 | E32: =E22*E15*1.013733/10 | F32: =F22*F15*1.013733/10 | G32: =G22*G15*1.013733/10 | H32: =H22*H15*1.013733/10 | I32: =I22*I15*1.013733/10 | J32: =J22*J15*1.013733/10 | K32: =K22*K15*1.013733/10 | L32: =IFERROR(IF(AND(ISNUMBER(D32),ISNUMBER(K32),D32>0),(K32/D32)^(1/7)-1,""),"") | M32: S09 | N32: Medium | O32: FY2026 realisation Rs 60,797/t = 1.01x the industry blend, held constant. Basis: India operations.
B33: SAIL - revenue | C33: Rs cr | D33: 110811 | E33: =E23*E15*0.927070/10 | F33: =F23*F15*0.927070/10 | G33: =G23*G15*0.927070/10 | H33: =H23*H15*0.927070/10 | I33: =I23*I15*0.927070/10 | J33: =J23*J15*0.927070/10 | K33: =K23*K15*0.927070/10 | L33: =IFERROR(IF(AND(ISNUMBER(D33),ISNUMBER(K33),D33>0),(K33/D33)^(1/7)-1,""),"") | M33: S10 | N33: Medium | O33: FY2026 realisation Rs 55,600/t = 0.93x the industry blend, held constant. Basis: Consolidated.
B34: Jindal Steel - revenue | C34: Rs cr | D34: 53225 | E34: =E24*E15*1.022428/10 | F34: =F24*F15*1.022428/10 | G34: =G24*G15*1.022428/10 | H34: =H24*H15*1.022428/10 | I34: =I24*I15*1.022428/10 | J34: =J24*J15*1.022428/10 | K34: =K24*K15*1.022428/10 | L34: =IFERROR(IF(AND(ISNUMBER(D34),ISNUMBER(K34),D34>0),(K34/D34)^(1/7)-1,""),"") | M34: S11 | N34: Medium | O34: FY2026 realisation Rs 61,319/t = 1.02x the industry blend, held constant. Basis: Consolidated.
B35: Jindal Stainless - revenue | C35: Rs cr | D35: 42955 | E35: =E25*E15*2.786876/10 | F35: =F25*F15*2.786876/10 | G35: =G25*G15*2.786876/10 | H35: =H25*H15*2.786876/10 | I35: =I25*I15*2.786876/10 | J35: =J25*J15*2.786876/10 | K35: =K25*K15*2.786876/10 | L35: =IFERROR(IF(AND(ISNUMBER(D35),ISNUMBER(K35),D35>0),(K35/D35)^(1/7)-1,""),"") | M35: S12 | N35: Medium | O35: FY2026 realisation Rs 167,140/t = 2.79x the industry blend, held constant. Basis: Consolidated.
B36: AM/NS India - revenue | C36: Rs cr | D36: 548 | E36: =E26*E15*0.011457/10 | F36: =F26*F15*0.011457/10 | G36: =G26*G15*0.011457/10 | H36: =H26*H15*0.011457/10 | I36: =I26*I15*0.011457/10 | J36: =J26*J15*0.011457/10 | K36: =K26*K15*0.011457/10 | L36: =IFERROR(IF(AND(ISNUMBER(D36),ISNUMBER(K36),D36>0),(K36/D36)^(1/7)-1,""),"") | M36: S13/S14 | N36: Medium | O36: FY2026 realisation Rs 687/t = 0.01x the industry blend, held constant. Basis: 100% basis, USD converted at the derived FY2026 average USD/INR of 88.4.
B37: RINL - revenue | C37: Rs cr | D37: 22300 | E37: =E27*E15*0.845063/10 | F37: =F27*F15*0.845063/10 | G37: =G27*G15*0.845063/10 | H37: =H27*H15*0.845063/10 | I37: =I27*I15*0.845063/10 | J37: =J27*J15*0.845063/10 | K37: =K27*K15*0.845063/10 | L37: =IFERROR(IF(AND(ISNUMBER(D37),ISNUMBER(K37),D37>0),(K37/D37)^(1/7)-1,""),"") | M37: S16 | N37: Medium | O37: FY2026 realisation Rs 50,681/t = 0.85x the industry blend, held constant. Basis: Turnover, basis not specified by issuer.
B39: Company revenues are NOT additive to industry revenue: Jindal Stainless is stainless, AM/NS India is on a 100% JV basis, RINL turnover is on an unspecified basis, and the six together are only part of India's output. Use industry revenue for the market and company revenue for relative work.

Sheet 13 EBITDA Model
B1: 13 EBITDA Model
B2: Industry Financial Model | Indian Steel Industry | Horizon FY2027E-FY2033E | Base year FY2026A | Built 03-Aug-2026
B4: OBJECTIVE
B5: Industry and company EBITDA, the primary valuation input.
B6: METHODOLOGY
B7: Industry EBITDA per tonne equals effective realisation less cash cost - a spread, not a margin applied to revenue, which is the correct construction for a commodity where price and cost move independently. Company EBITDA per tonne holds each producer's FY2026 observed spread to the industry constant. The FY2026 weighted anchor of Rs 10,733/t reconciles to the sum of reported EBITDAs within 0.6%.
B8: UNITS
B9: Rs per tonne and Rs crore.
B10: DEPENDENCIES
B11: Reads 09 Price, 11 Cost, 12 Revenue. Read by 14, 16, 17, 21, 22, 23, 24.
B13: Line item | C13: Unit | D13: FY2026A | E13: FY2027E | F13: FY2028E | G13: FY2029E | H13: FY2030E | I13: FY2031E | J13: FY2032E | K13: FY2033E | L13: CAGR | M13: Source | N13: Conf. | O13: Notes / methodology
B14: Blended realisation - effective | C14: Rs/t | D14: 59974 | E14: ='09 Steel Price Forecast'!E$22 | F14: ='09 Steel Price Forecast'!F$22 | G14: ='09 Steel Price Forecast'!G$22 | H14: ='09 Steel Price Forecast'!H$22 | I14: ='09 Steel Price Forecast'!I$22 | J14: ='09 Steel Price Forecast'!J$22 | K14: ='09 Steel Price Forecast'!K$22 | M14: 09 Price | N14: Medium
B15: Industry cash cost per tonne | C15: Rs/t | D15: 49241 | E15: ='11 Cost Curve'!E$17 | F15: ='11 Cost Curve'!F$17 | G15: ='11 Cost Curve'!G$17 | H15: ='11 Cost Curve'!H$17 | I15: ='11 Cost Curve'!I$17 | J15: ='11 Cost Curve'!J$17 | K15: ='11 Cost Curve'!K$17 | M15: 11 Cost Curve | N15: Medium
B16: INDUSTRY EBITDA PER TONNE | C16: Rs/t | D16: 10733 | E16: =E14-E15 | F16: =F14-F15 | G16: =G14-G15 | H16: =H14-H15 | I16: =I14-I15 | J16: =J14-J15 | K16: =K14-K15 | L16: =IFERROR(IF(AND(ISNUMBER(D16),ISNUMBER(K16),D16>0),(K16/D16)^(1/7)-1,""),"") | M16: Computed | N16: Medium | O16: FY2026A of Rs 10,733/t is the volume-weighted actual across the four majors. Reconciliation: Rs 10,733/t x 79.90 Mt = Rs 85,759 cr against the Rs 86,318 cr sum of reported EBITDAs, a 0.6% rounding difference.
B17: Finished steel production | C17: Mt | D17: 160.94 | E17: ='05 Steel Supply Model'!E$27 | F17: ='05 Steel Supply Model'!F$27 | G17: ='05 Steel Supply Model'!G$27 | H17: ='05 Steel Supply Model'!H$27 | I17: ='05 Steel Supply Model'!I$27 | J17: ='05 Steel Supply Model'!J$27 | K17: ='05 Steel Supply Model'!K$27 | M17: 05 Supply | N17: High
B18: INDUSTRY EBITDA | C18: Rs cr | D18: 172736.9 | E18: =E17*E16/10 | F18: =F17*F16/10 | G18: =G17*G16/10 | H18: =H17*H16/10 | I18: =I17*I16/10 | J18: =J17*J16/10 | K18: =K17*K16/10 | L18: =IFERROR(IF(AND(ISNUMBER(D18),ISNUMBER(K18),D18>0),(K18/D18)^(1/7)-1,""),"") | M18: Computed | N18: Medium
B21: COMPANY EBITDA PER TONNE (FY2026 spread to industry held constant)
B22: Line item | C22: Unit | D22: FY2026A | E22: FY2027E | F22: FY2028E | G22: FY2029E | H22: FY2030E | I22: FY2031E | J22: FY2032E | K22: FY2033E | L22: CAGR | M22: Source | N22: Conf. | O22: Notes / methodology
B23: Tata Steel - EBITDA per tonne | C23: Rs/t | D23: 15213 | E23: =E16+4480 | F23: =F16+4480 | G23: =G16+4480 | H23: =H16+4480 | I23: =I16+4480 | J23: =J16+4480 | K23: =K16+4480 | M23: S08 | N23: Medium | O23: FY2026 actual Rs 15,213/t, a +4480 Rs/t spread to the industry weighted average, held constant. Basis: India reported.
B24: JSW Steel - EBITDA per tonne | C24: Rs/t | D24: 10167 | E24: =E16+(-566) | F24: =F16+(-566) | G24: =G16+(-566) | H24: =H16+(-566) | I24: =I16+(-566) | J24: =J16+(-566) | K24: =K16+(-566) | M24: S09 | N24: Medium | O24: FY2026 actual Rs 10,167/t, a -566 Rs/t spread to the industry weighted average, held constant. Basis: India reported.
B25: SAIL - EBITDA per tonne | C25: Rs/t | D25: 6596 | E25: =E16+(-4137) | F25: =F16+(-4137) | G25: =G16+(-4137) | H25: =H16+(-4137) | I25: =I16+(-4137) | J25: =J16+(-4137) | K25: =K16+(-4137) | M25: S10 | N25: Medium | O25: FY2026 actual Rs 6,596/t, a -4137 Rs/t spread to the industry weighted average, held constant. Basis: STANDALONE reported.
B26: Jindal Steel - EBITDA per tonne | C26: Rs/t | D26: 10482 | E26: =E16+(-251) | F26: =F16+(-251) | G26: =G16+(-251) | H26: =H16+(-251) | I26: =I16+(-251) | J26: =J16+(-251) | K26: =K16+(-251) | M26: S11 | N26: Medium | O26: FY2026 actual Rs 10,482/t, a -251 Rs/t spread to the industry weighted average, held constant. Basis: Consolidated reported (adj 9,099 plus 561 FX).
B27: Jindal Stainless - EBITDA per tonne | C27: Rs/t | D27: 21634 | E27: =E16+10901 | F27: =F16+10901 | G27: =G16+10901 | H27: =H16+10901 | I27: =I16+10901 | J27: =J16+10901 | K27: =K16+10901 | M27: S12 | N27: Medium | O27: FY2026 actual Rs 21,634/t, a +10901 Rs/t spread to the industry weighted average, held constant. Basis: Consolidated reported.
B28: AM/NS India - EBITDA per tonne | C28: Rs/t | D28: 86 | E28: =E16+(-10647) | F28: =F16+(-10647) | G28: =G16+(-10647) | H28: =H16+(-10647) | I28: =I16+(-10647) | J28: =J16+(-10647) | K28: =K16+(-10647) | M28: S13/S14 | N28: Medium | O28: FY2026 actual Rs 86/t, a -10647 Rs/t spread to the industry weighted average, held constant. Basis: 100% basis, USD converted.
B29: RINL - EBITDA per tonne | C29: Rs/t | E29: Data Not Publicly Available | F29: Data Not Publicly Available | G29: Data Not Publicly Available | H29: Data Not Publicly Available | I29: Data Not Publicly Available | J29: Data Not Publicly Available | K29: Data Not Publicly Available | M29: S16 | N29: n/a | O29: Unlisted and wholly Government-owned. No EBITDA, balance sheet or valuation data is publicly available, so RINL appears in the volume build only.
B31: COMPANY EBITDA
B32: Line item | C32: Unit | D32: FY2026A | E32: FY2027E | F32: FY2028E | G32: FY2029E | H32: FY2030E | I32: FY2031E | J32: FY2032E | K32: FY2033E | L32: CAGR | M32: Source | N32: Conf. | O32: Notes / methodology
B33: Tata Steel - EBITDA | C33: Rs cr | D33: 34272 | E33: =E21*E23/10 | F33: =F21*F23/10 | G33: =G21*G23/10 | H33: =H21*H23/10 | I33: =I21*I23/10 | J33: =J21*J23/10 | K33: =K21*K23/10 | L33: =IFERROR(IF(AND(ISNUMBER(D33),ISNUMBER(K33),D33>0),(K33/D33)^(1/7)-1,""),"") | M33: S08 | N33: Medium | O33: Volume from 12 Revenue x EBITDA/t above.
B34: JSW Steel - EBITDA | C34: Rs cr | D34: 29240 | E34: =E22*E24/10 | F34: =F22*F24/10 | G34: =G22*G24/10 | H34: =H22*H24/10 | I34: =I22*I24/10 | J34: =J22*J24/10 | K34: =K22*K24/10 | L34: =IFERROR(IF(AND(ISNUMBER(D34),ISNUMBER(K34),D34>0),(K34/D34)^(1/7)-1,""),"") | M34: S09 | N34: Medium | O34: Volume from 12 Revenue x EBITDA/t above.
B35: SAIL - EBITDA | C35: Rs cr | D35: 13146 | E35: =E23*E25/10 | F35: =F23*F25/10 | G35: =G23*G25/10 | H35: =H23*H25/10 | I35: =I23*I25/10 | J35: =J23*J25/10 | K35: =K23*K25/10 | L35: =IFERROR(IF(AND(ISNUMBER(D35),ISNUMBER(K35),D35>0),(K35/D35)^(1/7)-1,""),"") | M35: S10 | N35: Medium | O35: Volume from 12 Revenue x EBITDA/t above.
B36: Jindal Steel - EBITDA | C36: Rs cr | D36: 9660 | E36: =E24*E26/10 | F36: =F24*F26/10 | G36: =G24*G26/10 | H36: =H24*H26/10 | I36: =I24*I26/10 | J36: =J24*J26/10 | K36: =K24*K26/10 | L36: =IFERROR(IF(AND(ISNUMBER(D36),ISNUMBER(K36),D36>0),(K36/D36)^(1/7)-1,""),"") | M36: S11 | N36: Medium | O36: Volume from 12 Revenue x EBITDA/t above.
B37: Jindal Stainless - EBITDA | C37: Rs cr | D37: 5560 | E37: =E25*E27/10 | F37: =F25*F27/10 | G37: =G25*G27/10 | H37: =H25*H27/10 | I37: =I25*I27/10 | J37: =J25*J27/10 | K37: =K25*K27/10 | L37: =IFERROR(IF(AND(ISNUMBER(D37),ISNUMBER(K37),D37>0),(K37/D37)^(1/7)-1,""),"") | M37: S12 | N37: Medium | O37: Volume from 12 Revenue x EBITDA/t above.
B38: AM/NS India - EBITDA | C38: Rs cr | D38: 69 | E38: =E26*E28/10 | F38: =F26*F28/10 | G38: =G26*G28/10 | H38: =H26*H28/10 | I38: =I26*I28/10 | J38: =J26*J28/10 | K38: =K26*K28/10 | L38: =IFERROR(IF(AND(ISNUMBER(D38),ISNUMBER(K38),D38>0),(K38/D38)^(1/7)-1,""),"") | M38: S13/S14 | N38: Medium | O38: Volume from 12 Revenue x EBITDA/t above.
B39: RINL - EBITDA | C39: Rs cr | E39: Data Not Publicly Available | F39: Data Not Publicly Available | G39: Data Not Publicly Available | H39: Data Not Publicly Available | I39: Data Not Publicly Available | J39: Data Not Publicly Available | K39: Data Not Publicly Available | M39: S16 | N39: n/a | O39: Unlisted and wholly Government-owned. No EBITDA, balance sheet or valuation data is publicly available, so RINL appears in the volume build only.
B41: SAIL's EBITDA is on a STANDALONE basis while its revenue is consolidated - database Conflict C09. Never pair a consolidated enterprise value with SAIL's EBITDA headline without adjusting.

Sheet 14 Margin Analysis
B1: 14 Margin Analysis
B2: Industry Financial Model | Indian Steel Industry | Horizon FY2027E-FY2033E | Base year FY2026A | Built 03-Aug-2026
B4: OBJECTIVE
B5: Decomposes margin into its price and cost components and benchmarks the forecast against observed cycle peaks and troughs.
B6: METHODOLOGY
B7: Margin is EBITDA per tonne divided by realisation. The observed envelope from the database is used as a credibility test on every scenario: FY2022 cycle peak was roughly 24-26% at industry level (Tata 26%, JSW 27%, SAIL 21%, Jindal Steel 30%), FY2024 trough roughly 12-14%, and the worst single observation was SAIL at -7% in FY2016. Any forecast outside that envelope requires explicit justification.
B8: UNITS
B9: Percentages as decimals. Rs per tonne.
B10: DEPENDENCIES
B11: Reads 09 Price, 11 Cost, 13 EBITDA. Read by 18 Cycle, 21 Scenario, 24 Dashboard.
B13: Line item | C13: Unit | D13: FY2026A | E13: FY2027E | F13: FY2028E | G13: FY2029E | H13: FY2030E | I13: FY2031E | J13: FY2032E | K13: FY2033E | L13: CAGR | M13: Source | N13: Conf. | O13: Notes / methodology
B14: Realisation | C14: Rs/t | D14: 59974 | E14: ='09 Steel Price Forecast'!E$22 | F14: ='09 Steel Price Forecast'!F$22 | G14: ='09 Steel Price Forecast'!G$22 | H14: ='09 Steel Price Forecast'!H$22 | I14: ='09 Steel Price Forecast'!I$22 | J14: ='09 Steel Price Forecast'!J$22 | K14: ='09 Steel Price Forecast'!K$22 | M14: 09 Price | N14: Medium
B15: Cash cost | C15: Rs/t | D15: 49241 | E15: ='11 Cost Curve'!E$17 | F15: ='11 Cost Curve'!F$17 | G15: ='11 Cost Curve'!G$17 | H15: ='11 Cost Curve'!H$17 | I15: ='11 Cost Curve'!I$17 | J15: ='11 Cost Curve'!J$17 | K15: ='11 Cost Curve'!K$17 | M15: 11 Cost | N15: Medium
B16: EBITDA per tonne | C16: Rs/t | D16: 10733 | E16: ='13 EBITDA Model'!E$16 | F16: ='13 EBITDA Model'!F$16 | G16: ='13 EBITDA Model'!G$16 | H16: ='13 EBITDA Model'!H$16 | I16: ='13 EBITDA Model'!I$16 | J16: ='13 EBITDA Model'!J$16 | K16: ='13 EBITDA Model'!K$16 | M16: 13 EBITDA | N16: Medium
B17: INDUSTRY EBITDA MARGIN | C17: % | D17: 0.17896088 | E17: =E16/E14 | F17: =F16/F14 | G17: =G16/G14 | H17: =H16/H14 | I17: =I16/I14 | J17: =J16/J14 | K17: =K16/K14 | M17: Computed | N17: Medium | O17: FY2026A of 17.9% is the volume-weighted actual across the four majors.
B19: MARGIN BRIDGE - CHANGE VS FY2026A
B20: Realisation change vs FY2026A | C20: Rs/t | E20: =E14-$D$14 | F20: =F14-$D$14 | G20: =G14-$D$14 | H20: =H14-$D$14 | I20: =I14-$D$14 | J20: =J14-$D$14 | K20: =K14-$D$14 | M20: Computed | N20: Medium
B21: Cash cost change vs FY2026A | C21: Rs/t | E21: =-(E15-$D$15) | F21: =-(F15-$D$15) | G21: =-(G15-$D$15) | H21: =-(H15-$D$15) | I21: =-(I15-$D$15) | J21: =-(J15-$D$15) | K21: =-(K15-$D$15) | M21: Computed | N21: Medium | O21: Shown with the sign reversed so that the two bridge lines sum to the EBITDA/t change - a negative value means cost inflation is eroding margin.
B22: EBITDA per tonne change vs FY2026A | C22: Rs/t | E22: =E20+E21 | F22: =F20+F21 | G22: =G20+G21 | H22: =H20+H21 | I22: =I20+I21 | J22: =J20+J21 | K22: =K20+K21 | M22: Computed | N22: Medium | O22: BRIDGE CHECK: must equal EBITDA/t less the FY2026A EBITDA/t. Verified on 25 Audit Checks.
B24: CREDIBILITY BENCHMARKS FROM OBSERVED HISTORY (Master Database)
B25: Observed cycle PEAK margin, FY2022 | C25: % | D25: 0.26 | M25: Master DB | N25: High | O25: Standardised EBITDA margins FY2022: Tata Steel 26%, JSW Steel 27%, SAIL 21%, Jindal Steel 30%. The bull case is calibrated to peak at 26.0% in FY2030.
B26: Observed cycle TROUGH margin, FY2024 | C26: % | D26: 0.13 | M26: Master DB | N26: High | O26: FY2024: Tata Steel 10%, JSW Steel 16%, SAIL 11%, Jindal Steel 20%.
B27: Worst single observation, SAIL FY2016 | C27: % | D27: -0.07 | M27: Master DB | N27: High | O27: The floor reference. The stress case troughs at -9.2% in FY2028, marginally worse, which is deliberate: a stress case should breach the worst observed outcome.
B28: FY2026A actual industry margin | C28: % | D28: 0.17896088 | M28: Master DB | N28: High | O28: Volume-weighted across the four majors.
B30: If a scenario produces a margin outside the -7% to +26% observed envelope, 25 Audit Checks flags it. That is a warning, not necessarily an error - but it must be justified.

Sheet 15 Working Capital Model
B1: 15 Working Capital Model
B2: Industry Financial Model | Indian Steel Industry | Horizon FY2027E-FY2033E | Base year FY2026A | Built 03-Aug-2026
B4: OBJECTIVE
B5: Forecasts net working capital and the cash flow it absorbs or releases.
B6: METHODOLOGY
B7: NWC is modelled as days of revenue. THIS IS THE WEAKEST BLOCK IN THE MODEL and is flagged as such: the Master Database carries total assets and borrowings but not receivables, inventory or payables, so working capital days could NOT be derived from it. The only directional evidence available is Tata Steel's disclosed FY2026 working capital RELEASE of about Rs 6,470 cr, which on Rs 2,32,140 cr of revenue is roughly 10 days of tightening. 45 days is a sector convention and must be replaced with balance-sheet-derived days before transaction use.
B8: UNITS
B9: Days. Rs crore.
B10: DEPENDENCIES
B11: Reads 12 Revenue and 02 Model Assumptions. Read by 16 Cash Flow.
B13: Line item | C13: Unit | D13: FY2026A | E13: FY2027E | F13: FY2028E | G13: FY2029E | H13: FY2030E | I13: FY2031E | J13: FY2032E | K13: FY2033E | L13: CAGR | M13: Source | N13: Conf. | O13: Notes / methodology
B14: Industry revenue | C14: Rs cr | D14: 965221.56 | E14: ='12 Revenue Forecast'!E$16 | F14: ='12 Revenue Forecast'!F$16 | G14: ='12 Revenue Forecast'!G$16 | H14: ='12 Revenue Forecast'!H$16 | I14: ='12 Revenue Forecast'!I$16 | J14: ='12 Revenue Forecast'!J$16 | K14: ='12 Revenue Forecast'!K$16 | M14: 12 Revenue | N14: Medium
B15: Net working capital | C15: days of revenue | D15: 45 | E15: '02 Model Assumptions'!E$139 | F15: '02 Model Assumptions'!F$139 | G15: '02 Model Assumptions'!G$139 | H15: '02 Model Assumptions'!H$139 | I15: '02 Model Assumptions'!I$139 | J15: '02 Model Assumptions'!J$139 | K15: '02 Model Assumptions'!K$139 | M15: NOT SOURCED | N15: Low | O15: 45 days base, 40 bull, 52 bear, 62 stress. A working capital BUILD in a downturn is a first-order cash flow risk, not a second-order one, which is why the stress flex is large.
B16: Net working capital | C16: Rs cr | D16: 118999.92 | E16: =E14*E15/365 | F16: =F14*F15/365 | G16: =G14*G15/365 | H16: =H14*H15/365 | I16: =I14*I15/365 | J16: =J14*J15/365 | K16: =K14*K15/365 | M16: Computed | N16: Low
B17: Change in net working capital | C17: Rs cr | E17: =E16-D16 | F17: =F16-E16 | G17: =G16-F16 | H17: =H16-G16 | I17: =I16-H16 | J17: =J16-I16 | K17: =K16-J16 | M17: Computed | N17: Low | O17: Positive equals a cash OUTFLOW (working capital absorbed). Deducted on 16 Cash Flow. FY2027E is measured against the FY2026A NWC computed on the same days basis, so the first year is not distorted by a basis change.
B18: NWC as % of revenue | C18: % | D18: 0.12328767 | E18: =E16/E14 | F18: =F16/F14 | G18: =G16/G14 | H18: =H16/H14 | I18: =I16/I14 | J18: =J16/J14 | K18: =K16/K14 | M18: Computed | N18: Low
B20: ACTION REQUIRED. Derive receivable, inventory and payable days from each company's balance sheet and replace driver D18 before this model is used to support a financing or transaction.

Sheet 16 Cash Flow Model
B1: 16 Cash Flow Model
B2: Industry Financial Model | Indian Steel Industry | Horizon FY2027E-FY2033E | Base year FY2026A | Built 03-Aug-2026
B4: OBJECTIVE
B5: Unlevered free cash flow for the industry - the input a DCF requires.
B6: METHODOLOGY
B7: UNLEVERED by design: EBITDA less cash tax less total capex less the change in working capital. Interest is deliberately excluded and sits on 17 Capital Allocation instead, because an enterprise DCF discounts pre-financing cash flow. Cash tax is computed on EBIT, not EBITDA, using depreciation of 5.3% of revenue DERIVED from the database - FY2026 D&A of Rs 30,715 cr on Rs 5,81,646 cr of revenue for the four majors, a ratio that is tight across companies at 5.15% to 5.96%. Tax is floored at zero on negative EBIT with no loss carry-forward modelled, which is conservative.
B8: UNITS
B9: Rs crore. Percentages as decimals.
B10: DEPENDENCIES
B11: Reads 12 Revenue, 13 EBITDA, 15 Working Capital, 06 Capacity, 02 Assumptions. Read by 17, 21, 22, 23, 24.
B13: Line item | C13: Unit | D13: FY2026A | E13: FY2027E | F13: FY2028E | G13: FY2029E | H13: FY2030E | I13: FY2031E | J13: FY2032E | K13: FY2033E | L13: CAGR | M13: Source | N13: Conf. | O13: Notes / methodology
B14: Industry EBITDA | C14: Rs cr | D14: 172736.9 | E14: ='13 EBITDA Model'!E$18 | F14: ='13 EBITDA Model'!F$18 | G14: ='13 EBITDA Model'!G$18 | H14: ='13 EBITDA Model'!H$18 | I14: ='13 EBITDA Model'!I$18 | J14: ='13 EBITDA Model'!J$18 | K14: ='13 EBITDA Model'!K$18 | M14: 13 EBITDA | N14: Medium
B15: Industry revenue | C15: Rs cr | D15: 965221.56 | E15: ='12 Revenue Forecast'!E$16 | F15: ='12 Revenue Forecast'!F$16 | G15: ='12 Revenue Forecast'!G$16 | H15: ='12 Revenue Forecast'!H$16 | I15: ='12 Revenue Forecast'!I$16 | J15: ='12 Revenue Forecast'!J$16 | K15: ='12 Revenue Forecast'!K$16 | M15: 12 Revenue | N15: Medium
B16: Depreciation and amortisation | C16: % of revenue | D16: 0.0528 | E16: '02 Model Assumptions'!E$147 | F16: '02 Model Assumptions'!F$147 | G16: '02 Model Assumptions'!G$147 | H16: '02 Model Assumptions'!H$147 | I16: '02 Model Assumptions'!I$147 | J16: '02 Model Assumptions'!J$147 | K16: '02 Model Assumptions'!K$147 | M16: Derived from Master DB | N16: High | O16: FY2026A of 5.28% is derived: Rs 30,715 cr of D&A on Rs 5,81,646 cr of consolidated revenue for the four majors. Tight across companies - Tata 5.15%, JSW 5.18%, SAIL 5.40%, Jindal Steel 5.96%.
B17: Depreciation and amortisation | C17: Rs cr | E17: =E15*E16 | F17: =F15*F16 | G17: =G15*G16 | H17: =H15*H16 | I17: =I15*I16 | J17: =J15*J16 | K17: =K15*K16 | M17: Computed | N17: High
B18: EBIT | C18: Rs cr | E18: =E14-E17 | F18: =F14-F17 | G18: =G14-G17 | H18: =H14-H17 | I18: =I14-I17 | J18: =J14-J17 | K18: =K14-K17 | M18: Computed | N18: Medium
B19: Effective tax rate | C19: % | D19: 0.2517 | E19: '02 Model Assumptions'!E$136 | F19: '02 Model Assumptions'!F$136 | G19: '02 Model Assumptions'!G$136 | H19: '02 Model Assumptions'!H$136 | I19: '02 Model Assumptions'!I$136 | J19: '02 Model Assumptions'!J$136 | K19: '02 Model Assumptions'!K$136 | M19: Statutory 115BAA | N19: Medium | O19: 22% plus surcharge and cess. Company-specific effective rates differ because of MAT credits and deferred tax - the database flags Kirloskar Ferrous FY2026 net profit exceeding PBT on a write-back (Conflict C12).
B20: Cash tax | C20: Rs cr | E20: =MAX(0,E18)*E19 | F20: =MAX(0,F18)*F19 | G20: =MAX(0,G18)*G19 | H20: =MAX(0,H18)*H19 | I20: =MAX(0,I18)*I19 | J20: =MAX(0,J18)*J19 | K20: =MAX(0,K18)*K19 | M20: Computed | N20: Medium | O20: Floored at zero. No loss carry-forward is modelled, which understates cash flow in any recovery following a loss year - conservative and disclosed.
B22: CAPITAL EXPENDITURE
B23: Capacity added | C23: Mtpa | D23: 20.07 | E23: ='06 Capacity Forecast'!E$19 | F23: ='06 Capacity Forecast'!F$19 | G23: ='06 Capacity Forecast'!G$19 | H23: ='06 Capacity Forecast'!H$19 | I23: ='06 Capacity Forecast'!I$19 | J23: ='06 Capacity Forecast'!J$19 | K23: ='06 Capacity Forecast'!K$19 | M23: 06 Capacity | N23: Medium
B24: Capex intensity | C24: Rs/t of capacity | E24: '02 Model Assumptions'!E$137 | F24: '02 Model Assumptions'!F$137 | G24: '02 Model Assumptions'!G$137 | H24: '02 Model Assumptions'!H$137 | I24: '02 Model Assumptions'!I$137 | J24: '02 Model Assumptions'!J$137 | K24: '02 Model Assumptions'!K$137 | M24: Derived from Master DB | N24: Medium | O24: Rs 55,000/t base. Cross-checks: JSW JVML 5 Mtpa at Rs 26,000 cr = Rs 52,000/t; SAIL roughly Rs 1 lakh cr for about 15 Mtpa = roughly Rs 67,000/t; Tata Ludhiana 0.75 Mtpa EAF at Rs 3,200 cr = Rs 42,700/t (lower, no ironmaking).
B25: Growth capex | C25: Rs cr | E25: =E23*E24/10 | F25: =F23*F24/10 | G25: =G23*G24/10 | H25: =H23*H24/10 | I25: =I23*I24/10 | J25: =J23*J24/10 | K25: =K23*K24/10 | M25: Computed | N25: Medium | O25: Unit bridge: Mtpa x Rs/t / 10 = Rs crore.
B26: Maintenance capex | C26: % of revenue | E26: '02 Model Assumptions'!E$138 | F26: '02 Model Assumptions'!F$138 | G26: '02 Model Assumptions'!G$138 | H26: '02 Model Assumptions'!H$138 | I26: '02 Model Assumptions'!I$138 | J26: '02 Model Assumptions'!J$138 | K26: '02 Model Assumptions'!K$138 | M26: Indicative | N26: Low | O26: 3.0% of revenue. Cross-check: Tata Steel FY2026 total capex of Rs 14,026 cr on Rs 2,32,140 cr revenue is 6.0%, but that includes growth capex, so 3.0% sustaining implies a roughly 50/50 split.
B27: Maintenance capex | C27: Rs cr | E27: =E15*E26 | F27: =F15*F26 | G27: =G15*G26 | H27: =H15*H26 | I27: =I15*I26 | J27: =J15*J26 | K27: =K15*K26 | M27: Computed | N27: Low
B28: Total capex | C28: Rs cr | E28: =E25+E27 | F28: =F25+F27 | G28: =G25+G27 | H28: =H25+H27 | I28: =I25+I27 | J28: =J25+J27 | K28: =K25+K27 | M28: Computed | N28: Medium
B30: FREE CASH FLOW
B31: Change in net working capital | C31: Rs cr | E31: ='15 Working Capital Model'!E$17 | F31: ='15 Working Capital Model'!F$17 | G31: ='15 Working Capital Model'!G$17 | H31: ='15 Working Capital Model'!H$17 | I31: ='15 Working Capital Model'!I$17 | J31: ='15 Working Capital Model'!J$17 | K31: ='15 Working Capital Model'!K$17 | M31: 15 WC | N31: Low
B32: UNLEVERED FREE CASH FLOW | C32: Rs cr | E32: =E14-E20-E28-E31 | F32: =F14-F20-F28-F31 | G32: =G14-G20-G28-G31 | H32: =H14-H20-H28-H31 | I32: =I14-I20-I28-I31 | J32: =J14-J20-J28-J31 | K32: =K14-K20-K28-K31 | M32: Computed | N32: Medium | O32: EBITDA less cash tax less total capex less the change in working capital. Pre-financing, which is what an enterprise DCF discounts.
B33: FCF conversion | C33: % of EBITDA | E33: =IFERROR(E32/E14,"") | F33: =IFERROR(F32/F14,"") | G33: =IFERROR(G32/G14,"") | H33: =IFERROR(H32/H14,"") | I33: =IFERROR(I32/I14,"") | J33: =IFERROR(J32/J14,"") | K33: =IFERROR(K32/K14,"") | M33: Computed | N33: Medium | O33: Low or negative conversion in the early years is the signature of an industry in heavy build-out - roughly 20 Mtpa a year of capacity at Rs 55,000/t is about Rs 1.1 lakh crore of growth capex annually.
B35: This is an INDUSTRY aggregate. For a single-name DCF, substitute that company's volume, realisation spread, cost spread, capex programme and working capital, all of which are already isolated as separate lines in this workbook.

Sheet 17 Capital Allocation
B1: 17 Capital Allocation
B2: Industry Financial Model | Indian Steel Industry | Horizon FY2027E-FY2033E | Base year FY2026A | Built 03-Aug-2026
B4: OBJECTIVE
B5: Traces the industry balance sheet: capex funding, the net debt path and leverage against the covered producers' own stated caps.
B6: METHODOLOGY
B7: Net debt rolls forward from an FY2026 industry aggregate of Rs 1,85,001 cr - the sum of Tata Steel Rs 80,144 cr, JSW Steel Rs 53,870 cr, Jindal Steel Rs 16,019 cr, Jindal Stainless Rs 3,040 cr and SAIL's gross borrowings of Rs 31,928 cr used as a PROXY because SAIL's net debt is not disclosed in the database. Unlevered FCF is applied to debt reduction with no dividend or buyback modelled at industry level.
B8: UNITS
B9: Rs crore. Leverage in times.
B10: DEPENDENCIES
B11: Reads 16 Cash Flow and 13 EBITDA. Read by 23 Comparable Valuation and 25 Audit.
B13: Line item | C13: Unit | D13: FY2026A | E13: FY2027E | F13: FY2028E | G13: FY2029E | H13: FY2030E | I13: FY2031E | J13: FY2032E | K13: FY2033E | L13: CAGR | M13: Source | N13: Conf. | O13: Notes / methodology
B14: Opening net debt | C14: Rs cr | E14: =D17 | F14: =E17 | G14: =F17 | H14: =G17 | I14: =H17 | J14: =I17 | K14: =J17 | M14: Computed | N14: Medium
B15: Unlevered free cash flow | C15: Rs cr | E15: ='16 Cash Flow Model'!E$32 | F15: ='16 Cash Flow Model'!F$32 | G15: ='16 Cash Flow Model'!G$32 | H15: ='16 Cash Flow Model'!H$32 | I15: ='16 Cash Flow Model'!I$32 | J15: ='16 Cash Flow Model'!J$32 | K15: ='16 Cash Flow Model'!K$32 | M15: 16 Cash Flow | N15: Medium
B16: Interest paid (illustrative) | C16: Rs cr | E16: =E14*'02 Model Assumptions'!$D$168 | F16: =F14*'02 Model Assumptions'!$D$168 | G16: =G14*'02 Model Assumptions'!$D$168 | H16: =H14*'02 Model Assumptions'!$D$168 | I16: =I14*'02 Model Assumptions'!$D$168 | J16: =J14*'02 Model Assumptions'!$D$168 | K16: =K14*'02 Model Assumptions'!$D$168 | M16: Computed | N16: Medium | O16: Opening net debt at the pre-tax cost of debt of 7.44% from the WACC build-up. Illustrative: actual coupons differ by issuer and by instrument.
B17: Closing net debt | C17: Rs cr | D17: 185001 | E17: =E14-E15+E16 | F17: =F14-F15+F16 | G17: =G14-G15+G16 | H17: =H14-H15+H16 | I17: =I14-I15+I16 | J17: =J14-J15+J16 | K17: =K14-K15+K16 | M17: Master DB (aggregate) | N17: Medium | O17: FY2026A of Rs 1,85,001 cr. Note SAIL is a gross-borrowings proxy, so the aggregate is overstated by SAIL's cash balance, which the database does not disclose.
B19: LEVERAGE
B20: Industry EBITDA | C20: Rs cr | D20: 172736.9 | E20: ='13 EBITDA Model'!E$18 | F20: ='13 EBITDA Model'!F$18 | G20: ='13 EBITDA Model'!G$18 | H20: ='13 EBITDA Model'!H$18 | I20: ='13 EBITDA Model'!I$18 | J20: ='13 EBITDA Model'!J$18 | K20: ='13 EBITDA Model'!K$18 | M20: 13 EBITDA | N20: Medium
B21: Net debt / EBITDA | C21: x | D21: 1.0709987 | E21: =IFERROR(E17/E20,"") | F21: =IFERROR(F17/F20,"") | G21: =IFERROR(G17/G20,"") | H21: =IFERROR(H17/H20,"") | I21: =IFERROR(I17/I20,"") | J21: =IFERROR(J17/J20,"") | K21: =IFERROR(K17/K20,"") | M21: Computed | N21: Medium | O21: Benchmark against the producers' own stated caps from the database: JSW Steel revised its cap down from 3.75x to 3.00x and achieved 1.81x at Mar-2026; Jindal Steel 1.66x; Jindal Stainless 0.55x; Tata Steel 2.3x.
B22: Leverage covenant headroom vs 3.0x | C22: x | E22: =3-E21 | F22: =3-F21 | G22: =3-G21 | H22: =3-H21 | I22: =3-I21 | J22: =3-J21 | K22: =3-K21 | M22: Computed | N22: Medium | O22: Against JSW Steel's revised stated cap of 3.00x, the tightest publicly stated cap among the covered producers. Negative means the industry aggregate would breach it.
B24: CUMULATIVE CAPITAL DEPLOYED
B25: Total capex | C25: Rs cr | E25: ='16 Cash Flow Model'!E$28 | F25: ='16 Cash Flow Model'!F$28 | G25: ='16 Cash Flow Model'!G$28 | H25: ='16 Cash Flow Model'!H$28 | I25: ='16 Cash Flow Model'!I$28 | J25: ='16 Cash Flow Model'!J$28 | K25: ='16 Cash Flow Model'!K$28 | M25: 16 Cash Flow | N25: Medium
B26: Cumulative capex FY2027E onwards | C26: Rs cr | D26: 0 | E26: =D26+E25 | F26: =E26+F25 | G26: =F26+G25 | H26: =G26+H25 | I26: =H26+I25 | J26: =I26+J25 | K26: =J26+K25 | M26: Computed | N26: Medium | O26: The scale of the capital call on this industry over the horizon. For context the database records Jindal Steel's cumulative capex at Rs 40,450 cr through FY2026 and JSW Steel carrying forward Rs 96,888 cr of approved capex at 1-Apr-2026.
B28: No dividend or buyback is modelled at industry level. The database records FY2026 dividends of Rs 4.00 per share at Tata Steel, Rs 7.10 at JSW Steel, Rs 2.35 at SAIL, Rs 2.00 at Jindal Steel and Rs 4.00 at Jindal Stainless; add them in single-name models.

Sheet 18 Industry Cycle Model
B1: 18 Industry Cycle Model
B2: Industry Financial Model | Indian Steel Industry | Horizon FY2027E-FY2033E | Base year FY2026A | Built 03-Aug-2026
B4: OBJECTIVE
B5: Positions each forecast year in the industry cycle, so that a valuation is not struck on a peak or trough year by accident.
B6: METHODOLOGY
B7: Two independent cycle indicators are used: the utilisation gap against normal utilisation of 80%, and the margin gap against the mid-cycle margin. Mid-cycle margin is computed as the average of the observed FY2022 peak of 26% and the FY2024 trough of 13%, giving 19.5% - close to the FY2026 actual of 17.9%, which is reassuring. A composite score classifies each year.
B8: UNITS
B9: Percentages as decimals and percentage points.
B10: DEPENDENCIES
B11: Reads 08 Utilisation and 14 Margin. Read by 23 Valuation and 24 Dashboard.
B13: Line item | C13: Unit | D13: FY2026A | E13: FY2027E | F13: FY2028E | G13: FY2029E | H13: FY2030E | I13: FY2031E | J13: FY2032E | K13: FY2033E | L13: CAGR | M13: Source | N13: Conf. | O13: Notes / methodology
B14: Capacity utilisation | C14: % | D14: 0.76415608 | E14: ='08 Capacity Utilisation'!E$16 | F14: ='08 Capacity Utilisation'!F$16 | G14: ='08 Capacity Utilisation'!G$16 | H14: ='08 Capacity Utilisation'!H$16 | I14: ='08 Capacity Utilisation'!I$16 | J14: ='08 Capacity Utilisation'!J$16 | K14: ='08 Capacity Utilisation'!K$16 | M14: 08 Utilisation | N14: High
B15: Utilisation gap vs normal (80%) | C15: ppt | D15: -0.03584392 | E15: ='08 Capacity Utilisation'!E$18 | F15: ='08 Capacity Utilisation'!F$18 | G15: ='08 Capacity Utilisation'!G$18 | H15: ='08 Capacity Utilisation'!H$18 | I15: ='08 Capacity Utilisation'!I$18 | J15: ='08 Capacity Utilisation'!J$18 | K15: ='08 Capacity Utilisation'!K$18 | M15: 08 Utilisation | N15: High
B16: Industry EBITDA margin | C16: % | D16: 0.17896088 | E16: ='14 Margin Analysis'!E$17 | F16: ='14 Margin Analysis'!F$17 | G16: ='14 Margin Analysis'!G$17 | H16: ='14 Margin Analysis'!H$17 | I16: ='14 Margin Analysis'!I$17 | J16: ='14 Margin Analysis'!J$17 | K16: ='14 Margin Analysis'!K$17 | M16: 14 Margin | N16: Medium
B17: Mid-cycle margin | C17: % | D17: 0.195 | E17: 0.195 | F17: 0.195 | G17: 0.195 | H17: 0.195 | I17: 0.195 | J17: 0.195 | K17: 0.195 | M17: Derived from Master DB | N17: Medium | O17: Average of the observed FY2022 peak (26%) and FY2024 trough (13%). Close to the FY2026 actual of 17.9%, which supports the calibration.
B18: Margin gap vs mid-cycle | C18: ppt | E18: =E16-E17 | F18: =F16-F17 | G18: =G16-G17 | H18: =H16-H17 | I18: =I16-I17 | J18: =J16-J17 | K18: =K16-K17 | M18: Computed | N18: Medium
B19: CYCLE POSITION | C19: classification | E19: =IF(E18>0.04,"PEAK",IF(E18>0.015,"LATE UPCYCLE",IF(E18<-0.05,"TROUGH",IF(E18<-0.02,"DOWNCYCLE","MID-CYCLE")))) | F19: =IF(F18>0.04,"PEAK",IF(F18>0.015,"LATE UPCYCLE",IF(F18<-0.05,"TROUGH",IF(F18<-0.02,"DOWNCYCLE","MID-CYCLE")))) | G19: =IF(G18>0.04,"PEAK",IF(G18>0.015,"LATE UPCYCLE",IF(G18<-0.05,"TROUGH",IF(G18<-0.02,"DOWNCYCLE","MID-CYCLE")))) | H19: =IF(H18>0.04,"PEAK",IF(H18>0.015,"LATE UPCYCLE",IF(H18<-0.05,"TROUGH",IF(H18<-0.02,"DOWNCYCLE","MID-CYCLE")))) | I19: =IF(I18>0.04,"PEAK",IF(I18>0.015,"LATE UPCYCLE",IF(I18<-0.05,"TROUGH",IF(I18<-0.02,"DOWNCYCLE","MID-CYCLE")))) | J19: =IF(J18>0.04,"PEAK",IF(J18>0.015,"LATE UPCYCLE",IF(J18<-0.05,"TROUGH",IF(J18<-0.02,"DOWNCYCLE","MID-CYCLE")))) | K19: =IF(K18>0.04,"PEAK",IF(K18>0.015,"LATE UPCYCLE",IF(K18<-0.05,"TROUGH",IF(K18<-0.02,"DOWNCYCLE","MID-CYCLE")))) | M19: Computed | N19: Medium | O19: Classified on the margin gap: above +4ppt peak, +1.5 to +4ppt late upcycle, -2 to +1.5ppt mid-cycle, -2 to -5ppt downcycle, below -5ppt trough.
B21: OBSERVED CYCLE CHRONOLOGY (Master Database)
B22: FY2022 - cycle peak | C22: % | D22: 0.26 | M22: Master DB | N22: High | O22: Industry margin roughly 24-26%. Coking coal spiked but was passed through, so margins were at RECORD highs - the key evidence that a cost spike is not automatically margin-negative.
B23: FY2024 - cycle trough | C23: % | D23: 0.13 | M23: Master DB | N23: High | O23: Four years peak to trough.
B24: FY2026 - recovery | C24: % | D24: 0.17896088 | M24: Master DB | N24: High | O24: Aided by the safeguard duty, which lifted domestic HRC roughly 25% between early Dec-2025 and end-Mar-2026.
B25: Implied full cycle length | C25: years | D25: 7.5 | M25: Master DB | N25: High | O25: Roughly 7 to 8 years on a 4-year peak-to-trough leg. This is the quantitative basis for the 7-year horizon: the forecast average is approximately cycle-neutral.
B27: Use the cycle position row when selecting an exit multiple. Applying a mid-cycle multiple to a peak-year EBITDA is the most common way to overvalue a steel company.

Sheet 19 Trade Model
B1: 19 Trade Model
B2: Industry Financial Model | Indian Steel Industry | Horizon FY2027E-FY2033E | Base year FY2026A | Built 03-Aug-2026
B4: OBJECTIVE
B5: Forecasts imports, exports and the net trade position, and the penetration ratios that determine whether domestic prices set at import or export parity.
B6: METHODOLOGY
B7: Imports are a scenario driver plus any shortfall routed from 05 Steel Supply when the capacity ceiling binds. Exports are derived as the import driver plus net exports, so the two trade drivers are internally consistent by construction and cannot drift apart. Scenario signs are deliberately counter-intuitive and are explained on the rows.
B8: UNITS
B9: Mt. Percentages as decimals.
B10: DEPENDENCIES
B11: Reads 02 Assumptions, 04 Demand, 05 Supply. Read by 24 Dashboard.
B13: Line item | C13: Unit | D13: FY2026A | E13: FY2027E | F13: FY2028E | G13: FY2029E | H13: FY2030E | I13: FY2031E | J13: FY2032E | K13: FY2033E | L13: CAGR | M13: Source | N13: Conf. | O13: Notes / methodology
B14: Finished steel imports - driver | C14: Mt | D14: 6.524 | E14: '02 Model Assumptions'!E$142 | F14: '02 Model Assumptions'!F$142 | G14: '02 Model Assumptions'!G$142 | H14: '02 Model Assumptions'!H$142 | I14: '02 Model Assumptions'!I$142 | J14: '02 Model Assumptions'!J$142 | K14: '02 Model Assumptions'!K$142 | M14: Derived from Master DB | N14: Medium | O14: FY2026A of 6.524 Mt, down 31.7% from 9.551 Mt as the safeguard duty bit. NOTE THE SCENARIO SIGNS: the BULL case carries HIGHER imports because strong demand pulls material in; the BEAR case carries LOWER imports because weak demand makes imports uncompetitive.
B15: Shortfall routed from supply ceiling | C15: Mt | D15: 0 | E15: ='05 Steel Supply Model'!E$28 | F15: ='05 Steel Supply Model'!F$28 | G15: ='05 Steel Supply Model'!G$28 | H15: ='05 Steel Supply Model'!H$28 | I15: ='05 Steel Supply Model'!I$28 | J15: ='05 Steel Supply Model'!J$28 | K15: ='05 Steel Supply Model'!K$28 | M15: 05 Supply | N15: High | O15: Non-zero only where the capacity ceiling binds.
B16: Total finished steel imports | C16: Mt | D16: 6.524 | E16: =E14+E15 | F16: =F14+F15 | G16: =G14+G15 | H16: =H14+H15 | I16: =I14+I15 | J16: =J14+J15 | K16: =K14+K15 | M16: Computed | N16: Medium
B17: Net finished steel exports | C17: Mt | D17: 0.078 | E17: ='05 Steel Supply Model'!E$15 | F17: ='05 Steel Supply Model'!F$15 | G17: ='05 Steel Supply Model'!G$15 | H17: ='05 Steel Supply Model'!H$15 | I17: ='05 Steel Supply Model'!I$15 | J17: ='05 Steel Supply Model'!J$15 | K17: ='05 Steel Supply Model'!K$15 | M17: 05 Supply | N17: Medium
B18: Finished steel exports | C18: Mt | D18: 6.602 | E18: =E14+E17 | F18: =F14+F17 | G18: =G14+G17 | H18: =H14+H17 | I18: =I14+I17 | J18: =J14+J17 | K18: =K14+K17 | M18: Computed | N18: Medium | O18: Derived as the import driver plus net exports, which guarantees the trade block reconciles to the supply balance on 05.
B20: TRADE INTENSITY
B21: Apparent consumption | C21: Mt | D21: 163.74 | E21: ='04 Steel Demand Model'!E$17 | F21: ='04 Steel Demand Model'!F$17 | G21: ='04 Steel Demand Model'!G$17 | H21: ='04 Steel Demand Model'!H$17 | I21: ='04 Steel Demand Model'!I$17 | J21: ='04 Steel Demand Model'!J$17 | K21: ='04 Steel Demand Model'!K$17 | M21: 04 Demand | N21: High
B22: Finished steel production | C22: Mt | D22: 160.94 | E22: ='05 Steel Supply Model'!E$27 | F22: ='05 Steel Supply Model'!F$27 | G22: ='05 Steel Supply Model'!G$27 | H22: ='05 Steel Supply Model'!H$27 | I22: ='05 Steel Supply Model'!I$27 | J22: ='05 Steel Supply Model'!J$27 | K22: ='05 Steel Supply Model'!K$27 | M22: 05 Supply | N22: High
B23: Import penetration | C23: % of consumption | D23: 0.039843655 | E23: =E16/E21 | F23: =F16/F21 | G23: =G16/G21 | H23: =H16/H21 | I23: =I16/I21 | J23: =J16/J21 | K23: =K16/K21 | M23: Computed | N23: Medium | O23: FY2026A of 4.0%, down from 6.3% in FY2025. Below roughly 5% is generally consistent with domestic producers retaining pricing power.
B24: Export intensity | C24: % of production | D24: 0.041021499 | E24: =E18/E22 | F24: =F18/F22 | G24: =G18/G22 | H24: =H18/H22 | I24: =I18/I22 | J24: =J18/J22 | K24: =K18/K22 | M24: Computed | N24: Medium | O24: FY2026A of 4.1%. India is fundamentally a domestic market, so global steel prices matter through the IMPORT channel rather than the export channel.
B25: Net trade position | C25: Mt | D25: 0.078 | E25: =E18-E16 | F25: =F18-F16 | G25: =G18-G16 | H25: =H18-H16 | I25: =I18-I16 | J25: =J18-J16 | K25: =K18-K16 | M25: Computed | N25: Medium | O25: Positive equals net exporter. Determines whether the domestic price sets at import parity (net importer) or export parity (net exporter) - which drives the entire price deck.
B27: POLICY CONTEXT
B28: Safeguard duty on flat products | C28: % | D28: 0.12 | E28: ='09 Steel Price Forecast'!E$27 | F28: ='09 Steel Price Forecast'!F$27 | G28: ='09 Steel Price Forecast'!G$27 | H28: ='09 Steel Price Forecast'!H$27 | I28: ='09 Steel Price Forecast'!I$27 | J28: ='09 Steel Price Forecast'!J$27 | K28: ='09 Steel Price Forecast'!K$27 | M28: Master DB P03 | N28: High | O28: Schedule, not a forecast. Expires 20-Apr-2028 subject to a mid-term review. Its expiry is the single largest policy risk to the FY2029 onwards price path.
B30: EU destinations - Italy, Belgium and Spain - were 34.4% of India's FY2026 exports, so the EU CBAM definitive regime that began 01-Jan-2026 bears on roughly a third of the export book. Quantified on 20 ESG Model.

Sheet 20 ESG Model
B1: 20 ESG Model
B2: Industry Financial Model | Indian Steel Industry | Horizon FY2027E-FY2033E | Base year FY2026A | Built 03-Aug-2026
B4: OBJECTIVE
B5: Quantifies the industry's position against India's Green Steel Taxonomy and its exposure to the EU Carbon Border Adjustment Mechanism.
B6: METHODOLOGY
B7: Emission intensity is benchmarked against the taxonomy thresholds notified on 23-Dec-2024. CBAM exposure is computed as EU-destined exports multiplied by the excess of Indian emission intensity over an EU benchmark, multiplied by a carbon price. THE CARBON PRICE AND THE INDIAN EMISSION INTENSITY ARE NOT SOURCED and are user inputs - the calculation is a live framework, not an assertion.
B8: UNITS
B9: tCO2e per tonne of finished steel. EUR per tonne of CO2. Rs crore.
B10: DEPENDENCIES
B11: Reads 19 Trade Model. Inputs are user-editable on this sheet.
B13: Line item | C13: Unit | D13: FY2026A | E13: FY2027E | F13: FY2028E | G13: FY2029E | H13: FY2030E | I13: FY2031E | J13: FY2032E | K13: FY2033E | L13: CAGR | M13: Source | N13: Conf. | O13: Notes / methodology
B14: GREEN STEEL TAXONOMY THRESHOLDS (notified 23-Dec-2024)
B15: 5-star green steel | C15: tCO2e/tfs | D15: 1.6 | M15: Master DB P15 | N15: High | O15: Below 1.6 tCO2e/tfs. Tata Steel's 0.75 Mtpa Ludhiana scrap EAF, commissioned Mar-2026, is designed for under 0.3 tCO2e/t and therefore qualifies.
B16: 4-star green steel | C16: tCO2e/tfs | D16: 2 | M16: Master DB P15 | N16: High | O16: 1.6 to 2.0 tCO2e/tfs.
B17: 3-star green steel | C17: tCO2e/tfs | D17: 2.2 | M17: Master DB P15 | N17: High | O17: 2.0 to 2.2 tCO2e/tfs. This is also the headline definition of green steel.
B18: Not classified as green steel | C18: tCO2e/tfs | D18: 2.2 | M18: Master DB P15 | N18: High | O18: Above 2.2 tCO2e/tfs. Conventional Indian BF-BOF production sits well above this.
B20: USER INPUTS - NOT SOURCED, EDIT BEFORE USE
B21: Indian average emission intensity | C21: tCO2e/tfs | D21: 2.55 | E21: 2.55 | F21: 2.55 | G21: 2.55 | H21: 2.55 | I21: 2.55 | J21: 2.55 | K21: 2.55 | M21: NOT SOURCED | N21: Low | O21: USER INPUT. Not sourced in this research cycle. Indian BF-BOF is generally understood to sit well above the 2.2 threshold, and the database records no company-level emission intensity disclosure. Replace with company Business Responsibility and Sustainability Report data.
B22: EU benchmark emission intensity | C22: tCO2e/tfs | D22: 1.85 | E22: 1.85 | F22: 1.85 | G22: 1.85 | H22: 1.85 | I22: 1.85 | J22: 1.85 | K22: 1.85 | M22: NOT SOURCED | N22: Low | O22: USER INPUT. Not sourced.
B23: EU carbon price | C23: EUR/tCO2 | D23: 85 | E23: 85 | F23: 85 | G23: 85 | H23: 85 | I23: 85 | J23: 85 | K23: 85 | M23: NOT SOURCED | N23: Low | O23: USER INPUT. Not sourced. EU ETS prices are observable and should be substituted.
B24: EUR/INR | C24: Rs/EUR | D24: 103 | E24: 103 | F24: 103 | G24: 103 | H24: 103 | I24: 103 | J24: 103 | K24: 103 | M24: NOT SOURCED | N24: Low | O24: USER INPUT. Not sourced. Implied cross from the derived USD/INR of 88.4 at a EUR/USD of roughly 1.17.
B25: EU share of Indian exports | C25: % | D25: 0.344 | E25: 0.344 | F25: 0.344 | G25: 0.344 | H25: 0.344 | I25: 0.344 | J25: 0.344 | K25: 0.344 | M25: Master DB | N25: High | O25: Italy 16.2%, Belgium 10.9% and Spain 7.3% of FY2026 finished steel exports.
B27: CBAM EXPOSURE (live calculation on the inputs above)
B28: Finished steel exports | C28: Mt | D28: 6.602 | E28: ='19 Trade Model'!E$18 | F28: ='19 Trade Model'!F$18 | G28: ='19 Trade Model'!G$18 | H28: ='19 Trade Model'!H$18 | I28: ='19 Trade Model'!I$18 | J28: ='19 Trade Model'!J$18 | K28: ='19 Trade Model'!K$18 | M28: 19 Trade | N28: Medium
B29: EU-destined exports | C29: Mt | E29: =E28*E25 | F29: =F28*F25 | G29: =G28*G25 | H29: =H28*H25 | I29: =I28*I25 | J29: =J28*J25 | K29: =K28*K25 | M29: Computed | N29: Medium
B30: Emission intensity excess vs EU benchmark | C30: tCO2e/tfs | E30: =MAX(0,E21-E22) | F30: =MAX(0,F21-F22) | G30: =MAX(0,G21-G22) | H30: =MAX(0,H21-H22) | I30: =MAX(0,I21-I22) | J30: =MAX(0,J21-J22) | K30: =MAX(0,K21-K22) | M30: Computed | N30: Low
B31: CBAM cost | C31: Rs cr | E31: =E29*E30*E23*E24/10 | F31: =F29*F30*F23*F24/10 | G31: =G29*G30*G23*G24/10 | H31: =H29*H30*H23*H24/10 | I31: =I29*I30*I23*I24/10 | J31: =J29*J30*J23*J24/10 | K31: =K29*K30*K23*K24/10 | M31: Computed | N31: Low | O31: Mt x tCO2e/t x EUR/tCO2 x Rs/EUR / 10 = Rs crore. Live on the user inputs above.
B32: CBAM cost per tonne of EU-destined export | C32: Rs/t | E32: =IFERROR(E31/E29*10,"") | F32: =IFERROR(F31/F29*10,"") | G32: =IFERROR(G31/G29*10,"") | H32: =IFERROR(H31/H29*10,"") | I32: =IFERROR(I31/I29*10,"") | J32: =IFERROR(J31/J29*10,"") | K32: =IFERROR(K31/K29*10,"") | M32: Computed | N32: Low | O32: Compare against industry EBITDA per tonne on 13: this is the margin that CBAM removes from EU-destined tonnes unless emission intensity falls.
B34: Also unmodelled: the proposed 37% government procurement share for green steel (a PROPOSAL, not an enacted mandate) and the Tata Steel Netherlands going-concern uncertainty, which is company-specific and outside this India model.

Sheet 21 Scenario Manager
B1: 21 Scenario Manager
B2: Industry Financial Model | Indian Steel Industry | Horizon FY2027E-FY2033E | Base year FY2026A | Built 03-Aug-2026
B4: OBJECTIVE
B5: Compares all four scenarios side by side, and proves that the live workbook reproduces the intended arithmetic for whichever scenario is selected.
B6: METHODOLOGY
B7: Excel can only display one scenario at a time. The comparison block below was computed at BUILD TIME by fmodel/chain.py, which implements exactly the same arithmetic as the workbook formulas. The 'Live (active scenario)' column is a genuine link to the model. The tie-out row uses INDEX on ScenID to pick the pre-computed column matching the active scenario and compares it against the live value: if the Excel formulas and the intended arithmetic ever diverge, it fails. That is a real regression test, not a decoration.
B8: UNITS
B9: As stated per row. Terminal year FY2033E unless stated.
B10: DEPENDENCIES
B11: Reads 01 Control Panel, 05, 06, 08, 09, 11, 13, 14, 16. Read by 25 Audit Checks.
B13: FY2033E metric | C13: Unit | D13: Base Case | E13: Bull Case | F13: Bear Case | G13: Stress Case | H13: Live (active scenario) | I13: Tie-out | J13: Commentary
B14: Apparent consumption | C14: Mt | D14: 268.74253 | E14: 299.45106 | F14: 243.72666 | G14: 229.43871 | H14: ='05 Steel Supply Model'!K$14 | I14: =IF(ABS(H14-INDEX(D14:G14,ScenID))<=ABS(H14)*0.005+0.01,"OK","FAIL") | J14: Demand is the least contested part of the model: even the stress case grows consumption, because Indian demand has contracted only once (FY2021) in twelve years.
B15: Crude steel production | C15: Mt | D15: 285.42506 | E15: 314.41346 | F15: 263.78799 | G15: 237.38696 | H15: ='05 Steel Supply Model'!K$25 | I15: =IF(ABS(H15-INDEX(D15:G15,ScenID))<=ABS(H15)*0.005+0.01,"OK","FAIL")
B16: Crude steel capacity | C16: Mtpa | D16: 339.977 | E16: 357.839 | F16: 308.434 | G16: 275.891 | H16: ='06 Capacity Forecast'!K$20 | I16: =IF(ABS(H16-INDEX(D16:G16,ScenID))<=ABS(H16)*0.005+0.01,"OK","FAIL") | J16: Capacity is scenario-dependent through the delivery factor and the secondary residual, but the range is narrow relative to the price range.
B17: Capacity utilisation | C17: % | D17: 0.83954226 | E17: 0.87864502 | F17: 0.85524939 | G17: 0.8604375 | H17: ='08 Capacity Utilisation'!K$16 | I17: =IF(ABS(H17-INDEX(D17:G17,ScenID))<=ABS(H17)*0.005+0.01,"OK","FAIL") | J17: Counter-intuitively HIGHEST in the stress case, because capacity additions are cut harder than demand falls.
B18: Blended realisation | C18: Rs/t | D18: 69005.69 | E18: 70422.294 | F18: 60699.692 | G18: 70221.986 | H18: ='09 Steel Price Forecast'!K$22 | I18: =IF(ABS(H18-INDEX(D18:G18,ScenID))<=ABS(H18)*0.005+0.01,"OK","FAIL") | J18: Note the stress case sits ABOVE the bear case: a rupee collapse to 113/US$ lifts the rupee landed cost of imports by roughly 28% and supports domestic prices.
B19: Cash cost per tonne | C19: Rs/t | D19: 57427.438 | E19: 52672.573 | F19: 55826.576 | G19: 63253.106 | H19: ='11 Cost Curve'!K$17 | I19: =IF(ABS(H19-INDEX(D19:G19,ScenID))<=ABS(H19)*0.005+0.01,"OK","FAIL")
B20: EBITDA per tonne | C20: Rs/t | D20: 11578.252 | E20: 17749.721 | F20: 4873.1156 | G20: 6968.88 | H20: ='13 EBITDA Model'!K$16 | I20: =IF(ABS(H20-INDEX(D20:G20,ScenID))<=ABS(H20)*0.005+0.01,"OK","FAIL")
B21: Industry EBITDA margin | C21: % | D21: 0.16778691 | E21: 0.2520469 | F21: 0.080282378 | G21: 0.099240712 | H21: ='14 Margin Analysis'!K$17 | I21: =IF(ABS(H21-INDEX(D21:G21,ScenID))<=ABS(H21)*0.005+0.01,"OK","FAIL") | J21: Envelope check: bull 25.2% against the FY2022 observed peak of roughly 26%; stress 9.9% in the terminal year having troughed at -9.2% in FY2028.
B22: Industry revenue | C22: Rs cr | D22: 1882078.7 | E22: 2122887.5 | F22: 1524938.1 | G22: 1583075.4 | H22: ='12 Revenue Forecast'!K$16 | I22: =IF(ABS(H22-INDEX(D22:G22,ScenID))<=ABS(H22)*0.005+0.01,"OK","FAIL")
B23: Industry EBITDA | C23: Rs cr | D23: 315788.17 | E23: 535067.21 | F23: 122425.65 | G23: 157105.53 | H23: ='13 EBITDA Model'!K$18 | I23: =IF(ABS(H23-INDEX(D23:G23,ScenID))<=ABS(H23)*0.005+0.01,"OK","FAIL") | J23: The spread from stress to bull is roughly 4.4x, which is the honest measure of uncertainty in an Indian steel forecast seven years out.
B24: Unlevered free cash flow | C24: Rs cr | D24: 66854.321 | E24: 223085.75 | F24: -49522.091 | G24: -5039.8635 | H24: ='16 Cash Flow Model'!K$32 | I24: =IF(ABS(H24-INDEX(D24:G24,ScenID))<=ABS(H24)*0.005+0.01,"OK","FAIL") | J24: Negative in bear and stress: the industry cannot fund roughly Rs 1.1 lakh crore a year of growth capex from a compressed margin.
B25: TIE-OUT SUMMARY | I25: =IF(COUNTIF(I14:I24,"FAIL")=0,"ALL OK","0 CHECK(S) FAILED") | J25: Tolerance is 0.5% plus an absolute floor, to absorb floating-point and rounding differences between Excel and the Python mirror. Any genuine formula error would exceed it by orders of magnitude.
B27: SCENARIO DEFINITIONS
B28: Base Case | D28: RBI's June-2026 FY2027 GDP projection of 6.6% converging to 6.5%. Elasticity 1.15x tapering to 1.05x. Realisation grows at roughly 2.0% a year, BELOW expected inflation, reflecting structural surplus capacity. Iron ore continues its decline to US$93/dmt; coking coal eases to US$200/t. Terminal margin 16.8% against 17.9% in FY2026 - i.e. the base case assumes mild margin erosion, not expansion.
B29: Bull Case | D29: GDP roughly 80bps above base, elasticity 1.30x tapering to 1.15x, iron ore and coking coal at the low end, INR stable at 96. Calibrated to peak at a 26.0% industry margin in FY2030, matching the FY2022 observed cycle peak. This is a genuine ceiling, not an extrapolation.
B30: Bear Case | D30: A DEMAND-LED downturn. GDP roughly 100bps below base and elasticity at 1.00x, but critically iron ore and coking coal FALL WITH demand - to US$83/dmt and US$170/t - because a global demand shortfall is disinflationary for raw materials. Modelling a bear case with demand down AND raw materials up would be internally contradictory. Margins compress to 7-11% rather than collapsing.
B31: Stress Case | D31: A STAGFLATIONARY supply shock plus demand shock. Coking coal spikes to US$300/t - roughly 85% of the Oct-2023 peak of US$354/t - the rupee collapses to 113/US$, GDP falls to 4.4% in FY2027 and conversion cost inflation hits 7.5%. Realisation is HIGHER than the bear case in nominal rupees because of the import-parity effect of the currency, yet margin troughs at -9.2% in FY2028, marginally worse than the worst observation in the database (SAIL, FY2016, -7%). IMPORTANT LIMITATION: the model does not endogenise supply response, so it does not idle capacity when margins turn negative. Read the stress case as a lower bound on margin, not a central expectation.

Sheet 22 Sensitivity Analysis
B1: 22 Sensitivity Analysis
B2: Industry Financial Model | Indian Steel Industry | Horizon FY2027E-FY2033E | Base year FY2026A | Built 03-Aug-2026
B4: OBJECTIVE
B5: Isolates how much of the answer depends on each assumption, including the four that are unsourced.
B6: METHODOLOGY
B7: Three constructs. (1) A tornado ranking every driver by the FY2033 industry EBITDA impact of a 10% ADVERSE move - the direction that reduces EBITDA, which is +10% for cost drivers and -10% for revenue and volume drivers; getting that direction wrong is the commonest tornado error, so it is stated per row. Tornado values are computed by the Python mirror because each requires a full chain re-run. (2) Two LIVE two-variable tables that recompute in Excel. (3) A dedicated block quantifying the unsourced assumptions.
B8: UNITS
B9: Rs crore, Rs per tonne, percentages as decimals.
B10: DEPENDENCIES
B11: Reads the whole model. Read by 24 Dashboard.
B13: A - TORNADO: FY2033E INDUSTRY EBITDA, 10% ADVERSE MOVE (Base Case)
B14: Driver | C14: ID | D14: Adverse direction | E14: FY2033E EBITDA (Rs cr) | F14: Change (Rs cr) | G14: Change (%) | H14: Interpretation
B15: Blended realisation | C15: D09 | D15: -10% | E15: 127580.31 | F15: -188207.87 | G15: -0.59599403 | H15: By far the dominant driver. A 10% realisation move is worth roughly 60% of industry EBITDA, which is the arithmetic of a 17.9% margin: a 10% price move is a 56% move in the margin. Any valuation of this sector is primarily a price call.
B16: USD/INR | C16: D03 | D16: +10% | E16: 241003.39 | F16: -74784.781 | G16: -0.23681945 | H16: The second largest, and frequently underestimated. Iron ore and coking coal are dollar-priced, so a 10% rupee depreciation raises rupee input cost across the whole basket simultaneously. Note the model does NOT credit the offsetting import-parity support to realisation in this isolated flex - that interaction is captured in the stress scenario, which is why the stress case is not simply the sum of these individual flexes.
B17: Real GDP growth | C17: D01 | D17: -10% | E17: 277413.62 | F17: -38374.554 | G17: -0.12151992 | H17: Works through both volume and, via utilisation, price. The fact that GDP and elasticity show identical impacts confirms the model treats them as a pure product, as intended.
B18: Demand elasticity | C18: D02 | D18: -10% | E18: 277413.62 | F18: -38374.554 | G18: -0.12151992 | H18: Identical to GDP by construction - demand growth is their product.
B19: Iron ore price | C19: D10 | D19: +10% | E19: 277647.55 | F19: -38140.621 | G19: -0.12077913 | H19: Iron ore at 45% of the raw material basket, which is 60% of cash cost.
B20: Coking coal price | C20: D11 | D20: +10% | E20: 279144.01 | F20: -36644.16 | G20: -0.11604032 | H20: Coking coal, same basket weight. Note it ranks BELOW iron ore only because the FY2033 base level is closer to its FY2026 reference; in the stress case coking coal is the dominant cost driver.
B21: Conversion cost inflation | C21: D12 | D21: +10% | E21: 292957.34 | F21: -22830.832 | G21: -0.072297931 | H21: Conversion cost inflation on the 40% of cash cost not indexed to raw materials.
B22: Raw material share of cash cost | C22: D13 | D22: +10% | E22: 337081.44 | F22: 21293.273 | G22: 0.067428975 | H22: POSITIVE because raising the raw-material share shifts weight away from conversion cost, which is compounding faster than the raw material basket in the base case. This is a genuine model insight: the direction of this UNSOURCED parameter's effect depends on the relative escalation of the two components.
B23: Secondary capacity additions | C23: D22 | D23: +10% | E23: 303573.17 | F23: -12215.002 | G23: -0.038681 | H23: NEGATIVE - more capacity is EBITDA-negative because it depresses utilisation, which feeds back into price via D23. This is the economically correct result and the opposite of the naive intuition that more capacity means more earnings.
B24: Pipeline delivery factor | C24: D05 | D24: +10% | E24: 309138.12 | F24: -6650.049 | G24: -0.021058575 | H24: Same mechanism as D22, smaller because announced additions are a minority of total additions.
B25: Base Case FY2033E industry EBITDA | E25: 315788.17 | H25: Computed by the Python mirror. Cross-checked against the live workbook by the tie-out on 21 Scenario Manager.
B28: B - HELPER CONSTANTS FOR THE LIVE TABLES (all linked, none re-entered)
B29: FY2026 cash cost anchor | C29: Rs/t | D29: 49241
B30: Raw material share of cash cost | C30: % | D30: '02 Model Assumptions'!K$134
B31: Iron ore weight in basket | C31: % | D31: '02 Model Assumptions'!K$135
B32: FY2033E conversion cost index | C32: x | D32: ='10 Raw Material Forecast'!K$25
B33: FY2033E iron ore in rupees | C33: Rs/dmt | D33: ='10 Raw Material Forecast'!K$20
B34: FY2026 iron ore in rupees | C34: Rs/dmt | D34: 8885.968
B35: FY2026 coking coal in rupees | C35: Rs/t | D35: 19890
B36: FY2033E USD/INR | C36: Rs/US$ | D36: ='10 Raw Material Forecast'!K$17
B37: FY2033E price adjustment factor | C37: x | D37: ='09 Steel Price Forecast'!K$21
B38: FY2033E capacity | C38: Mtpa | D38: ='06 Capacity Forecast'!K$20
B39: FY2033E crude-to-finished ratio | C39: x | D39: ='05 Steel Supply Model'!K$18
B40: FY2033E cash cost | C40: Rs/t | D40: ='11 Cost Curve'!K$17
B43: C - LIVE TABLE 1: FY2033E EBITDA PER TONNE (Rs/t) - realisation vs coking coal
B44: Rows are the FY2033E realisation driver (Rs/t); columns are coking coal (US$/t). Every cell is a live formula rebuilding the cost equation from the helper constants above - change any driver and the whole grid moves.
B45: Realisation \ Coking coal | D45: 160 | E45: 180 | F45: 200 | G45: 220 | H45: 240 | I45: 260 | J45: 280
B46: 58000 | D46: =$B46*$D$37-($D$29*($D$30*($D$31*($D$33/$D$34)+$D$31*(D45*$D$36/$D$35)+(1-2*$D$31)*$D$32)+(1-$D$30)*$D$32)) | E46: =$B46*$D$37-($D$29*($D$30*($D$31*($D$33/$D$34)+$D$31*(E45*$D$36/$D$35)+(1-2*$D$31)*$D$32)+(1-$D$30)*$D$32)) | F46: =$B46*$D$37-($D$29*($D$30*($D$31*($D$33/$D$34)+$D$31*(F45*$D$36/$D$35)+(1-2*$D$31)*$D$32)+(1-$D$30)*$D$32)) | G46: =$B46*$D$37-($D$29*($D$30*($D$31*($D$33/$D$34)+$D$31*(G45*$D$36/$D$35)+(1-2*$D$31)*$D$32)+(1-$D$30)*$D$32)) | H46: =$B46*$D$37-($D$29*($D$30*($D$31*($D$33/$D$34)+$D$31*(H45*$D$36/$D$35)+(1-2*$D$31)*$D$32)+(1-$D$30)*$D$32)) | I46: =$B46*$D$37-($D$29*($D$30*($D$31*($D$33/$D$34)+$D$31*(I45*$D$36/$D$35)+(1-2*$D$31)*$D$32)+(1-$D$30)*$D$32)) | J46: =$B46*$D$37-($D$29*($D$30*($D$31*($D$33/$D$34)+$D$31*(J45*$D$36/$D$35)+(1-2*$D$31)*$D$32)+(1-$D$30)*$D$32))
B47: 61000 | D47: =$B47*$D$37-($D$29*($D$30*($D$31*($D$33/$D$34)+$D$31*(D45*$D$36/$D$35)+(1-2*$D$31)*$D$32)+(1-$D$30)*$D$32)) | E47: =$B47*$D$37-($D$29*($D$30*($D$31*($D$33/$D$34)+$D$31*(E45*$D$36/$D$35)+(1-2*$D$31)*$D$32)+(1-$D$30)*$D$32)) | F47: =$B47*$D$37-($D$29*($D$30*($D$31*($D$33/$D$34)+$D$31*(F45*$D$36/$D$35)+(1-2*$D$31)*$D$32)+(1-$D$30)*$D$32)) | G47: =$B47*$D$37-($D$29*($D$30*($D$31*($D$33/$D$34)+$D$31*(G45*$D$36/$D$35)+(1-2*$D$31)*$D$32)+(1-$D$30)*$D$32)) | H47: =$B47*$D$37-($D$29*($D$30*($D$31*($D$33/$D$34)+$D$31*(H45*$D$36/$D$35)+(1-2*$D$31)*$D$32)+(1-$D$30)*$D$32)) | I47: =$B47*$D$37-($D$29*($D$30*($D$31*($D$33/$D$34)+$D$31*(I45*$D$36/$D$35)+(1-2*$D$31)*$D$32)+(1-$D$30)*$D$32)) | J47: =$B47*$D$37-($D$29*($D$30*($D$31*($D$33/$D$34)+$D$31*(J45*$D$36/$D$35)+(1-2*$D$31)*$D$32)+(1-$D$30)*$D$32))
B48: 64000 | D48: =$B48*$D$37-($D$29*($D$30*($D$31*($D$33/$D$34)+$D$31*(D45*$D$36/$D$35)+(1-2*$D$31)*$D$32)+(1-$D$30)*$D$32)) | E48: =$B48*$D$37-($D$29*($D$30*($D$31*($D$33/$D$34)+$D$31*(E45*$D$36/$D$35)+(1-2*$D$31)*$D$32)+(1-$D$30)*$D$32)) | F48: =$B48*$D$37-($D$29*($D$30*($D$31*($D$33/$D$34)+$D$31*(F45*$D$36/$D$35)+(1-2*$D$31)*$D$32)+(1-$D$30)*$D$32)) | G48: =$B48*$D$37-($D$29*($D$30*($D$31*($D$33/$D$34)+$D$31*(G45*$D$36/$D$35)+(1-2*$D$31)*$D$32)+(1-$D$30)*$D$32)) | H48: =$B48*$D$37-($D$29*($D$30*($D$31*($D$33/$D$34)+$D$31*(H45*$D$36/$D$35)+(1-2*$D$31)*$D$32)+(1-$D$30)*$D$32)) | I48: =$B48*$D$37-($D$29*($D$30*($D$31*($D$33/$D$34)+$D$31*(I45*$D$36/$D$35)+(1-2*$D$31)*$D$32)+(1-$D$30)*$D$32)) | J48: =$B48*$D$37-($D$29*($D$30*($D$31*($D$33/$D$34)+$D$31*(J45*$D$36/$D$35)+(1-2*$D$31)*$D$32)+(1-$D$30)*$D$32))
B49: 66000 | D49: =$B49*$D$37-($D$29*($D$30*($D$31*($D$33/$D$34)+$D$31*(D45*$D$36/$D$35)+(1-2*$D$31)*$D$32)+(1-$D$30)*$D$32)) | E49: =$B49*$D$37-($D$29*($D$30*($D$31*($D$33/$D$34)+$D$31*(E45*$D$36/$D$35)+(1-2*$D$31)*$D$32)+(1-$D$30)*$D$32)) | F49: =$B49*$D$37-($D$29*($D$30*($D$31*($D$33/$D$34)+$D$31*(F45*$D$36/$D$35)+(1-2*$D$31)*$D$32)+(1-$D$30)*$D$32)) | G49: =$B49*$D$37-($D$29*($D$30*($D$31*($D$33/$D$34)+$D$31*(G45*$D$36/$D$35)+(1-2*$D$31)*$D$32)+(1-$D$30)*$D$32)) | H49: =$B49*$D$37-($D$29*($D$30*($D$31*($D$33/$D$34)+$D$31*(H45*$D$36/$D$35)+(1-2*$D$31)*$D$32)+(1-$D$30)*$D$32)) | I49: =$B49*$D$37-($D$29*($D$30*($D$31*($D$33/$D$34)+$D$31*(I45*$D$36/$D$35)+(1-2*$D$31)*$D$32)+(1-$D$30)*$D$32)) | J49: =$B49*$D$37-($D$29*($D$30*($D$31*($D$33/$D$34)+$D$31*(J45*$D$36/$D$35)+(1-2*$D$31)*$D$32)+(1-$D$30)*$D$32))
B50: 68000 | D50: =$B50*$D$37-($D$29*($D$30*($D$31*($D$33/$D$34)+$D$31*(D45*$D$36/$D$35)+(1-2*$D$31)*$D$32)+(1-$D$30)*$D$32)) | E50: =$B50*$D$37-($D$29*($D$30*($D$31*($D$33/$D$34)+$D$31*(E45*$D$36/$D$35)+(1-2*$D$31)*$D$32)+(1-$D$30)*$D$32)) | F50: =$B50*$D$37-($D$29*($D$30*($D$31*($D$33/$D$34)+$D$31*(F45*$D$36/$D$35)+(1-2*$D$31)*$D$32)+(1-$D$30)*$D$32)) | G50: =$B50*$D$37-($D$29*($D$30*($D$31*($D$33/$D$34)+$D$31*(G45*$D$36/$D$35)+(1-2*$D$31)*$D$32)+(1-$D$30)*$D$32)) | H50: =$B50*$D$37-($D$29*($D$30*($D$31*($D$33/$D$34)+$D$31*(H45*$D$36/$D$35)+(1-2*$D$31)*$D$32)+(1-$D$30)*$D$32)) | I50: =$B50*$D$37-($D$29*($D$30*($D$31*($D$33/$D$34)+$D$31*(I45*$D$36/$D$35)+(1-2*$D$31)*$D$32)+(1-$D$30)*$D$32)) | J50: =$B50*$D$37-($D$29*($D$30*($D$31*($D$33/$D$34)+$D$31*(J45*$D$36/$D$35)+(1-2*$D$31)*$D$32)+(1-$D$30)*$D$32))
B51: 71000 | D51: =$B51*$D$37-($D$29*($D$30*($D$31*($D$33/$D$34)+$D$31*(D45*$D$36/$D$35)+(1-2*$D$31)*$D$32)+(1-$D$30)*$D$32)) | E51: =$B51*$D$37-($D$29*($D$30*($D$31*($D$33/$D$34)+$D$31*(E45*$D$36/$D$35)+(1-2*$D$31)*$D$32)+(1-$D$30)*$D$32)) | F51: =$B51*$D$37-($D$29*($D$30*($D$31*($D$33/$D$34)+$D$31*(F45*$D$36/$D$35)+(1-2*$D$31)*$D$32)+(1-$D$30)*$D$32)) | G51: =$B51*$D$37-($D$29*($D$30*($D$31*($D$33/$D$34)+$D$31*(G45*$D$36/$D$35)+(1-2*$D$31)*$D$32)+(1-$D$30)*$D$32)) | H51: =$B51*$D$37-($D$29*($D$30*($D$31*($D$33/$D$34)+$D$31*(H45*$D$36/$D$35)+(1-2*$D$31)*$D$32)+(1-$D$30)*$D$32)) | I51: =$B51*$D$37-($D$29*($D$30*($D$31*($D$33/$D$34)+$D$31*(I45*$D$36/$D$35)+(1-2*$D$31)*$D$32)+(1-$D$30)*$D$32)) | J51: =$B51*$D$37-($D$29*($D$30*($D$31*($D$33/$D$34)+$D$31*(J45*$D$36/$D$35)+(1-2*$D$31)*$D$32)+(1-$D$30)*$D$32))
B52: 74000 | D52: =$B52*$D$37-($D$29*($D$30*($D$31*($D$33/$D$34)+$D$31*(D45*$D$36/$D$35)+(1-2*$D$31)*$D$32)+(1-$D$30)*$D$32)) | E52: =$B52*$D$37-($D$29*($D$30*($D$31*($D$33/$D$34)+$D$31*(E45*$D$36/$D$35)+(1-2*$D$31)*$D$32)+(1-$D$30)*$D$32)) | F52: =$B52*$D$37-($D$29*($D$30*($D$31*($D$33/$D$34)+$D$31*(F45*$D$36/$D$35)+(1-2*$D$31)*$D$32)+(1-$D$30)*$D$32)) | G52: =$B52*$D$37-($D$29*($D$30*($D$31*($D$33/$D$34)+$D$31*(G45*$D$36/$D$35)+(1-2*$D$31)*$D$32)+(1-$D$30)*$D$32)) | H52: =$B52*$D$37-($D$29*($D$30*($D$31*($D$33/$D$34)+$D$31*(H45*$D$36/$D$35)+(1-2*$D$31)*$D$32)+(1-$D$30)*$D$32)) | I52: =$B52*$D$37-($D$29*($D$30*($D$31*($D$33/$D$34)+$D$31*(I45*$D$36/$D$35)+(1-2*$D$31)*$D$32)+(1-$D$30)*$D$32)) | J52: =$B52*$D$37-($D$29*($D$30*($D$31*($D$33/$D$34)+$D$31*(J45*$D$36/$D$35)+(1-2*$D$31)*$D$32)+(1-$D$30)*$D$32))
B53: 77000 | D53: =$B53*$D$37-($D$29*($D$30*($D$31*($D$33/$D$34)+$D$31*(D45*$D$36/$D$35)+(1-2*$D$31)*$D$32)+(1-$D$30)*$D$32)) | E53: =$B53*$D$37-($D$29*($D$30*($D$31*($D$33/$D$34)+$D$31*(E45*$D$36/$D$35)+(1-2*$D$31)*$D$32)+(1-$D$30)*$D$32)) | F53: =$B53*$D$37-($D$29*($D$30*($D$31*($D$33/$D$34)+$D$31*(F45*$D$36/$D$35)+(1-2*$D$31)*$D$32)+(1-$D$30)*$D$32)) | G53: =$B53*$D$37-($D$29*($D$30*($D$31*($D$33/$D$34)+$D$31*(G45*$D$36/$D$35)+(1-2*$D$31)*$D$32)+(1-$D$30)*$D$32)) | H53: =$B53*$D$37-($D$29*($D$30*($D$31*($D$33/$D$34)+$D$31*(H45*$D$36/$D$35)+(1-2*$D$31)*$D$32)+(1-$D$30)*$D$32)) | I53: =$B53*$D$37-($D$29*($D$30*($D$31*($D$33/$D$34)+$D$31*(I45*$D$36/$D$35)+(1-2*$D$31)*$D$32)+(1-$D$30)*$D$32)) | J53: =$B53*$D$37-($D$29*($D$30*($D$31*($D$33/$D$34)+$D$31*(J45*$D$36/$D$35)+(1-2*$D$31)*$D$32)+(1-$D$30)*$D$32))
B54: Interpretation | D54: At the Base Case FY2033E realisation driver of Rs 68,000/t, EBITDA per tonne swings from roughly Rs 14,600/t at US$160/t coking coal to roughly Rs 6,100/t at US$280/t - a 2.4x range on the coking coal axis alone. This is why a licensed coking coal series is the highest-priority data gap in the model.
B57: D - LIVE TABLE 2: FY2033E INDUSTRY EBITDA (Rs cr) - utilisation vs realisation
B58: Rows are FY2033E capacity utilisation; columns are the FY2033E realisation driver (Rs/t). Volume is derived as capacity x utilisation / the crude-to-finished ratio. This is a PARTIAL sensitivity: it holds the lagged price feedback at its base value, so it isolates the volume and price effects and does not double-count the feedback.
B59: Utilisation \ Realisation | D59: 58000 | E59: 61000 | F59: 64000 | G59: 66000 | H59: 68000 | I59: 71000 | J59: 74000 | K59: 77000
B60: 0.74 | D60: =($D$38*$B60/$D$39)*(D59*$D$37-$D$40)/10 | E60: =($D$38*$B60/$D$39)*(E59*$D$37-$D$40)/10 | F60: =($D$38*$B60/$D$39)*(F59*$D$37-$D$40)/10 | G60: =($D$38*$B60/$D$39)*(G59*$D$37-$D$40)/10 | H60: =($D$38*$B60/$D$39)*(H59*$D$37-$D$40)/10 | I60: =($D$38*$B60/$D$39)*(I59*$D$37-$D$40)/10 | J60: =($D$38*$B60/$D$39)*(J59*$D$37-$D$40)/10 | K60: =($D$38*$B60/$D$39)*(K59*$D$37-$D$40)/10
B61: 0.78 | D61: =($D$38*$B61/$D$39)*(D59*$D$37-$D$40)/10 | E61: =($D$38*$B61/$D$39)*(E59*$D$37-$D$40)/10 | F61: =($D$38*$B61/$D$39)*(F59*$D$37-$D$40)/10 | G61: =($D$38*$B61/$D$39)*(G59*$D$37-$D$40)/10 | H61: =($D$38*$B61/$D$39)*(H59*$D$37-$D$40)/10 | I61: =($D$38*$B61/$D$39)*(I59*$D$37-$D$40)/10 | J61: =($D$38*$B61/$D$39)*(J59*$D$37-$D$40)/10 | K61: =($D$38*$B61/$D$39)*(K59*$D$37-$D$40)/10
B62: 0.82 | D62: =($D$38*$B62/$D$39)*(D59*$D$37-$D$40)/10 | E62: =($D$38*$B62/$D$39)*(E59*$D$37-$D$40)/10 | F62: =($D$38*$B62/$D$39)*(F59*$D$37-$D$40)/10 | G62: =($D$38*$B62/$D$39)*(G59*$D$37-$D$40)/10 | H62: =($D$38*$B62/$D$39)*(H59*$D$37-$D$40)/10 | I62: =($D$38*$B62/$D$39)*(I59*$D$37-$D$40)/10 | J62: =($D$38*$B62/$D$39)*(J59*$D$37-$D$40)/10 | K62: =($D$38*$B62/$D$39)*(K59*$D$37-$D$40)/10
B63: 0.84 | D63: =($D$38*$B63/$D$39)*(D59*$D$37-$D$40)/10 | E63: =($D$38*$B63/$D$39)*(E59*$D$37-$D$40)/10 | F63: =($D$38*$B63/$D$39)*(F59*$D$37-$D$40)/10 | G63: =($D$38*$B63/$D$39)*(G59*$D$37-$D$40)/10 | H63: =($D$38*$B63/$D$39)*(H59*$D$37-$D$40)/10 | I63: =($D$38*$B63/$D$39)*(I59*$D$37-$D$40)/10 | J63: =($D$38*$B63/$D$39)*(J59*$D$37-$D$40)/10 | K63: =($D$38*$B63/$D$39)*(K59*$D$37-$D$40)/10
B64: 0.86 | D64: =($D$38*$B64/$D$39)*(D59*$D$37-$D$40)/10 | E64: =($D$38*$B64/$D$39)*(E59*$D$37-$D$40)/10 | F64: =($D$38*$B64/$D$39)*(F59*$D$37-$D$40)/10 | G64: =($D$38*$B64/$D$39)*(G59*$D$37-$D$40)/10 | H64: =($D$38*$B64/$D$39)*(H59*$D$37-$D$40)/10 | I64: =($D$38*$B64/$D$39)*(I59*$D$37-$D$40)/10 | J64: =($D$38*$B64/$D$39)*(J59*$D$37-$D$40)/10 | K64: =($D$38*$B64/$D$39)*(K59*$D$37-$D$40)/10
B65: 0.9 | D65: =($D$38*$B65/$D$39)*(D59*$D$37-$D$40)/10 | E65: =($D$38*$B65/$D$39)*(E59*$D$37-$D$40)/10 | F65: =($D$38*$B65/$D$39)*(F59*$D$37-$D$40)/10 | G65: =($D$38*$B65/$D$39)*(G59*$D$37-$D$40)/10 | H65: =($D$38*$B65/$D$39)*(H59*$D$37-$D$40)/10 | I65: =($D$38*$B65/$D$39)*(I59*$D$37-$D$40)/10 | J65: =($D$38*$B65/$D$39)*(J59*$D$37-$D$40)/10 | K65: =($D$38*$B65/$D$39)*(K59*$D$37-$D$40)/10
B68: E - HOW MUCH OF THE ANSWER RESTS ON UNSOURCED ASSUMPTIONS
B69: Unsourced assumption | C69: ID | D69: Base value | E69: Plausible range | F69: FY2033E EBITDA impact across the range | G69: Materiality verdict
B70: Raw material share of cash cost | C70: D13 | D70: 60% | E70: 55% to 65% | F70: Roughly Rs 21,000 cr per 10% relative change, i.e. about 6.7% of FY2033E EBITDA | G70: MATERIAL but second-order. The direction depends on relative escalation of raw material versus conversion cost, so it is not a simple bias.
B71: Price sensitivity to utilisation | C71: D23 | D71: 0.40x | E71: 0.20x to 0.60x | F71: Sets the whole magnitude of the capacity feedback. At 0.20x the capacity drivers halve in importance; at 0.60x they roughly double. | G71: MATERIAL. This parameter determines whether capacity matters at all. It is the single most important unsourced input in the model.
B72: Net working capital days | C72: D18 | D72: 45 days | E72: 35 to 60 days | F72: Roughly Rs 12,000 cr of terminal-year cash flow per 4.5 days | G72: MATERIAL FOR CASH FLOW AND CREDIT, immaterial for EBITDA. Must be fixed before any financing work.
B73: Equity risk premium and beta (within WACC) | C73: R08 | D73: 6.5% and 1.20x | E73: 5.5-7.5%, 1.0-1.4x | F73: Roughly 11% of enterprise value per 120bps of WACC | G73: MATERIAL FOR VALUATION ONLY. Does not touch operating forecasts. Substitute house assumptions on 02 Section D.
B74: Maximum practical utilisation | C74: D25 | D74: 92% | E74: 88% to 95% | F74: Zero in the Base Case - the ceiling does not bind, peak utilisation is 84.0% | G74: IMMATERIAL in the base case; becomes material only in the bull case where utilisation reaches 87.9%.
B75: Maintenance capex | C75: D17 | D75: 3.0% of revenue | E75: 2.5% to 4.0% | F75: Roughly Rs 16,000 cr of terminal-year free cash flow per 100bps | G75: MATERIAL FOR CASH FLOW, immaterial for EBITDA.
B76: Indian emission intensity and EU carbon price | C76: 20 ESG | D76: 2.55 tCO2e/t, EUR 85/t | E76: Wide - both unsourced | F76: CBAM cost is roughly Rs 2,100 cr at the base inputs, under 1% of FY2033E EBITDA | G76: IMMATERIAL at current export volumes, but scales with the EU export share and the carbon price. Watch rather than model.
B78: Read this block first. It is the honest answer to 'how much should I trust this model?' - the operating forecast is robust to the unsourced inputs; the cash flow and valuation output is not, until working capital, WACC and a coking coal series are properly sourced.

Sheet 23 Comparable Valuation
B1: 23 Comparable Valuation
B2: Industry Financial Model | Indian Steel Industry | Horizon FY2027E-FY2033E | Base year FY2026A | Built 03-Aug-2026
B4: OBJECTIVE
B5: Valuation output: trading comparables, EV per tonne, replacement cost, ROIC and a DCF built off the industry free cash flow.
B6: METHODOLOGY
B7: SHARE PRICES WERE NOT SOURCED in this research cycle, so they are USER INPUTS (shaded). Every multiple, market capitalisation and enterprise value on this sheet is a live formula that computes the moment prices are entered - nothing has been fabricated to fill the gap. Share counts are DERIVED as profit after tax divided by earnings per share, which reconciles well for SAIL, Jindal Steel, Jindal Stainless and Tata Steel but NOT for JSW Steel, where EPS is struck on profit attributable to owners while PAT includes an Rs 18,051 cr exceptional gain; that row is flagged and the cell is editable.
B8: UNITS
B9: Rs crore, Rs per share, times, Rs per tonne.
B10: DEPENDENCIES
B11: Reads 13 EBITDA, 16 Cash Flow, 17 Capital Allocation, 02 Assumptions.
B13: A - TRADING COMPARABLES (enter share prices in the shaded column)
B14: Company | C14: FY2026 EBITDA (Rs cr) | D14: Net debt (Rs cr) | E14: PAT (Rs cr) | F14: EPS (Rs) | G14: Shares (cr) - derived | H14: Share price (Rs) - USER INPUT | I14: Market cap (Rs cr) | J14: EV (Rs cr) | K14: EV/EBITDA (x) | L14: Capacity (Mtpa) | M14: EV per tonne (Rs/t) | N14: Conf. | O14: Notes
B15: Tata Steel | C15: 34272 | D15: 80144 | E15: 10886 | F15: 8.65 | G15: =E15/F15 | I15: =IFERROR(G15*H15,"") | J15: =IFERROR(I15+D15,"") | K15: =IFERROR(J15/C15,"") | L15: 26 | M15: =IFERROR(J15/L15*10000,"") | N15: Medium | O15: India segment used for volume and margin. Netherlands carries a disclosed material uncertainty related to going concern (Master DB, policy P18) - the single largest identifiable downside in the universe and NOT captured in this industry model, which forecasts India only. Capacity basis: INDICATIVE - Tata Steel discloses 35 Mtpa GLOBAL group crude steel capacity. The India component is not separately disclosed in the database; 26 Mtpa is inferred from FY2026 India crude steel production of 23.43 Mt at roughly 90% utilisation and is flagged Low confidence.
B16: JSW Steel | C16: 29240 | D16: 53870 | E16: 25508 | F16: 91.26 | G16: =E16/F16 | I16: =IFERROR(G16*H16,"") | J16: =IFERROR(I16+D16,"") | K16: =IFERROR(J16/C16,"") | L16: 31.9 | M16: =IFERROR(J16/L16*10000,"") | N16: Medium | O16: FY2027 additions include BMM Ispat (0.90 Mtpa), an acquisition of existing capacity: it adds to JSW but NOT to national capacity. BPSL was deconsolidated from 27-Mar-2026, so FY2026 to FY2027 company volumes are not like-for-like. DERIVED SHARE COUNT IS UNRELIABLE for JSW: PAT of Rs 25,508 cr includes the Rs 18,051 cr BPSL slump-sale gain while EPS of Rs 91.26 is on profit attributable to owners, so PAT/EPS overstates the share count by roughly 15%. Overwrite column G with the actual count. Capacity basis: JSW Steel India existing capacity, disclosed. Cross-checked: FY2026 India production of 29.25 Mt at the stated 92% utilisation implies 31.8 Mtpa.
B17: SAIL | C17: 13146 | D17: 31928 | E17: 3373 | F17: 8.17 | G17: =E17/F17 | I17: =IFERROR(G17*H17,"") | J17: =IFERROR(I17+D17,"") | K17: =IFERROR(J17/C17,"") | L17: 19.676 | M17: =IFERROR(J17/L17*10000,"") | N17: Medium | O17: EBITDA per tonne is struck on the STANDALONE EBITDA headline over standalone sales volume. Do not pair a consolidated enterprise value with this EBITDA - see Master DB Conflict C09. Capacity basis: SAIL crude steel operating capacity per Ministry of Steel, Rajya Sabha USQ 3982 answered 27-Mar-2026.
B18: Jindal Steel | C18: 9660 | D18: 16019 | E18: 3361 | F18: 33.01 | G18: =E18/F18 | I18: =IFERROR(G18*H18,"") | J18: =IFERROR(I18+D18,"") | K18: =IFERROR(J18/C18,"") | L18: 15.6 | M18: =IFERROR(J18/L18*10000,"") | N18: Medium | O18: Capacity rose from 9.6 to 15.6 Mtpa in FY2026, so FY2027 volume growth comes from utilising capacity already built rather than from new additions. Company guidance for FY2027 is 11.0-11.5 Mt of production against 9.25 Mt in FY2026. Capacity basis: Jindal Steel total steelmaking capacity entering FY2027, disclosed.
B19: Jindal Stainless | C19: 5560 | D19: 3040 | E19: 3185 | F19: 38.74 | G19: =E19/F19 | I19: =IFERROR(G19*H19,"") | J19: =IFERROR(I19+D19,"") | K19: =IFERROR(J19/C19,"") | L19: 3 | M19: =IFERROR(J19/L19*10000,"") | N19: Medium | O19: STAINLESS. Realisation of roughly Rs 1,67,000/t and EBITDA per tonne of Rs 21,634 are not comparable with carbon steel and this company is EXCLUDED from the blended industry realisation anchor. Management guided FY2027 EBITDA per tonne to Rs 18,000-20,000, i.e. BELOW the FY2026 outcome. Capacity basis: Jindal Stainless INDIA melt capacity. Group melt capacity is 4.2 Mtpa including 1.2 Mtpa in Indonesia, which is excluded from the India build.
B20: AM/NS India | C20: 69 | L20: 9 | M20: =IFERROR(J20/L20*10000,"") | N20: n/a | O20: Unlisted 60:40 joint venture. All figures are 100% basis, USD, calendar quarters, converted at the derived FY2026 average USD/INR of 88.4. The fiscal-year figures are themselves derived by summing calendar quarters - Master DB Conflict C16. Unlisted - no market-based valuation is possible. Capacity basis: AM/NS India Hazira capacity, expanding to 15 Mtpa.
B21: RINL | N21: n/a | O21: Unlisted and wholly Government-owned. No EBITDA, balance sheet or valuation data is publicly available, so RINL appears in the volume build only. Unlisted - no market-based valuation is possible. Capacity basis: Not verified - a 7.3 Mtpa liquid steel nameplate is widely cited but is not asserted in the database.
B23: Median EV/EBITDA (listed, once prices entered) | K23: =IFERROR(MEDIAN(K15:K21),"enter prices") | O23: Live. Compare against the exit multiple driver D19 of 6.0x, which is NOT sourced and should be re-based on this observed evidence once prices are entered.
B26: B - REPLACEMENT COST AND EV PER TONNE BENCHMARK
B27: Greenfield / brownfield capex intensity | D27: '02 Model Assumptions'!K$137 | O27: From driver D16 - Rs 55,000/t base. Cross-checked against JSW JVML at Rs 52,000/t, SAIL at roughly Rs 67,000/t and Tata Ludhiana EAF at Rs 42,700/t.
B28: Replacement cost of India's FY2026 capacity | D28: =220.4*D27/10 | O28: 220.4 Mtpa at the capex intensity above. A useful sanity bound: an acquirer should not pay materially more per tonne than it costs to build, adjusted for time to market, permits and captive raw material.
B29: Implied EV per tonne at the exit multiple | D29: =IFERROR('13 EBITDA Model'!K$18*'02 Model Assumptions'!K$140/('06 Capacity Forecast'!K$20)*10,"") | O29: FY2033E industry EBITDA at the exit multiple D19, divided by FY2033E capacity. Compare against replacement cost: an implied EV/t far above build cost signals either scarcity value or overvaluation.
B32: C - INDUSTRY DCF (unlevered, off 16 Cash Flow Model)
B33: Line item | C33: Unit | D33: FY2026A | E33: FY2027E | F33: FY2028E | G33: FY2029E | H33: FY2030E | I33: FY2031E | J33: FY2032E | K33: FY2033E | L33: CAGR | M33: Source | N33: Conf. | O33: Notes / methodology
B34: Unlevered free cash flow | C34: Rs cr | E34: ='16 Cash Flow Model'!E$32 | F34: ='16 Cash Flow Model'!F$32 | G34: ='16 Cash Flow Model'!G$32 | H34: ='16 Cash Flow Model'!H$32 | I34: ='16 Cash Flow Model'!I$32 | J34: ='16 Cash Flow Model'!J$32 | K34: ='16 Cash Flow Model'!K$32 | M34: 16 Cash Flow | N34: Medium
B35: WACC | C35: % | E35: '02 Model Assumptions'!E$141 | F35: '02 Model Assumptions'!F$141 | G35: '02 Model Assumptions'!G$141 | H35: '02 Model Assumptions'!H$141 | I35: '02 Model Assumptions'!I$141 | J35: '02 Model Assumptions'!J$141 | K35: '02 Model Assumptions'!K$141 | M35: 02 Assumptions | N35: Medium | O35: Cross-checked against the build-up on 02 Section D by 25 Audit Checks.
B36: Discount period | C36: years | E36: 0.5 | F36: 1.5 | G36: 2.5 | H36: 3.5 | I36: 4.5 | J36: 5.5 | K36: 6.5 | M36: Convention | N36: High | O36: MID-YEAR CONVENTION: cash flows are assumed to arise evenly through the year, so they are discounted from the mid-point. Using year-end would understate value by roughly 5-6% at a 12% WACC.
B37: Discount factor | C37: x | E37: =1/(1+E35)^E36 | F37: =1/(1+F35)^F36 | G37: =1/(1+G35)^G36 | H37: =1/(1+H35)^H36 | I37: =1/(1+I35)^I36 | J37: =1/(1+J35)^J36 | K37: =1/(1+K35)^K36 | M37: Computed | N37: Medium
B38: Present value of FCF | C38: Rs cr | E38: =E34*E37 | F38: =F34*F37 | G38: =G34*G37 | H38: =H34*H37 | I38: =I34*I37 | J38: =J34*J37 | K38: =K34*K37 | M38: Computed | N38: Medium
B40: Sum of PV of explicit forecast FCF | D40: =SUM(E38:K38) | O40: Seven years, FY2027E to FY2033E.
B41: Terminal EBITDA (FY2033E) | D41: ='13 EBITDA Model'!K$18 | O41: FY2033 is a NORMALISED year - the FY2030-FY2031 capacity cohort has reached steady-state utilisation - which is the whole reason the horizon is 7 years rather than 5. Check the cycle position on 18 before accepting it as mid-cycle.
B42: Exit EV/EBITDA multiple | D42: ='02 Model Assumptions'!K$140 | O42: 6.0x base. NOT SOURCED - re-base on the observed median in section A once share prices are entered.
B43: Terminal value | D43: =D41*D42 | O43: Terminal EBITDA times the exit multiple.
B44: PV of terminal value | D44: =D43*K37 | O44: Discounted at the terminal-year discount factor.
B45: ENTERPRISE VALUE | D45: =D40+D44 | O45: Sum of the explicit PV and the discounted terminal value.
B46: Terminal value as % of EV | D46: =IFERROR(D44/D45,"") | O46: IF THIS EXCEEDS ROUGHLY 75% the valuation is essentially a terminal-multiple assertion rather than a forecast, and the exit multiple - which is unsourced - dominates. Watch this number.
B48: D - RETURNS
B49: Line item | C49: Unit | D49: FY2026A | E49: FY2027E | F49: FY2028E | G49: FY2029E | H49: FY2030E | I49: FY2031E | J49: FY2032E | K49: FY2033E | L49: CAGR | M49: Source | N49: Conf. | O49: Notes / methodology
B50: EBIT | C50: Rs cr | E50: ='16 Cash Flow Model'!E$18 | F50: ='16 Cash Flow Model'!F$18 | G50: ='16 Cash Flow Model'!G$18 | H50: ='16 Cash Flow Model'!H$18 | I50: ='16 Cash Flow Model'!I$18 | J50: ='16 Cash Flow Model'!J$18 | K50: ='16 Cash Flow Model'!K$18 | M50: 16 Cash Flow | N50: Medium
B51: Effective tax rate | C51: % | E51: '02 Model Assumptions'!E$136 | F51: '02 Model Assumptions'!F$136 | G51: '02 Model Assumptions'!G$136 | H51: '02 Model Assumptions'!H$136 | I51: '02 Model Assumptions'!I$136 | J51: '02 Model Assumptions'!J$136 | K51: '02 Model Assumptions'!K$136 | M51: 02 Assumptions | N51: Medium
B52: NOPAT | C52: Rs cr | E52: =E50*(1-E51) | F52: =F50*(1-F51) | G52: =G50*(1-G51) | H52: =H50*(1-H51) | I52: =I50*(1-I51) | J52: =J50*(1-J51) | K52: =K50*(1-K51) | M52: Computed | N52: Medium
B53: Invested capital (proxy) | C53: Rs cr | E53: =220.4*'02 Model Assumptions'!E$137/10+'15 Working Capital Model'!E$16 | F53: =220.4*'02 Model Assumptions'!F$137/10+'15 Working Capital Model'!F$16 | G53: =220.4*'02 Model Assumptions'!G$137/10+'15 Working Capital Model'!G$16 | H53: =220.4*'02 Model Assumptions'!H$137/10+'15 Working Capital Model'!H$16 | I53: =220.4*'02 Model Assumptions'!I$137/10+'15 Working Capital Model'!I$16 | J53: =220.4*'02 Model Assumptions'!J$137/10+'15 Working Capital Model'!J$16 | K53: =220.4*'02 Model Assumptions'!K$137/10+'15 Working Capital Model'!K$16 | M53: Computed - PROXY | N53: Low | O53: PROXY ONLY: FY2026 capacity at replacement cost plus net working capital. The database does not carry net fixed assets, so a true invested-capital base could not be built. A replacement-cost proxy understates ROIC for older, depreciated assets and is stated as indicative.
B54: ROIC (indicative) | C54: % | E54: =IFERROR(E52/E53,"") | F54: =IFERROR(F52/F53,"") | G54: =IFERROR(G52/G53,"") | H54: =IFERROR(H52/H53,"") | I54: =IFERROR(I52/I53,"") | J54: =IFERROR(J52/J53,"") | K54: =IFERROR(K52/K53,"") | M54: Computed | N54: Low
B55: ROIC less WACC (value spread) | C55: ppt | E55: =E54-E35 | F55: =F54-F35 | G55: =G54-G35 | H55: =H54-H35 | I55: =I54-I35 | J55: =J54-J35 | K55: =K54-K35 | M55: Computed | N55: Low | O55: THE VALUE-CREATION TEST. A persistently negative spread means the industry destroys value by adding capacity, however strong the volume growth - which is the central strategic question for Indian steel and the reason capacity discipline matters more than capacity ambition.
B57: This is an INDUSTRY DCF. It is a sanity frame and a source of mid-cycle multiples, not a substitute for a single-name model. Every line needed for a single-name build - volume, realisation spread, cost spread, capex, working capital - is isolated elsewhere in this workbook.

Sheet 24 Industry Dashboard
B1: 24 Industry Dashboard
B2: Industry Financial Model | Indian Steel Industry | Horizon FY2027E-FY2033E | Base year FY2026A | Built 03-Aug-2026
B4: OBJECTIVE
B5: One-page summary of the active scenario for an investment committee or board pack.
B6: METHODOLOGY
B7: Every figure is a live link. Nothing on this sheet is entered.
B8: UNITS
B9: As stated per row.
B10: DEPENDENCIES
B11: Reads the whole model.
B13: ACTIVE SCENARIO | D13: ='01 Control Panel'!$D$14
B15: Line item | C15: Unit | D15: FY2026A | E15: FY2027E | F15: FY2028E | G15: FY2029E | H15: FY2030E | I15: FY2031E | J15: FY2032E | K15: FY2033E | L15: CAGR | M15: Source | N15: Conf. | O15: Notes / methodology
B16: DEMAND AND SUPPLY
B17: Apparent finished steel consumption | C17: Mt | D17: =IF(ISBLANK('04 Steel Demand Model'!D$17),"n/a",'04 Steel Demand Model'!D$17) | E17: ='04 Steel Demand Model'!E$17 | F17: ='04 Steel Demand Model'!F$17 | G17: ='04 Steel Demand Model'!G$17 | H17: ='04 Steel Demand Model'!H$17 | I17: ='04 Steel Demand Model'!I$17 | J17: ='04 Steel Demand Model'!J$17 | K17: ='04 Steel Demand Model'!K$17 | L17: =IFERROR(IF(AND(ISNUMBER(D17),ISNUMBER(K17),D17>0),(K17/D17)^(1/7)-1,""),"") | M17: 04
B18: Consumption growth | C18: % | D18: =IF(ISBLANK('04 Steel Demand Model'!D$16),"n/a",'04 Steel Demand Model'!D$16) | E18: ='04 Steel Demand Model'!E$16 | F18: ='04 Steel Demand Model'!F$16 | G18: ='04 Steel Demand Model'!G$16 | H18: ='04 Steel Demand Model'!H$16 | I18: ='04 Steel Demand Model'!I$16 | J18: ='04 Steel Demand Model'!J$16 | K18: ='04 Steel Demand Model'!K$16 | M18: 04
B19: Per capita consumption | C19: kg | D19: =IF(ISBLANK('04 Steel Demand Model'!D$23),"n/a",'04 Steel Demand Model'!D$23) | E19: ='04 Steel Demand Model'!E$23 | F19: ='04 Steel Demand Model'!F$23 | G19: ='04 Steel Demand Model'!G$23 | H19: ='04 Steel Demand Model'!H$23 | I19: ='04 Steel Demand Model'!I$23 | J19: ='04 Steel Demand Model'!J$23 | K19: ='04 Steel Demand Model'!K$23 | L19: =IFERROR(IF(AND(ISNUMBER(D19),ISNUMBER(K19),D19>0),(K19/D19)^(1/7)-1,""),"") | M19: 04
B20: Crude steel production | C20: Mt | D20: =IF(ISBLANK('05 Steel Supply Model'!D$25),"n/a",'05 Steel Supply Model'!D$25) | E20: ='05 Steel Supply Model'!E$25 | F20: ='05 Steel Supply Model'!F$25 | G20: ='05 Steel Supply Model'!G$25 | H20: ='05 Steel Supply Model'!H$25 | I20: ='05 Steel Supply Model'!I$25 | J20: ='05 Steel Supply Model'!J$25 | K20: ='05 Steel Supply Model'!K$25 | L20: =IFERROR(IF(AND(ISNUMBER(D20),ISNUMBER(K20),D20>0),(K20/D20)^(1/7)-1,""),"") | M20: 05
B21: Crude steel capacity | C21: Mtpa | D21: =IF(ISBLANK('06 Capacity Forecast'!D$20),"n/a",'06 Capacity Forecast'!D$20) | E21: ='06 Capacity Forecast'!E$20 | F21: ='06 Capacity Forecast'!F$20 | G21: ='06 Capacity Forecast'!G$20 | H21: ='06 Capacity Forecast'!H$20 | I21: ='06 Capacity Forecast'!I$20 | J21: ='06 Capacity Forecast'!J$20 | K21: ='06 Capacity Forecast'!K$20 | L21: =IFERROR(IF(AND(ISNUMBER(D21),ISNUMBER(K21),D21>0),(K21/D21)^(1/7)-1,""),"") | M21: 06
B22: Capacity utilisation | C22: % | D22: =IF(ISBLANK('08 Capacity Utilisation'!D$16),"n/a",'08 Capacity Utilisation'!D$16) | E22: ='08 Capacity Utilisation'!E$16 | F22: ='08 Capacity Utilisation'!F$16 | G22: ='08 Capacity Utilisation'!G$16 | H22: ='08 Capacity Utilisation'!H$16 | I22: ='08 Capacity Utilisation'!I$16 | J22: ='08 Capacity Utilisation'!J$16 | K22: ='08 Capacity Utilisation'!K$16 | M22: 08
B23: PRICES AND COSTS
B24: Blended realisation | C24: Rs/t | D24: =IF(ISBLANK('09 Steel Price Forecast'!D$22),"n/a",'09 Steel Price Forecast'!D$22) | E24: ='09 Steel Price Forecast'!E$22 | F24: ='09 Steel Price Forecast'!F$22 | G24: ='09 Steel Price Forecast'!G$22 | H24: ='09 Steel Price Forecast'!H$22 | I24: ='09 Steel Price Forecast'!I$22 | J24: ='09 Steel Price Forecast'!J$22 | K24: ='09 Steel Price Forecast'!K$22 | L24: =IFERROR(IF(AND(ISNUMBER(D24),ISNUMBER(K24),D24>0),(K24/D24)^(1/7)-1,""),"") | M24: 09
B25: Iron ore 62% Fe CFR China | C25: US$/dmt | D25: =IF(ISBLANK('10 Raw Material Forecast'!D$15),"n/a",'10 Raw Material Forecast'!D$15) | E25: ='10 Raw Material Forecast'!E$15 | F25: ='10 Raw Material Forecast'!F$15 | G25: ='10 Raw Material Forecast'!G$15 | H25: ='10 Raw Material Forecast'!H$15 | I25: ='10 Raw Material Forecast'!I$15 | J25: ='10 Raw Material Forecast'!J$15 | K25: ='10 Raw Material Forecast'!K$15 | L25: =IFERROR(IF(AND(ISNUMBER(D25),ISNUMBER(K25),D25>0),(K25/D25)^(1/7)-1,""),"") | M25: 10
B26: Premium HCC coking coal | C26: US$/t | D26: =IF(ISBLANK('10 Raw Material Forecast'!D$16),"n/a",'10 Raw Material Forecast'!D$16) | E26: ='10 Raw Material Forecast'!E$16 | F26: ='10 Raw Material Forecast'!F$16 | G26: ='10 Raw Material Forecast'!G$16 | H26: ='10 Raw Material Forecast'!H$16 | I26: ='10 Raw Material Forecast'!I$16 | J26: ='10 Raw Material Forecast'!J$16 | K26: ='10 Raw Material Forecast'!K$16 | L26: =IFERROR(IF(AND(ISNUMBER(D26),ISNUMBER(K26),D26>0),(K26/D26)^(1/7)-1,""),"") | M26: 10
