Workbook
Name ScenID: #REF!
Name Selected_Scenario: 'Scenario Manager'!#REF!

Sheet Cover
A1: INDUSTRY FINANCIAL MODEL
A2: INDIAN STEEL INDUSTRY
A4: Indian Steel Industry Research & Valuation Model
A5: Forecast horizon FY2027E-FY2033E (7 years) | Base year FY2026A
A7: An integrated financial modelling platform for analysing the Indian steel industry.
A8: This workbook integrates macroeconomic forecasting, industry demand and supply modelling, capacity expansion, pricing, raw material economics, profitability, cash flow, valuation and scenario analysis into a single dynamic platform designed for institutional investment research and company valuation.
A9: Designed to support equity research, investment banking, corporate finance, private equity and individual company valuation.
A11: Coverage Universe | D11: Model Information | G11: Data Sources
A12: Core Coverage | B12: Supporting Coverage | D12: Field | E12: Value | G12: Primary Sources | H12: Industry Sources
A13: Tata Steel | B13: AM/NS India | D13: Industry | E13: Steel | G13: Annual Reports | H13: World Steel Association
A14: JSW Steel | B14: RINL (Vizag Steel) | D14: Version | E14: 1 | G14: Quarterly Results | H14: Joint Plant Committee
A15: SAIL | B15: Shyam Metalics | D15: Base Year | E15: FY2026A | G15: Investor Presentations | H15: Ministry of Steel
A16: Jindal Steel | B16: Godawari Power | D16: Forecast | E16: FY2027E–FY2033E | G16: Exchange Filings | H16: OECD
A17: Jindal Stainless | B17: APL Apollo | D17: Forecast Horizon | E17: 7 Years | H17: DGFT
B18: Kirloskar Ferrous | D18: Currency | E18: INR | H18: RBI
B19: Others - secondary | D19: Reporting Basis | E19: Consolidated | H19: IMF
D20: Last Upload | E20: 46237 | H20: World Bank
A25: Prepared By : Om Prakash Panda
A26: Confidential For Educational & Research Purposes
A28: Internal analytical model prepared solely for research and valuation purposes. Figures are derived from publicly available information and analyst assumptions. Not intended for public distribution.

Sheet Index
A1: INDEX
A2: Click a sheet name to navigate.
A4: No | B4: Worksheet | C4: Category | D4: Description
A5: Project Administration
A6: C | B6: Cover | C6: Information | D6: Workbook cover page
A7: 0 | B7: Database Import | C7: Input | D7: Import data from Master Industry Database
A8: 0H | B8: Forecast Horizon | C8: Documentation | D8: Forecast horizon selection
A9: Model Control
A10: 1 | B10: Control Panel | C10: Control | D10: Model settings and scenario selection
A11: =A10+1 | B11: Model Assumptions | C11: Input | D11: Global modelling assumptions
A12: =A11+1 | B12: Model Calibration | C12: Input | D12: Benchmark values and calibration variables
A13: Core Industry Models
A14: =A12+1 | B14: Macroeconomic Model | C14: Model | D14: Economic forecasts
A15: =A14+1 | B15: Steel Demand Model | C15: Model | D15: Industry demand forecast
A16: =A15+1 | B16: Steel Supply Model | C16: Model | D16: Industry supply forecast
A17: =A16+1 | B17: Capacity Forecast | C17: Model | D17: Installed capacity forecast
A18: =A17+1 | B18: Capacity Expansion Tracker | C18: Input | D18: Capacity additions
A19: =A18+1 | B19: Capacity Utilisation | C19: Model | D19: Utilisation analysis
A20: =A19+1 | B20: Steel Price Forecast | C20: Model | D20: Steel price forecast
A21: =A20+1 | B21: Raw Material Forecast | C21: Model | D21: Raw material forecast
A22: =A21+1 | B22: Cost Curve | C22: Model | D22: Industry cost position
A23: =A22+1 | B23: Revenue Forecast | C23: Model | D23: Forecast Industry Revenue
A24: =A23+1 | B24: EBITDA Model | C24: Model | D24: Forecast Profitability
A25: =A24+1 | B25: Margin Analysis | C25: Model | D25: Margin analysis
A26: =A25+1 | B26: Working Capital Model | C26: Model | D26: Working capital forecast
... A31: =A30+1 | B31: ESG Model | C31: Model | D31: Sustainability analysis
A32: Outputs
A33: =A31+1 | B33: Scenario Manager | C33: Output | D33: Scenario comparison
A34: =A33+1 | B34: Sensitivity Analysis | C34: Output | D34: Sensitivity testing
A35: =A34+1 | B35: Comparable Valuation | C35: Output | D35: Sector valuation
A36: =A35+1 | B36: Industry Dashboard | C36: Output | D36: Executive dashboard
A37: Validation & Documentation
A38: =A36+1 | B38: Audit Checks | C38: Audit | D38: Model validation
A39: =A38+1 | B39: Sources | C39: Documentation | D39: References and source log
A42: 🟦 Input
A43: ⬛ Formula
A44: 🟩 External Link
A45: 🟥 External Workbook
A46: 🟧 Missing Data

Sheet Database Import
A1: DATABASE IMPORT
A2: Industry Financial Model | Indian Steel Industry | Horizon FY2027E-FY2033E | Base year FY2026A
A4: Workbook Information
A5: Field | B5: Value
A6: Source Workbook | B6: Master Industry Database.xlsx
A7: Workbook Version | B7: 1
A8: Last Updated | B8: Linked
A9: Reporting Basis | B9: Consolidated
A10: Currency | B10: INR
A11: Coverage Universe | B11: 5 Companies
A12: Historical Period | B12: FY2021–FY2026
A13: Import Status | B13: ✅ Connected
A16: Data Quality Checks
A17: Dataset | B17: Dataset
A18: Duplicate Companies | B18: ✅
A19: Missing Financial Years | B19: ✅
A20: Missing Capacity Data | B20: ✅
A21: Missing Revenue Data | B21: ✅
A22: Missing EBITDA Data | B22: ✅
A23: Missing Price Series | B23: ✅
A24: Currency Consistent | B24: ✅
A25: Units Consistent | B25: ✅
A29: Data Flow Diagram
A30: Master Industry Database
A31: │
A32: ▼
A33: Database Import
A34: │
A35: ▼
A36: Model Assumptions
A37: │
A38: ▼
A39: Industry Models
A40: │
... A49: Purpose: This worksheet serves as the controlled interface between the Master Industry Database and the Industry Financial Model. No manual analytical inputs or calculations should be performed on this sheet. All imported datasets are validated before being used by downstream models.

Sheet Forecast Horizon
A1: FORECAST HORIZON
A2: Industry Financial Model | Indian Steel Industry | Horizon FY2027E-FY2033E | Base year FY2026A
A4: Forecast Horizon Decision
A5: Field | B5: Value
A6: Historical Period | B6: FY2021A – FY2026A
A7: Forecast Period | B7: FY2027E – FY2033E
A8: Forecast Horizon | B8: 7 Years
A9: Base Year | B9: FY2026A
A10: Terminal Year | B10: FY2033E
A13: Horizon Comparison
A14: Criterion | B14: Weight | C14: 5-Year (FY2027-FY2031) | D14: 7-Year (FY2027-FY2033) | E14: 10-Year (FY2027-FY2036) | F14: Score 5Y | G14: Score 7Y | H14: Score 10Y | I14: Basis of assessment / evidence | J14: Audit Code
A15: Coverage of the announced capacity pipeline | B15: 0.25 | C15: Ends FY2031, exactly the terminal year of the announced pipeline. Captures 100% of commissioning but 0 years of post-commissioning ramp. | D15: Ends FY2033. Captures 100% of commissioning PLUS a 2-year ramp tail, so the terminal year reflects normalised rather than ramping utilisation. | E15: Ends FY2036, five years beyond the last dated project. Years 8-10 have no project-level visibility and become pure extrapolation. | F15: 3 | G15: 5 | H15: 2 | I15: Dated pipeline in the Master Database terminates FY2031: POSCO-JSW 6 Mtpa greenfield by 2031, SAIL ~35 Mt ambition by FY2031, PLI 1.2 capacity 8.7 Mt by FY2031, National Steel Policy 2017 target year FY2031. No credible dated project extends beyond FY2031.
A16: Terminal year is a normalised, valuation-usable year | B16: 0.25 | C16: NO. Capacity commissioned FY2030-FY2031 is still ramping in FY2031, so terminal-year utilisation is artificially depressed and a terminal value struck there is understated. | D16: YES. The FY2030-FY2031 capacity cohort reaches normalised utilisation by FY2033 on a 2-3 year ramp, so the terminal year is a fair steady state. | E16: YES but redundant - steady state is already reached by FY2033, so FY2034-FY2036 add extrapolation risk without adding information. | F16: 1 | G16: 5 | H16: 4 | I16: Greenfield and large brownfield Indian steel capacity historically takes 2-3 years from commissioning to normalised utilisation. Observed in the database: NMDC Steel Nagarnar (3 Mtpa) produced 1.471 Mt in FY2025 and 2.382 Mt in FY2026, i.e. ~79% of nameplate in year 3+; RINL required a full year to recover to 5.43 Mt.
A17: Coverage of a complete industry cycle | B17: 0.2 | C17: ~0.7 cycles. Truncates the cycle, so the average forecast year is not cycle-neutral and the result is highly sensitive to where the start point sits in the cycle. | D17: ~1.0 cycle. The forecast average is approximately cycle-neutral, which is the property a mid-cycle valuation requires. | E17: ~1.4 cycles. Cycle-neutral but the second partial cycle is unforecastable in its timing. | F17: 2 | G17: 5 | H17: 3 | I17: Observed cycle length in the database: standardised EBITDA margin for Tata Steel peaked at 26% in FY2022, troughed at 10% in FY2024 and recovered to 15% in FY2026 - a 4-year peak-to-trough leg implying a ~7-8 year full cycle. Coking coal peaked at US$354/t in Oct-2023 and troughed at ~US$175/t in Mar-2025; iron ore peaked at US$155.52/dmt in FY2022 and troughed at US$100.52/dmt in FY2026.
A18: Reliability of the macro anchor | B18: 0.15 | C18: Strong. RBI publishes an explicit FY2027 projection and the IMF medium-term path is credible to roughly 5 years. | D18: Adequate. Years 6-7 rely on a converging steady-state growth assumption rather than a published projection, which is disclosed and sensitised. | E18: Weak. Years 8-10 require a GDP path with no institutional publisher support at all. | F18: 5 | G18: 4 | H18: 2 | I18: RBI's June-2026 MPC projects FY2027 real GDP growth at 6.6%. No official Indian source publishes a real GDP path beyond roughly 5 years, so any year past FY2031 is the modeller's own convergence assumption.
A19: Usability for DCF terminal value | B19: 0.15 | C19: Poor. A terminal value struck on a non-normalised year requires a manual mid-cycle adjustment, which defeats the purpose of an explicit forecast period. | D19: Good. Terminal value can be struck directly off FY2033 with no manual normalisation. | E19: Good but the incremental years add estimation error to the discounted stub, where their present-value weight is small. | F19: 2 | G19: 5 | H19: 3 | I19: At a ~12% nominal WACC the present-value weight of forecast years 8-10 is under 12% of total enterprise value, so extending the horizon adds materially more estimation error than valuation information.
A20: WEIGHTED TOTAL | B20: =SUM(B15:B19) | F20: =SUMPRODUCT($B$15:$B$19,F15:F19) | G20: =SUMPRODUCT($B$15:$B$19,G15:G19) | H20: =SUMPRODUCT($B$15:$B$19,H15:H19) | I20: Live formula. The 7-year option wins on four of five criteria and ties on none; it loses only on macro-anchor reliability, where the 5-year option is stronger. | J20: FH01
A23: Scope
A24: This model forecasts:
A25: Steel demand
A26: Steel supply
A27: Installed capacity
A28: Capacity utilisation
A29: Steel prices
A30: Raw material prices
A31: Revenue
A32: EBITDA
A33: Margins
A34: Working capital
... A39: Review Policy
A40: Item | B40: Frequency
A41: Forecast Horizon | B41: Annual
A42: Base Year Roll Forward | B42: Annual
A43: Historical Data Update | B43: Quarterly
A44: Assumption Review | B44: Quarterly
A45: Full Model Review | B45: Annual
A48: FY21A FY22A FY23A FY24A FY25A FY26A | FY27E FY28E FY29E FY30E FY31E FY32E FY33E
A49: Historical (Actual) | Forecast

Sheet Control Panel
A1: CONTROL PANEL
A2: Industry Financial Model | Indian Steel Industry | Horizon FY2027E-FY2033E | Base year FY2026A
A4: Model Information | D4: Global Controls | G4: Workbook Status
A5: Parameter | B5: Value | D5: Settings | E5: Value | G5: Check | H5: Status
A6: Model Name | B6: Indian Steel Industry Financial Model | D6: Scenario | E6: =E17 | G6: Database Connected | H6: =IF(COUNT('Model Calibration'!$D$10:$D$14)=5,"OK","CHECK")
A7: Version | B7: 1 | D7: Currency Display | E7: INR | G7: Assumptions Complete | H7: =IF(COUNT('Model Assumptions'!$E$8:$K$33)=182,"OK","CHECK")
A8: Status | B8: Final | D8: Number Format | E8: Crore | G8: Calibration Complete | H8: =IF(AND(ISNUMBER('Model Calibration'!$D$19),ISNUMBER('Model Calibration'!$D$21),ABS('Model Calibration'!$D$19-'Model Calibration'!$D$21-'Model Calibration'!$D$20)<1),"OK","CHECK")
A9: Last Uploaded | B9: =TODAY() | D9: Forecast Year | E9: 7 | G9: Forecast Built | H9: =IF(COUNT('EBITDA Model'!$D$103:$J$103)=7,"OK","CHECK")
A10: Base Year | B10: FY2026A | D10: Steel Price Basis | E10: Domestic | G10: Dashboard Updated | H10: =IF(COUNT('Industry Dashboard'!$D$32:$J$32)=7,"OK","CHECK")
A11: Forecast Horizon | B11: FY2027E-FY2033E | D11: Inflation Basis | E11: CPI
A12: Currency | B12: INR
A13: Reporting Basis | B13: Consolidated
A16: Quick Navigation | D16: SCENARIO SELECTOR
A17: Module | B17: Link | D17: Active scenario | E17: Base Case
A18: Database Import | B18: Go → | D18: Scenario Index | E18: =MATCH(E$17,E$20:E$23,0)
A19: Model Assumptions | B19: Go →
A20: Model Calibration | B20: Go → | D20: 1. | E20: Base Case | F20: Central case. RBI FY2027 GDP of 6.6%, realisation calibrated to a FY2033 industry margin of 16.8%.
A21: Macro Model | B21: Go → | D21: 2. | E21: Bull Case | F21: Demand-led upcycle. Peaks at a 26.0% industry margin in FY2030, matching the FY2022 cycle peak.
A22: Demand Model | B22: Go → | D22: 3. | E22: Bear Case | F22: Demand-led downturn. Raw materials FALL with demand, so margins compress to 7-11% rather than collapsing.
A23: Supply Model | B23: Go → | D23: 4. | E23: Stress Case | F23: Stagflationary supply shock plus demand shock. Coking coal to US$300/t, INR to 113. Troughs at -9.2% in FY2028.
A24: Capacity Model | B24: Go →
A25: Price Model | B25: Go →
A26: Revenue Model | B26: Go →
A27: EBITDA Model | B27: Go →
A28: Valuation | B28: Go →
A29: Dashboard | B29: Go →
A30: Audit | B30: Go →
A31: Sources | B31: Go →
A34: LIVE MODEL OUTPUT - ACTIVE SCENARIO
A35: Line item | B35: Unit | C35: FY2026A | D35: FY2027E | E35: FY2028E | F35: FY2029E | G35: FY2030E | H35: FY2031E | I35: FY2032E | J35: FY2033E | K35: CAGR | L35: Audit Code | M35: Source
A36: India finished steel consumption | B36: Mt | C36: ='Steel Demand Model'!C$75 | D36: ='Steel Demand Model'!D$75 | E36: ='Steel Demand Model'!E$75 | F36: ='Steel Demand Model'!F$75 | G36: ='Steel Demand Model'!G$75 | H36: ='Steel Demand Model'!H$75 | I36: ='Steel Demand Model'!I$75 | J36: ='Steel Demand Model'!J$75 | K36: =IFERROR(IF(AND(ISNUMBER(C36),ISNUMBER(J36),C36>0),(J36/C36)^(1/7)-1,""),"") | L36: CP01 | M36: 04
A37: India crude steel production | B37: Mt | C37: ='Steel Supply Model'!C$88 | D37: ='Steel Supply Model'!D$88 | E37: ='Steel Supply Model'!E$88 | F37: ='Steel Supply Model'!F$88 | G37: ='Steel Supply Model'!G$88 | H37: ='Steel Supply Model'!H$88 | I37: ='Steel Supply Model'!I$88 | J37: ='Steel Supply Model'!J$88 | K37: =IFERROR(IF(AND(ISNUMBER(C37),ISNUMBER(J37),C37>0),(J37/C37)^(1/7)-1,""),"") | L37: CP02 | M37: 05
A38: India crude steel capacity | B38: Mtpa | C38: ='Capacity Forecast'!C$96 | D38: ='Capacity Forecast'!D$96 | E38: ='Capacity Forecast'!E$96 | F38: ='Capacity Forecast'!F$96 | G38: ='Capacity Forecast'!G$96 | H38: ='Capacity Forecast'!H$96 | I38: ='Capacity Forecast'!I$96 | J38: ='Capacity Forecast'!J$96 | K38: =IFERROR(IF(AND(ISNUMBER(C38),ISNUMBER(J38),C38>0),(J38/C38)^(1/7)-1,""),"") | L38: CP03 | M38: 06
A39: Capacity utilisation | B39: % | C39: ='Capacity Utilisation'!C$65 | D39: ='Capacity Utilisation'!D$65 | E39: ='Capacity Utilisation'!E$65 | F39: ='Capacity Utilisation'!F$65 | G39: ='Capacity Utilisation'!G$65 | H39: ='Capacity Utilisation'!H$65 | I39: ='Capacity Utilisation'!I$65 | J39: ='Capacity Utilisation'!J$65 | K39: =IFERROR(IF(AND(ISNUMBER(C39),ISNUMBER(J39),C39>0),(J39/C39)^(1/7)-1,""),"") | L39: CP04 | M39: 08
A40: Blended realisation | B40: Rs/t | C40: ='Steel Price Forecast'!C$72 | D40: ='Steel Price Forecast'!D$72 | E40: ='Steel Price Forecast'!E$72 | F40: ='Steel Price Forecast'!F$72 | G40: ='Steel Price Forecast'!G$72 | H40: ='Steel Price Forecast'!H$72 | I40: ='Steel Price Forecast'!I$72 | J40: ='Steel Price Forecast'!J$72 | K40: =IFERROR(IF(AND(ISNUMBER(C40),ISNUMBER(J40),C40>0),(J40/C40)^(1/7)-1,""),"") | L40: CP05 | M40: 09
A41: Cash cost per tonne | B41: Rs/t | C41: ='Cost Curve'!C$65 | D41: ='Cost Curve'!D$65 | E41: ='Cost Curve'!E$65 | F41: ='Cost Curve'!F$65 | G41: ='Cost Curve'!G$65 | H41: ='Cost Curve'!H$65 | I41: ='Cost Curve'!I$65 | J41: ='Cost Curve'!J$65 | K41: =IFERROR(IF(AND(ISNUMBER(C41),ISNUMBER(J41),C41>0),(J41/C41)^(1/7)-1,""),"") | L41: CP06 | M41: 11
A42: EBITDA per tonne | B42: Rs/t | C42: ='EBITDA Model'!C$101 | D42: ='EBITDA Model'!D$101 | E42: ='EBITDA Model'!E$101 | F42: ='EBITDA Model'!F$101 | G42: ='EBITDA Model'!G$101 | H42: ='EBITDA Model'!H$101 | I42: ='EBITDA Model'!I$101 | J42: ='EBITDA Model'!J$101 | K42: =IFERROR(IF(AND(ISNUMBER(C42),ISNUMBER(J42),C42>0),(J42/C42)^(1/7)-1,""),"") | L42: CP07 | M42: 13
A43: Industry EBITDA margin | B43: % | C43: ='Margin Analysis'!C$81 | D43: ='Margin Analysis'!D$81 | E43: ='Margin Analysis'!E$81 | F43: ='Margin Analysis'!F$81 | G43: ='Margin Analysis'!G$81 | H43: ='Margin Analysis'!H$81 | I43: ='Margin Analysis'!I$81 | J43: ='Margin Analysis'!J$81 | K43: =IFERROR(IF(AND(ISNUMBER(C43),ISNUMBER(J43),C43>0),(J43/C43)^(1/7)-1,""),"") | L43: CP08 | M43: 14
A44: Industry revenue | B44: Rs cr | C44: ='Revenue Forecast'!C$95 | D44: ='Revenue Forecast'!D$95 | E44: ='Revenue Forecast'!E$95 | F44: ='Revenue Forecast'!F$95 | G44: ='Revenue Forecast'!G$95 | H44: ='Revenue Forecast'!H$95 | I44: ='Revenue Forecast'!I$95 | J44: ='Revenue Forecast'!J$95 | K44: =IFERROR(IF(AND(ISNUMBER(C44),ISNUMBER(J44),C44>0),(J44/C44)^(1/7)-1,""),"") | L44: CP09 | M44: 12
A45: Industry EBITDA | B45: Rs cr | C45: ='EBITDA Model'!C$103 | D45: ='EBITDA Model'!D$103 | E45: ='EBITDA Model'!E$103 | F45: ='EBITDA Model'!F$103 | G45: ='EBITDA Model'!G$103 | H45: ='EBITDA Model'!H$103 | I45: ='EBITDA Model'!I$103 | J45: ='EBITDA Model'!J$103 | K45: =IFERROR(IF(AND(ISNUMBER(C45),ISNUMBER(J45),C45>0),(J45/C45)^(1/7)-1,""),"") | L45: CP10 | M45: 13
A46: Unlevered free cash flow | B46: Rs cr | C46: ='Cash Flow Model'!C$108 | D46: ='Cash Flow Model'!D$108 | E46: ='Cash Flow Model'!E$108 | F46: ='Cash Flow Model'!F$108 | G46: ='Cash Flow Model'!G$108 | H46: ='Cash Flow Model'!H$108 | I46: ='Cash Flow Model'!I$108 | J46: ='Cash Flow Model'!J$108 | K46: =IFERROR(IF(AND(ISNUMBER(C46),ISNUMBER(J46),C46>0),(J46/C46)^(1/7)-1,""),"") | L46: CP11 | M46: 16
A48: DEPENDENCIES
A49: Drives 02 Model Assumptions and therefore every sheet from 03 to 24.
A50: Every figure above is a live link. Change the selector and this panel, and every other sheet, recomputes.

Sheet Model Assumptions
A1: MODEL ASSUMPTIONS
A2: Industry Financial Model | Indian Steel Industry | Horizon FY2027E-FY2033E | Base year FY2026A
A4: Running Scenario | C4: ='Control Panel'!E17
A6: ACTIVE DRIVERS
A7: No | B7: Line item | C7: Unit | D7: FY2026A | E7: FY2027E | F7: FY2028E | G7: FY2029E | H7: FY2030E | I7: FY2031E | J7: FY2032E | K7: FY2033E | L7: Source | M7: Conf.
A8: D01 | B8: India real GDP growth | C8: % | D8: =[1]Macroeconomic!$H$6 | E8: =_xlfn.XLOOKUP($C$4,$D$38:$D$41,E38:E41) | F8: =_xlfn.XLOOKUP($C$4,$D$38:$D$41,F38:F41) | G8: =_xlfn.XLOOKUP($C$4,$D$38:$D$41,G38:G41) | H8: =_xlfn.XLOOKUP($C$4,$D$38:$D$41,H38:H41) | I8: =_xlfn.XLOOKUP($C$4,$D$38:$D$41,I38:I41) | J8: =_xlfn.XLOOKUP($C$4,$D$38:$D$41,J38:J41) | K8: =_xlfn.XLOOKUP($C$4,$D$38:$D$41,K38:K41) | L8: RBI-Jun26 | M8: High
A9: D02 | B9: Steel demand elasticity to real GDP | C9: x | D9: =[1]Macroeconomic!$H$11 | E9: =_xlfn.XLOOKUP($C$4,$D$42:$D$45,E42:E45) | F9: =_xlfn.XLOOKUP($C$4,$D$42:$D$45,F42:F45) | G9: =_xlfn.XLOOKUP($C$4,$D$42:$D$45,G42:G45) | H9: =_xlfn.XLOOKUP($C$4,$D$42:$D$45,H42:H45) | I9: =_xlfn.XLOOKUP($C$4,$D$42:$D$45,I42:I45) | J9: =_xlfn.XLOOKUP($C$4,$D$42:$D$45,J42:J45) | K9: =_xlfn.XLOOKUP($C$4,$D$42:$D$45,K42:K45) | L9: Derived-DB | M9: High
A10: D03 | B10: USD/INR average | C10: Rs/US$ | D10: =[1]Macroeconomic!$H$8 | E10: =_xlfn.XLOOKUP($C$4,$D$46:$D$49,E46:E49) | F10: =_xlfn.XLOOKUP($C$4,$D$46:$D$49,F46:F49) | G10: =_xlfn.XLOOKUP($C$4,$D$46:$D$49,G46:G49) | H10: =_xlfn.XLOOKUP($C$4,$D$46:$D$49,H46:H49) | I10: =_xlfn.XLOOKUP($C$4,$D$46:$D$49,I46:I49) | J10: =_xlfn.XLOOKUP($C$4,$D$46:$D$49,J46:J49) | K10: =_xlfn.XLOOKUP($C$4,$D$46:$D$49,K46:K49) | L10: IDBI-22Jun26 | M10: High
A11: D04 | B11: CPI inflation | C11: % | D11: =[1]Macroeconomic!$H$7 | E11: =_xlfn.XLOOKUP($C$4,$D$50:$D$53,E50:E53) | F11: =_xlfn.XLOOKUP($C$4,$D$50:$D$53,F50:F53) | G11: =_xlfn.XLOOKUP($C$4,$D$50:$D$53,G50:G53) | H11: =_xlfn.XLOOKUP($C$4,$D$50:$D$53,H50:H53) | I11: =_xlfn.XLOOKUP($C$4,$D$50:$D$53,I50:I53) | J11: =_xlfn.XLOOKUP($C$4,$D$50:$D$53,J50:J53) | K11: =_xlfn.XLOOKUP($C$4,$D$50:$D$53,K50:K53) | L11: RBI-Jun26 | M11: High
A12: D05 | B12: Announced pipeline delivery factor | C12: % | D12: ='[1]Production Volume'!$H$10 | E12: =_xlfn.XLOOKUP($C$4,$D$54:$D$57,E54:E57) | F12: =_xlfn.XLOOKUP($C$4,$D$54:$D$57,F54:F57) | G12: =_xlfn.XLOOKUP($C$4,$D$54:$D$57,G54:G57) | H12: =_xlfn.XLOOKUP($C$4,$D$54:$D$57,H54:H57) | I12: =_xlfn.XLOOKUP($C$4,$D$54:$D$57,I54:I57) | J12: =_xlfn.XLOOKUP($C$4,$D$54:$D$57,J54:J57) | K12: =_xlfn.XLOOKUP($C$4,$D$54:$D$57,K54:K57) | L12: Derived-DB | M12: Medium
A13: D06 | B13: Crude-to-finished steel ratio | C13: x | D13: ='[1]Production Volume'!$H$11 | E13: =_xlfn.XLOOKUP($C$4,$D$58:$D$61,E58:E61) | F13: =_xlfn.XLOOKUP($C$4,$D$58:$D$61,F58:F61) | G13: =_xlfn.XLOOKUP($C$4,$D$58:$D$61,G58:G61) | H13: =_xlfn.XLOOKUP($C$4,$D$58:$D$61,H58:H61) | I13: =_xlfn.XLOOKUP($C$4,$D$58:$D$61,I58:I61) | J13: =_xlfn.XLOOKUP($C$4,$D$58:$D$61,J58:J61) | K13: =_xlfn.XLOOKUP($C$4,$D$58:$D$61,K58:K61) | L13: Derived-DB | M13: High
A14: D07 | B14: Net finished steel exports | C14: Mt | D14: ='[1]Imports & Exports'!$H$8 | E14: =_xlfn.XLOOKUP($C$4,$D$62:$D$65,E62:E65) | F14: =_xlfn.XLOOKUP($C$4,$D$62:$D$65,F62:F65) | G14: =_xlfn.XLOOKUP($C$4,$D$62:$D$65,G62:G65) | H14: =_xlfn.XLOOKUP($C$4,$D$62:$D$65,H62:H65) | I14: =_xlfn.XLOOKUP($C$4,$D$62:$D$65,I62:I65) | J14: =_xlfn.XLOOKUP($C$4,$D$62:$D$65,J62:J65) | K14: =_xlfn.XLOOKUP($C$4,$D$62:$D$65,K62:K65) | L14: Derived-DB | M14: Medium
A15: D08 | B15: Variation in stock | C15: Mt | D15: ='[1]Demand & Consumption'!$H$9 | E15: =_xlfn.XLOOKUP($C$4,$D$66:$D$69,E66:E69) | F15: =_xlfn.XLOOKUP($C$4,$D$66:$D$69,F66:F69) | G15: =_xlfn.XLOOKUP($C$4,$D$66:$D$69,G66:G69) | H15: =_xlfn.XLOOKUP($C$4,$D$66:$D$69,H66:H69) | I15: =_xlfn.XLOOKUP($C$4,$D$66:$D$69,I66:I69) | J15: =_xlfn.XLOOKUP($C$4,$D$66:$D$69,J66:J69) | K15: =_xlfn.XLOOKUP($C$4,$D$66:$D$69,K66:K69) | L15: Derived-DB | M15: Medium
A16: D09 | B16: Blended industry realisation | C16: Rs/t | D16: ='[1]Steel Prices'!$H$12 | E16: =_xlfn.XLOOKUP($C$4,$D$70:$D$73,E70:E73) | F16: =_xlfn.XLOOKUP($C$4,$D$70:$D$73,F70:F73) | G16: =_xlfn.XLOOKUP($C$4,$D$70:$D$73,G70:G73) | H16: =_xlfn.XLOOKUP($C$4,$D$70:$D$73,H70:H73) | I16: =_xlfn.XLOOKUP($C$4,$D$70:$D$73,I70:I73) | J16: =_xlfn.XLOOKUP($C$4,$D$70:$D$73,J70:J73) | K16: =_xlfn.XLOOKUP($C$4,$D$70:$D$73,K70:K73) | L16: Derived-DB | M16: Medium
A17: D10 | B17: Iron ore 62% Fe CFR China | C17: US$/dmt | D17: ='[1]Raw Materials'!$H$6 | E17: =_xlfn.XLOOKUP($C$4,$D$74:$D$77,E74:E77) | F17: =_xlfn.XLOOKUP($C$4,$D$74:$D$77,F74:F77) | G17: =_xlfn.XLOOKUP($C$4,$D$74:$D$77,G74:G77) | H17: =_xlfn.XLOOKUP($C$4,$D$74:$D$77,H74:H77) | I17: =_xlfn.XLOOKUP($C$4,$D$74:$D$77,I74:I77) | J17: =_xlfn.XLOOKUP($C$4,$D$74:$D$77,J74:J77) | K17: =_xlfn.XLOOKUP($C$4,$D$74:$D$77,K74:K77) | L17: S17 | M17: High
A18: D11 | B18: Premium HCC coking coal FOB Australia | C18: US$/t | D18: ='[1]Raw Materials'!$H$11 | E18: =_xlfn.XLOOKUP($C$4,$D$78:$D$81,E78:E81) | F18: =_xlfn.XLOOKUP($C$4,$D$78:$D$81,F78:F81) | G18: =_xlfn.XLOOKUP($C$4,$D$78:$D$81,G78:G81) | H18: =_xlfn.XLOOKUP($C$4,$D$78:$D$81,H78:H81) | I18: =_xlfn.XLOOKUP($C$4,$D$78:$D$81,I78:I81) | J18: =_xlfn.XLOOKUP($C$4,$D$78:$D$81,J78:J81) | K18: =_xlfn.XLOOKUP($C$4,$D$78:$D$81,K78:K81) | L18: S01 | M18: Medium
A19: D12 | B19: Conversion cost inflation | C19: % | D19: 0.05 | E19: =_xlfn.XLOOKUP($C$4,$D$82:$D$85,E82:E85) | F19: =_xlfn.XLOOKUP($C$4,$D$82:$D$85,F82:F85) | G19: =_xlfn.XLOOKUP($C$4,$D$82:$D$85,G82:G85) | H19: =_xlfn.XLOOKUP($C$4,$D$82:$D$85,H82:H85) | I19: =_xlfn.XLOOKUP($C$4,$D$82:$D$85,I82:I85) | J19: =_xlfn.XLOOKUP($C$4,$D$82:$D$85,J82:J85) | K19: =_xlfn.XLOOKUP($C$4,$D$82:$D$85,K82:K85) | L19: RBI-Jun26 | M19: Medium
A20: D13 | B20: Raw material share of cash cost | C20: % | D20: ='[1]Raw Materials'!$H$29 | E20: =_xlfn.XLOOKUP($C$4,$D$86:$D$89,E86:E89) | F20: =_xlfn.XLOOKUP($C$4,$D$86:$D$89,F86:F89) | G20: =_xlfn.XLOOKUP($C$4,$D$86:$D$89,G86:G89) | H20: =_xlfn.XLOOKUP($C$4,$D$86:$D$89,H86:H89) | I20: =_xlfn.XLOOKUP($C$4,$D$86:$D$89,I86:I89) | J20: =_xlfn.XLOOKUP($C$4,$D$86:$D$89,J86:J89) | K20: =_xlfn.XLOOKUP($C$4,$D$86:$D$89,K86:K89) | L20: Indicative | M20: Low
A21: D14 | B21: Iron ore weight in the raw material basket | C21: % | D21: ='[1]Raw Materials'!$H$30 | E21: =_xlfn.XLOOKUP($C$4,$D$90:$D$93,E90:E93) | F21: =_xlfn.XLOOKUP($C$4,$D$90:$D$93,F90:F93) | G21: =_xlfn.XLOOKUP($C$4,$D$90:$D$93,G90:G93) | H21: =_xlfn.XLOOKUP($C$4,$D$90:$D$93,H90:H93) | I21: =_xlfn.XLOOKUP($C$4,$D$90:$D$93,I90:I93) | J21: =_xlfn.XLOOKUP($C$4,$D$90:$D$93,J90:J93) | K21: =_xlfn.XLOOKUP($C$4,$D$90:$D$93,K90:K93) | L21: Indicative | M21: Low
A22: D15 | B22: Effective tax rate | C22: % | D22: 0.2517 | E22: =_xlfn.XLOOKUP($C$4,$D$94:$D$97,E94:E97) | F22: =_xlfn.XLOOKUP($C$4,$D$94:$D$97,F94:F97) | G22: =_xlfn.XLOOKUP($C$4,$D$94:$D$97,G94:G97) | H22: =_xlfn.XLOOKUP($C$4,$D$94:$D$97,H94:H97) | I22: =_xlfn.XLOOKUP($C$4,$D$94:$D$97,I94:I97) | J22: =_xlfn.XLOOKUP($C$4,$D$94:$D$97,J94:J97) | K22: =_xlfn.XLOOKUP($C$4,$D$94:$D$97,K94:K97) | L22: Statutory | M22: Medium
A23: D16 | B23: Capex intensity | C23: Rs/t of capacity added | D23: 55000 | E23: =_xlfn.XLOOKUP($C$4,$D$98:$D$101,E98:E101) | F23: =_xlfn.XLOOKUP($C$4,$D$98:$D$101,F98:F101) | G23: =_xlfn.XLOOKUP($C$4,$D$98:$D$101,G98:G101) | H23: =_xlfn.XLOOKUP($C$4,$D$98:$D$101,H98:H101) | I23: =_xlfn.XLOOKUP($C$4,$D$98:$D$101,I98:I101) | J23: =_xlfn.XLOOKUP($C$4,$D$98:$D$101,J98:J101) | K23: =_xlfn.XLOOKUP($C$4,$D$98:$D$101,K98:K101) | L23: Derived-DB | M23: Medium
A24: D17 | B24: Maintenance capex | C24: % of revenue | D24: 0.03 | E24: =_xlfn.XLOOKUP($C$4,$D$102:$D$105,E102:E105) | F24: =_xlfn.XLOOKUP($C$4,$D$102:$D$105,F102:F105) | G24: =_xlfn.XLOOKUP($C$4,$D$102:$D$105,G102:G105) | H24: =_xlfn.XLOOKUP($C$4,$D$102:$D$105,H102:H105) | I24: =_xlfn.XLOOKUP($C$4,$D$102:$D$105,I102:I105) | J24: =_xlfn.XLOOKUP($C$4,$D$102:$D$105,J102:J105) | K24: =_xlfn.XLOOKUP($C$4,$D$102:$D$105,K102:K105) | L24: Indicative | M24: Low
A25: D18 | B25: Net working capital | C25: days of revenue | D25: 45 | E25: =_xlfn.XLOOKUP($C$4,$D$106:$D$109,E106:E109) | F25: =_xlfn.XLOOKUP($C$4,$D$106:$D$109,F106:F109) | G25: =_xlfn.XLOOKUP($C$4,$D$106:$D$109,G106:G109) | H25: =_xlfn.XLOOKUP($C$4,$D$106:$D$109,H106:H109) | I25: =_xlfn.XLOOKUP($C$4,$D$106:$D$109,I106:I109) | J25: =_xlfn.XLOOKUP($C$4,$D$106:$D$109,J106:J109) | K25: =_xlfn.XLOOKUP($C$4,$D$106:$D$109,K106:K109) | L25: Not sourced | M25: Low
A26: D19 | B26: Exit EV/EBITDA multiple | C26: x | E26: =_xlfn.XLOOKUP($C$4,$D$110:$D$113,E110:E113) | F26: =_xlfn.XLOOKUP($C$4,$D$110:$D$113,F110:F113) | G26: =_xlfn.XLOOKUP($C$4,$D$110:$D$113,G110:G113) | H26: =_xlfn.XLOOKUP($C$4,$D$110:$D$113,H110:H113) | I26: =_xlfn.XLOOKUP($C$4,$D$110:$D$113,I110:I113) | J26: =_xlfn.XLOOKUP($C$4,$D$110:$D$113,J110:J113) | K26: =_xlfn.XLOOKUP($C$4,$D$110:$D$113,K110:K113) | L26: Not sourced | M26: Low
A27: D20 | B27: WACC (nominal, INR) | C27: % | D27: =$D$168 | E27: =_xlfn.XLOOKUP($C$4,$D$114:$D$117,E114:E117) | F27: =_xlfn.XLOOKUP($C$4,$D$114:$D$117,F114:F117) | G27: =_xlfn.XLOOKUP($C$4,$D$114:$D$117,G114:G117) | H27: =_xlfn.XLOOKUP($C$4,$D$114:$D$117,H114:H117) | I27: =_xlfn.XLOOKUP($C$4,$D$114:$D$117,I114:I117) | J27: =_xlfn.XLOOKUP($C$4,$D$114:$D$117,J114:J117) | K27: =_xlfn.XLOOKUP($C$4,$D$114:$D$117,K114:K117) | L27: Composite | M27: Medium
A28: D21 | B28: Finished steel imports | C28: Mt | D28: ='[1]Imports & Exports'!$H$6 | E28: =_xlfn.XLOOKUP($C$4,$D$118:$D$121,E118:E121) | F28: =_xlfn.XLOOKUP($C$4,$D$118:$D$121,F118:F121) | G28: =_xlfn.XLOOKUP($C$4,$D$118:$D$121,G118:G121) | H28: =_xlfn.XLOOKUP($C$4,$D$118:$D$121,H118:H121) | I28: =_xlfn.XLOOKUP($C$4,$D$118:$D$121,I118:I121) | J28: =_xlfn.XLOOKUP($C$4,$D$118:$D$121,J118:J121) | K28: =_xlfn.XLOOKUP($C$4,$D$118:$D$121,K118:K121) | L28: Derived-DB | M28: Medium
A29: D22 | B29: Secondary and unattributed capacity additions | C29: Mtpa p.a. | D29: ='[1]Production Capacity'!$H$7 | E29: =_xlfn.XLOOKUP($C$4,$D$122:$D$125,E122:E125) | F29: =_xlfn.XLOOKUP($C$4,$D$122:$D$125,F122:F125) | G29: =_xlfn.XLOOKUP($C$4,$D$122:$D$125,G122:G125) | H29: =_xlfn.XLOOKUP($C$4,$D$122:$D$125,H122:H125) | I29: =_xlfn.XLOOKUP($C$4,$D$122:$D$125,I122:I125) | J29: =_xlfn.XLOOKUP($C$4,$D$122:$D$125,J122:J125) | K29: =_xlfn.XLOOKUP($C$4,$D$122:$D$125,K122:K125) | L29: Derived-DB | M29: Medium
A30: D23 | B30: Price sensitivity to capacity utilisation (lagged) | C30: x | D30: 0.4 | E30: =_xlfn.XLOOKUP($C$4,$D$126:$D$129,E126:E129) | F30: =_xlfn.XLOOKUP($C$4,$D$126:$D$129,F126:F129) | G30: =_xlfn.XLOOKUP($C$4,$D$126:$D$129,G126:G129) | H30: =_xlfn.XLOOKUP($C$4,$D$126:$D$129,H126:H129) | I30: =_xlfn.XLOOKUP($C$4,$D$126:$D$129,I126:I129) | J30: =_xlfn.XLOOKUP($C$4,$D$126:$D$129,J126:J129) | K30: =_xlfn.XLOOKUP($C$4,$D$126:$D$129,K126:K129) | L30: Indicative | M30: Low
A31: D24 | B31: Normal capacity utilisation | C31: % | D31: 0.8 | E31: =_xlfn.XLOOKUP($C$4,$D$130:$D$133,E130:E133) | F31: =_xlfn.XLOOKUP($C$4,$D$130:$D$133,F130:F133) | G31: =_xlfn.XLOOKUP($C$4,$D$130:$D$133,G130:G133) | H31: =_xlfn.XLOOKUP($C$4,$D$130:$D$133,H130:H133) | I31: =_xlfn.XLOOKUP($C$4,$D$130:$D$133,I130:I133) | J31: =_xlfn.XLOOKUP($C$4,$D$130:$D$133,J130:J133) | K31: =_xlfn.XLOOKUP($C$4,$D$130:$D$133,K130:K133) | L31: Derived-DB | M31: Medium
A32: D25 | B32: Maximum practical capacity utilisation | C32: % | D32: 0.92 | E32: =_xlfn.XLOOKUP($C$4,$D$134:$D$137,E134:E137) | F32: =_xlfn.XLOOKUP($C$4,$D$134:$D$137,F134:F137) | G32: =_xlfn.XLOOKUP($C$4,$D$134:$D$137,G134:G137) | H32: =_xlfn.XLOOKUP($C$4,$D$134:$D$137,H134:H137) | I32: =_xlfn.XLOOKUP($C$4,$D$134:$D$137,I134:I137) | J32: =_xlfn.XLOOKUP($C$4,$D$134:$D$137,J134:J137) | K32: =_xlfn.XLOOKUP($C$4,$D$134:$D$137,K134:K137) | L32: Indicative | M32: Low
A33: D26 | B33: Depreciation and amortisation | C33: % of revenue | D33: ='Cash Flow Model'!$C$92 | E33: =_xlfn.XLOOKUP($C$4,$D$138:$D$141,E138:E141) | F33: =_xlfn.XLOOKUP($C$4,$D$138:$D$141,F138:F141) | G33: =_xlfn.XLOOKUP($C$4,$D$138:$D$141,G138:G141) | H33: =_xlfn.XLOOKUP($C$4,$D$138:$D$141,H138:H141) | I33: =_xlfn.XLOOKUP($C$4,$D$138:$D$141,I138:I141) | J33: =_xlfn.XLOOKUP($C$4,$D$138:$D$141,J138:J141) | K33: =_xlfn.XLOOKUP($C$4,$D$138:$D$141,K138:K141) | L33: Derived-DB | M33: High
A36: SCENARIO DRIVER MATRIX
A37: Sl No | B37: Driver | C37: Unit | D37: Scenario | E37: FY2027E | F37: FY2028E | G37: FY2029E | H37: FY2030E | I37: FY2031E | J37: FY2032E | K37: FY2033E | L37: Source | M37: Audit Code
A38: 1 | B38: India real GDP growth | C38: % | D38: Base Case | E38: 0.066 | F38: 0.068 | G38: 0.068 | H38: 0.067 | I38: 0.067 | J38: 0.065 | K38: 0.065 | L38: RBI-Jun26 | M38: MA01
D39: Bull Case | E39: 0.074 | F39: 0.076 | G39: 0.075 | H39: 0.074 | I39: 0.073 | J39: 0.072 | K39: 0.07
D40: Bear Case | E40: 0.056 | F40: 0.058 | G40: 0.06 | H40: 0.061 | I40: 0.062 | J40: 0.062 | K40: 0.062
D41: Stress Case | E41: 0.044 | F41: 0.048 | G41: 0.055 | H41: 0.058 | I41: 0.06 | J41: 0.06 | K41: 0.06
A42: 2 | B42: Steel demand elasticity to real GDP | C42: x | D42: Base Case | E42: 1.15 | F42: 1.15 | G42: 1.12 | H42: 1.1 | I42: 1.08 | J42: 1.06 | K42: 1.05 | L42: Derived-DB | M42: MA02
D43: Bull Case | E43: 1.3 | F43: 1.28 | G43: 1.25 | H43: 1.22 | I43: 1.2 | J43: 1.18 | K43: 1.15
D44: Bear Case | E44: 1 | F44: 1 | G44: 0.98 | H44: 0.97 | I44: 0.96 | J44: 0.95 | K44: 0.95
D45: Stress Case | E45: 0.75 | F45: 0.85 | G45: 0.9 | H45: 0.92 | I45: 0.93 | J45: 0.94 | K45: 0.95
A46: 3 | B46: USD/INR average | C46: Rs/US$ | D46: Base Case | E46: 94.5 | F46: 95.5 | G46: 96.5 | H46: 97.5 | I46: 98.5 | J46: 99.5 | K46: 100.5 | L46: IDBI-22Jun26 | M46: MA03
D47: Bull Case | E47: 93 | F47: 93.5 | G47: 94 | H47: 94.5 | I47: 95 | J47: 95.5 | K47: 96
D48: Bear Case | E48: 96.5 | F48: 98.5 | G48: 100 | H48: 101.5 | I48: 103 | J48: 104.5 | K48: 106
D49: Stress Case | E49: 101 | F49: 105 | G49: 107 | H49: 108.5 | I49: 110 | J49: 111.5 | K49: 113
A50: 4 | B50: CPI inflation | C50: % | D50: Base Case | E50: 0.051 | F50: 0.046 | G50: 0.045 | H50: 0.045 | I50: 0.045 | J50: 0.045 | K50: 0.045 | L50: RBI-Jun26 | M50: MA04
D51: Bull Case | E51: 0.045 | F51: 0.042 | G51: 0.042 | H51: 0.042 | I51: 0.042 | J51: 0.042 | K51: 0.042
D52: Bear Case | E52: 0.057 | F52: 0.052 | G52: 0.05 | H52: 0.048 | I52: 0.048 | J52: 0.048 | K52: 0.048
D53: Stress Case | E53: 0.068 | F53: 0.062 | G53: 0.055 | H53: 0.052 | I53: 0.05 | J53: 0.05 | K53: 0.05
A54: 5 | B54: Announced pipeline delivery factor | C54: % | D54: Base Case | E54: 0.85 | F54: 0.85 | G54: 0.85 | H54: 0.85 | I54: 0.85 | J54: 0.85 | K54: 0.85 | L54: Derived-DB | M54: MA05
D55: Bull Case | E55: 0.95 | F55: 0.95 | G55: 0.95 | H55: 0.95 | I55: 0.95 | J55: 0.95 | K55: 0.95
D56: Bear Case | E56: 0.7 | F56: 0.7 | G56: 0.7 | H56: 0.7 | I56: 0.7 | J56: 0.7 | K56: 0.7
D57: Stress Case | E57: 0.55 | F57: 0.55 | G57: 0.55 | H57: 0.55 | I57: 0.55 | J57: 0.55 | K57: 0.55
A58: 6 | B58: Crude-to-finished steel ratio | C58: x | D58: Base Case | E58: 1.0465 | F58: 1.0465 | G58: 1.0465 | H58: 1.0465 | I58: 1.0465 | J58: 1.0465 | K58: 1.0465 | L58: Derived-DB | M58: MA06
D59: Bull Case | E59: 1.043 | F59: 1.043 | G59: 1.043 | H59: 1.043 | I59: 1.043 | J59: 1.043 | K59: 1.043
D60: Bear Case | E60: 1.05 | F60: 1.05 | G60: 1.05 | H60: 1.05 | I60: 1.05 | J60: 1.05 | K60: 1.05
D61: Stress Case | E61: 1.053 | F61: 1.053 | G61: 1.053 | H61: 1.053 | I61: 1.053 | J61: 1.053 | K61: 1.053
A62: 7 | B62: Net finished steel exports | C62: Mt | D62: Base Case | E62: 0.5 | F62: 1 | G62: 1.5 | H62: 2 | I62: 2.5 | J62: 3 | K62: 3.5 | L62: Derived-DB | M62: MA07
D63: Bull Case | E63: 0 | F63: 0 | G63: 0.5 | H63: 0.5 | I63: 1 | J63: 1 | K63: 1.5
D64: Bear Case | E64: 1.5 | F64: 2.5 | G64: 3.5 | H64: 4.5 | I64: 5.5 | J64: 6 | K64: 6.5
D65: Stress Case | E65: -1 | F65: -2.5 | G65: -3.5 | H65: -4 | I65: -4.5 | J65: -5 | K65: -5
A66: 8 | B66: Variation in stock | C66: Mt | D66: Base Case | E66: -1 | F66: 0 | G66: 0.5 | H66: 0.5 | I66: 0.5 | J66: 0.5 | K66: 0.5 | L66: Derived-DB | M66: MA08
D67: Bull Case | E67: -1.5 | F67: -0.5 | G67: 0 | H67: 0 | I67: 0.5 | J67: 0.5 | K67: 0.5
D68: Bear Case | E68: 0.5 | F68: 1.5 | G68: 1.5 | H68: 1 | I68: 1 | J68: 1 | K68: 1
D69: Stress Case | E69: 2 | F69: 3 | G69: 2.5 | H69: 2 | I69: 1.5 | J69: 1 | K69: 1
A70: 9 | B70: Blended industry realisation | C70: Rs/t | D70: Base Case | E70: 61800 | F70: 61000 | G70: 60500 | H70: 62000 | I70: 64000 | J70: 66000 | K70: 68000 | L70: Derived-DB | M70: MA09
D71: Bull Case | E71: 62500 | F71: 63500 | G71: 64000 | H71: 65500 | I71: 66500 | J71: 67500 | K71: 68500
D72: Bear Case | E72: 57500 | F72: 55000 | G72: 54000 | H72: 55000 | I72: 56500 | J72: 58000 | K72: 59500
D73: Stress Case | E73: 59000 | F73: 58500 | G73: 60000 | H73: 62500 | I73: 65000 | J73: 67000 | K73: 69000
A74: 10 | B74: Iron ore 62% Fe CFR China | C74: US$/dmt | D74: Base Case | E74: 102 | F74: 97 | G74: 93 | H74: 90 | I74: 90 | J74: 91 | K74: 93 | L74: S17 | M74: MA10
D75: Bull Case | E75: 98 | F75: 92 | G75: 88 | H75: 85 | I75: 84 | J75: 84 | K75: 86
D76: Bear Case | E76: 96 | F76: 90 | G76: 86 | H76: 83 | I76: 82 | J76: 82 | K76: 83
D77: Stress Case | E77: 115 | F77: 112 | G77: 104 | H77: 98 | I77: 94 | J77: 92 | K77: 92
A78: 11 | B78: Premium HCC coking coal FOB Australia | C78: US$/t | D78: Base Case | E78: 210 | F78: 200 | G78: 195 | H78: 190 | I78: 190 | J78: 195 | K78: 200 | L78: S01 | M78: MA11
D79: Bull Case | E79: 200 | F79: 188 | G79: 182 | H79: 178 | I79: 178 | J79: 180 | K79: 184
D80: Bear Case | E80: 200 | F80: 185 | G80: 176 | H80: 170 | I80: 168 | J80: 168 | K80: 170
D81: Stress Case | E81: 300 | F81: 285 | G81: 245 | H81: 220 | I81: 208 | J81: 202 | K81: 200
A82: 12 | B82: Conversion cost inflation | C82: % | D82: Base Case | E82: 0.045 | F82: 0.042 | G82: 0.04 | H82: 0.04 | I82: 0.04 | J82: 0.04 | K82: 0.04 | L82: RBI-Jun26 | M82: MA12
D83: Bull Case | E83: 0.038 | F83: 0.035 | G83: 0.033 | H83: 0.032 | I83: 0.032 | J83: 0.032 | K83: 0.032
D84: Bear Case | E84: 0.05 | F84: 0.046 | G84: 0.044 | H84: 0.042 | I84: 0.042 | J84: 0.042 | K84: 0.042
D85: Stress Case | E85: 0.075 | F85: 0.068 | G85: 0.055 | H85: 0.048 | I85: 0.044 | J85: 0.042 | K85: 0.042
A86: 13 | B86: Raw material share of cash cost | C86: % | D86: Base Case | E86: 0.6 | F86: 0.6 | G86: 0.6 | H86: 0.6 | I86: 0.6 | J86: 0.6 | K86: 0.6 | L86: Indicative | M86: MA13
D87: Bull Case | E87: 0.6 | F87: 0.6 | G87: 0.6 | H87: 0.6 | I87: 0.6 | J87: 0.6 | K87: 0.6
D88: Bear Case | E88: 0.6 | F88: 0.6 | G88: 0.6 | H88: 0.6 | I88: 0.6 | J88: 0.6 | K88: 0.6
D89: Stress Case | E89: 0.6 | F89: 0.6 | G89: 0.6 | H89: 0.6 | I89: 0.6 | J89: 0.6 | K89: 0.6
A90: 14 | B90: Iron ore weight in the raw material basket | C90: % | D90: Base Case | E90: 0.45 | F90: 0.45 | G90: 0.45 | H90: 0.45 | I90: 0.45 | J90: 0.45 | K90: 0.45 | L90: Indicative | M90: MA14
D91: Bull Case | E91: 0.45 | F91: 0.45 | G91: 0.45 | H91: 0.45 | I91: 0.45 | J91: 0.45 | K91: 0.45
D92: Bear Case | E92: 0.45 | F92: 0.45 | G92: 0.45 | H92: 0.45 | I92: 0.45 | J92: 0.45 | K92: 0.45
D93: Stress Case | E93: 0.45 | F93: 0.45 | G93: 0.45 | H93: 0.45 | I93: 0.45 | J93: 0.45 | K93: 0.45
A94: 15 | B94: Effective tax rate | C94: % | D94: Base Case | E94: 0.2517 | F94: 0.2517 | G94: 0.2517 | H94: 0.2517 | I94: 0.2517 | J94: 0.2517 | K94: 0.2517 | L94: Statutory | M94: MA15
D95: Bull Case | E95: 0.2517 | F95: 0.2517 | G95: 0.2517 | H95: 0.2517 | I95: 0.2517 | J95: 0.2517 | K95: 0.2517
D96: Bear Case | E96: 0.2517 | F96: 0.2517 | G96: 0.2517 | H96: 0.2517 | I96: 0.2517 | J96: 0.2517 | K96: 0.2517
D97: Stress Case | E97: 0.2517 | F97: 0.2517 | G97: 0.2517 | H97: 0.2517 | I97: 0.2517 | J97: 0.2517 | K97: 0.2517
A98: 16 | B98: Capex intensity | C98: Rs/t of capacity added | D98: Base Case | E98: 55000 | F98: 55000 | G98: 55000 | H98: 55000 | I98: 55000 | J98: 55000 | K98: 55000 | L98: Derived-DB | M98: MA16
D99: Bull Case | E99: 52000 | F99: 52000 | G99: 52000 | H99: 52000 | I99: 52000 | J99: 52000 | K99: 52000
D100: Bear Case | E100: 60000 | F100: 60000 | G100: 60000 | H100: 60000 | I100: 60000 | J100: 60000 | K100: 60000
D101: Stress Case | E101: 65000 | F101: 65000 | G101: 65000 | H101: 65000 | I101: 65000 | J101: 65000 | K101: 65000
A102: 17 | B102: Maintenance capex | C102: % of revenue | D102: Base Case | E102: 0.03 | F102: 0.03 | G102: 0.03 | H102: 0.03 | I102: 0.03 | J102: 0.03 | K102: 0.03 | L102: Indicative | M102: MA17
D103: Bull Case | E103: 0.028 | F103: 0.028 | G103: 0.028 | H103: 0.028 | I103: 0.028 | J103: 0.028 | K103: 0.028
D104: Bear Case | E104: 0.033 | F104: 0.033 | G104: 0.033 | H104: 0.033 | I104: 0.033 | J104: 0.033 | K104: 0.033
...

Sheet Model Calibration
A1: MODEL CALIBRATION
A2: Industry Financial Model | Indian Steel Industry | Horizon FY2027E-FY2033E | Base year FY2026A
L3: Active Scenario | N3: ='Control Panel'!$E$17
A4: Purpose
A5: This sheet extracts the key industry benchmark values from the Master Industry Database and converts them into modelling variables used throughout the workbook.
A8: Industry Size Calibration
A9: ID | B9: Variable | C9: Unit | D9: FY2026A | E9: Source | F9: Model Used In | G9: Status
A10: MC001 | B10: Crude Steel Production | C10: Mt | D10: ='[1]Production Volume'!$H$6 | E10: Database | F10: Demand Model | G10: ✅
A11: MC002 | B11: Finished Steel Production | C11: Mt | D11: ='[1]Production Volume'!$H$7 | E11: Database | F11: Supply Model | G11: ✅
A12: MC003 | B12: Finished Steel Consumption | C12: Mt | D12: ='[1]Demand & Consumption'!$H$6 | E12: Database | F12: Demand Model | G12: ✅
A13: MC004 | B13: Installed Capacity | C13: MTPA | D13: ='[1]Production Capacity'!$H$6 | E13: Database | F13: Capacity Model | G13: ✅
A14: MC005 | B14: Capacity Utilisation | C14: % | D14: =D10/D13 | E14: Derived | F14: Capacity Model | G14: ✅
A17: Industry Economics
A18: ID | B18: Variable | C18: Unit | D18: FY2026A | E18: Source | F18: Model Used In
A19: MC101 | B19: Average Steel Realisation | C19: ₹/t | D19: ='[1]Steel Prices'!$H$12 | E19: Database | F19: Revenue Model
A20: MC102 | B20: EBITDA per Ton | C20: ₹/t | D20: ='[1]Revenue & EBITDA'!$H$43 | E20: Database | F20: EBITDA Model
A21: MC103 | B21: Cash Cost per Ton | C21: ₹/t | D21: =D23-D20 | E21: Derived | F21: Cost Curve
A22: MC104 | B22: EBITDA Margin | C22: % | D22: ='[1]Revenue & EBITDA'!$H$33 | E22: Database | F22: Margin Model
A23: MC105 | B23: Revenue per Ton | C23: ₹/t | D23: ='Revenue Forecast'!$C$95/'Revenue Forecast'!$C$93*10 | E23: Derived | F23: Revenue Model
A26: Commodity Benchmarks
A27: ID | B27: Variable | C27: Unit | D27: FY2026A | E27: Source | F27: Model Used In
A28: MC201 | B28: Iron Ore (62% Fe CFR China) | C28: US$/dmt | D28: ='[1]Raw Materials'!$H$6 | E28: Database | F28: Raw Material Model
A29: MC202 | B29: Premium HCC Coal | C29: US$/t | D29: ='[1]Raw Materials'!$H$11 | E29: Database | F29: Raw Material Model
A30: MC203 | B30: Thermal Coal | C30: US$/t | D30: ='[1]Raw Materials'!$H$13 | E30: Database | F30: Cost Model
A31: MC204 | B31: Domestic HRC Price | C31: ₹/t | D31: ='[1]Steel Prices'!$H$6 | E31: Database | F31: Steel Price Model
A34: Trade Benchmarks
A35: ID | B35: Variable | C35: Unit | D35: FY2026A | E35: Source | F35: Model Used In
A36: MC301 | B36: Imports | C36: Mt | D36: ='[1]Imports & Exports'!$H$6 | E36: Database | F36: Trade Model
A37: MC302 | B37: Exports | C37: Mt | D37: ='[1]Imports & Exports'!$H$7 | E37: Database | F37: Trade Model
A38: MC303 | B38: Stock Change | C38: Mt | D38: ='[1]Demand & Consumption'!$H$9 | E38: Database | F38: Trade Model
A41: Industry Ratios
A42: ID | B42: Variable | C42: FY2026A | D42: Formula | E42: Model Used In
A43: MC401 | B43: Crude to Finished Ratio | C43: =D10/D12 | D43: Derived | E43: Demand
A44: MC402 | B44: Per Capita Consumption | C44: ='[1]Demand & Consumption'!$H$8 | D44: Database | E44: Demand
A45: MC403 | B45: Industry Volume Coverage | C45: =SUM('[1]Production Volume'!$H$15:$H$19)/'[1]Production Volume'!$H$21 | D45: Derived | E45: Calibration
A46: MC404 | B46: Capacity Utilisation | C46: =D10/D13 | D46: Derived | E46: Capacity
A47: MC405 | B47: Import Dependency | C47: =D36/D12 | D47: Derived | E47: Trade
A50: Calibration Checks
A51: ID | B51: Check | C51: Formula | E51: Result
A52: MC501 | B52: Production | C52: Capacity × Utilisation | E52: =IF(ABS($D$13*$D$14-$D$10)<0.05,"PASS","FAIL")
A53: MC502 | B53: Revenue | C53: Price × Volume | E53: =IF(ABS(D11*D19/10-'Revenue Forecast'!C95)<1,"PASS","FAIL")
A54: MC503 | B54: EBITDA | C54: Revenue − Cost | E54: =IF(ABS(($D$19-$D$21)-$D$20)<1,"PASS","FAIL")
A55: MC504 | B55: Consumption Identity Balances | C55: Finished production = Consumption + Net exports + Variation in stock | E55: =IF(ABS($D$11-($D$12+($D$37-$D$36)+$D$38))<0.02,"PASS","FAIL")
A56: MC505 | B56: Import/Export Balance | C56: Exports less Imports = Net trade position | E56: =IF(ABS(($D$37-$D$36)-'Steel Supply Model'!$C$79)<0.001,"PASS","FAIL")

Sheet Macroeconomic Model
A1: MACROECONOMIC MODEL
A2: Industry Financial Model | Indian Steel Industry | Horizon FY2027E-FY2033E | Base year FY2026A
N3: Active Scenario | P3: ='Control Panel'!$E$17
A4: OBJECTIVE
A5: Convert macroeconomic assumptions into economic drivers for the steel industry.
A6: METHODOLOGY
A7: Real GDP growth and CPI are taken from RBI's June-2026 Monetary Policy Committee projections for FY2027 and converge to a steady state thereafter, because no Indian official body publishes a real GDP path beyond roughly five years. USD/INR is anchored on the 22-Jun-2026 spot of 94. Index rows compound the growth rates so that cumulative effects are visible rather than implied.
A8: UNITS
A9: Percentages as decimals. Indices FY2026A = ~100 (USD/INR) in rupees per dollar.
A11: Executive Summary
A12: Metric | B12: FY2026A | C12: FY2027E | D12: FY2028E | E12: FY2029E | F12: FY2030E | G12: FY2031E | H12: FY2032E | I12: FY2033E | J12: Audit Code
A13: GDP Growth (%) | B13: ='Model Assumptions'!D8 | C13: ='Model Assumptions'!E8 | D13: ='Model Assumptions'!F8 | E13: ='Model Assumptions'!G8 | F13: ='Model Assumptions'!H8 | G13: ='Model Assumptions'!I8 | H13: ='Model Assumptions'!J8 | I13: ='Model Assumptions'!K8 | J13: MM01
A14: CPI Inflation (%) | B14: ='Model Assumptions'!D11 | C14: ='Model Assumptions'!E11 | D14: ='Model Assumptions'!F11 | E14: ='Model Assumptions'!G11 | F14: ='Model Assumptions'!H11 | G14: ='Model Assumptions'!I11 | H14: ='Model Assumptions'!J11 | I14: ='Model Assumptions'!K11 | J14: MM02
A15: Repo Rate (%) | B15: 0.0525 | C15: 0.0525 | D15: 0.0525 | E15: 0.0525 | F15: 0.0525 | G15: 0.0525 | H15: 0.0525 | I15: 0.0525 | J15: MM03
A16: Real GDP Index | B16: 100 | C16: =B16*(1+C13) | D16: =C16*(1+D13) | E16: =D16*(1+E13) | F16: =E16*(1+F13) | G16: =F16*(1+G13) | H16: =G16*(1+H13) | I16: =H16*(1+I13) | J16: MM04
A17: Nominal GDP Index | B17: 100 | C17: =B17*(1+C13)*(1+C14) | D17: =C17*(1+D13)*(1+D14) | E17: =D17*(1+E13)*(1+E14) | F17: =E17*(1+F13)*(1+F14) | G17: =F17*(1+G13)*(1+G14) | H17: =G17*(1+H13)*(1+H14) | I17: =H17*(1+I13)*(1+I14) | J17: MM05
A18: USD/INR | B18: ='Model Assumptions'!D10 | C18: ='Model Assumptions'!E10 | D18: ='Model Assumptions'!F10 | E18: ='Model Assumptions'!G10 | F18: ='Model Assumptions'!H10 | G18: ='Model Assumptions'!I10 | H18: ='Model Assumptions'!J10 | I18: ='Model Assumptions'!K10 | J18: MM06
A19: INR Depreciation | C19: =C18/B18-1 | D19: =D18/C18-1 | E19: =E18/D18-1 | F19: =F18/E18-1 | G19: =G18/F18-1 | H19: =H18/G18-1 | I19: =I18/H18-1 | J19: MM07
A20: Brent Oil (US$/bbl) | B20: 79 | C20: 79 | D20: 79 | E20: 79 | F20: 79 | G20: 79 | H20: 79 | I20: 79 | J20: MM08
A21: 10 Year G Sec Yield | B21: 0.068 | C21: 0.068 | D21: 0.068 | E21: 0.068 | F21: 0.068 | G21: 0.068 | H21: 0.068 | I21: 0.068 | J21: MM09
A22: WACC (Nominal) | B22: ='Model Assumptions'!D27 | C22: ='Model Assumptions'!E27 | D22: ='Model Assumptions'!F27 | E22: ='Model Assumptions'!G27 | F22: ='Model Assumptions'!H27 | G22: ='Model Assumptions'!I27 | H22: ='Model Assumptions'!J27 | I22: ='Model Assumptions'!K27 | J22: MM10
A25: Leading Indicators
A26: Indicator | B26: FY2025A | C26: FY2026A | D26: Trend | E26: Impact
A27: PMI Manufacturing | D27: =IF(C27>B27,"▲",IF(C27<B27,"▼","►"))
A28: Core Sector Growth | D28: =IF(C28>B28,"▲",IF(C28<B28,"▼","►"))
A29: Infrastructure Spending | D29: =IF(C29>B29,"▲",IF(C29<B29,"▼","►"))
A30: Government Capex | D30: =IF(C30>B30,"▲",IF(C30<B30,"▼","►"))
A31: Housing Completions | D31: =IF(C31>B31,"▲",IF(C31<B31,"▼","►"))
A32: Vehicle Production | D32: =IF(C32>B32,"▲",IF(C32<B32,"▼","►"))
A33: Railway Capex | D33: =IF(C33>B33,"▲",IF(C33<B33,"▼","►"))
A36: Commodity Environment
A37: Commodity | B37: FY2026A | C37: FY2033E | D37: Trend | E37: Audit Code
A38: Brent Oil | B38: =$B$20 | C38: =$I$20 | D38: =IF(C38>B38,"▲ Increase",IF(C38<B38,"▼ Decrease","► Stable")) | E38: MM11
A39: Iron Ore | B39: ='Raw Material Forecast'!$C$61 | C39: ='Raw Material Forecast'!$J$61 | D39: =IF(C39>B39,"▲ Increase",IF(C39<B39,"▼ Decrease","► Stable")) | E39: MM12
A40: HCC Coal | B40: ='Raw Material Forecast'!$C$62 | C40: ='Raw Material Forecast'!$J$62 | D40: =IF(C40>B40,"▲ Increase",IF(C40<B40,"▼ Decrease","► Stable")) | E40: MM13
A41: Thermal Coal | B41: 111.5 | D41: =IF(C41>B41,"▲ Increase",IF(C41<B41,"▼ Decrease","► Stable")) | E41: MM14
A44: Macro Outlook
A45: GROWTH. The RBI cut its FY2027 real GDP projection to 6.6% from 6.9% at the 05-Jun-2026 MPC, citing the West Asia conflict, energy prices and monsoon risk, against an estimated 7.6% for FY2026 and a Q4FY2026 actual of 7.7%. The base case adopts 6.6% unchanged and converges to a 6.5% steady state; it does not extrapolate the FY2026 outturn, which was flattered by a low base and front-loaded government capex.
A46: PRICES AND POLICY. CPI is projected at 5.1% for FY2027, 50bps above the previous projection, converging to the 4.5% mid-point of the RBI target band. The repo rate was held at 5.25% and the 10-year G-sec was 6.833% on 31-Jul-2026. Conversion cost inflation in the model is anchored on this CPI path rather than on a separately asserted wage or power series.
A47: CURRENCY. USD/INR averaged 88.4 in FY2026 and was 94 spot on 22-Jun-2026 within an 85 to 98 52-week range. The base case takes the rupee to 100.5 by FY2033E. This is the second largest single driver of industry EBITDA in the model, because iron ore and coking coal are priced in dollars while realisation is in rupees.
A48: TRANSMISSION TO STEEL. Macro reaches steel demand through exactly one channel in this model: real GDP growth multiplied by a demand elasticity of 1.15x tapering to 1.05x. That elasticity is the realised FY2015-FY2026 outturn, not an assertion. Everything downstream - supply, utilisation, price, cost, margin, cash flow and valuation - follows from that single link, which is why the GDP and elasticity rows are the two most important cells in the workbook.
A51: Outputs to Downstream Models
A52: Output Variable | B52: Destination
A53: GDP Growth | B53: Demand Model
A54: Construction Growth | B54: Demand Model
A55: Auto Growth | B55: Demand Model
A56: Infrastructure Growth | B56: Demand Model
A57: Inflation | B57: Revenue Model
A58: USD/INR | B58: Cost Model
A59: Repo Rate | B59: Valuation

Sheet Steel Demand Model
A1: STEEL DEMAND MODEL
A2: Industry Financial Model | Indian Steel Industry | Horizon FY2027E-FY2033E | Base year FY2026A
M3: Active Scenario | O3: ='Control Panel'!$E$17
A4: OBJECTIVE
A5: Forecasts India's apparent finished steel consumption, the demand anchor for the whole model.
A7: Executive Summary
A8: Metric | B8: FY26A | C8: FY27E | D8: FY28E | E8: FY29E | F8: FY30E | G8: FY31E | H8: FY32E | I8: FY33E | J8: Audit Code
A9: Apparent Steel Consumption (Mt) | B9: =$C$75 | C9: =$D$75 | D9: =$E$75 | E9: =$F$75 | F9: =$G$75 | G9: =$H$75 | H9: =$I$75 | I9: =$J$75 | J9: SD01
A10: Demand Growth (%) | B10: =$C$74 | C10: =$D$74 | D10: =$E$74 | E10: =$F$74 | F10: =$G$74 | G10: =$H$74 | H10: =$I$74 | I10: =$J$74 | J10: SD02
A11: Per Capita Consumption (kg) | B11: =$C$80 | C11: =$D$80 | D11: =$E$80 | E11: =$F$80 | F11: =$G$80 | G11: =$H$80 | H11: =$I$80 | I11: =$J$80 | J11: SD03
A12: Domestic Demand Share (%) | B12: =IFERROR(C75/(C75+'Trade Model'!C72),"") | C12: =IFERROR(D75/(D75+'Trade Model'!D72),"") | D12: =IFERROR(E75/(E75+'Trade Model'!E72),"") | E12: =IFERROR(F75/(F75+'Trade Model'!F72),"") | F12: =IFERROR(G75/(G75+'Trade Model'!G72),"") | G12: =IFERROR(H75/(H75+'Trade Model'!H72),"") | H12: =IFERROR(I75/(I75+'Trade Model'!I72),"") | I12: =IFERROR(J75/(J75+'Trade Model'!J72),"") | J12: SD04
A13: CAGR (FY26–FY33) | C13: =(C9-B9)/B9 | D13: =(D9-C9)/C9 | E13: =(E9-D9)/D9 | F13: =(F9-E9)/E9 | G13: =(G9-F9)/F9 | H13: =(H9-G9)/G9 | I13: =(I9-H9)/H9 | J13: SD05
A16: Historical Demand
A17: Year | B17: Consumption (Mt) | C17: Growth % | D17: Source | F17: Audit Code
A18: FY21 | B18: ='[1]Demand & Consumption'!$C$6 | C18: -0.0527 | D18: JPC / Ministry of Steel | F18: SD06
A19: FY22 | B19: ='[1]Demand & Consumption'!$D$6 | C19: =(B19-B18)/B18 | D19: JPC / Ministry of Steel | F19: SD07
A20: FY23 | B20: ='[1]Demand & Consumption'!$E$6 | C20: =(B20-B19)/B19 | D20: JPC / Ministry of Steel | F20: SD08
A21: FY24 | B21: ='[1]Demand & Consumption'!$F$6 | C21: =(B21-B20)/B20 | D21: JPC / Ministry of Steel | F21: SD09
A22: FY25 | B22: ='[1]Demand & Consumption'!$G$6 | C22: =(B22-B21)/B21 | D22: JPC / Ministry of Steel | F22: SD10
A23: FY26 | B23: ='[1]Demand & Consumption'!$H$6 | C23: =(B23-B22)/B22 | D23: JPC / Ministry of Steel | F23: SD11
A26: Per Capita Analysis
A27: Year | B27: Population (Mn) | C27: Steel Consumption (Mt) | D27: Per Capita (kg) | E27: Audit Code
A28: FY26 | B28: =$C$78*1000 | C28: =$C$75 | D28: =IFERROR(C28/B28*1000,"") | E28: SD12
A29: FY27 | B29: =$D$78*1000 | C29: =$D$75 | D29: =IFERROR(C29/B29*1000,"") | E29: SD13
A30: FY28 | B30: =$E$78*1000 | C30: =$E$75 | D30: =IFERROR(C30/B30*1000,"") | E30: SD14
A31: FY29 | B31: =$F$78*1000 | C31: =$F$75 | D31: =IFERROR(C31/B31*1000,"") | E31: SD15
A32: FY30 | B32: =$G$78*1000 | C32: =$G$75 | D32: =IFERROR(C32/B32*1000,"") | E32: SD16
A33: FY31 | B33: =$H$78*1000 | C33: =$H$75 | D33: =IFERROR(C33/B33*1000,"") | E33: SD17
A34: FY32 | B34: =$I$78*1000 | C34: =$I$75 | D34: =IFERROR(C34/B34*1000,"") | E34: SD18
A35: FY33 | B35: =$J$78*1000 | C35: =$J$75 | D35: =IFERROR(C35/B35*1000,"") | E35: SD19
A38: International Comparision
A39: Country | B39: Per Capita Steel Consumption (kg) | E39: Audit Code
A40: India | B40: =C80 | E40: SD20
A41: China | B41: 604 | E41: SD21
A42: Japan | E42: SD22
A43: South Korea | E43: SD23
A44: USA | E44: SD24
A45: Global Average | B45: 215 | E45: SD25
A48: Demand Forecast
A49: Year | B49: Base Demand | C49: Macro Adjustment | D49: Sector Adjustment | E49: Final Demand | F49: Audit Code
A50: FY27 | B50: =$C$75 | C50: =1+D$74 | D50: 1 | E50: =B50*C50*D50 | F50: SD26
A51: FY28 | B51: =E50 | C51: =1+E$74 | D51: 1 | E51: =B51*C51*D51 | F51: SD27
A52: FY29 | B52: =E51 | C52: =1+F$74 | D52: 1 | E52: =B52*C52*D52 | F52: SD28
A53: FY30 | B53: =E52 | C53: =1+G$74 | D53: 1 | E53: =B53*C53*D53 | F53: SD29
A54: FY31 | B54: =E53 | C54: =1+H$74 | D54: 1 | E54: =B54*C54*D54 | F54: SD30
A55: FY32 | B55: =E54 | C55: =1+I$74 | D55: 1 | E55: =B55*C55*D55 | F55: SD31
A56: FY33 | B56: =E55 | C56: =1+J$74 | D56: 1 | E56: =B56*C56*D56 | F56: SD32
A59: Scenario Analysis
A60: Year | B60: Base | C60: Bull | D60: Bear | E60: Stress
A61: FY27 | B61: ='Scenario Manager'!$D$92 | C61: ='Scenario Manager'!$D$159 | D61: ='Scenario Manager'!$D$226 | E61: ='Scenario Manager'!$D$293
A62: FY28 | B62: ='Scenario Manager'!$E$92 | C62: ='Scenario Manager'!$E$159 | D62: ='Scenario Manager'!$E$226 | E62: ='Scenario Manager'!$E$293
A63: FY29 | B63: ='Scenario Manager'!$F$92 | C63: ='Scenario Manager'!$F$159 | D63: ='Scenario Manager'!$F$226 | E63: ='Scenario Manager'!$F$293
A64: FY30 | B64: ='Scenario Manager'!$G$92 | C64: ='Scenario Manager'!$G$159 | D64: ='Scenario Manager'!$G$226 | E64: ='Scenario Manager'!$G$293
A65: FY31 | B65: ='Scenario Manager'!$H$92 | C65: ='Scenario Manager'!$H$159 | D65: ='Scenario Manager'!$H$226 | E65: ='Scenario Manager'!$H$293
A66: FY32 | B66: ='Scenario Manager'!#REF! | C66: ='Scenario Manager'!#REF! | D66: ='Scenario Manager'!#REF! | E66: ='Scenario Manager'!#REF!
A67: FY33 | B67: ='Scenario Manager'!$I$92 | C67: ='Scenario Manager'!$I$159 | D67: ='Scenario Manager'!$I$226 | E67: ='Scenario Manager'!$I$293
A70: Workbook
A71: Line item | B71: Unit | C71: FY2026A | D71: FY2027E | E71: FY2028E | F71: FY2029E | G71: FY2030E | H71: FY2031E | I71: FY2032E | J71: FY2033E | K71: Audit Code
A72: India real GDP growth | B72: % | C72: ='Model Assumptions'!D8 | D72: ='Model Assumptions'!E8 | E72: ='Model Assumptions'!F8 | F72: ='Model Assumptions'!G8 | G72: ='Model Assumptions'!H8 | H72: ='Model Assumptions'!I8 | I72: ='Model Assumptions'!J8 | J72: ='Model Assumptions'!K8 | K72: SD33
A73: Steel demand elasticity to GDP | B73: x | C73: ='Model Assumptions'!D9 | D73: ='Model Assumptions'!E9 | E73: ='Model Assumptions'!F9 | F73: ='Model Assumptions'!G9 | G73: ='Model Assumptions'!H9 | H73: ='Model Assumptions'!I9 | I73: ='Model Assumptions'!J9 | J73: ='Model Assumptions'!K9 | K73: SD34
A74: Implied consumption growth | B74: % | C74: =C72*C73 | D74: =D72*D73 | E74: =E72*E73 | F74: =F72*F73 | G74: =G72*G73 | H74: =H72*H73 | I74: =I72*I73 | J74: =J72*J73 | K74: SD35
A75: Apparent finished steel consumption | B75: Mt | C75: ='Model Calibration'!D12 | D75: =C75*(1+D74) | E75: =D75*(1+E74) | F75: =E75*(1+F74) | G75: =F75*(1+G74) | H75: =G75*(1+H74) | I75: =H75*(1+I74) | J75: =I75*(1+J74) | K75: SD36
A76: Memo: June-2026 JPC vintage, FY2026 actual | B76: Mt | C76: =C75 | K76: SD37
A77: DEMAND INTENSITY
A78: Population | B78: bn | C78: 1.4191 | D78: =C78*(1+$C$79) | E78: =D78*(1+$C$79) | F78: =E78*(1+$C$79) | G78: =F78*(1+$C$79) | H78: =G78*(1+$C$79) | I78: =H78*(1+$C$79) | J78: =I78*(1+$C$79) | K78: SD38
A79: Population growth | B79: % | C79: 0.0085 | D79: =C79 | E79: =D79 | F79: =E79 | G79: =F79 | H79: =G79 | I79: =H79 | J79: =I79 | K79: SD39
A80: Per capita finished steel consumption | B80: kg | C80: =C75/C78 | D80: =D75/D78 | E80: =E75/E78 | F80: =F75/F78 | G80: =G75/G78 | H80: =H75/H78 | I80: =I75/I78 | J80: =J75/J78 | K80: SD40
A82: Demand is the ONLY block in this model that is not capacity-aware. The capacity ceiling is applied on 05 Steel Supply, so consumption here is unconstrained demand.

Sheet Steel Supply Model
A1: STEEL SUPLY MODEL
A2: Industry Financial Model | Indian Steel Industry | Horizon FY2027E-FY2033E | Base year FY2026A
N3: Active Scenario | P3: ='Control Panel'!$E$17
A4: OBJECTIVE
A5: Forecast India's finished steel supply and reconcile it with domestic demand, capacity, imports, exports, and inventory changes.
A7: Executive Summary
A8: KPI | B8: FY26A | C8: FY27E | D8: FY28E | E8: FY29E | F8: FY30E | G8: FY31E | H8: FY32E | I8: FY33E
A9: Crude Steel Production (Mt) | B9: =$C$88 | C9: =$D$88 | D9: =$E$88 | E9: =$F$88 | F9: =$G$88 | G9: =$H$88 | H9: =$I$88 | I9: =$J$88
A10: Finished Steel Production (Mt) | B10: =$C$90 | C10: =$D$90 | D10: =$E$90 | E10: =$F$90 | F10: =$G$90 | G10: =$H$90 | H10: =$I$90 | I10: =$J$90
A11: Installed Capacity (MTPA) | B11: ='Capacity Forecast'!C$96 | C11: ='Capacity Forecast'!D$96 | D11: ='Capacity Forecast'!E$96 | E11: ='Capacity Forecast'!F$96 | F11: ='Capacity Forecast'!G$96 | G11: ='Capacity Forecast'!H$96 | H11: ='Capacity Forecast'!I$96 | I11: ='Capacity Forecast'!J$96
A12: Capacity Utilisation (%) | B12: ='Capacity Utilisation'!C$65 | C12: ='Capacity Utilisation'!D$65 | D12: ='Capacity Utilisation'!E$65 | E12: ='Capacity Utilisation'!F$65 | F12: ='Capacity Utilisation'!G$65 | G12: ='Capacity Utilisation'!H$65 | H12: ='Capacity Utilisation'!I$65 | I12: ='Capacity Utilisation'!J$65
A13: Domestic Supply (Mt) | B13: =C90+'Trade Model'!C70-'Trade Model'!C72 | C13: =D90+'Trade Model'!D70-'Trade Model'!D72 | D13: =E90+'Trade Model'!E70-'Trade Model'!E72 | E13: =F90+'Trade Model'!F70-'Trade Model'!F72 | F13: =G90+'Trade Model'!G70-'Trade Model'!G72 | G13: =H90+'Trade Model'!H70-'Trade Model'!H72 | H13: =I90+'Trade Model'!I70-'Trade Model'!I72 | I13: =J90+'Trade Model'!J70-'Trade Model'!J72
A14: Import Dependency (%) | B14: ='Trade Model'!C$77 | C14: ='Trade Model'!D$77 | D14: ='Trade Model'!E$77 | E14: ='Trade Model'!F$77 | F14: ='Trade Model'!G$77 | G14: ='Trade Model'!H$77 | H14: ='Trade Model'!I$77 | I14: ='Trade Model'!J$77
A15: Export Share (%) | B15: ='Trade Model'!C$78 | C15: ='Trade Model'!D$78 | D15: ='Trade Model'!E$78 | E15: ='Trade Model'!F$78 | F15: ='Trade Model'!G$78 | G15: ='Trade Model'!H$78 | H15: ='Trade Model'!I$78 | I15: ='Trade Model'!J$78
A16: Supply Surplus / Deficit (Mt) | B16: =B13-'Steel Demand Model'!B9 | C16: =C13-'Steel Demand Model'!C9 | D16: =D13-'Steel Demand Model'!D9 | E16: =E13-'Steel Demand Model'!E9 | F16: =F13-'Steel Demand Model'!F9 | G16: =G13-'Steel Demand Model'!G9 | H16: =H13-'Steel Demand Model'!H9 | I16: =I13-'Steel Demand Model'!I9
A19: Historical Supply
A20: Year | B20: Crude Production | C20: Finished Production | D20: Growth %
A21: FY21 | B21: ='[1]Production Volume'!$C$6 | C21: ='[1]Production Volume'!$C$7
A22: FY22 | B22: ='[1]Demand & Consumption'!$D$6 | C22: ='[1]Production Volume'!$D$7 | D22: =(C22-C21)/C21
A23: FY23 | B23: ='[1]Demand & Consumption'!$E$6 | C23: ='[1]Production Volume'!$E$7 | D23: =(C23-C22)/C22
A24: FY24 | B24: ='[1]Demand & Consumption'!$F$6 | C24: ='[1]Production Volume'!$F$7 | D24: =(C24-C23)/C23
A25: FY25 | B25: ='[1]Demand & Consumption'!$G$6 | C25: ='[1]Production Volume'!$G$7 | D25: =(C25-C24)/C24
A26: FY26 | B26: ='[1]Demand & Consumption'!$H$6 | C26: ='[1]Production Volume'!$H$7 | D26: =(C26-C25)/C25
A29: Supply Build Up
A30: Item | B30: FY26A | C30: FY27E | D30: FY28E | E30: FY29E | F30: FY30E | G30: FY31E | H30: FY32E | I30: FY33E | J30: Audit Code
A31: Opening Production | B31: ='[1]Production Capacity'!$G$8 | C31: =B35 | D31: =C35 | E31: =D35 | F31: =E35 | G31: =F35 | H31: =G35 | I31: =H35
A32: Capacity Addition | B32: ='Capacity Forecast'!C$95 | C32: ='Capacity Forecast'!D$95 | D32: ='Capacity Forecast'!E$95 | E32: ='Capacity Forecast'!F$95 | F32: ='Capacity Forecast'!G$95 | G32: ='Capacity Forecast'!H$95 | H32: ='Capacity Forecast'!I$95 | I32: ='Capacity Forecast'!J$95
A33: Effective Capacity | B33: ='Capacity Forecast'!C$96 | C33: ='Capacity Forecast'!D$96 | D33: ='Capacity Forecast'!E$96 | E33: ='Capacity Forecast'!F$96 | F33: ='Capacity Forecast'!G$96 | G33: ='Capacity Forecast'!H$96 | H33: ='Capacity Forecast'!I$96 | I33: ='Capacity Forecast'!J$96
A34: Capacity Utilisation | B34: ='Capacity Utilisation'!C$65 | C34: ='Capacity Utilisation'!D$65 | D34: ='Capacity Utilisation'!E$65 | E34: ='Capacity Utilisation'!F$65 | F34: ='Capacity Utilisation'!G$65 | G34: ='Capacity Utilisation'!H$65 | H34: ='Capacity Utilisation'!I$65 | I34: ='Capacity Utilisation'!J$65
A35: Crude Steel Production | B35: =C$88 | C35: =D$88 | D35: =E$88 | E35: =F$88 | F35: =G$88 | G35: =H$88 | H35: =I$88 | I35: =J$88
A36: Crude-to-Finished Ratio | B36: =C$82 | C36: =D$82 | D36: =E$82 | E36: =F$82 | F36: =G$82 | G36: =H$82 | H36: =I$82 | I36: =J$82
A37: Finished Steel Production | B37: =C$90 | C37: =D$90 | D37: =E$90 | E37: =F$90 | F37: =G$90 | G37: =H$90 | H37: =I$90 | I37: =J$90
A38: Imports | B38: ='Trade Model'!C$70 | C38: ='Trade Model'!D$70 | D38: ='Trade Model'!E$70 | E38: ='Trade Model'!F$70 | F38: ='Trade Model'!G$70 | G38: ='Trade Model'!H$70 | H38: ='Trade Model'!I$70 | I38: ='Trade Model'!J$70
A39: Exports | B39: ='Trade Model'!C$72 | C39: ='Trade Model'!D$72 | D39: ='Trade Model'!E$72 | E39: ='Trade Model'!F$72 | F39: ='Trade Model'!G$72 | G39: ='Trade Model'!H$72 | H39: ='Trade Model'!I$72 | I39: ='Trade Model'!J$72
A40: Inventory Adjustment | B40: =C$80 | C40: =D$80 | D40: =E$80 | E40: =F$80 | F40: =G$80 | G40: =H$80 | H40: =I$80 | I40: =J$80
A41: Domestic Supply Available | B41: =B37+B38-B39 | C41: =C37+C38-C39 | D41: =D37+D38-D39 | E41: =E37+E38-E39 | F41: =F37+F38-F39 | G41: =G37+G38-G39 | H41: =H37+H38-H39 | I41: =I37+I38-I39 | J41: SS01
A44: Supply Demand Reconcilation
A45: Item | B45: FY26A | C45: FY27E | D45: FY28E | E45: FY29E | F45: FY30E | G45: FY31E | H45: FY32E | I45: FY33E
A46: Domestic Supply | B46: =B37 | C46: =C37 | D46: =D37 | E46: =E37 | F46: =F37 | G46: =G37 | H46: =H37 | I46: =I37
A47: Imports | B47: =B38 | C47: =C38 | D47: =D38 | E47: =E38 | F47: =F38 | G47: =G38 | H47: =H38 | I47: =I38
A48: Total Supply | B48: =B47+B46 | C48: =C47+C46 | D48: =D47+D46 | E48: =E47+E46 | F48: =F47+F46 | G48: =G47+G46 | H48: =H47+H46 | I48: =I47+I46
A49: Domestic Demand | B49: ='Steel Demand Model'!B50 | C49: ='Steel Demand Model'!$E50 | D49: ='Steel Demand Model'!$E51 | E49: ='Steel Demand Model'!$E52 | F49: ='Steel Demand Model'!$E53 | G49: ='Steel Demand Model'!$E54 | H49: ='Steel Demand Model'!$E55 | I49: ='Steel Demand Model'!$E56
A50: Exports | B50: =B39 | C50: =C39 | D50: =D39 | E50: =E39 | F50: =F39 | G50: =G39 | H50: =H39 | I50: =I39
A51: Closing Inventory | B51: =B40 | C51: =C40 | D51: =D40 | E51: =E40 | F51: =F40 | G51: =G40 | H51: =H40 | I51: =I40
A52: Balance Check | B52: =IF((B48-B49-B50-B51)<1, "PASS", "FAIL") | C52: =IF(ABS(C46+C47-C49-C50-C51)<1,"PASS", "FAIL") | D52: =IF(ABS(D46+D47-D49-D50-D51)<1,"PASS", "FAIL") | E52: =IF(ABS(E46+E47-E49-E50-E51)<1,"PASS", "FAIL") | F52: =IF(ABS(F46+F47-F49-F50-F51)<1,"PASS", "FAIL") | G52: =IF(ABS(G46+G47-G49-G50-G51)<1,"PASS", "FAIL") | H52: =IF(ABS(H46+H47-H49-H50-H51)<1,"PASS", "FAIL") | I52: =IF(ABS(I46+I47-I49-I50-I51)<1,"PASS", "FAIL")
A55: Capacity Growth
A56: Year | B56: Existing Capacity | C56: New Capacity | D56: Total Capacity | E56: Growth %
A57: FY26 | B57: 200.33 | C57: ='Capacity Forecast'!$C$95 | D57: ='Capacity Forecast'!C$96 | E57: =IFERROR(D57/B57-1,"")
A58: FY27 | B58: =D57 | C58: ='Capacity Forecast'!$D$95 | D58: ='Capacity Forecast'!D$96 | E58: =IFERROR(D58/B58-1,"")
A59: FY28 | B59: =D58 | C59: ='Capacity Forecast'!$E$95 | D59: ='Capacity Forecast'!E$96 | E59: =IFERROR(D59/B59-1,"")
A60: FY29 | B60: =D59 | C60: ='Capacity Forecast'!$F$95 | D60: ='Capacity Forecast'!F$96 | E60: =IFERROR(D60/B60-1,"")
A61: FY30 | B61: =D60 | C61: ='Capacity Forecast'!$G$95 | D61: ='Capacity Forecast'!G$96 | E61: =IFERROR(D61/B61-1,"")
A62: FY31 | B62: =D61 | C62: ='Capacity Forecast'!$H$95 | D62: ='Capacity Forecast'!H$96 | E62: =IFERROR(D62/B62-1,"")
A63: FY32 | B63: =D62 | C63: ='Capacity Forecast'!$I$95 | D63: ='Capacity Forecast'!I$96 | E63: =IFERROR(D63/B63-1,"")
A64: FY33 | B64: =D63 | C64: ='Capacity Forecast'!$J$95 | D64: ='Capacity Forecast'!J$96 | E64: =IFERROR(D64/B64-1,"")
A67: Import & Export Dependancy
A68: Metric | B68: FY26A | C68: FY27E | D68: FY28E | E68: FY29E | F68: FY30E | G68: FY31E | H68: FY32E | I68: FY33E
A69: Imports (Mt) | B69: ='Trade Model'!C$70 | C69: ='Trade Model'!D$70 | D69: ='Trade Model'!E$70 | E69: ='Trade Model'!F$70 | F69: ='Trade Model'!G$70 | G69: ='Trade Model'!H$70 | H69: ='Trade Model'!I$70 | I69: ='Trade Model'!J$70
A70: Exports (Mt) | B70: ='Trade Model'!C$72 | C70: ='Trade Model'!D$72 | D70: ='Trade Model'!E$72 | E70: ='Trade Model'!F$72 | F70: ='Trade Model'!G$72 | G70: ='Trade Model'!H$72 | H70: ='Trade Model'!I$72 | I70: ='Trade Model'!J$72
A71: Net Imports (Mt) | B71: =B69-B70 | C71: =C69-C70 | D71: =D69-D70 | E71: =E69-E70 | F71: =F69-F70 | G71: =G69-G70 | H71: =H69-H70 | I71: =I69-I70
A72: Import Dependency (%) | B72: ='Trade Model'!C$77 | C72: ='Trade Model'!D$77 | D72: ='Trade Model'!E$77 | E72: ='Trade Model'!F$77 | F72: ='Trade Model'!G$77 | G72: ='Trade Model'!H$77 | H72: ='Trade Model'!I$77 | I72: ='Trade Model'!J$77
A73: Export Ratio (%) | B73: ='Trade Model'!C$78 | C73: ='Trade Model'!D$78 | D73: ='Trade Model'!E$78 | E73: ='Trade Model'!F$78 | F73: ='Trade Model'!G$78 | G73: ='Trade Model'!H$78 | H73: ='Trade Model'!I$78 | I73: ='Trade Model'!J$78
A76: Workbook
A77: Line item | B77: Unit | C77: FY2026A | D77: FY2027E | E77: FY2028E | F77: FY2029E | G77: FY2030E | H77: FY2031E | I77: FY2032E | J77: FY2033E | K77: Audit Code
A78: Apparent finished steel consumption | B78: Mt | C78: ='Model Calibration'!D12 | D78: ='Steel Demand Model'!D75 | E78: ='Steel Demand Model'!E75 | F78: ='Steel Demand Model'!F75 | G78: ='Steel Demand Model'!G75 | H78: ='Steel Demand Model'!H75 | I78: ='Steel Demand Model'!I75 | J78: ='Steel Demand Model'!J75
A79: Net finished steel exports | B79: Mt | C79: ='Model Assumptions'!D14 | D79: ='Model Assumptions'!E14 | E79: ='Model Assumptions'!F14 | F79: ='Model Assumptions'!G14 | G79: ='Model Assumptions'!H14 | H79: ='Model Assumptions'!I14 | I79: ='Model Assumptions'!J14 | J79: ='Model Assumptions'!K14 | K79: SS02
A80: Variation in stock | B80: Mt | C80: ='Model Assumptions'!D15 | D80: ='Model Assumptions'!E15 | E80: ='Model Assumptions'!F15 | F80: ='Model Assumptions'!G15 | G80: ='Model Assumptions'!H15 | H80: ='Model Assumptions'!I15 | I80: ='Model Assumptions'!J15 | J80: ='Model Assumptions'!K15 | K80: SS03
A81: Required finished steel production | B81: Mt | C81: ='Model Calibration'!D11 | D81: =D78+D79+D80 | E81: =E78+E79+E80 | F81: =F78+F79+F80 | G81: =G78+G79+G80 | H81: =H78+H79+H80 | I81: =I78+I79+I80 | J81: =J78+J79+J80 | K81: SS04
A82: Crude-to-finished steel ratio | B82: x | C82: ='Model Assumptions'!D$13 | D82: ='Model Assumptions'!E$13 | E82: ='Model Assumptions'!F$13 | F82: ='Model Assumptions'!G$13 | G82: ='Model Assumptions'!H$13 | H82: ='Model Assumptions'!I$13 | I82: ='Model Assumptions'!J$13 | J82: ='Model Assumptions'!K$13 | K82: SS05
A83: Required crude steel production (unconstrained) | B83: Mt | C83: =C81*C82 | D83: =D81*D82 | E83: =E81*E82 | F83: =F81*F82 | G83: =G81*G82 | H83: =H81*H82 | I83: =I81*I82 | J83: =J81*J82
A84: CAPACITY CEILING
A85: Crude steel capacity | B85: Mtpa | C85: ='Capacity Forecast'!C$96 | D85: ='Capacity Forecast'!D$96 | E85: ='Capacity Forecast'!E$96 | F85: ='Capacity Forecast'!F$96 | G85: ='Capacity Forecast'!G$96 | H85: ='Capacity Forecast'!H$96 | I85: ='Capacity Forecast'!I$96 | J85: ='Capacity Forecast'!J$96
A86: Maximum practical utilisation | B86: % | C86: ='Model Assumptions'!D$32 | D86: ='Model Assumptions'!E$32 | E86: ='Model Assumptions'!F$32 | F86: ='Model Assumptions'!G$32 | G86: ='Model Assumptions'!H$32 | H86: ='Model Assumptions'!I$32 | I86: ='Model Assumptions'!J$32 | J86: ='Model Assumptions'!K$32 | K86: SS06
A87: Maximum crude steel production | B87: Mt | C87: =C85*C86 | D87: =D85*D86 | E87: =E85*E86 | F87: =F85*F86 | G87: =G85*G86 | H87: =H85*H86 | I87: =I85*I86 | J87: =J85*J86 | K87: SS07
A88: Crude steel production | B88: Mt | C88: =MIN(C83,C87) | D88: =MIN(D83,D87) | E88: =MIN(E83,E87) | F88: =MIN(F83,F87) | G88: =MIN(G83,G87) | H88: =MIN(H83,H87) | I88: =MIN(I83,I87) | J88: =MIN(J83,J87)
A89: Capacity ceiling binding? | B89: flag | C89: =IF(C83>C87+0.001,"BINDING","no") | D89: =IF(D83>D87+0.001,"BINDING","no") | E89: =IF(E83>E87+0.001,"BINDING","no") | F89: =IF(F83>F87+0.001,"BINDING","no") | G89: =IF(G83>G87+0.001,"BINDING","no") | H89: =IF(H83>H87+0.001,"BINDING","no") | I89: =IF(I83>I87+0.001,"BINDING","no") | J89: =IF(J83>J87+0.001,"BINDING","no") | K89: SS08
A90: Finished steel production | B90: Mt | C90: =C88/C82 | D90: =D88/D82 | E90: =E88/E82 | F90: =F88/F82 | G90: =G88/G82 | H90: =H88/H82 | I90: =I88/I82 | J90: =J88/J82
A91: Shortfall met by additional imports | B91: Mt | C91: =MAX(0,C81-C90) | D91: =MAX(0,D81-D90) | E91: =MAX(0,E81-E90) | F91: =MAX(0,F81-F90) | G91: =MAX(0,G81-G90) | H91: =MAX(0,H81-H90) | I91: =MAX(0,I81-I90) | J91: =MAX(0,J81-J90) | K91: SS09
A93: The model does NOT endogenise supply response - it does not idle capacity when margins turn negative. This is why the stress case should be read as a lower bound on margin rather than a central expectation, and is a documented limitation on 25 Audit Checks.

Sheet Capacity Forecast
A1: CAPACITY FORECAST
A2: Industry Financial Model | Indian Steel Industry | Horizon FY2027E-FY2033E | Base year FY2026A
J3: Active Scenario | L3: ='Control Panel'!$E$17
A4: OBJECTIVE
A5: Forecast installed steelmaking capacity by incorporating brownfield expansions, greenfield projects, closures, and debottlenecking.
A7: Executive Summary
A8: KPI | B8: FY26A | C8: FY27E | D8: FY28E | E8: FY29E | F8: FY30E | G8: FY31E | H8: FY32E | I8: FY33E
A9: Installed Capacity (Mtpa) | B9: =C$96 | C9: =D$96 | D9: =E$96 | E9: =F$96 | F9: =G$96 | G9: =H$96 | H9: =I$96 | I9: =J$96
A10: Capacity Addition (Mt) | B10: =C$95 | C10: =D$95 | D10: =E$95 | E10: =F$95 | F10: =G$95 | G10: =H$95 | H10: =I$95 | I10: =J$95
A11: Capacity Growth (%) | B11: =B10/B9 | C11: =C10/C9 | D11: =D10/D9 | E11: =E10/E9 | F11: =F10/F9 | G11: =G10/G9 | H11: =H10/H9 | I11: =I10/I9
A12: Capacity Utilisation (%) | B12: ='Capacity Utilisation'!C$65 | C12: ='Capacity Utilisation'!D$65 | D12: ='Capacity Utilisation'!E$65 | E12: ='Capacity Utilisation'!F$65 | F12: ='Capacity Utilisation'!G$65 | G12: ='Capacity Utilisation'!H$65 | H12: ='Capacity Utilisation'!I$65 | I12: ='Capacity Utilisation'!J$65
A13: Spare Capacity (Mt) | B13: =C96-'Steel Supply Model'!C88 | C13: =D96-'Steel Supply Model'!D88 | D13: =E96-'Steel Supply Model'!E88 | E13: =F96-'Steel Supply Model'!F88 | F13: =G96-'Steel Supply Model'!G88 | G13: =H96-'Steel Supply Model'!H88 | H13: =I96-'Steel Supply Model'!I88 | I13: =J96-'Steel Supply Model'!J88
A14: Capacity Gap (Mt) | B14: =C96-'Steel Supply Model'!C83 | C14: =D96-'Steel Supply Model'!D83 | D14: =E96-'Steel Supply Model'!E83 | E14: =F96-'Steel Supply Model'!F83 | F14: =G96-'Steel Supply Model'!G83 | G14: =H96-'Steel Supply Model'!H83 | H14: =I96-'Steel Supply Model'!I83 | I14: =J96-'Steel Supply Model'!J83
A17: Company-wise Capacity
A18: Company | B18: FY26A | C18: FY27E | D18: FY28E | E18: FY29E | F18: FY30E | G18: FY31E | H18: FY32E | I18: FY33E
A19: Tata Steel | B19: ='[1]Production Capacity'!$H$13 | C19: =B19 | D19: =C19 | E19: =D19 | F19: =E19+F30 | G19: =F19 | H19: =G19 | I19: =H19+F31
A20: JSW Steel | B20: ='[1]Production Capacity'!$H$14 | C20: =B20+F32 | D20: =C20 | E20: =D20 | F20: =E20+F33 | G20: =F20+F34 | H20: =G20 | I20: =H20
A21: SAIL | B21: ='[1]Production Capacity'!$H$15 | C21: =B21 | D21: =C21 | E21: =D21+F37 | F21: =E21+F36 | G21: =F21+F35 | H21: =G21 | I21: =H21+F38
A22: Jindal Steel | B22: ='[1]Production Capacity'!$H$16 | C22: =B22 | D22: =C22 | E22: =D22 | F22: =E22 | G22: =F22 | H22: =G22 | I22: =H22
A23: Jindal Stainless | B23: ='[1]Production Capacity'!$H$17 | C23: =B23 | D23: =C23+F41 | E23: =D23 | F23: =E23 | G23: =F23 | H23: =G23 | I23: =H23
A24: Others | B24: ='[1]Production Capacity'!$H$18 | C24: =$D$96-SUM(C19:C23) | D24: =$E$96-SUM(D19:D23) | E24: =$F$96-SUM(E19:E23) | F24: =$G$96-SUM(F19:F23) | G24: =$H$96-SUM(G19:G23) | H24: =$I$96-SUM(H19:H23) | I24: =$J$96-SUM(I19:I23)
A25: India Total | B25: =SUM(B19:B24) | C25: =SUM(C19:C24) | D25: =SUM(D19:D24) | E25: =SUM(E19:E24) | F25: =SUM(F19:F24) | G25: =SUM(G19:G24) | H25: =SUM(H19:H24) | I25: =SUM(I19:I24)
A28: Capacity Expansion Pipeline
A29: Project | B29: Company | C29: Type | D29: Start | E29: Completion | F29: Capacity (Mt) | G29: Status
A30: NINL Expansion | B30: Tata Steel | C30: Brownfield Int | D30: FY2027 | E30: FY2030 | F30: 4.8 | G30: Approved
A31: India Roadmap to 40 Mtpa | B31: Tata Steel | C31: Programme | D31: FY2027 | E31: FY2033 | F31: 5 | G31: Announced (Aspirational)
A32: Vijayanagar BF-3 Expansion | B32: JSW Steel | C32: Brownfield BF | D32: FY2026 | E32: FY2027 | F32: 1.5 | G32: Under Testing & Commissioning
A33: Vijayanagar Brownfield Expansion | B33: JSW Steel | C33: Brownfield Int | D33: FY2027 | E33: FY2030 | F33: 5 | G33: Board Approved
A34: Greenfield Integrated Plant JV | B34: JSW/POSCO | C34: Greenfield JV | D34: FY2027 | E34: FY2031 | F34: 6 | G34: Announced
A35: IISCO Steel Plant Expansion | B35: SAIL | C35: Greenfield | D35: FY2028 | E35: FY2031 | F35: 4.08 | G35: Board Approved
A36: Bokaro Steel Plant Expansion | B36: SAIL | C36: Brownfield | D36: FY2027 | E36: FY2030 | F36: 2.65 | G36: Board Approved
A37: Durgapur Steel Plant Expansion | B37: SAIL | C37: Brownfield | D37: FY2027 | E37: FY2029 | F37: 0.89 | G37: Board Approved
A38: Residual Ambition to 35 Mt | B38: SAIL | C38: Programme | D38: FY2028 | E38: FY2033 | F38: 8 | G38: Announced (Aspirational)
A39: Hazira Expansion (9→15 Mtpa) | B39: AM/NS India | C39: Brownfield Int | D39: FY2026 | E39: FY2029 | F39: 6 | G39: Under Implementation
A40: Rajayyapeta Phase 1 | B40: AM/NS India | C40: Greenfield | D40: FY2027 | E40: FY2032 | F40: 8.2 | G40: Announced
A41: Jajpur HARP | B41: JSL | C41: Downstream | D41: FY2025 | E41: FY2028 | F41: 1.27 | G41: In Progress
A42: Bokaro Capacity Doubling | B42: Electrosteel | C42: Brownfield | D42: FY2026 | E42: FY2027 | F42: 1.5 | G42: Announced by Parent
A45: Capacity Bridge
A46: Item | B46: FY27E | C46: FY28E | D46: FY29E | E46: FY30E | F46: FY31E | G46: FY32E | H46: FY33E
A47: Opening Capacity | B47: =C96 | C47: =B53 | D47: =C53 | E47: =D53 | F47: =E53 | G47: =F53 | H47: =G53
A48: Brownfield Additions | B48: =(SUMIFS('Capacity Expansion Tracker'!$H$20:$H$39,'Capacity Expansion Tracker'!$F$20:$F$39,"*Brownfield*",'Capacity Expansion Tracker'!$K$20:$K$39, "FY2027"))*D92 | C48: =SUMIFS('Capacity Expansion Tracker'!$H$20:$H$39,'Capacity Expansion Tracker'!$F$20:$F$39,"*Brownfield*",'Capacity Expansion Tracker'!$K$20:$K$39, "FY2028")*E92 | D48: =SUMIFS('Capacity Expansion Tracker'!$H$20:$H$39,'Capacity Expansion Tracker'!$F$20:$F$39,"*Brownfield*",'Capacity Expansion Tracker'!$K$20:$K$39, "FY2029")*F92 | E48: =SUMIFS('Capacity Expansion Tracker'!$H$20:$H$39,'Capacity Expansion Tracker'!$F$20:$F$39,"*Brownfield*",'Capacity Expansion Tracker'!$K$20:$K$39, "FY2030")*G92 | F48: =SUMIFS('Capacity Expansion Tracker'!$H$20:$H$39,'Capacity Expansion Tracker'!$F$20:$F$39,"*Brownfield*",'Capacity Expansion Tracker'!$K$20:$K$39, "FY2031")*H92 | G48: =SUMIFS('Capacity Expansion Tracker'!$H$20:$H$39,'Capacity Expansion Tracker'!$F$20:$F$39,"*Brownfield*",'Capacity Expansion Tracker'!$K$20:$K$39, "FY2032")*I92 | H48: =SUMIFS('Capacity Expansion Tracker'!$H$20:$H$39,'Capacity Expansion Tracker'!$F$20:$F$39,"*Brownfield*",'Capacity Expansion Tracker'!$K$20:$K$39, "FY2033")*J92
A49: Greenfield Additions | B49: =(SUMIFS('Capacity Expansion Tracker'!$H$20:$H$39,'Capacity Expansion Tracker'!$F$20:$F$39,"*Greenfield*",'Capacity Expansion Tracker'!$K$20:$K$39, "FY2027"))*D92 | C49: =SUMIFS('Capacity Expansion Tracker'!$H$20:$H$39,'Capacity Expansion Tracker'!$F$20:$F$39,"*Greenfield*",'Capacity Expansion Tracker'!$K$20:$K$39, "FY2028")*E92 | D49: =SUMIFS('Capacity Expansion Tracker'!$H$20:$H$39,'Capacity Expansion Tracker'!$F$20:$F$39,"*Greenfield*",'Capacity Expansion Tracker'!$K$20:$K$39, "FY2029")*F92 | E49: =SUMIFS('Capacity Expansion Tracker'!$H$20:$H$39,'Capacity Expansion Tracker'!$F$20:$F$39,"*Greenfield*",'Capacity Expansion Tracker'!$K$20:$K$39, "FY2030")*G92 | F49: =SUMIFS('Capacity Expansion Tracker'!$H$20:$H$39,'Capacity Expansion Tracker'!$F$20:$F$39,"*Greenfield*",'Capacity Expansion Tracker'!$K$20:$K$39, "FY2031")*H92 | G49: =SUMIFS('Capacity Expansion Tracker'!$H$20:$H$39,'Capacity Expansion Tracker'!$F$20:$F$39,"*Greenfield*",'Capacity Expansion Tracker'!$K$20:$K$39, "FY2032")*I92 | H49: =SUMIFS('Capacity Expansion Tracker'!$H$20:$H$39,'Capacity Expansion Tracker'!$F$20:$F$39,"*Greenfield*",'Capacity Expansion Tracker'!$K$20:$K$39, "FY2033")*J92+SUMIFS('Capacity Expansion Tracker'!$H$20:$H$39,'Capacity Expansion Tracker'!$F$20:$F$39,"*Programme*",'Capacity Expansion Tracker'!$K$20:$K$39, "FY2033")*J92
A50: Debottlenecking | B50: =$D$94 | C50: =$E$94 | D50: =$F$94 | E50: =$G$94 | F50: =$H$94 | G50: =$I$94 | H50: =$J$94
A51: Permanent Closures | B51: 0 | C51: 0 | D51: 0 | E51: 0 | F51: 0 | G51: 0 | H51: 0
A52: Net Capacity Addition | B52: =B48+B49+B50-B51 | C52: =C48+C49+C50-C51 | D52: =D48+D49+D50-D51 | E52: =E48+E49+E50-E51 | F52: =F48+F49+F50-F51 | G52: =G48+G49+G50-G51 | H52: =H48+H49+H50-H51
A53: Closing Capacity | B53: =B47+B52 | C53: =C47+C52 | D53: =D47+D52 | E53: =E47+E52 | F53: =F47+F52 | G53: =G47+G52 | H53: =H47+H52
A56: Capacity vs Demand
A57: Year | B57: Capacity | C57: Demand | D57: Buffer | E57: Coverage
A58: FY27 | B58: =$D$96 | C58: ='Steel Demand Model'!E50 | D58: =B58-C58 | E58: =B58/C58
A59: FY28 | B59: =$E$96 | C59: ='Steel Demand Model'!E51 | D59: =B59-C59 | E59: =B59/C59
A60: FY29 | B60: =$F$96 | C60: ='Steel Demand Model'!E52 | D60: =B60-C60 | E60: =B60/C60
A61: FY30 | B61: =$G$96 | C61: ='Steel Demand Model'!E53 | D61: =B61-C61 | E61: =B61/C61
A62: FY31 | B62: =$H$96 | C62: ='Steel Demand Model'!E54 | D62: =B62-C62 | E62: =B62/C62
A63: FY32 | B63: =$I$96 | C63: ='Steel Demand Model'!E55 | D63: =B63-C63 | E63: =B63/C63
A64: FY33 | B64: =$J$96 | C64: ='Steel Demand Model'!E56 | D64: =B64-C64 | E64: =B64/C64
A67: Capacity Utilisation Outlook
A68: Year | B68: Capacity | C68: Production | D68: Utilisation
A69: FY27 | B69: =$D$96 | C69: ='Steel Supply Model'!C$9 | D69: =C69/B69
A70: FY28 | B70: =$E$96 | C70: ='Steel Supply Model'!D$9 | D70: =C70/B70
A71: FY29 | B71: =$F$96 | C71: ='Steel Supply Model'!E$9 | D71: =C71/B71
A72: FY30 | B72: =$G$96 | C72: ='Steel Supply Model'!F$9 | D72: =C72/B72
A73: FY31 | B73: =$H$96 | C73: ='Steel Supply Model'!G$9 | D73: =C73/B73
A74: FY32 | B74: =$I$96 | C74: ='Steel Supply Model'!H$9 | D74: =C74/B74
A75: FY33 | B75: =$J$96 | C75: ='Steel Supply Model'!I$9 | D75: =C75/B75
A78: Regional Capacity
A79: Region | B79: FY26A | C79: FY33E
A80: East | B80: 116.5 | C80: 188.5
A81: West | B81: 47 | C81: 78.5
A82: South | B82: 42 | C82: 63.5
A83: North | B83: 0 | C83: 2
A84: Central | B84: 14.9 | C84: 25.3
A85: Total | B85: =SUM(B80:B84) | C85: =SUM(C80:C84)
A88: Workbook
A89: Line item | B89: Unit | C89: FY2026A | D89: FY2027E | E89: FY2028E | F89: FY2029E | G89: FY2030E | H89: FY2031E | I89: FY2032E | J89: FY2033E
A90: Opening capacity | B90: Mtpa | D90: =C96 | E90: =D96 | F90: =E96 | G90: =F96 | H90: =G96 | I90: =H96 | J90: =I96
A91: Gross announced additions (from tracker) | B91: Mtpa | D91: ='Capacity Expansion Tracker'!E$89 | E91: ='Capacity Expansion Tracker'!F$89 | F91: ='Capacity Expansion Tracker'!G$89 | G91: ='Capacity Expansion Tracker'!H$89 | H91: ='Capacity Expansion Tracker'!I$89 | I91: ='Capacity Expansion Tracker'!J$89 | J91: ='Capacity Expansion Tracker'!K$89
A92: Pipeline delivery factor | B92: % | C92: ='Model Assumptions'!D$12 | D92: ='Model Assumptions'!E$12 | E92: ='Model Assumptions'!F$12 | F92: ='Model Assumptions'!G$12 | G92: ='Model Assumptions'!H$12 | H92: ='Model Assumptions'!I$12 | I92: ='Model Assumptions'!J$12 | J92: ='Model Assumptions'!K$12
A93: Announced additions delivered | B93: Mtpa | D93: =D91*D92 | E93: =E91*E92 | F93: =F91*F92 | G93: =G91*G92 | H93: =H91*H92 | I93: =I91*I92 | J93: =J91*J92
A94: Secondary and unattributed additions | B94: Mtpa | C94: ='Model Assumptions'!D$29 | D94: ='Model Assumptions'!E$29 | E94: ='Model Assumptions'!F$29 | F94: ='Model Assumptions'!G$29 | G94: ='Model Assumptions'!H$29 | H94: ='Model Assumptions'!I$29 | I94: ='Model Assumptions'!J$29 | J94: ='Model Assumptions'!K$29
A95: Total additions | B95: Mtpa | C95: =C93+C94 | D95: =D93+D94 | E95: =E93+E94 | F95: =F93+F94 | G95: =G93+G94 | H95: =H93+H94 | I95: =I93+I94 | J95: =J93+J94
A96: Closing crude steel capacity | B96: Mtpa | C96: ='Model Calibration'!D13 | D96: =C96+D95 | E96: =D96+E95 | F96: =E96+F95 | G96: =F96+G95 | H96: =G96+H95 | I96: =H96+I95 | J96: =I96+J95
A98: VALIDATION AGAINST NATIONAL STEEL POLICY 2017
A99: National Steel Policy 2017 target | B99: Mtpa | H99: 300
A100: Model capacity in FY2031E | B100: Mtpa | H100: =H96
A101: Model as % of policy target | B101: % | H101: =H100/H99
A103: Sign warning: more capacity is EBITDA-NEGATIVE in this model, because it depresses utilisation which feeds back into price via driver D23. See 09 Steel Price Forecast.

Sheet Capacity Expansion Tracker
A1: CAPACITY EXPANSION TRACKER
A2: Industry Financial Model | Indian Steel Industry | Horizon FY2027E-FY2033E | Base year FY2026A
H3: Active Scenario | I3: ='Control Panel'!$E$17
A4: OBJECTIVE
A5: The dated project pipeline that drives the capacity forecast. Twenty projects, each with its capacity, status, expected commissioning year and whether it counts towards INDIA's national crude steel capacity.
A7: Executive Summary
A8: KPI | B8: Value
A9: Total Active Projects | B9: =COUNTA($A$67:$A$86)
A10: Total Planned Capacity (Mtpa) | B10: =SUM($F$67:$F$86)
A11: Capacity Under Construction (Mtpa) | B11: =SUMIFS($F$67:$F$86,$H$67:$H$86,"Under*")
A12: Capacity Commissioned (Mtpa) | B12: =SUMIFS($F$67:$F$86,$H$67:$H$86,"Commissioned*")+SUMIFS($F$67:$F$86,$H$67:$H$86,"Completed*")
A13: Weighted Expected Capacity (Mtpa) | B13: =$D$91*'Model Assumptions'!$E$12
A14: Average Completion Probability | B14: ='Model Assumptions'!$E$12
A15: Average Project Size (Mtpa) | B15: =IFERROR(SUM($F$67:$F$86)/COUNT($F$67:$F$86),"")
A18: Master Project Resigter
A19: Project ID | B19: Company | C19: Plant | D19: State | E19: Route | F19: Project Type | G19: Existing Capacity | H19: Expansion Capacity | I19: Total Capacity | J19: Announcement | K19: COD | L19: Probability | M19: Status | N19: Capex (₹ Cr) | O19: Source
A20: P01 | B20: =$B$67 | C20: =$C$67 | D20: =$D$67 | E20: =IF(ISNUMBER(SEARCH("EAF",$E$67)),"EAF",IF(ISNUMBER(SEARCH("BF",$E$67)),"BF-BOF",IF(ISNUMBER(SEARCH("integrated",$E$67)),"BF-BOF (integrated)",IF(ISNUMBER(SEARCH("melt",$G$67)),"Stainless melt","Not specified")))) | F20: =$E$67 | H20: =$F$67 | K20: =$I$67 | L20: =IF($L67="Yes",'Model Assumptions'!$E$12,0) | M20: =$H$67 | N20: =$J$67 | O20: =$M$67
A21: P02 | B21: =$B$68 | C21: =$C$68 | D21: =$D$68 | E21: =IF(ISNUMBER(SEARCH("EAF",$E$68)),"EAF",IF(ISNUMBER(SEARCH("BF",$E$68)),"BF-BOF",IF(ISNUMBER(SEARCH("integrated",$E$68)),"BF-BOF (integrated)",IF(ISNUMBER(SEARCH("melt",$G$68)),"Stainless melt","Not specified")))) | F21: =$E$68 | H21: =$F$68 | K21: =$I$68 | L21: =IF($L68="Yes",'Model Assumptions'!$E$12,0) | M21: =$H$68 | N21: =$J$68 | O21: =$M$68
A22: P03 | B22: =$B$69 | C22: =$C$69 | D22: =$D$69 | E22: =IF(ISNUMBER(SEARCH("EAF",$E$69)),"EAF",IF(ISNUMBER(SEARCH("BF",$E$69)),"BF-BOF",IF(ISNUMBER(SEARCH("integrated",$E$69)),"BF-BOF (integrated)",IF(ISNUMBER(SEARCH("melt",$G$69)),"Stainless melt","Not specified")))) | F22: =$E$69 | H22: =$F$69 | K22: =$I$69 | L22: =IF($L69="Yes",'Model Assumptions'!$E$12,0) | M22: =$H$69 | N22: =$J$69 | O22: =$M$69
A23: P04 | B23: =$B$70 | C23: =$C$70 | D23: =$D$70 | E23: =IF(ISNUMBER(SEARCH("EAF",$E$70)),"EAF",IF(ISNUMBER(SEARCH("BF",$E$70)),"BF-BOF",IF(ISNUMBER(SEARCH("integrated",$E$70)),"BF-BOF (integrated)",IF(ISNUMBER(SEARCH("melt",$G$70)),"Stainless melt","Not specified")))) | F23: =$E$70 | H23: =$F$70 | K23: =$I$70 | L23: =IF($L70="Yes",'Model Assumptions'!$E$12,0) | M23: =$H$70 | N23: =$J$70 | O23: =$M$70
A24: P05 | B24: =$B$71 | C24: =$C$71 | D24: =$D$71 | E24: =IF(ISNUMBER(SEARCH("EAF",$E$71)),"EAF",IF(ISNUMBER(SEARCH("BF",$E$71)),"BF-BOF",IF(ISNUMBER(SEARCH("integrated",$E$71)),"BF-BOF (integrated)",IF(ISNUMBER(SEARCH("melt",$G$71)),"Stainless melt","Not specified")))) | F24: =$E$71 | H24: =$F$71 | K24: =$I$71 | L24: =IF($L71="Yes",'Model Assumptions'!$E$12,0) | M24: =$H$71 | N24: =$J$71 | O24: =$M$71
A25: P06 | B25: =$B$72 | C25: =$C$72 | D25: =$D$72 | E25: =IF(ISNUMBER(SEARCH("EAF",$E$72)),"EAF",IF(ISNUMBER(SEARCH("BF",$E$72)),"BF-BOF",IF(ISNUMBER(SEARCH("integrated",$E$72)),"BF-BOF (integrated)",IF(ISNUMBER(SEARCH("melt",$G$72)),"Stainless melt","Not specified")))) | F25: =$E$72 | H25: =$F$72 | K25: =$I$72 | L25: =IF($L72="Yes",'Model Assumptions'!$E$12,0) | M25: =$H$72 | N25: =$J$72 | O25: =$M$72
A26: P07 | B26: =$B$73 | C26: =$C$73 | D26: =$D$73 | E26: =IF(ISNUMBER(SEARCH("EAF",$E$73)),"EAF",IF(ISNUMBER(SEARCH("BF",$E$73)),"BF-BOF",IF(ISNUMBER(SEARCH("integrated",$E$73)),"BF-BOF (integrated)",IF(ISNUMBER(SEARCH("melt",$G$73)),"Stainless melt","Not specified")))) | F26: =$E$73 | H26: =$F$73 | K26: =$I$73 | L26: =IF($L73="Yes",'Model Assumptions'!$E$12,0) | M26: =$H$73 | N26: =$J$73 | O26: =$M$73
A27: P08 | B27: =$B$74 | C27: =$C$74 | D27: =$D$74 | E27: =IF(ISNUMBER(SEARCH("EAF",$E$74)),"EAF",IF(ISNUMBER(SEARCH("BF",$E$74)),"BF-BOF",IF(ISNUMBER(SEARCH("integrated",$E$74)),"BF-BOF (integrated)",IF(ISNUMBER(SEARCH("melt",$G$74)),"Stainless melt","Not specified")))) | F27: =$E$74 | H27: =$F$74 | K27: =$I$74 | L27: =IF($L74="Yes",'Model Assumptions'!$E$12,0) | M27: =$H$74 | N27: =$J$74 | O27: =$M$74
A28: P09 | B28: =$B$75 | C28: =$C$75 | D28: =$D$75 | E28: =IF(ISNUMBER(SEARCH("EAF",$E$75)),"EAF",IF(ISNUMBER(SEARCH("BF",$E$75)),"BF-BOF",IF(ISNUMBER(SEARCH("integrated",$E$75)),"BF-BOF (integrated)",IF(ISNUMBER(SEARCH("melt",$G$75)),"Stainless melt","Not specified")))) | F28: =$E$75 | H28: =$F$75 | K28: =$I$75 | L28: =IF($L75="Yes",'Model Assumptions'!$E$12,0) | M28: =$H$75 | N28: =$J$75 | O28: =$M$75
A29: P10 | B29: =$B$76 | C29: =$C$76 | D29: =$D$76 | E29: =IF(ISNUMBER(SEARCH("EAF",$E$76)),"EAF",IF(ISNUMBER(SEARCH("BF",$E$76)),"BF-BOF",IF(ISNUMBER(SEARCH("integrated",$E$76)),"BF-BOF (integrated)",IF(ISNUMBER(SEARCH("melt",$G$76)),"Stainless melt","Not specified")))) | F29: =$E$76 | H29: =$F$76 | K29: =$I$76 | L29: =IF($L76="Yes",'Model Assumptions'!$E$12,0) | M29: =$H$76 | N29: =$J$76 | O29: =$M$76
A30: P11 | B30: =$B$77 | C30: =$C$77 | D30: =$D$77 | E30: =IF(ISNUMBER(SEARCH("EAF",$E$77)),"EAF",IF(ISNUMBER(SEARCH("BF",$E$77)),"BF-BOF",IF(ISNUMBER(SEARCH("integrated",$E$77)),"BF-BOF (integrated)",IF(ISNUMBER(SEARCH("melt",$G$77)),"Stainless melt","Not specified")))) | F30: =$E$77 | H30: =$F$77 | K30: =$I$77 | L30: =IF($L77="Yes",'Model Assumptions'!$E$12,0) | M30: =$H$77 | N30: =$J$77 | O30: =$M$77
A31: P12 | B31: =$B$78 | C31: =$C$78 | D31: =$D$78 | E31: =IF(ISNUMBER(SEARCH("EAF",$E$78)),"EAF",IF(ISNUMBER(SEARCH("BF",$E$78)),"BF-BOF",IF(ISNUMBER(SEARCH("integrated",$E$78)),"BF-BOF (integrated)",IF(ISNUMBER(SEARCH("melt",$G$78)),"Stainless melt","Not specified")))) | F31: =$E$78 | H31: =$F$78 | K31: =$I$78 | L31: =IF($L78="Yes",'Model Assumptions'!$E$12,0) | M31: =$H$78 | N31: =$J$78 | O31: =$M$78
A32: P13 | B32: =$B$79 | C32: =$C$79 | D32: =$D$79 | E32: =IF(ISNUMBER(SEARCH("EAF",$E$79)),"EAF",IF(ISNUMBER(SEARCH("BF",$E$79)),"BF-BOF",IF(ISNUMBER(SEARCH("integrated",$E$79)),"BF-BOF (integrated)",IF(ISNUMBER(SEARCH("melt",$G$79)),"Stainless melt","Not specified")))) | F32: =$E$79 | H32: =$F$79 | K32: =$I$79 | L32: =IF($L79="Yes",'Model Assumptions'!$E$12,0) | M32: =$H$79 | N32: =$J$79 | O32: =$M$79
A33: P14 | B33: =$B$80 | C33: =$C$80 | D33: =$D$80 | E33: =IF(ISNUMBER(SEARCH("EAF",$E$80)),"EAF",IF(ISNUMBER(SEARCH("BF",$E$80)),"BF-BOF",IF(ISNUMBER(SEARCH("integrated",$E$80)),"BF-BOF (integrated)",IF(ISNUMBER(SEARCH("melt",$G$80)),"Stainless melt","Not specified")))) | F33: =$E$80 | H33: =$F$80 | K33: =$I$80 | L33: =IF($L80="Yes",'Model Assumptions'!$E$12,0) | M33: =$H$80 | N33: =$J$80 | O33: =$M$80
A34: P15 | B34: =$B$81 | C34: =$C$81 | D34: =$D$81 | E34: =IF(ISNUMBER(SEARCH("EAF",$E$81)),"EAF",IF(ISNUMBER(SEARCH("BF",$E$81)),"BF-BOF",IF(ISNUMBER(SEARCH("integrated",$E$81)),"BF-BOF (integrated)",IF(ISNUMBER(SEARCH("melt",$G$81)),"Stainless melt","Not specified")))) | F34: =$E$81 | H34: =$F$81 | K34: =$I$81 | L34: =IF($L81="Yes",'Model Assumptions'!$E$12,0) | M34: =$H$81 | N34: =$J$81 | O34: =$M$81
A35: P16 | B35: =$B$82 | C35: =$C$82 | D35: =$D$82 | E35: =IF(ISNUMBER(SEARCH("EAF",$E$82)),"EAF",IF(ISNUMBER(SEARCH("BF",$E$82)),"BF-BOF",IF(ISNUMBER(SEARCH("integrated",$E$82)),"BF-BOF (integrated)",IF(ISNUMBER(SEARCH("melt",$G$82)),"Stainless melt","Not specified")))) | F35: =$E$82 | H35: =$F$82 | K35: =$I$82 | L35: =IF($L82="Yes",'Model Assumptions'!$E$12,0) | M35: =$H$82 | N35: =$J$82 | O35: =$M$82
A36: P17 | B36: =$B$83 | C36: =$C$83 | D36: =$D$83 | E36: =IF(ISNUMBER(SEARCH("EAF",$E$83)),"EAF",IF(ISNUMBER(SEARCH("BF",$E$83)),"BF-BOF",IF(ISNUMBER(SEARCH("integrated",$E$83)),"BF-BOF (integrated)",IF(ISNUMBER(SEARCH("melt",$G$83)),"Stainless melt","Not specified")))) | F36: =$E$83 | H36: =$F$83 | K36: =$I$83 | L36: =IF($L83="Yes",'Model Assumptions'!$E$12,0) | M36: =$H$83 | N36: =$J$83 | O36: =$M$83
A37: P18 | B37: =$B$84 | C37: =$C$84 | D37: =$D$84 | E37: =IF(ISNUMBER(SEARCH("EAF",$E$84)),"EAF",IF(ISNUMBER(SEARCH("BF",$E$84)),"BF-BOF",IF(ISNUMBER(SEARCH("integrated",$E$84)),"BF-BOF (integrated)",IF(ISNUMBER(SEARCH("melt",$G$84)),"Stainless melt","Not specified")))) | F37: =$E$84 | H37: =$F$84 | K37: =$I$84 | L37: =IF($L84="Yes",'Model Assumptions'!$E$12,0) | M37: =$H$84 | N37: =$J$84 | O37: =$M$84
A38: P19 | B38: =$B$85 | C38: =$C$85 | D38: =$D$85 | E38: =IF(ISNUMBER(SEARCH("EAF",$E$85)),"EAF",IF(ISNUMBER(SEARCH("BF",$E$85)),"BF-BOF",IF(ISNUMBER(SEARCH("integrated",$E$85)),"BF-BOF (integrated)",IF(ISNUMBER(SEARCH("melt",$G$85)),"Stainless melt","Not specified")))) | F38: =$E$85 | H38: =$F$85 | K38: =$I$85 | L38: =IF($L85="Yes",'Model Assumptions'!$E$12,0) | M38: =$H$85 | N38: =$J$85 | O38: =$M$85
A39: P20 | B39: =$B$86 | C39: =$C$86 | D39: =$D$86 | E39: =IF(ISNUMBER(SEARCH("EAF",$E$86)),"EAF",IF(ISNUMBER(SEARCH("BF",$E$86)),"BF-BOF",IF(ISNUMBER(SEARCH("integrated",$E$86)),"BF-BOF (integrated)",IF(ISNUMBER(SEARCH("melt",$G$86)),"Stainless melt","Not specified")))) | F39: =$E$86 | H39: =$F$86 | K39: =$I$86 | L39: =IF($L86="Yes",'Model Assumptions'!$E$12,0) | M39: =$H$86 | N39: =$J$86 | O39: =$M$86
A42: Annual Capacity Addition
A43: Year | B43: Brownfield | C43: Greenfield | D43: Debottlenecking | E43: Restart | F43: Total
A44: FY27 | B44: =SUMIFS($F$67:$F$86,$E$67:$E$86,"*Brownfield*",$I$67:$I$86,"FY2027",$L$67:$L$86,"Yes") | C44: =SUMIFS($F$67:$F$86,$E$67:$E$86,"Greenfield*",$I$67:$I$86,"FY2027",$L$67:$L$86,"Yes")+SUMIFS($F$67:$F$86,$E$67:$E$86,"Programme",$I$67:$I$86,"FY2027",$L$67:$L$86,"Yes") | D44: =SUMIFS($F$67:$F$86,$E$67:$E$86,"Debottlenecking*",$I$67:$I$86,"FY2027",$L$67:$L$86,"Yes") | E44: =SUMIFS($F$67:$F$86,$E$67:$E$86,"Restart*",$I$67:$I$86,"FY2027",$L$67:$L$86,"Yes") | F44: =SUM(B44:E44)
A45: FY28 | B45: =SUMIFS($F$67:$F$86,$E$67:$E$86,"Brownfield*",$I$67:$I$86,"FY2028",$L$67:$L$86,"Yes") | C45: =SUMIFS($F$67:$F$86,$E$67:$E$86,"Greenfield*",$I$67:$I$86,"FY2028",$L$67:$L$86,"Yes")+SUMIFS($F$67:$F$86,$E$67:$E$86,"Programme",$I$67:$I$86,"FY2028",$L$67:$L$86,"Yes") | D45: =SUMIFS($F$67:$F$86,$E$67:$E$86,"Debottlenecking*",$I$67:$I$86,"FY2028",$L$67:$L$86,"Yes") | E45: =SUMIFS($F$67:$F$86,$E$67:$E$86,"Restart*",$I$67:$I$86,"FY2028",$L$67:$L$86,"Yes") | F45: =SUM(B45:E45)
A46: FY29 | B46: =SUMIFS($F$67:$F$86,$E$67:$E$86,"Brownfield*",$I$67:$I$86,"FY2029",$L$67:$L$86,"Yes") | C46: =SUMIFS($F$67:$F$86,$E$67:$E$86,"Greenfield*",$I$67:$I$86,"FY2029",$L$67:$L$86,"Yes")+SUMIFS($F$67:$F$86,$E$67:$E$86,"Programme",$I$67:$I$86,"FY2029",$L$67:$L$86,"Yes") | D46: =SUMIFS($F$67:$F$86,$E$67:$E$86,"Debottlenecking*",$I$67:$I$86,"FY2029",$L$67:$L$86,"Yes") | E46: =SUMIFS($F$67:$F$86,$E$67:$E$86,"Restart*",$I$67:$I$86,"FY2029",$L$67:$L$86,"Yes") | F46: =SUM(B46:E46)
A47: FY30 | B47: =SUMIFS($F$67:$F$86,$E$67:$E$86,"Brownfield*",$I$67:$I$86,"FY2030",$L$67:$L$86,"Yes") | C47: =SUMIFS($F$67:$F$86,$E$67:$E$86,"Greenfield*",$I$67:$I$86,"FY2030",$L$67:$L$86,"Yes")+SUMIFS($F$67:$F$86,$E$67:$E$86,"Programme",$I$67:$I$86,"FY2030",$L$67:$L$86,"Yes") | D47: =SUMIFS($F$67:$F$86,$E$67:$E$86,"Debottlenecking*",$I$67:$I$86,"FY2030",$L$67:$L$86,"Yes") | E47: =SUMIFS($F$67:$F$86,$E$67:$E$86,"Restart*",$I$67:$I$86,"FY2030",$L$67:$L$86,"Yes") | F47: =SUM(B47:E47)
A48: FY31 | B48: =SUMIFS($F$67:$F$86,$E$67:$E$86,"Brownfield*",$I$67:$I$86,"FY2031",$L$67:$L$86,"Yes") | C48: =SUMIFS($F$67:$F$86,$E$67:$E$86,"Greenfield*",$I$67:$I$86,"FY2031",$L$67:$L$86,"Yes")+SUMIFS($F$67:$F$86,$E$67:$E$86,"Programme",$I$67:$I$86,"FY2031",$L$67:$L$86,"Yes") | D48: =SUMIFS($F$67:$F$86,$E$67:$E$86,"Debottlenecking*",$I$67:$I$86,"FY2031",$L$67:$L$86,"Yes") | E48: =SUMIFS($F$67:$F$86,$E$67:$E$86,"Restart*",$I$67:$I$86,"FY2031",$L$67:$L$86,"Yes") | F48: =SUM(B48:E48)
A49: FY32 | B49: =SUMIFS($F$67:$F$86,$E$67:$E$86,"Brownfield*",$I$67:$I$86,"FY2032",$L$67:$L$86,"Yes") | C49: =SUMIFS($F$67:$F$86,$E$67:$E$86,"Greenfield*",$I$67:$I$86,"FY2032",$L$67:$L$86,"Yes")+SUMIFS($F$67:$F$86,$E$67:$E$86,"Programme",$I$67:$I$86,"FY2032",$L$67:$L$86,"Yes") | D49: =SUMIFS($F$67:$F$86,$E$67:$E$86,"Debottlenecking*",$I$67:$I$86,"FY2032",$L$67:$L$86,"Yes") | E49: =SUMIFS($F$67:$F$86,$E$67:$E$86,"Restart*",$I$67:$I$86,"FY2032",$L$67:$L$86,"Yes") | F49: =SUM(B49:E49)
A50: FY33 | B50: =SUMIFS($F$67:$F$86,$E$67:$E$86,"Brownfield*",$I$67:$I$86,"FY2033",$L$67:$L$86,"Yes") | C50: =SUMIFS($F$67:$F$86,$E$67:$E$86,"Greenfield*",$I$67:$I$86,"FY2033",$L$67:$L$86,"Yes")+SUMIFS($F$67:$F$86,$E$67:$E$86,"Programme",$I$67:$I$86,"FY2033",$L$67:$L$86,"Yes") | D50: =SUMIFS($F$67:$F$86,$E$67:$E$86,"Debottlenecking*",$I$67:$I$86,"FY2033",$L$67:$L$86,"Yes") | E50: =SUMIFS($F$67:$F$86,$E$67:$E$86,"Restart*",$I$67:$I$86,"FY2033",$L$67:$L$86,"Yes") | F50: =SUM(B50:E50)
A53: Probability Matrix
A54: Status | B54: Probability
A55: Commissioned | B55: 1
A56: Under Construction | B56: 0.95
A57: Financial Closure | B57: 0.85
A58: Approved | B58: 0.7
A59: Announced | B59: 0.5
A60: Proposed | B60: 0.25
A61: Suspended | B61: 0.1
A62: Cancelled | B62: 0
A65: Master Project Register
A66: Project ID | B66: Company | C66: Project / Asset | D66: State / Country | E66: Type | F66: Capacity Added (Mtpa) | G66: Capacity Definition | H66: Status At Cutoff | I66: Expected Commissioning FY | J66: Capex (Rs cr) | K66: Implied Capex (Rs/t) | L66: Included In Forecast? | M66: Source ID | N66: Confidence | O66: Notes
A67: P01 | B67: Tata Steel | C67: Ludhiana scrap-based EAF | D67: Punjab | E67: Brownfield EAF | F67: 0.75 | G67: Crude steel | H67: Commissioned Mar-2026 | I67: FY2026 | J67: 3200 | K67: =J67/F67*10000 | L67: No - already in base | M67: S08 | N67: High | O67: Commissioned in Mar-2026 and therefore already inside the FY2026 capacity base of 220.4 Mtpa. Designed for under 0.3 tCO2e per tonne of crude steel, which makes it 5-star green steel under the Taxonomy notified 23-Dec-2024.
A68: P02 | B68: Tata Steel | C68: NINL expansion | D68: Odisha | E68: Brownfield integrated | F68: 4.8 | G68: Crude steel | H68: Proposed | I68: FY2030 | L68: Yes | M68: S08 | N68: Medium | O68: Described as proposed in the FY2026 results release, so not yet Board-approved capex. Commissioning year is the modeller's estimate based on typical 4-year build.
A69: P03 | B69: Tata Steel | C69: India roadmap to 40 Mtpa | D69: India | E69: Programme | F69: 5 | G69: Crude steel | H69: Announced - aspirational | I69: FY2033 | L69: Yes | M69: S37 | N69: Low | O69: Tata Steel's Q1FY2027 presentation (31-Jul-2026) sets out an India roadmap to 40 Mtpa. The residual above identified projects is carried at low confidence and is materially reduced by the delivery factor D05.
A70: P04 | B70: JSW Steel | C70: Vijayanagar BF-3 expansion 3.0 to 4.5 Mtpa | D70: Karnataka | E70: Brownfield BF | F70: 1.5 | G70: Crude steel | H70: Under testing and commissioning | I70: FY2027 | L70: Yes | M70: S09 | N70: High | O70: Was under testing at FY2026 year-end and excluded from the FY2026 utilisation calculation, so it is genuinely incremental to the base.
A71: P05 | B71: JSW Steel | C71: JVML-Vijayanagar brownfield expansion | D71: Karnataka | E71: Brownfield integrated | F71: 5 | G71: Crude steel | H71: Board approved | I71: FY2030 | J71: 26000 | K71: =J71/F71*10000 | L71: Yes | M71: S09 | N71: High | O71: Board approved. Rs 26,000 cr for 5 Mtpa gives Rs 52,000 per tonne, the cleanest brownfield capex-intensity datapoint available and the primary calibration for D16.
A72: P06 | B72: JSW Steel | C72: BMM Ispat acquisition | D72: Karnataka | E72: Acquisition | F72: 0.9 | G72: Crude steel | H72: Board approved | I72: FY2027 | L72: No - acquisition, not new national capacity | M72: S09 | N72: High | O72: Acquisition of existing operating capacity, so it adds to JSW Steel's own capacity and volume but adds NOTHING to India's national capacity - those tonnes are already in the 220.4 Mtpa FY2026 base. Correctly excluded from the industry capacity build. This is a standard trap: summing company announcements without stripping out acquisitions double-counts national capacity. JSW's FY2027 guidance explicitly includes BMM Ispat production of 0.75 Mt and sales of 0.70 Mt, so it IS included in the company-level volume build on sheet 12.
A73: P07 | B73: JSW Steel / POSCO | C73: Greenfield integrated plant, 50:50 JV | D73: Odisha | E73: Greenfield JV | F73: 6 | G73: Crude steel | H73: Announced Apr-2026 | I73: FY2031 | L73: Yes | M73: S09 | N73: Medium | O73: 50:50 joint venture announced Apr-2026 targeting commissioning by 2031. This is the single most distant dated project in the pipeline and is the reason the announced pipeline terminates in FY2031, which in turn drives the horizon selection.
A74: P08 | B74: SAIL | C74: IISCO Steel Plant greenfield expansion | D74: West Bengal | E74: Greenfield | F74: 4.08 | G74: Crude steel | H74: Board approved | I74: FY2031 | L74: Yes | M74: S26 | N74: High | O74: Board approved per Ministry of Steel, Rajya Sabha USQ 3982 answered 27-Mar-2026. IISCO averaged 91.6% utilisation over FY2021-FY2025 on 2.5 Mtpa.
A75: P09 | B75: SAIL | C75: Bokaro Steel Plant brownfield expansion | D75: Jharkhand | E75: Brownfield | F75: 2.65 | G75: Crude steel | H75: Board approved | I75: FY2030 | L75: Yes | M75: S26 | N75: High | O75: Board approved per the same Parliamentary answer. Bokaro averaged 87.8% utilisation on 4.6 Mtpa, so there is headroom in the existing asset as well.
A76: P10 | B76: SAIL | C76: Durgapur Steel Plant brownfield expansion | D76: West Bengal | E76: Brownfield | F76: 0.89 | G76: Crude steel | H76: Board approved | I76: FY2029 | L76: Yes | M76: S26 | N76: High | O76: Board approved. Durgapur already averaged 101.6% utilisation on 2.2 Mtpa over FY2021-FY2025, i.e. it is running above nameplate and the expansion is debottlenecking.
A77: P11 | B77: SAIL | C77: Residual ambition to ~35 Mt by FY2031 | D77: India | E77: Programme | F77: 8 | G77: Crude steel | H77: Announced - aspirational | I77: FY2033 | L77: Yes | M77: S47 | N77: Low | O77: SAIL has publicly targeted roughly 35 Mt by FY2031 against 19.676 Mtpa today at an indicated roughly Rs 1 lakh crore outlay. Board-approved tranches total only 7.62 Mtpa, so about 8 Mtpa of the ambition is unapproved and is carried at low confidence.
A78: P12 | B78: AM/NS India | C78: Hazira expansion 9 to 15 Mtpa | D78: Gujarat | E78: Brownfield integrated | F78: 6 | G78: Crude steel | H78: Under implementation | I78: FY2029 | L78: Yes | M78: S13 | N78: High | O78: Under implementation. The largest single brownfield addition in the pipeline.
A79: P13 | B79: AM/NS India | C79: Rajayyapeta greenfield, Phase 1 | D79: Andhra Pradesh | E79: Greenfield | F79: 8.2 | G79: Crude steel | H79: Announced 23-Mar-2026 | I79: FY2032 | L79: Yes | M79: S14 | N79: Medium | O79: Announced 23-Mar-2026 as a low-cost, highly efficient coastal asset. Phase 1 of 8.2 Mtpa. Greenfield of this scale in India has historically taken 5 to 7 years.
A80: P14 | B80: AM/NS India | C80: Hazira further expansion to 24 Mtpa | D80: Gujarat | E80: Brownfield | F80: 9 | G80: Crude steel | H80: Detailed engineering under way | I80: Beyond FY2033 | L80: No - beyond horizon | M80: S13 | N80: Low | O80: Detailed engineering only. Falls outside the FY2033 horizon and is therefore excluded from the capacity build. Retained in the tracker for completeness and for terminal-value context.
A81: P15 | B81: Jindal Steel | C81: Angul expansion 6.0 to 12.0 Mtpa | D81: Odisha | E81: Brownfield integrated | F81: 6 | G81: Crude steel | H81: Completed in FY2026 | I81: FY2026 | L81: No - already in base | M81: S11 | N81: High | O81: Completed during FY2026, taking group steelmaking capacity from 9.6 to 15.6 Mtpa. Already inside the FY2026 capacity base. Ironmaking capacity is being raised by a further 6.6 Mtpa with elements still under construction.
A82: P16 | B82: Jindal Stainless | C82: Indonesia stainless melt shop | D82: Indonesia | E82: Greenfield | F82: 1.2 | G82: Stainless melt | H82: Commissioned in FY2026 | I82: FY2026 | L82: No - outside India and in base | M82: S12 | N82: High | O82: Commissioned ahead of schedule in FY2026, taking group melt capacity to 4.2 Mtpa. OUTSIDE INDIA, so excluded from the India capacity build.
A83: P17 | B83: Jindal Stainless | C83: Jajpur HRAP and CRAP downstream lines | D83: Odisha | E83: Downstream | F83: 1.27 | G83: Downstream processing | H83: Upcoming | I83: FY2028 | L83: No - downstream, not melt | M83: S12 | N83: High | O83: 1.1 Mtpa HRAP plus 0.17 Mtpa CRAP. DOWNSTREAM PROCESSING, not melt capacity, so it must not be added to crude steel capacity. Included in the tracker because it drives mix and realisation, not tonnage.
A84: P18 | B84: Jindal Stainless | C84: Hisar and Kharagpur cold rolling augmentation | D84: Haryana / West Bengal | E84: Downstream | G84: Downstream processing | H84: Announced - Rs 900 cr committed | I84: FY2028 | J84: 900 | L84: No - downstream, not melt | M84: S12 | N84: High | O84: Takes CRAP capacity to 2.67 Mtpa by FY2028. Downstream only.
A85: P19 | B85: Electrosteel / ESL | C85: Bokaro capacity doubling | D85: Jharkhand | E85: Brownfield | F85: 1.5 | G85: Crude steel | H85: Announced by parent | I85: FY2027 | L85: Yes | M85: S43 | N85: Low | O85: Vedanta targeting a doubling of Bokaro from 1.5 to 3.0 Mtpa by end-CY2026. Rests on a single secondary source and is carried at low confidence.
A86: P20 | B86: NMDC Steel | C86: Nagarnar ramp-up to nameplate | D86: Chhattisgarh | E86: Ramp-up | G86: Crude steel | H86: Ramping | I86: FY2028 | L86: No - utilisation, not capacity | M86: S01 | N86: High | O86: The 3 Mtpa plant produced 2.382 Mt in FY2026, up 61.9%. The remaining roughly 0.6 Mt is a UTILISATION gain within existing capacity, not new capacity, and is captured through the utilisation forecast rather than the capacity build. Included here because it is one of the two empirical ramp-rate observations underpinning the horizon choice.
A88: SUMMARY - GROSS ANNOUNCED INDIA CRUDE STEEL ADDITIONS BY YEAR (live SUMIFS)
A89: Included projects only | C89: Mtpa | E89: =SUMIFS($F$67:$F$86,$I$67:$I$86,"FY2027",$L$67:$L$86,"Yes") | F89: =SUMIFS($F$67:$F$86,$I$67:$I$86,"FY2028",$L$67:$L$86,"Yes") | G89: =SUMIFS($F$67:$F$86,$I$67:$I$86,"FY2029",$L$67:$L$86,"Yes") | H89: =SUMIFS($F$67:$F$86,$I$67:$I$86,"FY2030",$L$67:$L$86,"Yes") | I89: =SUMIFS($F$67:$F$86,$I$67:$I$86,"FY2031",$L$67:$L$86,"Yes") | J89: =SUMIFS($F$67:$F$86,$I$67:$I$86,"FY2032",$L$67:$L$86,"Yes") | K89: =SUMIFS($F$67:$F$86,$I$67:$I$86,"FY2033",$L$67:$L$86,"Yes") | O89: Live SUMIFS across the table above. Matches on the commissioning year AND on the inclusion flag being exactly 'Yes'.
A91: Total gross announced additions, FY2027E-FY2033E | C91: Mtpa | D91: =SUM(E89:K89) | O91: 53.62 Mtpa of individually announced projects. Note this averages only 7.7 Mtpa a year against India's ACTUAL 20.8 and 20.1 Mtpa additions in FY2025 and FY2026, which is precisely why driver D22 exists - see 06.

Sheet Capacity Utilisation
A1: CAPACITY UTILIZATION
A2: Industry Financial Model | Indian Steel Industry | Horizon FY2027E-FY2033E | Base year FY2026A
G3: Active Scenario | I3: ='Control Panel'!$E$17
A4: OBJECTIVE
A5: Forecast annual capacity utilisation for the Indian steel industry by comparing available production capacity with expected crude steel production.
A7: Executive Summary
A8: KPI | B8: FY26A | C8: FY27E | D8: FY28E | E8: FY29E | F8: FY30E | G8: FY31E | H8: FY32E | I8: FY33E
A9: Installed Capacity (Mtpa) | B9: =$C$64 | C9: =$D$64 | D9: =$E$64 | E9: =$F$64 | F9: =$G$64 | G9: =$H$64 | H9: =$I$64 | I9: =$J$64
A10: Crude Steel Production (Mt) | B10: =$C$63 | C10: =$D$63 | D10: =$E$63 | E10: =$F$63 | F10: =$G$63 | G10: =$H$63 | H10: =$I$63 | I10: =$J$63
A11: Capacity Utilisation (%) | B11: =$C$65 | C11: =$D$65 | D11: =$E$65 | E11: =$F$65 | F11: =$G$65 | G11: =$H$65 | H11: =$I$65 | I11: =$J$65
A12: Growth (%) | C12: =C11/B11-1 | D12: =D11/C11-1 | E12: =E11/D11-1 | F12: =F11/E11-1 | G12: =G11/F11-1 | H12: =H11/G11-1 | I12: =I11/H11-1
A13: Idle Capacity (Mt) | B13: =C64-C63 | C13: =D64-D63 | D13: =E64-E63 | E13: =F64-F63 | F13: =G64-G63 | G13: =H64-H63 | H13: =I64-I63 | I13: =J64-J63
A14: Spare Capacity (%) | B14: =IFERROR(1-C65,"") | C14: =IFERROR(1-D65,"") | D14: =IFERROR(1-E65,"") | E14: =IFERROR(1-F65,"") | F14: =IFERROR(1-G65,"") | G14: =IFERROR(1-H65,"") | H14: =IFERROR(1-I65,"") | I14: =IFERROR(1-J65,"")
A15: Capacity Tightness | B15: =IF(C65>0.9,"Capacity constrained",IF(C65>0.85,"Tight market",IF(C65>0.75,"Balanced market",IF(C65>0.65,"Weak market","Significant overcapacity")))) | C15: =IF(D65>0.9,"Capacity constrained",IF(D65>0.85,"Tight market",IF(D65>0.75,"Balanced market",IF(D65>0.65,"Weak market","Significant overcapacity")))) | D15: =IF(E65>0.9,"Capacity constrained",IF(E65>0.85,"Tight market",IF(E65>0.75,"Balanced market",IF(E65>0.65,"Weak market","Significant overcapacity")))) | E15: =IF(F65>0.9,"Capacity constrained",IF(F65>0.85,"Tight market",IF(F65>0.75,"Balanced market",IF(F65>0.65,"Weak market","Significant overcapacity")))) | F15: =IF(G65>0.9,"Capacity constrained",IF(G65>0.85,"Tight market",IF(G65>0.75,"Balanced market",IF(G65>0.65,"Weak market","Significant overcapacity")))) | G15: =IF(H65>0.9,"Capacity constrained",IF(H65>0.85,"Tight market",IF(H65>0.75,"Balanced market",IF(H65>0.65,"Weak market","Significant overcapacity")))) | H15: =IF(I65>0.9,"Capacity constrained",IF(I65>0.85,"Tight market",IF(I65>0.75,"Balanced market",IF(I65>0.65,"Weak market","Significant overcapacity")))) | I15: =IF(J65>0.9,"Capacity constrained",IF(J65>0.85,"Tight market",IF(J65>0.75,"Balanced market",IF(J65>0.65,"Weak market","Significant overcapacity"))))
A18: Industry Utilization | F18: Company Wise Utilization
A19: Year | B19: Installed Capacity | C19: Production | D19: Utilisation % | F19: Company | G19: Capacity | H19: Production | I19: Utilisation % | J19: Audit Code
A20: FY26A | B20: =$C$64 | C20: =$C$63 | D20: =IFERROR(C20/B20,"") | F20: Tata Steel | G20: ='Capacity Forecast'!B19 | H20: ='[1]Production Volume'!$H15 | I20: =IFERROR(H20/G20,"") | J20: CU01
A21: FY27E | B21: =$D$64 | C21: =$D$63 | D21: =IFERROR(C21/B21,"") | F21: JSW Steel | G21: ='Capacity Forecast'!B20 | H21: ='[1]Production Volume'!$H16 | I21: =IFERROR(H21/G21,"") | J21: CU02
A22: FY28E | B22: =$E$64 | C22: =$E$63 | D22: =IFERROR(C22/B22,"") | F22: SAIL | G22: ='Capacity Forecast'!B21 | H22: ='[1]Production Volume'!$H17 | I22: =IFERROR(H22/G22,"") | J22: CU03
A23: FY29E | B23: =$F$64 | C23: =$F$63 | D23: =IFERROR(C23/B23,"") | F23: Jindal Steel | G23: ='Capacity Forecast'!B22 | H23: ='[1]Production Volume'!$H18 | I23: =IFERROR(H23/G23,"") | J23: CU04
A24: FY30E | B24: =$G$64 | C24: =$G$63 | D24: =IFERROR(C24/B24,"") | F24: Jindal Stainless | G24: ='Capacity Forecast'!B23 | H24: ='[1]Production Volume'!$H19 | I24: =IFERROR(H24/G24,"") | J24: CU05
A25: FY31E | B25: =$H$64 | C25: =$H$63 | D25: =IFERROR(C25/B25,"") | F25: Others | G25: ='Capacity Forecast'!B24 | H25: ='[1]Production Volume'!$H20 | I25: =IFERROR(H25/G25,"") | J25: CU08
A26: FY32E | B26: =$I$64 | C26: =$I$63 | D26: =IFERROR(C26/B26,"") | F26: Industry Average | G26: =SUM(G20:G25) | H26: =SUM(H20:H25) | I26: =IFERROR(H26/G26,"") | J26: CU09
A27: FY33E | B27: =$J$64 | C27: =$J$63 | D27: =IFERROR(C27/B27,"")
A28: Industry Average | B28: =AVERAGE(B20:B27) | C28: =AVERAGE(C20:C27) | D28: =IFERROR(C28/B28,"")
A31: Company Wise Utilization Forecast
A32: Company | B32: FY26A | C32: FY27E | D32: FY28E | E32: FY29E | F32: FY30E | G32: FY31E | H32: FY32E | I32: FY33E | J32: Audit Code
A33: Tata Steel | B33: =I20 | C33: =B33 | D33: =C33+0.5% | E33: =D33+0.5% | F33: =E33 | G33: =F33+0.5% | H33: =G33+0.5% | I33: 0.9 | J33: CC10
A34: JSW Steel | B34: =I21 | C34: 0.905 | D34: 0.9 | E34: =D34 | F34: =E34 | G34: =F34 | H34: =G34 | I34: =H34 | J34: CC11
A35: SAIL | B35: =I22 | C35: 0.93 | D35: 0.91 | E35: 0.9 | F35: 0.89 | G35: 0.885 | H35: 0.88 | I35: 0.88 | J35: CC12
A36: Jindal Steel | B36: =I23 | C36: 0.68 | D36: 0.73 | E36: 0.78 | F36: 0.8 | G36: 0.82 | H36: 0.84 | I36: 0.85 | J36: CC13
A37: Jindal Stainless | B37: =I24 | C37: 0.87 | D37: 0.875 | E37: 0.88 | F37: 0.88 | G37: 0.885 | H37: 0.89 | I37: 0.89 | J37: CC14
A38: Others | B38: =I25 | C38: 0.715 | D38: 0.765 | E38: 0.78 | F38: 0.78 | G38: 0.795 | H38: 0.815 | I38: 0.825 | J38: CC15
A39: Industry Average | B39: =C65 | C39: =D65 | D39: =E65 | E39: =F65 | F39: =G65 | G39: =H65 | H39: =I65 | I39: =J65 | J39: CC16
A41: Utilization Bands | F41: Price Relationship
A42: Utilisation | B42: Interpretation | F42: Utilisation | G42: Expected Steel Price Impact
A43: <65% | B43: Significant Overcapacity | F43: Below 70% | G43: Strong Downward Pressure
A44: 65–75% | B44: Weak Market | F44: 70–80% | G44: Mild Downward Pressure
A45: 75–85% | B45: Balanced Market | F45: 80–85% | G45: Stable
A46: 85–90% | B46: Tight Market | F46: 85–90% | G46: Upward Pressure
A47: >90% | B47: Capacity Constrained | F47: Above 90% | G47: Strong Upward Pressure
A50: Scenario Comparision
A51: Year | B51: Base | C51: Bull | D51: Bear | E51: Stress
A52: FY27
A53: FY28
A54: FY29
A55: FY30
A56: FY31
A57: FY32
A58: FY33
A61: Workbook
A62: Line item | B62: Unit | C62: FY2026A | D62: FY2027E | E62: FY2028E | F62: FY2029E | G62: FY2030E | H62: FY2031E | I62: FY2032E | J62: FY2033E
A63: Crude steel production | B63: Mt | C63: ='Steel Supply Model'!C$88 | D63: ='Steel Supply Model'!D$88 | E63: ='Steel Supply Model'!E$88 | F63: ='Steel Supply Model'!F$88 | G63: ='Steel Supply Model'!G$88 | H63: ='Steel Supply Model'!H$88 | I63: ='Steel Supply Model'!I$88 | J63: ='Steel Supply Model'!J$88
A64: Crude steel capacity | B64: Mtpa | C64: ='Capacity Forecast'!C$96 | D64: ='Capacity Forecast'!D$96 | E64: ='Capacity Forecast'!E$96 | F64: ='Capacity Forecast'!F$96 | G64: ='Capacity Forecast'!G$96 | H64: ='Capacity Forecast'!H$96 | I64: ='Capacity Forecast'!I$96 | J64: ='Capacity Forecast'!J$96
A65: Capacity utilisation | B65: % | C65: =C63/C64 | D65: =D63/D64 | E65: =E63/E64 | F65: =F63/F64 | G65: =G63/G64 | H65: =H63/H64 | I65: =I63/I64 | J65: =J63/J64
A66: Normal utilisation | B66: % | C66: ='Model Assumptions'!D$31 | D66: ='Model Assumptions'!E$31 | E66: ='Model Assumptions'!F$31 | F66: ='Model Assumptions'!G$31 | G66: ='Model Assumptions'!H$31 | H66: ='Model Assumptions'!I$31 | I66: ='Model Assumptions'!J$31 | J66: ='Model Assumptions'!K$31
A67: Utilisation gap vs normal | B67: ppt | C67: =C65-C66 | D67: =D65-D66 | E67: =E65-E66 | F67: =F65-F66 | G67: =G65-G66 | H67: =H65-H66 | I67: =I65-I66 | J67: =J65-J66
A68: Spare capacity | B68: Mt | C68: =C64-C63 | D68: =D64-D63 | E68: =E64-E63 | F68: =F64-F63 | G68: =G64-G63 | H68: =H64-H63 | I68: =I64-I63 | J68: =J64-J63
A70: FY2026 utilisation of 76.4% against 80.4% in FY2024 is the single most important structural fact in the Indian steel investment case: capacity has been added faster than demand, which caps domestic pricing power and is why a safeguard duty was needed.

Sheet Steel Price Forecast
A1: STEEL PRICE FORECAST
A2: Industry Financial Model | Indian Steel Industry | Horizon FY2027E-FY2033E | Base year FY2026A
H3: Active Scenario | J3: ='Control Panel'!$E$17
A4: OBJECTIVE
A5: Forecast Indian domestic steel prices by integrating supply-demand fundamentals, capacity utilisation, raw material costs, international prices, trade dynamics, and macroeconomic conditions.
A7: Executive Summary
A8: KPIs | B8: FY26A | C8: FY27E | D8: FY28E | E8: FY29E | F8: FY30E | G8: FY31E | H8: FY32E | I8: FY33E | J8: Audit Code
A9: Domestic HRC Price (₹/t) | B9: =C74 | C9: =$B$9*D72/$C$72 | D9: =$B$9*E72/$C$72 | E9: =$B$9*F72/$C$72 | F9: =$B$9*G72/$C$72 | G9: =$B$9*H72/$C$72 | H9: =$B$9*I72/$C$72 | I9: =$B$9*J72/$C$72 | J9: SP01
A10: Steel Price Growth (%) | C10: =(D72-C72)/C72 | D10: =(E72-D72)/D72 | E10: =(F72-E72)/E72 | F10: =(G72-F72)/F72 | G10: =(H72-G72)/G72 | H10: =(I72-H72)/H72 | I10: =(J72-I72)/I72 | J10: SP02
A11: Blened Steel ASP | B11: =$C$72 | C11: =$D$72 | D11: =$E$72 | E11: =$F$72 | F11: =$G$72 | G11: =$H$72 | H11: =$I$72 | I11: =$J$72 | J11: SP03
A12: Price Index (FY26=100) | B12: =B11/B11*100 | C12: =C11/$B$11*100 | D12: =D11/$B$11*100 | E12: =E11/$B$11*100 | F12: =F11/$B$11*100 | G12: =G11/$B$11*100 | H12: =H11/$B$11*100 | I12: =I11/$B$11*100 | J12: SP04
A13: Real Price Growth (%) | C13: =IFERROR((1+C10)/(1+'Model Assumptions'!E$11)-1,"") | D13: =IFERROR((1+D10)/(1+'Model Assumptions'!F$11)-1,"") | E13: =IFERROR((1+E10)/(1+'Model Assumptions'!G$11)-1,"") | F13: =IFERROR((1+F10)/(1+'Model Assumptions'!H$11)-1,"") | G13: =IFERROR((1+G10)/(1+'Model Assumptions'!I$11)-1,"") | H13: =IFERROR((1+H10)/(1+'Model Assumptions'!J$11)-1,"") | I13: =IFERROR((1+I10)/(1+'Model Assumptions'!K$11)-1,"") | J13: SP05
A16: Steel Price Forecast by Product.
A17: Year | B17: FY26A | C17: FY27E | D17: FY28E | E17: FY29E | F17: FY30E | G17: FY31E | H17: FY32E | I17: FY33E | J17: Audit Code
A18: HRC | B18: =$B$9 | C18: =$B$18*D72/$C$72 | D18: =$B$18*E72/$C$72 | E18: =$B$18*F72/$C$72 | F18: =$B$18*G72/$C$72 | G18: =$B$18*H72/$C$72 | H18: =$B$18*I72/$C$72 | I18: =$B$18*J72/$C$72 | J18: SP06
A19: CRC | B19: ='[1]Steel Prices'!$H$7 | C19: =$B$19*C11/$B$11 | D19: =$B$19*D11/$B$11 | E19: =$B$19*E11/$B$11 | F19: =$B$19*F11/$B$11 | G19: =$B$19*G11/$B$11 | H19: =$B$19*H11/$B$11 | I19: =$B$19*I11/$B$11 | J19: SP07
A20: Rebar | B20: ='[1]Steel Prices'!$H$8 | C20: =$B$20*D72/$C$72 | D20: =$B$20*E72/$C$72 | E20: =$B$20*F72/$C$72 | F20: =$B$20*G72/$C$72 | G20: =$B$20*H72/$C$72 | H20: =$B$20*I72/$C$72 | I20: =$B$20*J72/$C$72 | J20: SP08
A21: Wire Rod | B21: ='[1]Steel Prices'!$H$9 | C21: =$B$21*C11/$B$11 | D21: =$B$21*D11/$B$11 | E21: =$B$21*E11/$B$11 | F21: =$B$21*F11/$B$11 | G21: =$B$21*G11/$B$11 | H21: =$B$21*H11/$B$11 | I21: =$B$21*I11/$B$11 | J21: SP09
A22: Plates | B22: ='[1]Steel Prices'!$H$10 | C22: =$B$22*C11/$B$11 | D22: =$B$22*D11/$B$11 | E22: =$B$22*E11/$B$11 | F22: =$B$22*F11/$B$11 | G22: =$B$22*G11/$B$11 | H22: =$B$22*H11/$B$11 | I22: =$B$22*I11/$B$11 | J22: SP10
A23: Billets | B23: ='[1]Steel Prices'!$H$11 | C23: =$B$23*D72/$C$72 | D23: =$B$23*E72/$C$72 | E23: =$B$23*F72/$C$72 | F23: =$B$23*G72/$C$72 | G23: =$B$23*H72/$C$72 | H23: =$B$23*I72/$C$72 | I23: =$B$23*J72/$C$72 | J23: SP11
A24: Avg Industry ASP | B24: =$C$72 | C24: =$D$72 | D24: =$E$72 | E24: =$F$72 | F24: =$G$72 | G24: =$H$72 | H24: =$I$72 | I24: =$J$72 | J24: SP12
A27: Selling Cost & Realisation Bridge (₹/t)
A28: Item | B28: FY26A | C28: FY27E | D28: FY28E | E28: FY29E | F28: FY30E | G28: FY31E | H28: FY32E | I28: FY33E | J28: Audit Code
A29: Iron Ore | B29: ='Raw Material Forecast'!C65 | C29: ='Raw Material Forecast'!D65 | D29: ='Raw Material Forecast'!E65 | E29: ='Raw Material Forecast'!F65 | F29: ='Raw Material Forecast'!G65 | G29: ='Raw Material Forecast'!H65 | H29: ='Raw Material Forecast'!I65 | I29: ='Raw Material Forecast'!J65 | J29: SP13
A30: Coking Coal | B30: ='Raw Material Forecast'!C66 | C30: ='Raw Material Forecast'!D66 | D30: ='Raw Material Forecast'!E66 | E30: ='Raw Material Forecast'!F66 | F30: ='Raw Material Forecast'!G66 | G30: ='Raw Material Forecast'!H66 | H30: ='Raw Material Forecast'!I66 | I30: ='Raw Material Forecast'!J66 | J30: SP14
A31: Fluxes | J31: SP15
A32: Power | J32: SP16
A33: Logistics | J33: SP17
A34: Conversion Cost | B34: =B31+B32+B33 | C34: =C31+C32+C33 | D34: =D31+D32+D33 | E34: =E31+E32+E33 | F34: =F31+F32+F33 | G34: =G31+G32+G33 | H34: =H31+H32+H33 | I34: =I31+I32+I33 | J34: SP18
A35: Cash Cost | B35: =B29+B30+B34 | C35: =C29+C30+C34 | D35: =D29+D30+D34 | E35: =E29+E30+E34 | F35: =F29+F30+F34 | G35: =G29+G30+G34 | H35: =H29+H30+H34 | I35: =I29+I30+I34 | J35: SP19
A36: Base Realisation | B36: =C66 | C36: =D66 | D36: =E66 | E36: =F66 | F36: =G66 | G36: =H66 | H36: =I66 | I36: =J66 | J36: SP20
A37: Utilisation Adjustment | B37: =B38-B36 | C37: =C38-C36 | D37: =D38-D36 | E37: =E38-E36 | F37: =F38-F36 | G37: =G38-G36 | H37: =H38-H36 | I37: =I38-I36 | J37: SP21
A38: Effective Realisation | B38: =C72 | C38: =D72 | D38: =E72 | E38: =F72 | F38: =G72 | G38: =H72 | H38: =I72 | I38: =J72 | J38: SP22
A39: EBITDA | B39: =B38-B35 | C39: =C38-C35 | D39: =D38-D35 | E39: =E38-E35 | F39: =F38-F35 | G39: =G38-G35 | H39: =H38-H35 | I39: =I38-I35 | J39: SP23
A40: EBITDA Margin | B40: =B39/B38 | C40: =C39/C38 | D40: =D39/D38 | E40: =E39/E38 | F40: =F39/F38 | G40: =G39/G38 | H40: =H39/H38 | I40: =I39/I38 | J40: SP24
A43: International Price Comparison
A44: Region | B44: FY26A | C44: FY27E | D44: FY28E | E44: FY29E | F44: Audit Code
A45: India | B45: =$B$9 | C45: =$B$9*D72/$C$72 | D45: =$B$9*E72/$C$72 | E45: =$B$9*F72/$C$72 | F45: SP25
A46: China | B46: 48580 | F46: SP26
A47: Japan | F47: SP27
A48: Europe | F48: SP28
A49: USA | F49: SP29
A52: Scenario Analysis
A53: Year | B53: Base | C53: Bull | D53: Bear | E53: Stress
A54: FY27
A55: FY28
A56: FY29
A57: FY30
A58: FY31
A59: FY32
A60: FY33
A63: Workbook
A64: Line item | B64: Unit | C64: FY2026A | D64: FY2027E | E64: FY2028E | F64: FY2029E | G64: FY2030E | H64: FY2031E | I64: FY2032E | J64: FY2033E | K64: Audit Code
A65: DRIVER REALISATION (before the utilisation feedback)
A66: Blended realisation - scenario driver | B66: Rs/t | C66: ='Model Assumptions'!D$16 | D66: ='Model Assumptions'!E$16 | E66: ='Model Assumptions'!F$16 | F66: ='Model Assumptions'!G$16 | G66: ='Model Assumptions'!H$16 | H66: ='Model Assumptions'!I$16 | I66: ='Model Assumptions'!J$16 | J66: ='Model Assumptions'!K$16 | K66: SP31
A67: UTILISATION FEEDBACK (lagged one year - no circular reference)
A68: Prior-year capacity utilisation | B68: % | C68: ='Capacity Utilisation'!C$65 | D68: ='Capacity Utilisation'!D$65 | E68: ='Capacity Utilisation'!E$65 | F68: ='Capacity Utilisation'!F$65 | G68: ='Capacity Utilisation'!G$65 | H68: ='Capacity Utilisation'!H$65 | I68: ='Capacity Utilisation'!I$65 | J68: ='Capacity Utilisation'!J$65 | K68: SP32
A69: Normal utilisation | B69: % | C69: ='Model Assumptions'!D$31 | D69: ='Model Assumptions'!E$31 | E69: ='Model Assumptions'!F$31 | F69: ='Model Assumptions'!G$31 | G69: ='Model Assumptions'!H$31 | H69: ='Model Assumptions'!I$31 | I69: ='Model Assumptions'!J$31 | J69: ='Model Assumptions'!K$31 | K69: SP33
A70: Price sensitivity to utilisation | B70: x | C70: ='Model Assumptions'!D$30 | D70: ='Model Assumptions'!E$30 | E70: ='Model Assumptions'!F$30 | F70: ='Model Assumptions'!G$30 | G70: ='Model Assumptions'!H$30 | H70: ='Model Assumptions'!I$30 | I70: ='Model Assumptions'!J$30 | J70: ='Model Assumptions'!K$30 | K70: SP34
A71: Price adjustment factor | B71: x | C71: 1 | D71: =1+D70*(D68-D69) | E71: =1+E70*(E68-E69) | F71: =1+F70*(F68-F69) | G71: =1+G70*(G68-G69) | H71: =1+H70*(H68-H69) | I71: =1+I70*(I68-I69) | J71: =1+J70*(J68-J69) | K71: SP35
A72: Blended realisation - effective | B72: Rs/t | C72: =C66*C71 | D72: =D66*D71 | E72: =E66*E71 | F72: =F66*F71 | G72: =G66*G71 | H72: =H66*H71 | I72: =I66*I71 | J72: =J66*J71 | K72: SP36
A73: REFERENCE PRICES AND POLICY
A74: Memo: domestic HRC, end-Mar-2026 (ICRA) | B74: Rs/t | C74: ='Model Calibration'!D31 | K74: SP37
A75: Memo: HRC 52-week range to Jun-2026 | B75: Rs/t | D75: Rs 45,700 - 59,600/t | K75: SP38
A76: Safeguard duty on flat products | B76: % | C76: 0.12 | D76: 0.115 | E76: 0.11 | F76: 0 | G76: 0 | H76: 0 | I76: 0 | J76: 0 | K76: SP39
A78: The duty covers FLAT products only, which is why the database records primary rebar rising 25% against HRC's 18% between the Dec-2025 quarter and Mar-2026.

Sheet Raw Material Forecast
A1: RAW MATERIAL FORECAST
A2: Industry Financial Model | Indian Steel Industry | Horizon FY2027E-FY2033E | Base year FY2026A
L3: Active Scenario | N3: ='Control Panel'!$E$17
A4: OBJECTIVE
A5: Forecast the cost and availability of key steelmaking raw materials and translate them into future production costs.
A7: Executive Summary
A8: KPI | B8: FY21 | C8: FY22 | D8: FY23 | E8: FY24 | F8: FY25 | G8: FY26A | H8: FY27E | I8: FY28E | J8: FY29E | K8: FY30E | L8: FY31E | M8: FY32E | N8: FY33E | O8: Audit Code
A9: Iron Ore (₹/t) | B9: ='[1]Raw Materials'!C$6*[1]Macroeconomic!C$8 | C9: ='[1]Raw Materials'!D$6*[1]Macroeconomic!D$8 | D9: ='[1]Raw Materials'!E$6*[1]Macroeconomic!E$8 | E9: ='[1]Raw Materials'!F$6*[1]Macroeconomic!F$8 | F9: ='[1]Raw Materials'!G$6*[1]Macroeconomic!G$8 | G9: ='[1]Raw Materials'!H$6*[1]Macroeconomic!H$8 | H9: =D65 | I9: =E65 | J9: =F65 | K9: =G65 | L9: =H65 | M9: =I65 | N9: =J65 | O9: RM01
A10: Premium HCC Coal (₹/t) | B10: ='[1]Raw Materials'!C$11*[1]Macroeconomic!C$8 | C10: ='[1]Raw Materials'!D$11*[1]Macroeconomic!D$8 | D10: ='[1]Raw Materials'!E$11*[1]Macroeconomic!E$8 | E10: ='[1]Raw Materials'!F$11*[1]Macroeconomic!F$8 | F10: ='[1]Raw Materials'!G$11*[1]Macroeconomic!G$8 | G10: ='[1]Raw Materials'!H$11*[1]Macroeconomic!H$8 | H10: =D66 | I10: =E66 | J10: =F66 | K10: =G66 | L10: =H66 | M10: =I66 | N10: =J66 | O10: RM02
A11: PCI Coal (₹/t) | B11: ='[1]Raw Materials'!C$12*[1]Macroeconomic!C$8 | C11: ='[1]Raw Materials'!D$12*[1]Macroeconomic!D$8 | D11: ='[1]Raw Materials'!E$12*[1]Macroeconomic!E$8 | E11: ='[1]Raw Materials'!F$12*[1]Macroeconomic!F$8 | F11: ='[1]Raw Materials'!G$12*[1]Macroeconomic!G$8 | G11: ='[1]Raw Materials'!H$12*[1]Macroeconomic!H$8 | H11: =H10*0.62 | I11: =I10*0.62 | J11: =J10*0.62 | K11: =K10*0.62 | L11: =L10*0.62 | M11: =M10*0.62 | N11: =N10*0.62 | O11: RM03
A12: Thermal Coal (₹/t) | B12: ='[1]Raw Materials'!C$13*[1]Macroeconomic!C$8 | C12: ='[1]Raw Materials'!D$13*[1]Macroeconomic!D$8 | D12: ='[1]Raw Materials'!E$13*[1]Macroeconomic!E$8 | E12: ='[1]Raw Materials'!F$13*[1]Macroeconomic!F$8 | F12: ='[1]Raw Materials'!G$13*[1]Macroeconomic!G$8 | G12: ='[1]Raw Materials'!H$13*[1]Macroeconomic!H$8 | H12: =G12*(1+'Model Assumptions'!E11) | I12: =H12*(1+'Model Assumptions'!F11) | J12: =I12*(1+'Model Assumptions'!G11) | K12: =J12*(1+'Model Assumptions'!H11) | L12: =K12*(1+'Model Assumptions'!I11) | M12: =L12*(1+'Model Assumptions'!J11) | N12: =M12*(1+'Model Assumptions'!K11) | O12: RM04
A13: Scrap (₹/t) | B13: ='[1]Raw Materials'!C$14*[1]Macroeconomic!C$8 | C13: ='[1]Raw Materials'!D$14*[1]Macroeconomic!D$8 | D13: ='[1]Raw Materials'!E$14*[1]Macroeconomic!E$8 | E13: ='[1]Raw Materials'!F$14*[1]Macroeconomic!F$8 | F13: ='[1]Raw Materials'!G$14*[1]Macroeconomic!G$8 | G13: ='[1]Raw Materials'!H$14*[1]Macroeconomic!H$8 | H13: =G13*(1+'Model Assumptions'!E11) | I13: =H13*(1+'Model Assumptions'!F11) | J13: =I13*(1+'Model Assumptions'!G11) | K13: =J13*(1+'Model Assumptions'!H11) | L13: =K13*(1+'Model Assumptions'!I11) | M13: =L13*(1+'Model Assumptions'!J11) | N13: =M13*(1+'Model Assumptions'!K11) | O13: RM05
A14: Limestone (₹/t) | B14: ='[1]Raw Materials'!C$18 | C14: ='[1]Raw Materials'!D$18 | D14: ='[1]Raw Materials'!E$18 | E14: ='[1]Raw Materials'!F$18 | F14: ='[1]Raw Materials'!G$18 | G14: ='[1]Raw Materials'!H$18 | H14: =G14*(1+'Model Assumptions'!E11) | I14: =H14*(1+'Model Assumptions'!F11) | J14: =I14*(1+'Model Assumptions'!G11) | K14: =J14*(1+'Model Assumptions'!H11) | L14: =K14*(1+'Model Assumptions'!I11) | M14: =L14*(1+'Model Assumptions'!J11) | N14: =M14*(1+'Model Assumptions'!K11) | O14: RM06
A15: Dolomite (₹/t) | B15: ='[1]Raw Materials'!C$19 | C15: ='[1]Raw Materials'!D$19 | D15: ='[1]Raw Materials'!E$19 | E15: ='[1]Raw Materials'!F$19 | F15: ='[1]Raw Materials'!G$19 | G15: ='[1]Raw Materials'!H$19 | H15: =G15*(1+'Model Assumptions'!E11) | I15: =H15*(1+'Model Assumptions'!F11) | J15: =I15*(1+'Model Assumptions'!G11) | K15: =J15*(1+'Model Assumptions'!H11) | L15: =K15*(1+'Model Assumptions'!I11) | M15: =L15*(1+'Model Assumptions'!J11) | N15: =M15*(1+'Model Assumptions'!K11) | O15: RM07
A16: Ferro Alloys (₹/t) | B16: ='[1]Raw Materials'!C$22 | C16: ='[1]Raw Materials'!D$22 | D16: ='[1]Raw Materials'!E$22 | E16: ='[1]Raw Materials'!F$22 | F16: ='[1]Raw Materials'!G$22 | G16: ='[1]Raw Materials'!H$22 | H16: =G16*(1+'Model Assumptions'!E11) | I16: =H16*(1+'Model Assumptions'!F11) | J16: =I16*(1+'Model Assumptions'!G11) | K16: =J16*(1+'Model Assumptions'!H11) | L16: =K16*(1+'Model Assumptions'!I11) | M16: =L16*(1+'Model Assumptions'!J11) | N16: =M16*(1+'Model Assumptions'!K11) | O16: RM08
A17: Raw Material Basket Cost (₹/t) | B17: 20450 | C17: 29410 | D17: 32157 | E17: 27460 | F17: 25101 | G17: ='Cost Curve'!C65*'Model Assumptions'!D$20 | H17: ='Cost Curve'!D65*'Model Assumptions'!E$20 | I17: ='Cost Curve'!E65*'Model Assumptions'!F$20 | J17: ='Cost Curve'!F65*'Model Assumptions'!G$20 | K17: ='Cost Curve'!G65*'Model Assumptions'!H$20 | L17: ='Cost Curve'!H65*'Model Assumptions'!I$20 | M17: ='Cost Curve'!I65*'Model Assumptions'!J$20 | N17: ='Cost Curve'!J65*'Model Assumptions'!K$20 | O17: RM09
A20: Cost Build Up
A21: Raw Material | B21: Consumption per tonne | C21: Forecast Price | D21: Cost per tonne | E21: Audit Code
A22: Iron Ore | B22: 1.55 | C22: =D65 | D22: =C22*B22 | E22: RM10
A23: Coking Coal | B23: 0.55 | C23: =D66 | D23: =C23*B23 | E23: RM11
A24: PCI Coal | B24: 0.06 | C24: =G11 | D24: =C24*B24 | E24: RM12
A25: Fluxes | B25: 0.25 | C25: 1880 | D25: =C25*B25 | E25: RM13
A26: Ferro Alloys | B26: 0.015 | C26: =G16 | D26: =C26*B26 | E26: RM14
A27: Electrodes | B27: 0.002 | C27: 370000 | D27: =C27*B27 | E27: RM15
A28: Power | B28: 0.55 | C28: 6500 | D28: =C28*B28 | E28: RM16
A29: Total Raw Material Cost | D29: =SUM(D22:D28) | E29: RM17
A32: Import Dependancy
A33: Material | B33: Domestic Supply | C33: Imported | D33: Countries | H33: Audit Code
A34: Iron Ore | B34: 0.98 | C34: =1-B34 | D34: NA | H34: RM18
A35: Coking Coal | B35: 0.12 | C35: =1-B35 | D35: Australia, USA, Russia, Canada, Mozambique, others | H35: RM19
A36: Scrap | B36: 0.75 | C36: =1-B36 | D36: UAE, USA, UK, West Africa, EU | H36: RM20
A37: Ferro Alloys | B37: 0.9 | C37: =1-B37 | H37: RM21
A40: Scenario Analysis
A41: Commodity | B41: Base | C41: Bull | D41: Bear | E41: Stress
A42: Iron Ore
A43: Premium HCC Coal
A44: Scrap
A45: Thermal Coal
A46: Ferro Alloys
A49: Sensitivity Analysis
A50: Variable | B50: Impact on Raw Material Cost | E50: Audit Code
A51: Iron Ore +10% | B51: Iron ore is 45% of the RM basket, which is 60% of cash cost → +10% iron ore = +4.5% × 0.60 × Rs 49,581/t = +Rs 1,338/t on cash cost (EBITDA –Rs 1,338/t; –Rs 23,810 cr at FY2033E volume) | E51: RM22
A52: HCC Coal +10% | B52: Coking coal = 45% RM basket × 60% cash cost → same magnitude → +Rs 1,338/t on cash cost (–Rs 23,810 cr) | E52: RM23
A53: Scrap +10% | B53: Zero impact. Scrap is not in the raw material basket. The model's RM basket = iron ore 45% + coking coal 45% + fluxes 10% (driver D14). Scrap sits in the DRI-EAF route which is not separately cost-modelled. This is a stated limitation — the sensitivity cell is Rs 0 and a deliberate zero, disclosed as a structural limitation. | E53: RM24
A54: USD/INR +5% | B54: Iron ore AND coking coal are dollar-priced. +5% INR depreciation raises both simultaneously. Impact = 0.90 × 60% of cash cost × 5% = +Rs 1,337/t (–Rs 23,794 cr). This is 90% of the basket — all except the 10% domestic fluxes. This is why USD/INR ranks as the 2nd largest driver in the tornado on Sensitivity Analysis (–Rs 74,785 cr for 10% move, ~23.7% of EBITDA). For 5% move that is approximately half: –Rs 37,392 cr. | E54: RM25 | G54: *
A55: Freight +10% | B55: Zero impact in isolation. Freight is inside the conversion cost block, which is indexed to CPI as a single line. A freight-specific shock is therefore not separable and would be understated. This cell is Rs 0 — a deliberate structural zero, same logic as scrap. The note in the register explains: if you want to stress freight specifically, adjust driver D12 (conversion cost inflation). | E55: RM26
A58: Workbook
A59: Line item | B59: Unit | C59: FY2026A | D59: FY2027E | E59: FY2028E | F59: FY2029E | G59: FY2030E | H59: FY2031E | I59: FY2032E | J59: FY2033E | K59: Audit Code
A60: DOLLAR PRICES
A61: Iron ore 62% Fe fines, CFR China | B61: US$/dmt | C61: ='Model Assumptions'!D$17 | D61: ='Model Assumptions'!E$17 | E61: ='Model Assumptions'!F$17 | F61: ='Model Assumptions'!G$17 | G61: ='Model Assumptions'!H$17 | H61: ='Model Assumptions'!I$17 | I61: ='Model Assumptions'!J$17 | J61: ='Model Assumptions'!K$17 | K61: RM27
A62: Premium HCC coking coal, FOB Australia | B62: US$/t | C62: ='Model Assumptions'!D$18 | D62: ='Model Assumptions'!E$18 | E62: ='Model Assumptions'!F$18 | F62: ='Model Assumptions'!G$18 | G62: ='Model Assumptions'!H$18 | H62: ='Model Assumptions'!I$18 | I62: ='Model Assumptions'!J$18 | J62: ='Model Assumptions'!K$18 | K62: RM28
A63: USD/INR | B63: Rs/US$ | C63: ='Macroeconomic Model'!B18 | D63: ='Macroeconomic Model'!C18 | E63: ='Macroeconomic Model'!D18 | F63: ='Macroeconomic Model'!E18 | G63: ='Macroeconomic Model'!F18 | H63: ='Macroeconomic Model'!G18 | I63: ='Macroeconomic Model'!H18 | J63: ='Macroeconomic Model'!I18 | K63: RM29
A64: RUPEE-CONVERTED PRICES
A65: Iron ore in rupees | B65: Rs/dmt | C65: =C63*C61 | D65: =D63*D61 | E65: =E63*E61 | F65: =F63*F61 | G65: =G63*G61 | H65: =H63*H61 | I65: =I63*I61 | J65: =J63*J61 | K65: RM30
A66: Coking coal in rupees | B66: Rs/t | C66: =C63*C62 | D66: =D63*D62 | E66: =E63*E62 | F66: =F63*F62 | G66: =G63*G62 | H66: =H63*H62 | I66: =I63*I62 | J66: =J63*J62 | K66: RM31
A67: COST INDICES
A68: Conversion cost inflation | B68: % | D68: ='Model Assumptions'!E$19 | E68: ='Model Assumptions'!F$19 | F68: ='Model Assumptions'!G$19 | G68: ='Model Assumptions'!H$19 | H68: ='Model Assumptions'!I$19 | I68: ='Model Assumptions'!J$19 | J68: ='Model Assumptions'!K$19 | K68: RM32
A69: Conversion cost index | B69: x | C69: 1 | D69: =C69*(1+D68) | E69: =D69*(1+E68) | F69: =E69*(1+F68) | G69: =F69*(1+G68) | H69: =G69*(1+H68) | I69: =H69*(1+I68) | J69: =I69*(1+J68) | K69: RM33
A70: Iron ore weight in basket | B70: % | C70: ='Model Assumptions'!D$21 | D70: ='Model Assumptions'!E$21 | E70: ='Model Assumptions'!F$21 | F70: ='Model Assumptions'!G$21 | G70: ='Model Assumptions'!H$21 | H70: ='Model Assumptions'!I$21 | I70: ='Model Assumptions'!J$21 | J70: ='Model Assumptions'!K$21 | K70: RM34
A71: Raw material cost index | B71: x | C71: 1 | D71: =D70*(D65/$C$65)+D70*(D66/$C$66)+(1-2*D70)*D69 | E71: =E70*(E65/$C$65)+E70*(E66/$C$66)+(1-2*E70)*E69 | F71: =F70*(F65/$C$65)+F70*(F66/$C$66)+(1-2*F70)*F69 | G71: =G70*(G65/$C$65)+G70*(G66/$C$66)+(1-2*G70)*G69 | H71: =H70*(H65/$C$65)+H70*(H66/$C$66)+(1-2*H70)*H69 | I71: =I70*(I65/$C$65)+I70*(I66/$C$66)+(1-2*I70)*I69 | J71: =J70*(J65/$C$65)+J70*(J66/$C$66)+(1-2*J70)*J69 | K71: RM35
A73: The Australian THERMAL coal series in the database (FY2026 average US$111.50/mt) is deliberately NOT used here. It is thermal, not metallurgical, coal - see database Conflict C15.

Sheet Cost Curve
A1: COST CURVE
A2: Industry Financial Model | Indian Steel Industry | Horizon FY2027E-FY2033E | Base year FY2026A
H3: Active Scenario | J3: ='Control Panel'!$E$17
A4: OBJECTIVE
A5: Estimate the cash cost of steel production across major Indian producers, rank them by cost competitiveness, and determine the industry cost curve and marginal producer.
A7: Executive Summary
A8: KPI | B8: FY26A | C8: FY27E | D8: FY28E | E8: FY29E | F8: FY30E | G8: FY31E | H8: FY32E | I8: FY33E | J8: Audit Code
A9: Average Cash Cost (₹/t) | B9: =C65 | C9: =D65 | D9: =E65 | E9: =F65 | F9: =G65 | G9: =H65 | H9: =I65 | I9: =J65 | J9: CC01
A10: Average Total Cost (₹/t) | B10: =C65+'Cash Flow Model'!C93/'Steel Supply Model'!C90*10 | C10: =D65+'Cash Flow Model'!D93/'Steel Supply Model'!D90*10 | D10: =E65+'Cash Flow Model'!E93/'Steel Supply Model'!E90*10 | E10: =F65+'Cash Flow Model'!F93/'Steel Supply Model'!F90*10 | F10: =G65+'Cash Flow Model'!G93/'Steel Supply Model'!G90*10 | G10: =H65+'Cash Flow Model'!H93/'Steel Supply Model'!H90*10 | H10: =I65+'Cash Flow Model'!I93/'Steel Supply Model'!I90*10 | I10: =J65+'Cash Flow Model'!J93/'Steel Supply Model'!J90*10 | J10: CC02
A11: Industry ASP (₹/t) | B11: ='Steel Price Forecast'!B24 | C11: ='Steel Price Forecast'!C24 | D11: ='Steel Price Forecast'!D24 | E11: ='Steel Price Forecast'!E24 | F11: ='Steel Price Forecast'!F24 | G11: ='Steel Price Forecast'!G24 | H11: ='Steel Price Forecast'!H24 | I11: ='Steel Price Forecast'!I24 | J11: CC03
A12: EBITDA/t (₹/t) | B12: ='EBITDA Model'!C101 | C12: ='EBITDA Model'!D101 | D12: ='EBITDA Model'!E101 | E12: ='EBITDA Model'!F101 | F12: ='EBITDA Model'!G101 | G12: ='EBITDA Model'!H101 | H12: ='EBITDA Model'!I101 | I12: ='EBITDA Model'!J101 | J12: CC04
A13: Marginal Producer Cost (₹/t) | B13: =MAX(C70:C74) | C13: =MAX(D70:D74) | D13: =MAX(E70:E74) | E13: =MAX(F70:F74) | F13: =MAX(G70:G74) | G13: =MAX(H70:H74) | H13: =MAX(I70:I74) | I13: =MAX(J70:J74) | J13: CC05
A14: Industry Spread (₹/t) | B14: =B11-B9 | C14: =C11-C9 | D14: =D11-D9 | E14: =E11-E9 | F14: =F11-F9 | G14: =G11-G9 | H14: =H11-H9 | I14: =I11-I9 | J14: CC06
A17: Company Cost Curve
A18: Rank | B18: Company | C18: Production (Mt) | D18: Cash Cost (₹/t) | E18: Total Cost (₹/t) | F18: EBITDA/t | G18: Cumulative Production (Mt) | H18: Audit Code
A19: 1 | B19: Tata Steel | C19: ='Revenue Forecast'!C100 | D19: =C70 | E19: =D19+('Cash Flow Model'!$C$93/'Steel Supply Model'!$C$90)*10 | F19: ='EBITDA Model'!C108 | G19: =C19 | H19: CC07
A20: 2 | B20: SAIL | C20: ='Revenue Forecast'!C102 | D20: =C72 | E20: =D20+('Cash Flow Model'!$C$93/'Steel Supply Model'!$C$90)*10 | F20: ='EBITDA Model'!C110 | G20: =G19+C20 | H20: CC08
A21: 3 | B21: JSW Steel | C21: ='Revenue Forecast'!C101 | D21: =C71 | E21: =D21+('Cash Flow Model'!$C$93/'Steel Supply Model'!$C$90)*10 | F21: ='EBITDA Model'!C109 | G21: =G20+C21 | H21: CC09
A22: 4 | B22: Jindal Steel | C22: ='Revenue Forecast'!C103 | D22: =C73 | E22: =D22+('Cash Flow Model'!$C$93/'Steel Supply Model'!$C$90)*10 | F22: ='EBITDA Model'!C111 | G22: =G21+C22 | H22: CC10
A23: 5 | B23: Jindal Stainless | C23: ='Revenue Forecast'!C104 | D23: =C74 | E23: =D23+('Cash Flow Model'!$C$93/'Steel Supply Model'!$C$90)*10 | F23: ='EBITDA Model'!C112 | G23: =G22+C23 | H23: CC11
A26: Cost Build Up
A27: Cost Component | B27: ₹/t | C27: % of Total Cost | D27: Audit Code
A28: Iron Ore | B28: =$B$38/$C$38*C28 | C28: 0.252 | D28: CC13
A29: Coking Coal | B29: =$B$38/$C$38*C29 | C29: 0.2065 | D29: CC14
A30: PCI Coal | B30: =$B$38/$C$38*C30 | C30: 0.038 | D30: CC15
A31: Scrap | B31: =$B$38/$C$38*C31 | C31: 0.028 | D31: CC16
A32: Fluxes | B32: =$B$38/$C$38*C32 | C32: 0.038 | D32: CC17
A33: Power & Fuel | B33: =$B$38/$C$38*C33 | C33: 0.075 | D33: CC18 | F33: =(B33*'Steel Supply Model'!$C$88/10)/'Revenue Forecast'!$B$11
A34: Labour | B34: =$B$38/$C$38*C34 | C34: 0.056 | D34: CC19 | F34: =(B34*'Steel Supply Model'!$C$88/10)/'Revenue Forecast'!$B$11
A35: Maintenance | B35: =$B$38/$C$38*C35 | C35: 0.056 | D35: CC20 | F35: =(B35*'Steel Supply Model'!$C$88/10)/'Revenue Forecast'!$B$11
A36: Logistics | B36: =$B$38/$C$38*C36 | C36: 0.075 | D36: CC21 | F36: =(B36*'Steel Supply Model'!$C$88/10)/'Revenue Forecast'!$B$11
A37: Other Manufacturing | B37: =$B$38/$C$38*C37 | C37: 0.115 | D37: CC22 | F37: =(B37*'Steel Supply Model'!$C$88/10)/'Revenue Forecast'!$B$11
A38: Cash Cost | B38: =C65 | C38: =SUM(C28:C37) | D38: CC23 | F38: =(B38*'Steel Supply Model'!$C$88/10)/'Revenue Forecast'!$B$11
A39: Depreciation | B39: ='Cash Flow Model'!C93/'Steel Supply Model'!C90*10 | C39: 0.06 | D39: CC24 | F39: =(B39*'Steel Supply Model'!$C$88/10)/'Revenue Forecast'!$B$11
A40: SG&A | B40: =B41*C40 | C40: 0.06 | D40: CC25 | F40: =(B40*'Steel Supply Model'!$C$88/10)/'Revenue Forecast'!$B$11
A41: Total Cost | B41: =B39+B38 | C41: =SUM(C28:C37,C39)
A44: Margin at Forecast Price
A45: Company | B45: Forecast ASP | C45: Cash Cost | D45: EBITDA/t | E45: EBITDA Margin | F45: Audit Code
A46: Tata Steel | B46: ='Steel Price Forecast'!C11*('EBITDA Model'!C108+'Cost Curve'!C70)/'Steel Price Forecast'!B11 | C46: =D70 | D46: ='EBITDA Model'!D108 | E46: =D46/B46 | F46: CC26
A47: JSW Steel | B47: ='Steel Price Forecast'!$C$11*('EBITDA Model'!C109+'Cost Curve'!C71)/'Steel Price Forecast'!B11 | C47: =D71 | D47: ='EBITDA Model'!D109 | E47: =D47/B47 | F47: CC27
A48: SAIL | B48: ='Steel Price Forecast'!$C$11*('EBITDA Model'!C110+'Cost Curve'!C72)/'Steel Price Forecast'!B11 | C48: =D72 | D48: ='EBITDA Model'!C110 | E48: =D48/B48 | F48: CC28
A49: Jindal Steel | B49: ='Steel Price Forecast'!$C$11*('EBITDA Model'!C111+'Cost Curve'!C73)/'Steel Price Forecast'!B11 | C49: =D73 | D49: ='EBITDA Model'!C111 | E49: =D49/B49 | F49: CC29
A52: Scenario Analysis
A53: Scenario | B53: Average Cost | C53: EBITDA/t | D53: Spread
A54: Base
A55: Bull
A56: Bear
A57: Stress
A60: Workbook
A61: Line item | B61: Unit | C61: FY2026A | D61: FY2027E | E61: FY2028E | F61: FY2029E | G61: FY2030E | H61: FY2031E | I61: FY2032E | J61: FY2033E | K61: Audit Code
A62: Raw material share of cash cost | B62: % | C62: ='Model Assumptions'!D$20 | D62: ='Model Assumptions'!E$20 | E62: ='Model Assumptions'!F$20 | F62: ='Model Assumptions'!G$20 | G62: ='Model Assumptions'!H$20 | H62: ='Model Assumptions'!I$20 | I62: ='Model Assumptions'!J$20 | J62: ='Model Assumptions'!K$20 | K62: CC30
A63: Raw material cost index | B63: x | C63: ='Raw Material Forecast'!C$71 | D63: ='Raw Material Forecast'!D$71 | E63: ='Raw Material Forecast'!E$71 | F63: ='Raw Material Forecast'!F$71 | G63: ='Raw Material Forecast'!G$71 | H63: ='Raw Material Forecast'!H$71 | I63: ='Raw Material Forecast'!I$71 | J63: ='Raw Material Forecast'!J$71 | K63: CC31
A64: Conversion cost index | B64: x | C64: ='Raw Material Forecast'!C$69 | D64: ='Raw Material Forecast'!D$69 | E64: ='Raw Material Forecast'!E$69 | F64: ='Raw Material Forecast'!F$69 | G64: ='Raw Material Forecast'!G$69 | H64: ='Raw Material Forecast'!H$69 | I64: ='Raw Material Forecast'!I$69 | J64: ='Raw Material Forecast'!J$69 | K64: CC32
A65: Industry cash cost per tonne | B65: Rs/t | C65: ='[1]Cash Cost'!$H$13 | D65: =$C$65*(D62*D63+(1-D62)*D64) | E65: =$C$65*(E62*E63+(1-E62)*E64) | F65: =$C$65*(F62*F63+(1-F62)*F64) | G65: =$C$65*(G62*G63+(1-G62)*G64) | H65: =$C$65*(H62*H63+(1-H62)*H64) | I65: =$C$65*(I62*I63+(1-I62)*I64) | J65: =$C$65*(J62*J63+(1-J62)*J64) | K65: CC33
A67: PRODUCER COST CURVE - FY2026A ACTUAL AND FORECAST
A68: Each producer's FY2026 implied cash cost is realisation less reported EBITDA/t. The forecast holds each producer's SPREAD to the industry constant, which assumes relative competitive position is stable - a strong assumption, stated explicitly.
A69: Line item | B69: Unit | C69: FY2026A | D69: FY2027E | E69: FY2028E | F69: FY2029E | G69: FY2030E | H69: FY2031E | I69: FY2032E | J69: FY2033E | K69: Audit Code
A70: Tata Steel - cash cost | B70: Rs/t | C70: ='[1]Cash Cost'!$H$17 | D70: =$C$70*((0.6*D63)+(0.4*D64)) | E70: =$C$70*((0.6*E63)+(0.4*E64)) | F70: =$C$70*((0.6*F63)+(0.4*F64)) | G70: =$C$70*((0.6*G63)+(0.4*G64)) | H70: =$C$70*((0.6*H63)+(0.4*H64)) | I70: =$C$70*((0.6*I63)+(0.4*I64)) | J70: =$C$70*((0.6*J63)+(0.4*J64)) | K70: CC34
A71: JSW Steel - cash cost | B71: Rs/t | C71: ='[1]Cash Cost'!$H$18 | D71: =$C$71*((0.6*D63)+(0.4*D64)) | E71: =$C$71*((0.6*E63)+(0.4*E64)) | F71: =$C$71*((0.6*F63)+(0.4*F64)) | G71: =$C$71*((0.6*G63)+(0.4*G64)) | H71: =$C$71*((0.6*H63)+(0.4*H64)) | I71: =$C$71*((0.6*I63)+(0.4*I64)) | J71: =$C$71*((0.6*J63)+(0.4*J64)) | K71: CC35
A72: SAIL - cash cost | B72: Rs/t | C72: ='[1]Cash Cost'!$H$19 | D72: =$C$72*((0.6*D63)+(0.4*D64)) | E72: =$C$72*((0.6*E63)+(0.4*E64)) | F72: =$C$72*((0.6*F63)+(0.4*F64)) | G72: =$C$72*((0.6*G63)+(0.4*G64)) | H72: =$C$72*((0.6*H63)+(0.4*H64)) | I72: =$C$72*((0.6*I63)+(0.4*I64)) | J72: =$C$72*((0.6*J63)+(0.4*J64)) | K72: CC36
A73: Jindal Steel - cash cost | B73: Rs/t | C73: ='[1]Cash Cost'!$H$20 | D73: =$C$73*((0.6*D63)+(0.4*D64)) | E73: =$C$73*((0.6*E63)+(0.4*E64)) | F73: =$C$73*((0.6*F63)+(0.4*F64)) | G73: =$C$73*((0.6*G63)+(0.4*G64)) | H73: =$C$73*((0.6*H63)+(0.4*H64)) | I73: =$C$73*((0.6*I63)+(0.4*I64)) | J73: =$C$73*((0.6*J63)+(0.4*J64)) | K73: CC37
A74: Jindal Stainless - cash cost (not comparable) | B74: Rs/t | C74: ='[1]Cash Cost'!$H21 | K74: CC38
A75: Others (India, residual) - cash cost | B75: Rs/t | C75: ='[1]Cash Cost'!$H22 | D75: =$C$75*((0.6*D63)+(0.4*D64)) | E75: =$C$75*((0.6*E63)+(0.4*E64)) | F75: =$C$75*((0.6*F63)+(0.4*F64)) | G75: =$C$75*((0.6*G63)+(0.4*G64)) | H75: =$C$75*((0.6*H63)+(0.4*H64)) | I75: =$C$75*((0.6*I63)+(0.4*I64)) | J75: =$C$75*((0.6*J63)+(0.4*J64)) | K75: CC39
A76: TOTAL (Industry) - cash cost | B76: Rs/t | C76: ='[1]Cash Cost'!$H23 | D76: =$C$76*((0.6*D63)+(0.4*D64)) | E76: =$C$76*((0.6*E63)+(0.4*E64)) | F76: =$C$76*((0.6*F63)+(0.4*F64)) | G76: =$C$76*((0.6*G63)+(0.4*G64)) | H76: =$C$76*((0.6*H63)+(0.4*H64)) | I76: =$C$76*((0.6*I63)+(0.4*I64)) | J76: =$C$76*((0.6*J63)+(0.4*J64)) | K76: CC40
A78: Cost-curve position is the primary determinant of who survives a downturn. On FY2026 actuals Tata Steel India sits roughly Rs 2,180/t BELOW the industry weighted cash cost and Jindal Steel roughly Rs 1,600/t above it - a Rs 3,780/t spread between best and worst of the four, equal to about 35% of industry EBITDA per tonne.

Sheet Revenue Forecast
A1: REVENUE FORECAST
A2: Industry Financial Model | Indian Steel Industry | Horizon FY2027E-FY2033E | Base year FY2026A
N3: Active Scenario | P3: ='Control Panel'!$E$17
A4: OBJECTIVE
A5: Forecast the Indian steel industry's revenue by combining production volumes, product mix, and realized selling prices.
A7: Executive Summary
A8: KPI | B8: FY26A | C8: FY27E | D8: FY28E | E8: FY29E | F8: FY30E | G8: FY31E | H8: FY32E | I8: FY33E | J8: Audit Code
A9: Sales Volume (Mt) | B9: =$C$93 | C9: =$D$93 | D9: =$E$93 | E9: =$F$93 | F9: =$G$93 | G9: =$H$93 | H9: =$I$93 | I9: =$J$93 | J9: RF01
A10: Average Selling Price (₹/t) | B10: =$C$94 | C10: =$D$94 | D10: =$E$94 | E10: =$F$94 | F10: =$G$94 | G10: =$H$94 | H10: =$I$94 | I10: =$J$94 | J10: RF02
A11: Revenue (₹ Cr) | B11: =$C$95 | C11: =$D$95 | D11: =$E$95 | E11: =$F$95 | F11: =$G$95 | G11: =$H$95 | H11: =$I$95 | I11: =$J$95 | J11: RF03
A12: Revenue Growth (%) | C12: =(C11-B11)/B11 | D12: =(D11-C11)/C11 | E12: =(E11-D11)/D11 | F12: =(F11-E11)/E11 | G12: =(G11-F11)/F11 | H12: =(H11-G11)/G11 | I12: =(I11-H11)/H11 | J12: RF04
A13: Revenue CAGR | B13: =$K$95 | C13: =IFERROR((D95/$C$95)^(1/1)-1,"") | D13: =IFERROR((E95/$C$95)^(1/2)-1,"") | E13: =IFERROR((F95/$C$95)^(1/3)-1,"") | F13: =IFERROR((G95/$C$95)^(1/4)-1,"") | G13: =IFERROR((H95/$C$95)^(1/5)-1,"") | H13: =IFERROR((I95/$C$95)^(1/6)-1,"") | I13: =IFERROR((J95/$C$95)^(1/7)-1,"") | J13: RF05
A16: Revenue Build Up
A17: KPI / Year | B17: FY26A | C17: FY27E | D17: FY28E | E17: FY29E | F17: FY30E | G17: FY31E | H17: FY32E | I17: FY33E | J17: Audit Code
A18: Sales Volume (Mt) | B18: =C$93 | C18: =D$93 | D18: =E$93 | E18: =F$93 | F18: =G$93 | G18: =H$93 | H18: =I$93 | I18: =J$93 | J18: RF06
A19: ASP (₹/t) | B19: =C$94 | C19: =D$94 | D19: =E$94 | E19: =F$94 | F19: =G$94 | G19: =H$94 | H19: =I$94 | I19: =J$94 | J19: RF07
A20: Gross Revenue (₹ Cr) | B20: =B19*B18/10 | C20: =C19*C18/10 | D20: =D19*D18/10 | E20: =E19*E18/10 | F20: =F19*F18/10 | G20: =G19*G18/10 | H20: =H19*H18/10 | I20: =I19*I18/10 | J20: RF08
A21: Discounts | B21: 0 | C21: 0 | D21: 0 | E21: 0 | F21: 0 | G21: 0 | H21: 0 | I21: 0 | J21: RF09
A22: Net Revenue (₹ Cr) | B22: =B20-B21 | C22: =C20-C21 | D22: =D20-D21 | E22: =E20-E21 | F22: =F20-F21 | G22: =G20-G21 | H22: =H20-H21 | I22: =I20-I21 | J22: RF10
A25: Revenue Bridge
A26: Driver | B26: FY27E | C26: FY28E | D26: FY29E | E26: FY30E | F26: FY31E | G26: FY32E | H26: FY33E | I26: Audit Code
A27: Previous Revenue | B27: =B20 | C27: =C20 | D27: =D20 | E27: =E20 | F27: =F20 | G27: =G20 | H27: =H20 | I27: RF11
A28: Volume Effect | B28: =(D93-C93)*C94/10 | C28: =(E93-D93)*D94/10 | D28: =(F93-E93)*E94/10 | E28: =(G93-F93)*F94/10 | F28: =(H93-G93)*G94/10 | G28: =(I93-H93)*H94/10 | H28: =(J93-I93)*I94/10 | I28: RF12
A29: Price Effect | B29: =D93*(D94-C94)/10 | C29: =E93*(E94-D94)/10 | D29: =F93*(F94-E94)/10 | E29: =G93*(G94-F94)/10 | F29: =H93*(H94-G94)/10 | G29: =I93*(I94-H94)/10 | H29: =J93*(J94-I94)/10 | I29: RF13
A30: Product Mix Effect | B30: 0 | C30: 0 | D30: 0 | E30: 0 | F30: 0 | G30: 0 | H30: 0 | I30: RF14
A31: Export Mix Effect | B31: 0 | C31: 0 | D31: 0 | E31: 0 | F31: 0 | G31: 0 | H31: 0 | I31: RF15
A32: Currency Effect | B32: 0 | C32: 0 | D32: 0 | E32: 0 | F32: 0 | G32: 0 | H32: 0 | I32: RF16
A33: Net Revenue | B33: =SUM(B27:B32) | C33: =SUM(C27:C32) | D33: =SUM(D27:D32) | E33: =SUM(E27:E32) | F33: =SUM(F27:F32) | G33: =SUM(G27:G32) | H33: =SUM(H27:H32) | I33: RF17
A36: Product Wise Revenue
A37: Product | B37: Volume (Mt) | C37: ASP (₹/t) | D37: Revenue (₹ Cr) | E37: % Share
A38: HRC
A39: CRC
A40: Rebar
A41: Wire Rod
A42: Plates
A43: Structural Steel
A44: Stainless Steel
A45: Others
A46: Total
A49: Domestic vs Export Revenue
A50: Year | B50: Domestic | C50: Export | D50: Total | E50: Export % | F50: Audit Code
A51: FY26A | B51: =D51-C51 | C51: ='Trade Model'!C71*C94/10 | D51: =C95 | E51: =IFERROR(C51/D51,"") | F51: RM18
A52: FY27E | B52: =D52-C52 | C52: ='Trade Model'!D71*D94/10 | D52: =D95 | E52: =IFERROR(C52/D52,"") | F52: RM19
A53: FY28E | B53: =D53-C53 | C53: ='Trade Model'!E71*E94/10 | D53: =E95 | E53: =IFERROR(C53/D53,"") | F53: RM20
A54: FY29E | B54: =D54-C54 | C54: ='Trade Model'!F71*F94/10 | D54: =F95 | E54: =IFERROR(C54/D54,"") | F54: RM21
A55: FY30E | B55: =D55-C55 | C55: ='Trade Model'!G$71*G$94/10 | D55: =G95 | E55: =IFERROR(C55/D55,"") | F55: RM22
A56: FY31E | B56: =D56-C56 | C56: ='Trade Model'!H$71*H$94/10 | D56: =H95 | E56: =IFERROR(C56/D56,"") | F56: RM23
A57: FY32E | B57: =D57-C57 | C57: ='Trade Model'!I$71*I$94/10 | D57: =I95 | E57: =IFERROR(C57/D57,"") | F57: RM24
A58: FY33E | B58: =D58-C58 | C58: ='Trade Model'!J$71*J$94/10 | D58: =J95 | E58: =IFERROR(C58/D58,"") | F58: RM25
A61: Company Revenue Benchmark
A62: Company | B62: Revenue | C62: Volume | D62: ASP | E62: Audit Code
A63: Tata Steel | B63: =C110 | C63: =C100 | D63: =B63/C63*10 | E63: RF26
A64: JSW Steel | B64: =C111 | C64: =C101 | D64: =B64/C64*10 | E64: RF27
A65: SAIL | B65: =C112 | C65: =C102 | D65: =B65/C65*10 | E65: RF28
A66: Jindal Steel | B66: =C113 | C66: =C103 | D66: =B66/C66*10 | E66: RF29
A67: Others | B67: =C95-SUM(B64:B66,B63) | C67: =C93-SUM(C63:C66) | D67: =B67/C67*10 | E67: RF30
A70: Revenue Drivers
A71: Driver | B71: Contribution
A72: Volume Growth | B72: =IFERROR(SUM($B$28:$H$28)/($J$95-$C$95),"")
A73: Price Growth | B73: =IFERROR(SUM($B$29:$H$29)/($J$95-$C$95),"")
A74: Product Mix | B74: =IFERROR(SUM($B$30:$H$30)/($J$95-$C$95),"")
A75: Export Mix | B75: =IFERROR(SUM($B$31:$H$31)/($J$95-$C$95),"")
A76: Currency | B76: =IFERROR(SUM($B$32:$H$32)/($J$95-$C$95),"")
A77: Others | B77: =1-SUM(B72:B76)
A80: Scenario Analysis
A81: Year | B81: Base | C81: Bull | D81: Bear | E81: Stress
A82: FY27
A83: FY28
A84: FY29
A85: FY30
A86: FY31
A87: FY32
A88: FY33
A92: Line item | B92: Unit | C92: FY2026A | D92: FY2027E | E92: FY2028E | F92: FY2029E | G92: FY2030E | H92: FY2031E | I92: FY2032E | J92: FY2033E | K92: CAGR | L92: Audit Code
A93: Finished steel production | B93: Mt | C93: ='Steel Supply Model'!C90 | D93: ='Steel Supply Model'!D$90 | E93: ='Steel Supply Model'!E$90 | F93: ='Steel Supply Model'!F$90 | G93: ='Steel Supply Model'!G$90 | H93: ='Steel Supply Model'!H$90 | I93: ='Steel Supply Model'!I$90 | J93: ='Steel Supply Model'!J$90 | K93: =IFERROR(IF(AND(ISNUMBER(C93),ISNUMBER(J93),C93>0),(J93/C93)^(1/7)-1,""),"") | L93: RF31
A94: Blended realisation - effective | B94: Rs/t | C94: ='Steel Price Forecast'!C72 | D94: ='Steel Price Forecast'!D$72 | E94: ='Steel Price Forecast'!E$72 | F94: ='Steel Price Forecast'!F$72 | G94: ='Steel Price Forecast'!G$72 | H94: ='Steel Price Forecast'!H$72 | I94: ='Steel Price Forecast'!I$72 | J94: ='Steel Price Forecast'!J$72 | K94: =IFERROR(IF(AND(ISNUMBER(C94),ISNUMBER(J94),C94>0),(J94/C94)^(1/7)-1,""),"") | L94: RF32
A95: INDUSTRY REVENUE | B95: Rs cr | C95: =C94*C93/10 | D95: =D94*D93/10 | E95: =E94*E93/10 | F95: =F94*F93/10 | G95: =G94*G93/10 | H95: =H94*H93/10 | I95: =I94*I93/10 | J95: =J94*J93/10 | K95: =IFERROR(IF(AND(ISNUMBER(C95),ISNUMBER(J95),C95>0),(J95/C95)^(1/7)-1,""),"") | L95: RF33
A98: COMPANY VOLUME BUILD
A99: Line item | B99: Unit | C99: FY2026A | D99: FY2027E | E99: FY2028E | F99: FY2029E | G99: FY2030E | H99: FY2031E | I99: FY2032E | J99: FY2033E | K99: CAGR | L99: Audit Code
A100: Tata Steel - volume | B100: Mt | C100: ='Capacity Utilisation'!H20 | D100: ='Capacity Forecast'!C19*'Capacity Utilisation'!C33 | E100: ='Capacity Forecast'!D19*'Capacity Utilisation'!D33 | F100: ='Capacity Forecast'!E19*'Capacity Utilisation'!E33 | G100: ='Capacity Forecast'!F19*'Capacity Utilisation'!F33 | H100: ='Capacity Forecast'!G19*'Capacity Utilisation'!G33 | I100: ='Capacity Forecast'!H19*'Capacity Utilisation'!H33 | J100: ='Capacity Forecast'!I19*'Capacity Utilisation'!I33 | K100: =IFERROR(IF(AND(ISNUMBER(C100),ISNUMBER(J100),C100>0),(J100/C100)^(1/7)-1,""),"") | L100: RF34
A101: JSW Steel - volume | B101: Mt | C101: ='Capacity Utilisation'!H21 | D101: ='Capacity Forecast'!C20*'Capacity Utilisation'!C34 | E101: ='Capacity Forecast'!D20*'Capacity Utilisation'!D34 | F101: ='Capacity Forecast'!E20*'Capacity Utilisation'!E34 | G101: ='Capacity Forecast'!F20*'Capacity Utilisation'!F34 | H101: ='Capacity Forecast'!G20*'Capacity Utilisation'!G34 | I101: ='Capacity Forecast'!H20*'Capacity Utilisation'!H34 | J101: ='Capacity Forecast'!I20*'Capacity Utilisation'!I34 | K101: =IFERROR(IF(AND(ISNUMBER(C101),ISNUMBER(J101),C101>0),(J101/C101)^(1/7)-1,""),"") | L101: RF35
A102: SAIL - volume | B102: Mt | C102: ='Capacity Utilisation'!H22 | D102: ='Capacity Forecast'!C21*'Capacity Utilisation'!C35 | E102: ='Capacity Forecast'!D21*'Capacity Utilisation'!D35 | F102: ='Capacity Forecast'!E21*'Capacity Utilisation'!E35 | G102: ='Capacity Forecast'!F21*'Capacity Utilisation'!F35 | H102: ='Capacity Forecast'!G21*'Capacity Utilisation'!G35 | I102: ='Capacity Forecast'!H21*'Capacity Utilisation'!H35 | J102: ='Capacity Forecast'!I21*'Capacity Utilisation'!I35 | K102: =IFERROR(IF(AND(ISNUMBER(C102),ISNUMBER(J102),C102>0),(J102/C102)^(1/7)-1,""),"") | L102: RF36
A103: Jindal Steel - volume | B103: Mt | C103: ='Capacity Utilisation'!H23 | D103: ='Capacity Forecast'!C22*'Capacity Utilisation'!C36 | E103: ='Capacity Forecast'!D22*'Capacity Utilisation'!D36 | F103: ='Capacity Forecast'!E22*'Capacity Utilisation'!E36 | G103: ='Capacity Forecast'!F22*'Capacity Utilisation'!F36 | H103: ='Capacity Forecast'!G22*'Capacity Utilisation'!G36 | I103: ='Capacity Forecast'!H22*'Capacity Utilisation'!H36 | J103: ='Capacity Forecast'!I22*'Capacity Utilisation'!I36 | K103: =IFERROR(IF(AND(ISNUMBER(C103),ISNUMBER(J103),C103>0),(J103/C103)^(1/7)-1,""),"") | L103: RF37
A104: Jindal Stainless - volume | B104: Mt | C104: ='Capacity Utilisation'!H24 | D104: ='Capacity Forecast'!C23*'Capacity Utilisation'!C37 | E104: ='Capacity Forecast'!D23*'Capacity Utilisation'!D37 | F104: ='Capacity Forecast'!E23*'Capacity Utilisation'!E37 | G104: ='Capacity Forecast'!F23*'Capacity Utilisation'!F37 | H104: ='Capacity Forecast'!G23*'Capacity Utilisation'!G37 | I104: ='Capacity Forecast'!H23*'Capacity Utilisation'!H37 | J104: ='Capacity Forecast'!I23*'Capacity Utilisation'!I37 | K104: =IFERROR(IF(AND(ISNUMBER(C104),ISNUMBER(J104),C104>0),(J104/C104)^(1/7)-1,""),"") | L104: RF38
A105: Others | B105: Mt | C105: ='Capacity Utilisation'!H25 | D105: ='Capacity Forecast'!C24*'Capacity Utilisation'!C38 | E105: ='Capacity Forecast'!D24*'Capacity Utilisation'!D38 | F105: ='Capacity Forecast'!E24*'Capacity Utilisation'!E38 | G105: ='Capacity Forecast'!F24*'Capacity Utilisation'!F38 | H105: ='Capacity Forecast'!G24*'Capacity Utilisation'!G38 | I105: ='Capacity Forecast'!H24*'Capacity Utilisation'!H38 | J105: ='Capacity Forecast'!I24*'Capacity Utilisation'!I38 | K105: =IFERROR(IF(AND(ISNUMBER(C105),ISNUMBER(J105),C105>0),(J105/C105)^(1/7)-1,""),"") | L105: RF39
A106: TOTAL | B106: Mt | C106: =SUM(C100:C105) | D106: =SUM(D100:D105) | E106: =SUM(E100:E105) | F106: =SUM(F100:F105) | G106: =SUM(G100:G105) | H106: =SUM(H100:H105) | I106: =SUM(I100:I105) | J106: =SUM(J100:J105) | K106: =IFERROR(IF(AND(ISNUMBER(C106),ISNUMBER(J106),C106>0),(J106/C106)^(1/7)-1,""),"") | L106: RF40
A108: COMPANY REVENUE BUILD
A109: Line item | B109: Unit | C109: FY2026A | D109: FY2027E | E109: FY2028E | F109: FY2029E | G109: FY2030E | H109: FY2031E | I109: FY2032E | J109: FY2033E | K109: CAGR | L109: Audit Code
A110: Tata Steel - revenue | B110: Rs cr | C110: ='[1]Revenue & EBITDA'!$H6 | D110: =D100*D94*1.03834/10 | E110: =E100*E94*1.03834/10 | F110: =F100*F94*1.03834/10 | G110: =G100*G94*1.03834/10 | H110: =H100*H94*1.03834/10 | I110: =I100*I94*1.03834/10 | J110: =J100*J94*1.03834/10 | K110: =IFERROR(IF(AND(ISNUMBER(C110),ISNUMBER(J110),C110>0),(J110/C110)^(1/7)-1,""),"") | L110: RF41
A111: JSW Steel - revenue | B111: Rs cr | C111: ='[1]Revenue & EBITDA'!$H7 | D111: =D101*D94*1.013733/10 | E111: =E101*E94*1.013733/10 | F111: =F101*F94*1.013733/10 | G111: =G101*G94*1.013733/10 | H111: =H101*H94*1.013733/10 | I111: =I101*I94*1.013733/10 | J111: =J101*J94*1.013733/10 | K111: =IFERROR(IF(AND(ISNUMBER(C111),ISNUMBER(J111),C111>0),(J111/C111)^(1/7)-1,""),"") | L111: RF42
A112: SAIL - revenue | B112: Rs cr | C112: ='[1]Revenue & EBITDA'!$H8 | D112: =D102*D94*0.92707/10 | E112: =E102*E94*0.92707/10 | F112: =F102*F94*0.92707/10 | G112: =G102*G94*0.92707/10 | H112: =H102*H94*0.92707/10 | I112: =I102*I94*0.92707/10 | J112: =J102*J94*0.92707/10 | K112: =IFERROR(IF(AND(ISNUMBER(C112),ISNUMBER(J112),C112>0),(J112/C112)^(1/7)-1,""),"") | L112: RF43
A113: Jindal Steel - revenue | B113: Rs cr | C113: ='[1]Revenue & EBITDA'!$H9 | D113: =D103*D94*1.022428/10 | E113: =E103*E94*1.022428/10 | F113: =F103*F94*1.022428/10 | G113: =G103*G94*1.022428/10 | H113: =H103*H94*1.022428/10 | I113: =I103*I94*1.022428/10 | J113: =J103*J94*1.022428/10 | K113: =IFERROR(IF(AND(ISNUMBER(C113),ISNUMBER(J113),C113>0),(J113/C113)^(1/7)-1,""),"") | L113: RF44
A114: Jindal Stainless - revenue | B114: Rs cr | C114: ='[1]Revenue & EBITDA'!$H10 | D114: =D104*D94*2.786876/10 | E114: =E104*E94*2.786876/10 | F114: =F104*F94*2.786876/10 | G114: =G104*G94*2.786876/10 | H114: =H104*H94*2.786876/10 | I114: =I104*I94*2.786876/10 | J114: =J104*J94*2.786876/10 | K114: =IFERROR(IF(AND(ISNUMBER(C114),ISNUMBER(J114),C114>0),(J114/C114)^(1/7)-1,""),"") | L114: RF45
A115: Others | B115: Rs cr | C115: ='[1]Revenue & EBITDA'!$H11 | D115: =D105*D94*0.845063/10 | E115: =E105*E94*0.845063/10 | F115: =F105*F94*0.845063/10 | G115: =G105*G94*0.845063/10 | H115: =H105*H94*0.845063/10 | I115: =I105*I94*0.845063/10 | J115: =J105*J94*0.845063/10 | K115: =IFERROR(IF(AND(ISNUMBER(C115),ISNUMBER(J115),C115>0),(J115/C115)^(1/7)-1,""),"") | L115: RF46
A117: Company revenues are NOT additive to industry revenue: Jindal Stainless is stainless, AM/NS India is on a 100% JV basis, RINL turnover is on an unspecified basis, and the six together are only part of India's output. Use industry revenue for the market and company revenue for relative work.

Sheet EBITDA Model
A1: EBITDA MODEL
A2: Industry Financial Model | Indian Steel Industry | Horizon FY2027E-FY2033E | Base year FY2026A
I3: Active Scenario | K3: ='Control Panel'!$E$17
A4: OBJECTIVE
A5: Forecast industry EBITDA by integrating revenue, raw material costs, conversion costs, operating expenses, and operating leverage.
A7: Executive Summary
A8: KPI | B8: FY26A | C8: FY27E | D8: FY28E | E8: FY29E | F8: FY30E | G8: FY31E | H8: FY32E | I8: FY33E | J8: Audit Code
A9: Revenue (₹ Cr) | B9: ='Revenue Forecast'!C95 | C9: ='Revenue Forecast'!D95 | D9: ='Revenue Forecast'!E95 | E9: ='Revenue Forecast'!F95 | F9: ='Revenue Forecast'!G95 | G9: ='Revenue Forecast'!H95 | H9: ='Revenue Forecast'!I95 | I9: ='Revenue Forecast'!J95 | J9: EE01
A10: EBITDA (₹ Cr) | B10: =C103 | C10: =D103 | D10: =E103 | E10: =F103 | F10: =G103 | G10: =H103 | H10: =I103 | I10: =J103 | J10: EE02
A11: EBITDA Margin (%) | B11: =B10/B9 | C11: =C10/C9 | D11: =D10/D9 | E11: =E10/E9 | F11: =F10/F9 | G11: =G10/G9 | H11: =H10/H9 | I11: =I10/I9 | J11: EE03
A12: EBITDA/Tonne (₹/t) | B12: =C101 | C12: =D101 | D12: =E101 | E12: =F101 | F12: =G101 | G12: =H101 | H12: =I101 | I12: =J101 | J12: EE04
A13: Cash Cost (₹/t) | B13: =C100 | C13: =D100 | D13: =E100 | E13: =F100 | F13: =G100 | G13: =H100 | H13: =I100 | I13: =J100 | J13: EE05
A14: Operating Cost (₹ Cr) | B14: =B9-B10 | C14: =C9-C10 | D14: =D9-D10 | E14: =E9-E10 | F14: =F9-F10 | G14: =G9-G10 | H14: =H9-H10 | I14: =I9-I10 | J14: EE06
A17: EBITDA Build Up
A18: Year | B18: Revenue | C18: RM Cost | D18: Conversion Cost | E18: Logistics | F18: SG&A | G18: Other Opex | H18: Total Opex | I18: EBITDA | J18: Audit Code
A19: FY26A | B19: ='Revenue Forecast'!C95 | C19: ='Cost Curve'!C$65*'Model Assumptions'!D$20*'Steel Supply Model'!C$90/10 | D19: ='Cost Curve'!C$65*(1-'Model Assumptions'!D$20)*'Steel Supply Model'!C$90/10 | E19: =D19*0.15 | F19: =D19*0.12 | G19: =D19*0.08 | H19: =C19+D19 | I19: =B19-H19 | J19: EE07
A20: FY27E | B20: ='Revenue Forecast'!D95 | C20: ='Cost Curve'!D$65*'Model Assumptions'!E$20*'Steel Supply Model'!D$90/10 | D20: ='Cost Curve'!D$65*(1-'Model Assumptions'!E$20)*'Steel Supply Model'!D$90/10 | E20: =D20*0.15 | F20: =D20*0.12 | G20: =D20*0.08 | H20: =C20+D20 | I20: =B20-H20 | J20: EE08
A21: FY28E | B21: ='Revenue Forecast'!E95 | C21: ='Cost Curve'!E$65*'Model Assumptions'!F$20*'Steel Supply Model'!E$90/10 | D21: ='Cost Curve'!E$65*(1-'Model Assumptions'!F$20)*'Steel Supply Model'!E$90/10 | E21: =D21*0.15 | F21: =D21*0.12 | G21: =D21*0.08 | H21: =C21+D21 | I21: =B21-H21 | J21: EE09
A22: FY29E | B22: ='Revenue Forecast'!F95 | C22: ='Cost Curve'!F$65*'Model Assumptions'!G$20*'Steel Supply Model'!F$90/10 | D22: ='Cost Curve'!F$65*(1-'Model Assumptions'!G$20)*'Steel Supply Model'!F$90/10 | E22: =D22*0.15 | F22: =D22*0.12 | G22: =D22*0.08 | H22: =C22+D22 | I22: =B22-H22 | J22: EE10
A23: FY30E | B23: ='Revenue Forecast'!G95 | C23: ='Cost Curve'!G$65*'Model Assumptions'!H$20*'Steel Supply Model'!G$90/10 | D23: ='Cost Curve'!G$65*(1-'Model Assumptions'!H$20)*'Steel Supply Model'!G$90/10 | E23: =D23*0.15 | F23: =D23*0.12 | G23: =D23*0.08 | H23: =C23+D23 | I23: =B23-H23 | J23: EE11
A24: FY31E | B24: ='Revenue Forecast'!H95 | C24: ='Cost Curve'!H$65*'Model Assumptions'!I$20*'Steel Supply Model'!H$90/10 | D24: ='Cost Curve'!H$65*(1-'Model Assumptions'!I$20)*'Steel Supply Model'!H$90/10 | E24: =D24*0.15 | F24: =D24*0.12 | G24: =D24*0.08 | H24: =C24+D24 | I24: =B24-H24 | J24: EE12
A25: FY32E | B25: ='Revenue Forecast'!I95 | C25: ='Cost Curve'!I$65*'Model Assumptions'!J$20*'Steel Supply Model'!I$90/10 | D25: ='Cost Curve'!I$65*(1-'Model Assumptions'!J$20)*'Steel Supply Model'!I$90/10 | E25: =D25*0.15 | F25: =D25*0.12 | G25: =D25*0.08 | H25: =C25+D25 | I25: =B25-H25 | J25: EE13
A26: FY33E | B26: ='Revenue Forecast'!J95 | C26: ='Cost Curve'!J$65*'Model Assumptions'!K$20*'Steel Supply Model'!J$90/10 | D26: ='Cost Curve'!J$65*(1-'Model Assumptions'!K$20)*'Steel Supply Model'!J$90/10 | E26: =D26*0.15 | F26: =D26*0.12 | G26: =D26*0.08 | H26: =C26+D26 | I26: =B26-H26 | J26: EE14
A29: Cost Bridge
A30: Cost Component | B30: ₹ Cr | C30: % of Total Opex | D30: Audit Code
A31: Iron Ore | B31: =$B$14*C31 | C31: ='Cost Curve'!C28 | D31: EE15
A32: Coking Coal | B32: =$B$14*C32 | C32: ='Cost Curve'!C29 | D32: EE16
A33: PCI Coal | B33: =$B$14*C33 | C33: ='Cost Curve'!C30 | D33: EE17
A34: Scrap | B34: =$B$14*C34 | C34: ='Cost Curve'!C31 | D34: EE18
A35: Fluxes | B35: =$B$14*C35 | C35: ='Cost Curve'!C32 | D35: EE19
A36: Power & Fuel | B36: =$B$14*C36 | C36: ='Cost Curve'!C33 | D36: EE20
A37: Labour | B37: =$B$14*C37 | C37: ='Cost Curve'!C34 | D37: EE21
A38: Maintenance | B38: =$B$14*C38 | C38: ='Cost Curve'!C35 | D38: EE22
A39: Logistics | B39: =$B$14*C39 | C39: ='Cost Curve'!C36 | D39: EE23
A40: SG&A | B40: =$B$14*C40 | C40: ='Cost Curve'!C40 | D40: EE24
A41: Other Operating Cost | B41: =$B$14*C41 | C41: ='Cost Curve'!C37 | D41: EE25
A42: Total Opex | B42: =SUM(B31:B41) | C42: =SUM(C31:C41) | D42: EE26
A45: EBITDA Bridge
A46: Driver | B46: FY27E | C46: FY28E | D46: FY29E | E46: FY30E | F46: FY31E | G46: FY32E | H46: FY33E | I46: Audit Code
A47: Previous EBITDA | B47: =C103 | C47: =D103 | D47: =E103 | E47: =F103 | F47: =G103 | G47: =H103 | H47: =I103 | I47: EE27
A48: Volume Effect | B48: =(D102-C102)*C101/10 | C48: =(E102-D102)*D101/10 | D48: =(F102-E102)*E101/10 | E48: =(G102-F102)*F101/10 | F48: =(H102-G102)*G101/10 | G48: =(I102-H102)*H101/10 | H48: =(J102-I102)*I101/10 | I48: EE28
A49: Price Effect | B49: =D102*(D99-C99)/10 | C49: =E102*(E99-D99)/10 | D49: =F102*(F99-E99)/10 | E49: =G102*(G99-F99)/10 | F49: =H102*(H99-G99)/10 | G49: =I102*(I99-H99)/10 | H49: =J102*(J99-I99)/10 | I49: EE29
A50: Raw Material Effect | B50: =-D102*('Cost Curve'!D65*'Cost Curve'!D62-'Cost Curve'!C65*'Cost Curve'!C62)/10 | C50: =-E102*('Cost Curve'!E65*'Cost Curve'!E62-'Cost Curve'!D65*'Cost Curve'!D62)/10 | D50: =-F102*('Cost Curve'!F65*'Cost Curve'!F62-'Cost Curve'!E65*'Cost Curve'!E62)/10 | E50: =-G102*('Cost Curve'!G65*'Cost Curve'!G62-'Cost Curve'!F65*'Cost Curve'!F62)/10 | F50: =-H102*('Cost Curve'!H65*'Cost Curve'!H62-'Cost Curve'!G65*'Cost Curve'!G62)/10 | G50: =-I102*('Cost Curve'!I65*'Cost Curve'!I62-'Cost Curve'!H65*'Cost Curve'!H62)/10 | H50: =-J102*('Cost Curve'!J65*'Cost Curve'!J62-'Cost Curve'!I65*'Cost Curve'!I62)/10 | I50: EE30
A51: Energy Effect | B51: =-D102*('Cost Curve'!D65*(1-'Cost Curve'!D62)-'Cost Curve'!C65*(1-'Cost Curve'!C62))/10*0.2 | C51: =-E102*('Cost Curve'!E65*(1-'Cost Curve'!E62)-'Cost Curve'!D65*(1-'Cost Curve'!D62))/10*0.2 | D51: =-F102*('Cost Curve'!F65*(1-'Cost Curve'!F62)-'Cost Curve'!E65*(1-'Cost Curve'!E62))/10*0.2 | E51: =-G102*('Cost Curve'!G65*(1-'Cost Curve'!G62)-'Cost Curve'!F65*(1-'Cost Curve'!F62))/10*0.2 | F51: =-H102*('Cost Curve'!H65*(1-'Cost Curve'!H62)-'Cost Curve'!G65*(1-'Cost Curve'!G62))/10*0.2 | G51: =-I102*('Cost Curve'!I65*(1-'Cost Curve'!I62)-'Cost Curve'!H65*(1-'Cost Curve'!H62))/10*0.2 | H51: =-J102*('Cost Curve'!J65*(1-'Cost Curve'!J62)-'Cost Curve'!I65*(1-'Cost Curve'!I62))/10*0.2 | I51: EE31
A52: Logistics Effect | B52: =-D102*('Cost Curve'!D65*(1-'Cost Curve'!D62)-'Cost Curve'!C65*(1-'Cost Curve'!C62))/10*0.2 | C52: =-E102*('Cost Curve'!E65*(1-'Cost Curve'!E62)-'Cost Curve'!D65*(1-'Cost Curve'!D62))/10*0.2 | D52: =-F102*('Cost Curve'!F65*(1-'Cost Curve'!F62)-'Cost Curve'!E65*(1-'Cost Curve'!E62))/10*0.2 | E52: =-G102*('Cost Curve'!G65*(1-'Cost Curve'!G62)-'Cost Curve'!F65*(1-'Cost Curve'!F62))/10*0.2 | F52: =-H102*('Cost Curve'!H65*(1-'Cost Curve'!H62)-'Cost Curve'!G65*(1-'Cost Curve'!G62))/10*0.2 | G52: =-I102*('Cost Curve'!I65*(1-'Cost Curve'!I62)-'Cost Curve'!H65*(1-'Cost Curve'!H62))/10*0.2 | H52: =-J102*('Cost Curve'!J65*(1-'Cost Curve'!J62)-'Cost Curve'!I65*(1-'Cost Curve'!I62))/10*0.2 | I52: EE32
A53: Operating Leverage | B53: =-D102*('Cost Curve'!D65*(1-'Cost Curve'!D62)-'Cost Curve'!C65*(1-'Cost Curve'!C62))/10*0.6 | C53: =-E102*('Cost Curve'!E65*(1-'Cost Curve'!E62)-'Cost Curve'!D65*(1-'Cost Curve'!D62))/10*0.6 | D53: =-F102*('Cost Curve'!F65*(1-'Cost Curve'!F62)-'Cost Curve'!E65*(1-'Cost Curve'!E62))/10*0.6 | E53: =-G102*('Cost Curve'!G65*(1-'Cost Curve'!G62)-'Cost Curve'!F65*(1-'Cost Curve'!F62))/10*0.6 | F53: =-H102*('Cost Curve'!H65*(1-'Cost Curve'!H62)-'Cost Curve'!G65*(1-'Cost Curve'!G62))/10*0.6 | G53: =-I102*('Cost Curve'!I65*(1-'Cost Curve'!I62)-'Cost Curve'!H65*(1-'Cost Curve'!H62))/10*0.6 | H53: =-J102*('Cost Curve'!J65*(1-'Cost Curve'!J62)-'Cost Curve'!I65*(1-'Cost Curve'!I62))/10*0.6 | I53: EE33
A54: Mix Effect | B54: 0 | C54: 0 | D54: 0 | E54: 0 | F54: 0 | G54: 0 | H54: 0 | I54: EE34
A55: Net EBITDA | B55: =SUM(B47:B54) | C55: =SUM(C47:C54) | D55: =SUM(D47:D54) | E55: =SUM(E47:E54) | F55: =SUM(F47:F54) | G55: =SUM(G47:G54) | H55: =SUM(H47:H54) | I55: EE35
A58: EBITDA/Tonne Analysis
A59: Year | B59: EBITDA | C59: Sales Volume | D59: EBITDA/Tonne
A60: FY26A | B60: =C103 | C60: =C102 | D60: =B60/C60*10
A61: FY27E | B61: =D103 | C61: =D102 | D61: =B61/C61*10
A62: FY28E | B62: =E103 | C62: =E102 | D62: =B62/C62*10
A63: FY29E | B63: =F103 | C63: =F102 | D63: =B63/C63*10
A64: FY30E | B64: =G103 | C64: =G102 | D64: =B64/C64*10
A65: FY31E | B65: =H103 | C65: =H102 | D65: =B65/C65*10
A66: FY32E | B66: =I103 | C66: =I102 | D66: =B66/C66*10
A67: FY33E | B67: =J103 | C67: =J102 | D67: =B67/C67*10
A70: Company Benchmark
A71: Company | B71: Revenue | C71: EBITDA | D71: EBITDA Margin | E71: EBITDA/t
A72: Tata Steel | B72: ='Revenue Forecast'!C110 | C72: =C116 | D72: =C72/B72 | E72: =C108
A73: JSW Steel | B73: ='Revenue Forecast'!C111 | C73: =C117 | D73: =C73/B73 | E73: =C109
A74: SAIL | B74: ='Revenue Forecast'!C112 | C74: =C118 | D74: =C74/B74 | E74: =C110
A75: Jindal Steel | B75: ='Revenue Forecast'!C113 | C75: =C119 | D75: =C75/B75 | E75: =C111
A76: Others | B76: ='Revenue Forecast'!C115+'Revenue Forecast'!C114 | C76: =C103-SUM(C116:C119) | D76: =C76/B76
A79: Margin Walk
A80: Metric | B80: FY27E | C80: FY28E | D80: FY29E | E80: FY30E | F80: FY31E | G80: FY32E | H80: FY33E | I80: Audit Code
A81: Gross Margin | B81: =1-('Cost Curve'!D65*'Cost Curve'!D62)/'Revenue Forecast'!D94 | C81: =1-('Cost Curve'!E65*'Cost Curve'!E62)/'Revenue Forecast'!E94 | D81: =1-('Cost Curve'!F65*'Cost Curve'!F62)/'Revenue Forecast'!F94 | E81: =1-('Cost Curve'!G65*'Cost Curve'!G62)/'Revenue Forecast'!G94 | F81: =1-('Cost Curve'!H65*'Cost Curve'!H62)/'Revenue Forecast'!H94 | G81: =1-('Cost Curve'!I65*'Cost Curve'!I62)/'Revenue Forecast'!I94 | H81: =1-('Cost Curve'!J65*'Cost Curve'!J62)/'Cost Curve'!I11 | I81: EE36
A82: EBITDA Margin | B82: ='Margin Analysis'!D81 | C82: ='Margin Analysis'!E81 | D82: ='Margin Analysis'!F81 | E82: ='Margin Analysis'!G81 | F82: ='Margin Analysis'!H81 | G82: ='Margin Analysis'!I81 | H82: ='Margin Analysis'!J81 | I82: EE37
A83: Operating Margin | B83: ='Cash Flow Model'!D94/'Cash Flow Model'!D91 | C83: ='Cash Flow Model'!E94/'Cash Flow Model'!E91 | D83: ='Cash Flow Model'!F94/'Cash Flow Model'!F91 | E83: ='Cash Flow Model'!G94/'Cash Flow Model'!G91 | F83: ='Cash Flow Model'!H94/'Cash Flow Model'!H91 | G83: ='Cash Flow Model'!I94/'Cash Flow Model'!I91 | H83: ='Cash Flow Model'!J94/'Cash Flow Model'!J91 | I83: EE38
A84: Cash Margin | B84: =('Cash Flow Model'!C94-'Cash Flow Model'!D96)/'Cash Flow Model'!D91 | C84: =('Cash Flow Model'!D94-'Cash Flow Model'!E96)/'Cash Flow Model'!E91 | D84: =('Cash Flow Model'!E94-'Cash Flow Model'!F96)/'Cash Flow Model'!F91 | E84: =('Cash Flow Model'!F94-'Cash Flow Model'!G96)/'Cash Flow Model'!G91 | F84: =('Cash Flow Model'!G94-'Cash Flow Model'!H96)/'Cash Flow Model'!H91 | G84: =('Cash Flow Model'!H94-'Cash Flow Model'!I96)/'Cash Flow Model'!I91 | H84: =('Cash Flow Model'!J90-'Cash Flow Model'!J96)/'Cash Flow Model'!J91 | I84: EE39
A87: Scenario Analysis
A88: Year | B88: Base | C88: Bull | D88: Bear | E88: Stress
A89: FY27
A90: FY28
A91: FY29
A92: FY30
A93: FY31
A94: FY32
A95: FY33
A98: Line item | B98: Unit | C98: FY2026A | D98: FY2027E | E98: FY2028E | F98: FY2029E | G98: FY2030E | H98: FY2031E | I98: FY2032E | J98: FY2033E | K98: CAGR | L98: Audit Code
A99: Blended realisation - effective | B99: Rs/t | C99: ='Steel Price Forecast'!C72 | D99: ='Steel Price Forecast'!D$72 | E99: ='Steel Price Forecast'!E$72 | F99: ='Steel Price Forecast'!F$72 | G99: ='Steel Price Forecast'!G$72 | H99: ='Steel Price Forecast'!H$72 | I99: ='Steel Price Forecast'!I$72 | J99: ='Steel Price Forecast'!J$72 | K99: =IFERROR(IF(AND(ISNUMBER(C99),ISNUMBER(J99),C99>0),(J99/C99)^(1/7)-1,""),"") | L99: EE40
A100: Industry cash cost per tonne | B100: Rs/t | C100: ='Cost Curve'!C$65 | D100: ='Cost Curve'!D$65 | E100: ='Cost Curve'!E$65 | F100: ='Cost Curve'!F$65 | G100: ='Cost Curve'!G$65 | H100: ='Cost Curve'!H$65 | I100: ='Cost Curve'!I$65 | J100: ='Cost Curve'!J$65 | K100: =IFERROR(IF(AND(ISNUMBER(C100),ISNUMBER(J100),C100>0),(J100/C100)^(1/7)-1,""),"") | L100: EE41
A101: INDUSTRY EBITDA PER TONNE | B101: Rs/t | C101: =C99-C100 | D101: =D99-D100 | E101: =E99-E100 | F101: =F99-F100 | G101: =G99-G100 | H101: =H99-H100 | I101: =I99-I100 | J101: =J99-J100 | K101: =IFERROR(IF(AND(ISNUMBER(C101),ISNUMBER(J101),C101>0),(J101/C101)^(1/7)-1,""),"")
A102: Finished steel production | B102: Mt | C102: ='Steel Supply Model'!C$90 | D102: ='Steel Supply Model'!D$90 | E102: ='Steel Supply Model'!E$90 | F102: ='Steel Supply Model'!F$90 | G102: ='Steel Supply Model'!G$90 | H102: ='Steel Supply Model'!H$90 | I102: ='Steel Supply Model'!I$90 | J102: ='Steel Supply Model'!J$90 | K102: =IFERROR(IF(AND(ISNUMBER(C102),ISNUMBER(J102),C102>0),(J102/C102)^(1/7)-1,""),"") | L102: EE42
A103: INDUSTRY EBITDA | B103: Rs cr | C103: =C101*C102/10 | D103: =D101*D102/10 | E103: =E101*E102/10 | F103: =F101*F102/10 | G103: =G101*G102/10 | H103: =H101*H102/10 | I103: =I101*I102/10 | J103: =J101*J102/10 | K103: =IFERROR(IF(AND(ISNUMBER(C103),ISNUMBER(J103),C103>0),(J103/C103)^(1/7)-1,""),"")
A106: COMPANY EBITDA PER TONNE (FY2026 spread to industry held constant)
A107: Line item | B107: Unit | C107: FY2026A | D107: FY2027E | E107: FY2028E | F107: FY2029E | G107: FY2030E | H107: FY2031E | I107: FY2032E | J107: FY2033E | K107: CAGR | L107: Audit Code
A108: Tata Steel - EBITDA per tonne | B108: Rs/t | C108: =C101+4480 | D108: =D101+4480 | E108: =E101+4480 | F108: =F101+4480 | G108: =G101+4480 | H108: =H101+4480 | I108: =I101+4480 | J108: =J101+4480 | K108: =IFERROR(IF(AND(ISNUMBER(C108),ISNUMBER(J108),C108>0),(J108/C108)^(1/7)-1,""),"") | L108: EE43
A109: JSW Steel - EBITDA per tonne | B109: Rs/t | C109: =C101+(-566) | D109: =D101+(-566) | E109: =E101+(-566) | F109: =F101+(-566) | G109: =G101+(-566) | H109: =H101+(-566) | I109: =I101+(-566) | J109: =J101+(-566) | K109: =IFERROR(IF(AND(ISNUMBER(C109),ISNUMBER(J109),C109>0),(J109/C109)^(1/7)-1,""),"") | L109: EE44
A110: SAIL - EBITDA per tonne | B110: Rs/t | C110: =C101+(-4137) | D110: =D101+(-4137) | E110: =E101+(-4137) | F110: =F101+(-4137) | G110: =G101+(-4137) | H110: =H101+(-4137) | I110: =I101+(-4137) | J110: =J101+(-4137) | K110: =IFERROR(IF(AND(ISNUMBER(C110),ISNUMBER(J110),C110>0),(J110/C110)^(1/7)-1,""),"") | L110: EE45
A111: Jindal Steel - EBITDA per tonne | B111: Rs/t | C111: =C101+(-251) | D111: =D101+(-251) | E111: =E101+(-251) | F111: =F101+(-251) | G111: =G101+(-251) | H111: =H101+(-251) | I111: =I101+(-251) | J111: =J101+(-251) | K111: =IFERROR(IF(AND(ISNUMBER(C111),ISNUMBER(J111),C111>0),(J111/C111)^(1/7)-1,""),"") | L111: EE46
A112: Jindal Stainless - EBITDA per tonne | B112: Rs/t | C112: =C101+10901 | D112: =D101+10901 | E112: =E101+10901 | F112: =F101+10901 | G112: =G101+10901 | H112: =H101+10901 | I112: =I101+10901 | J112: =J101+10901 | K112: =IFERROR(IF(AND(ISNUMBER(C112),ISNUMBER(J112),C112>0),(J112/C112)^(1/7)-1,""),"") | L112: EE47
A114: COMPANY EBITDA
A115: Line item | B115: Unit | C115: FY2026A | D115: FY2027E | E115: FY2028E | F115: FY2029E | G115: FY2030E | H115: FY2031E | I115: FY2032E | J115: FY2033E | K115: CAGR | L115: Audit Code
A116: Tata Steel - EBITDA | B116: Rs cr | C116: =C108*'Revenue Forecast'!C100/10 | D116: =D108*'Revenue Forecast'!D100/10 | E116: =E108*'Revenue Forecast'!E100/10 | F116: =F108*'Revenue Forecast'!F100/10 | G116: =G108*'Revenue Forecast'!G100/10 | H116: =H108*'Revenue Forecast'!H100/10 | I116: =I108*'Revenue Forecast'!I100/10 | J116: =J108*'Revenue Forecast'!J100/10 | K116: =IFERROR(IF(AND(ISNUMBER(C116),ISNUMBER(J116),C116>0),(J116/C116)^(1/7)-1,""),"")
A117: JSW Steel - EBITDA | B117: Rs cr | C117: =C109*'Revenue Forecast'!C101/10 | D117: =D109*'Revenue Forecast'!D101/10 | E117: =E109*'Revenue Forecast'!E101/10 | F117: =F109*'Revenue Forecast'!F101/10 | G117: =G109*'Revenue Forecast'!G101/10 | H117: =H109*'Revenue Forecast'!H101/10 | I117: =I109*'Revenue Forecast'!I101/10 | J117: =J109*'Revenue Forecast'!J101/10 | K117: =IFERROR(IF(AND(ISNUMBER(C117),ISNUMBER(J117),C117>0),(J117/C117)^(1/7)-1,""),"")
A118: SAIL - EBITDA | B118: Rs cr | C118: =C110*'Revenue Forecast'!C102/10 | D118: =D110*'Revenue Forecast'!D102/10 | E118: =E110*'Revenue Forecast'!E102/10 | F118: =F110*'Revenue Forecast'!F102/10 | G118: =G110*'Revenue Forecast'!G102/10 | H118: =H110*'Revenue Forecast'!H102/10 | I118: =I110*'Revenue Forecast'!I102/10 | J118: =J110*'Revenue Forecast'!J102/10 | K118: =IFERROR(IF(AND(ISNUMBER(C118),ISNUMBER(J118),C118>0),(J118/C118)^(1/7)-1,""),"")
A119: Jindal Steel - EBITDA | B119: Rs cr | C119: =C111*'Revenue Forecast'!C103/10 | D119: =D111*'Revenue Forecast'!D103/10 | E119: =E111*'Revenue Forecast'!E103/10 | F119: =F111*'Revenue Forecast'!F103/10 | G119: =G111*'Revenue Forecast'!G103/10 | H119: =H111*'Revenue Forecast'!H103/10 | I119: =I111*'Revenue Forecast'!I103/10 | J119: =J111*'Revenue Forecast'!J103/10 | K119: =IFERROR(IF(AND(ISNUMBER(C119),ISNUMBER(J119),C119>0),(J119/C119)^(1/7)-1,""),"")
A120: Jindal Stainless - EBITDA | B120: Rs cr | C120: =C112*'Revenue Forecast'!C104/10 | D120: =D112*'Revenue Forecast'!D104/10 | E120: =E112*'Revenue Forecast'!E104/10 | F120: =F112*'Revenue Forecast'!F104/10 | G120: =G112*'Revenue Forecast'!G104/10 | H120: =H112*'Revenue Forecast'!H104/10 | I120: =I112*'Revenue Forecast'!I104/10 | J120: =J112*'Revenue Forecast'!J104/10 | K120: =IFERROR(IF(AND(ISNUMBER(C120),ISNUMBER(J120),C120>0),(J120/C120)^(1/7)-1,""),"")
...

Sheet Margin Analysis
A1: MARGIN ANALYSIS
A2: Industry Financial Model | Indian Steel Industry | Horizon FY2027E-FY2033E | Base year FY2026A
I3: Active Scenario | K3: ='Control Panel'!$E$17
A4: OBJECTIVE
A5: Analyze historical and forecast profitability by examining margins, cost drivers, operating leverage, and sensitivity to key variables.
A7: Executive Summary
A8: KPI | B8: FY26A | C8: FY27E | D8: FY28E | E8: FY29E | F8: FY30E | G8: FY31E | H8: FY32E | I8: FY33E
A9: Gross Margin (%) | B9: =1-('Cost Curve'!C65*'Cost Curve'!C62)/'Revenue Forecast'!C94 | C9: =1-('Cost Curve'!D65*'Cost Curve'!D62)/'Revenue Forecast'!D94 | D9: =1-('Cost Curve'!E65*'Cost Curve'!E62)/'Revenue Forecast'!E94 | E9: =1-('Cost Curve'!F65*'Cost Curve'!F62)/'Revenue Forecast'!F94 | F9: =1-('Cost Curve'!G65*'Cost Curve'!G62)/'Revenue Forecast'!G94 | G9: =1-('Cost Curve'!H65*'Cost Curve'!H62)/'Revenue Forecast'!H94 | H9: =1-('Cost Curve'!I65*'Cost Curve'!I62)/'Revenue Forecast'!I94 | I9: =1-('Cost Curve'!J65*'Cost Curve'!J62)/'Revenue Forecast'!J94
A10: EBITDA Margin (%) | B10: =C81 | C10: =D81 | D10: =E81 | E10: =F81 | F10: =G81 | G10: =H81 | H10: =I81 | I10: =J81
A11: Operating Margin (%) | B11: ='Cash Flow Model'!C94/'Cash Flow Model'!C91 | C11: ='Cash Flow Model'!D94/'Cash Flow Model'!D91 | D11: ='Cash Flow Model'!E94/'Cash Flow Model'!E91 | E11: ='Cash Flow Model'!F94/'Cash Flow Model'!F91 | F11: ='Cash Flow Model'!G94/'Cash Flow Model'!G91 | G11: ='Cash Flow Model'!H94/'Cash Flow Model'!H91 | H11: ='Cash Flow Model'!I94/'Cash Flow Model'!I91 | I11: ='Cash Flow Model'!J94/'Cash Flow Model'!J91
A12: Cash Margin (%) | B12: =('Cash Flow Model'!C94-'Cash Flow Model'!C96)/'Cash Flow Model'!C91 | C12: =('Cash Flow Model'!D94-'Cash Flow Model'!D96)/'Cash Flow Model'!D91 | D12: =('Cash Flow Model'!E94-'Cash Flow Model'!E96)/'Cash Flow Model'!E91 | E12: =('Cash Flow Model'!F94-'Cash Flow Model'!F96)/'Cash Flow Model'!F91 | F12: =('Cash Flow Model'!G94-'Cash Flow Model'!G96)/'Cash Flow Model'!G91 | G12: =('Cash Flow Model'!H94-'Cash Flow Model'!H96)/'Cash Flow Model'!H91 | H12: =('Cash Flow Model'!I94-'Cash Flow Model'!I96)/'Cash Flow Model'!I91 | I12: =('Cash Flow Model'!J94-'Cash Flow Model'!J96)/'Cash Flow Model'!J91
A13: EBITDA/t (₹/t) | B13: =C80 | C13: =D80 | D13: =E80 | E13: =F80 | F13: =G80 | G13: =H80 | H13: =I80 | I13: =J80
A14: Cost/Revenue (%) | B14: ='Cost Curve'!C65/'Margin Analysis'!C78 | C14: ='Cost Curve'!D65/'Margin Analysis'!D78 | D14: ='Cost Curve'!E65/'Margin Analysis'!E78 | E14: ='Cost Curve'!F65/'Margin Analysis'!F78 | F14: ='Cost Curve'!G65/'Margin Analysis'!G78 | G14: ='Cost Curve'!H65/'Margin Analysis'!H78 | H14: ='Cost Curve'!I65/'Margin Analysis'!I78 | I14: ='Cost Curve'!J65/'Margin Analysis'!J78
A17: Margin Trend
A18: Year | B18: Revenue | C18: EBITDA | D18: EBITDA Margin | E18: Operating Margin | F18: Gross Margin
A19: FY26A | B19: ='Revenue Forecast'!C95 | C19: ='EBITDA Model'!C103 | D19: =C19/B19 | E19: =B11 | F19: =B9
A20: FY27E | B20: ='Revenue Forecast'!D95 | C20: ='EBITDA Model'!D103 | D20: =C20/B20 | E20: =C11 | F20: =C9
A21: FY28E | B21: ='Revenue Forecast'!E95 | C21: ='EBITDA Model'!E103 | D21: =C21/B21 | E21: =D11 | F21: =D9
A22: FY29E | B22: ='Revenue Forecast'!F95 | C22: ='EBITDA Model'!F103 | D22: =C22/B22 | E22: =E11 | F22: =E9
A23: FY30E | B23: ='Revenue Forecast'!G95 | C23: ='EBITDA Model'!G103 | D23: =C23/B23 | E23: =F11 | F23: =F9
A24: FY31E | B24: ='Revenue Forecast'!H95 | C24: ='EBITDA Model'!H103 | D24: =C24/B24 | E24: =G11 | F24: =G9
A25: FY32E | B25: ='Revenue Forecast'!I95 | C25: ='EBITDA Model'!I103 | D25: =C25/B25 | E25: =H11 | F25: =H9
A26: FY33E | B26: ='Revenue Forecast'!J95 | C26: ='EBITDA Model'!J103 | D26: =C26/B26 | E26: =I11 | F26: =I9
A29: Margin Bridge
A30: Driver | B30: FY27E | C30: FY28E | D30: FY29E | E30: FY30E | F30: FY31E | G30: FY32E | H30: FY33E
A31: Previous Margin | B31: =C81 | C31: =D81 | D31: =E81 | E31: =F81 | F31: =G81 | G31: =H81 | H31: =I81
A32: Steel Price Effect | B32: ='Cost Curve'!C65*(D78-C78)/(C78*D78) | C32: ='Cost Curve'!D65*(E78-D78)/(D78*E78) | D32: ='Cost Curve'!E65*(F78-E78)/(E78*F78) | E32: ='Cost Curve'!F65*(G78-F78)/(F78*G78) | F32: ='Cost Curve'!G65*(H78-G78)/(G78*H78) | G32: ='Cost Curve'!H65*(I78-H78)/(H78*I78) | H32: ='Cost Curve'!I65*(J78-I78)/(I78*J78)
A33: Raw Material Effect | B33: =('Cost Curve'!C65*'Model Assumptions'!D$20-'Cost Curve'!D65*'Model Assumptions'!E$20)/D78 | C33: =('Cost Curve'!D65*'Model Assumptions'!E$20-'Cost Curve'!E65*'Model Assumptions'!F$20)/E78 | D33: =('Cost Curve'!E65*'Model Assumptions'!F$20-'Cost Curve'!F65*'Model Assumptions'!G$20)/F78 | E33: =('Cost Curve'!F65*'Model Assumptions'!G$20-'Cost Curve'!G65*'Model Assumptions'!H$20)/G78 | F33: =('Cost Curve'!G65*'Model Assumptions'!H$20-'Cost Curve'!H65*'Model Assumptions'!I$20)/H78 | G33: =('Cost Curve'!H65*'Model Assumptions'!I$20-'Cost Curve'!I65*'Model Assumptions'!J$20)/I78 | H33: =('Cost Curve'!I65*'Model Assumptions'!J$20-'Cost Curve'!J65*'Model Assumptions'!K$20)/J78
A34: Volume Effect | B34: 0 | C34: 0 | D34: 0 | E34: 0 | F34: 0 | G34: 0 | H34: 0
A35: Product Mix Effect | B35: 0 | C35: 0 | D35: 0 | E35: 0 | F35: 0 | G35: 0 | H35: 0
A36: Operating Leverage | B36: =('Cost Curve'!C65*(1-'Model Assumptions'!D$20)-'Cost Curve'!D65*(1-'Model Assumptions'!E$20))/D78 | C36: =('Cost Curve'!D65*(1-'Model Assumptions'!E$20)-'Cost Curve'!E65*(1-'Model Assumptions'!F$20))/E78 | D36: =('Cost Curve'!E65*(1-'Model Assumptions'!F$20)-'Cost Curve'!F65*(1-'Model Assumptions'!G$20))/F78 | E36: =('Cost Curve'!F65*(1-'Model Assumptions'!G$20)-'Cost Curve'!G65*(1-'Model Assumptions'!H$20))/G78 | F36: =('Cost Curve'!G65*(1-'Model Assumptions'!H$20)-'Cost Curve'!H65*(1-'Model Assumptions'!I$20))/H78 | G36: =('Cost Curve'!H65*(1-'Model Assumptions'!I$20)-'Cost Curve'!I65*(1-'Model Assumptions'!J$20))/I78 | H36: =('Cost Curve'!I65*(1-'Model Assumptions'!J$20)-'Cost Curve'!J65*(1-'Model Assumptions'!K$20))/J78
A37: Logistics
A38: Energy
A39: FX
A40: Final Margin | B40: =SUM(B31:B39) | C40: =SUM(C31:C39) | D40: =SUM(D31:D39) | E40: =SUM(E31:E39) | F40: =SUM(F31:F39) | G40: =SUM(G31:G39) | H40: =SUM(H31:H39)
A43: Cost Ratio Analysis
A44: Cost Head | B44: ₹ Cr | C44: % Cash Cost | D44: % Revenue | E44: Audit Code
A45: Raw Materials | B45: =SUM('EBITDA Model'!B31:B35) | C45: =B45/('Cost Curve'!$C$65*'Steel Supply Model'!$C$88/10) | D45: =B45/'Revenue Forecast'!$C$95
A46: Energy | B46: ='EBITDA Model'!B36 | C46: =B46/('Cost Curve'!$C$65*'Steel Supply Model'!$C$88/10) | D46: =B46/'Revenue Forecast'!$C$95
A47: Logistics | B47: ='EBITDA Model'!B39 | C47: =B47/('Cost Curve'!$C$65*'Steel Supply Model'!$C$88/10) | D47: =B47/'Revenue Forecast'!$C$95
A48: Labour | B48: ='EBITDA Model'!B37 | C48: =B48/('Cost Curve'!$C$65*'Steel Supply Model'!$C$88/10) | D48: =B48/'Revenue Forecast'!$C$95
A49: SG&A | B49: ='EBITDA Model'!B40 | C49: =B49/('Cost Curve'!$C$65*'Steel Supply Model'!$C$88/10) | D49: =B49/'Revenue Forecast'!$C$95
A50: Other Opex | B50: =SUM('EBITDA Model'!B41,'EBITDA Model'!B38) | C50: =C51-SUM(C45:C49) | D50: =B50/'Revenue Forecast'!$C$95
A51: Total Opex | B51: =SUM(B45:B50) | C51: 1 | D51: =SUM(D45:D50)
A54: Margin Sensitivity
A55: Variable | B55: Change | C55: EBITDA Margin Impact
A56: Steel Price | B56: 0.05
A57: Steel Price | B57: -0.05
A58: Iron Ore | B58: 0.1
A59: HCC Coal | B59: 0.1
A60: Volume | B60: 0.05
A61: Volume | B61: -0.05
A62: USD/INR | B62: 0.05
A65: Scenario Analysis
A66: Year | B66: Base | C66: Bull | D66: Bear | E66: Stress
A67: FY27
A68: FY28
A69: FY29
A70: FY30
A71: FY31
A72: FY32
A73: FY33
A76: Workbook
A77: Line item | B77: Unit | C77: FY2026A | D77: FY2027E | E77: FY2028E | F77: FY2029E | G77: FY2030E | H77: FY2031E | I77: FY2032E | J77: FY2033E | K77: Audit Code
A78: Realisation | B78: Rs/t | C78: ='Steel Price Forecast'!C$72 | D78: ='Steel Price Forecast'!D$72 | E78: ='Steel Price Forecast'!E$72 | F78: ='Steel Price Forecast'!F$72 | G78: ='Steel Price Forecast'!G$72 | H78: ='Steel Price Forecast'!H$72 | I78: ='Steel Price Forecast'!I$72 | J78: ='Steel Price Forecast'!J$72
A79: Cash cost | B79: Rs/t | C79: ='Cost Curve'!C$65 | D79: ='Cost Curve'!D$65 | E79: ='Cost Curve'!E$65 | F79: ='Cost Curve'!F$65 | G79: ='Cost Curve'!G$65 | H79: ='Cost Curve'!H$65 | I79: ='Cost Curve'!I$65 | J79: ='Cost Curve'!J$65
A80: EBITDA per tonne | B80: Rs/t | C80: ='EBITDA Model'!C$101 | D80: ='EBITDA Model'!D$101 | E80: ='EBITDA Model'!E$101 | F80: ='EBITDA Model'!F$101 | G80: ='EBITDA Model'!G$101 | H80: ='EBITDA Model'!H$101 | I80: ='EBITDA Model'!I$101 | J80: ='EBITDA Model'!J$101
A81: INDUSTRY EBITDA MARGIN | B81: % | C81: =C80/C78 | D81: =D80/D78 | E81: =E80/E78 | F81: =F80/F78 | G81: =G80/G78 | H81: =H80/H78 | I81: =I80/I78 | J81: =J80/J78
A82: MARGIN BRIDGE - CHANGE VS FY2026A
A83: Realisation change vs FY2026A | B83: Rs/t | D83: =D78-$C$78 | E83: =E78-$C$78 | F83: =F78-$C$78 | G83: =G78-$C$78 | H83: =H78-$C$78 | I83: =I78-$C$78 | J83: =J78-$C$78
A84: Cash cost change vs FY2026A | B84: Rs/t | D84: =-(D79-$C$79) | E84: =-(E79-$C$79) | F84: =-(F79-$C$79) | G84: =-(G79-$C$79) | H84: =-(H79-$C$79) | I84: =-(I79-$C$79) | J84: =-(J79-$C$79)
A85: EBITDA per tonne change vs FY2026A | B85: Rs/t | D85: =D83+D84 | E85: =E83+E84 | F85: =F83+F84 | G85: =G83+G84 | H85: =H83+H84 | I85: =I83+I84 | J85: =J83+J84
A86: CREDIBILITY BENCHMARKS FROM OBSERVED HISTORY (Master Database)
A87: Observed cycle PEAK margin, FY2022 | B87: % | C87: 0.26
A88: Observed cycle TROUGH margin, FY2024 | B88: % | C88: 0.13
A89: Worst single observation, SAIL FY2016 | B89: % | C89: -0.07
A90: FY2026A actual industry margin | B90: % | C90: 0.17896088
A92: If a scenario produces a margin outside the -7% to +26% observed envelope, 25 Audit Checks flags it. That is a warning, not necessarily an error - but it must be justified.

Sheet Working Capital Model
A1: WORKING CAPITAL MODEL
A2: Industry Financial Model | Indian Steel Industry | Horizon FY2027E-FY2033E | Base year FY2026A
I3: Active Scenario | K3: ='Control Panel'!$E$17
A4: OBJECTIVE
A5: Forecast the industry's working capital by modelling inventory, receivables, payables, and other operating assets and liabilities.
A7: Executive Summary
A8: KPI | B8: FY26A | C8: FY27E | D8: FY28E | E8: FY29E | F8: FY30E | G8: FY31E | H8: FY32E | I8: FY33E | J8: Audit Code
A9: Inventory (₹ Cr)
A10: Receivables (₹ Cr)
A11: Payables (₹ Cr)
A12: Net Working Capital (₹ Cr) | B12: =C71 | C12: =D71 | D12: =E71 | E12: =F71 | F12: =G71 | G12: =H71 | H12: =I71 | I12: =J71
A13: NWC / Revenue (%) | B13: =C73 | C13: =D73 | D13: =E73 | E13: =F73 | F13: =G73 | G13: =H73 | H13: =I73 | I13: =J73
A14: Cash Conversion Cycle (Days) | B14: =C70 | C14: =D70 | D14: =E70 | E14: =F70 | F14: =G70 | G14: =H70 | H14: =I70 | I14: =J70
A17: Working Capital Forecast
A18: Item | B18: FY26A | C18: FY27E | D18: FY28E | E18: FY29E | F18: FY30E | G18: FY31E | H18: FY32E | I18: FY33E
A19: Inventory
A20: Trade Receivables
A21: Other Receivables
A22: Trade Payables
A23: Other Current Liabilities
A24: Net Working Capital
A27: Working Capital Days
A28: Metric | B28: FY26A | C28: FY27E | D28: FY28E | E28: FY29E | F28: FY30E | G28: FY31E | H28: FY32E | I28: FY33E
A29: Inventory Days
A30: Receivable Days
A31: Payable Days
A32: Cash Conversion Cycle
A35: Working Capital Drivers
A36: Driver | B36: FY27E | C36: FY28E | D36: FY29E | E36: FY30E | F36: FY31E | G36: FY32E | H36: FY33E
A37: Revenue Growth | B37: =(D69-C69)/C69 | C37: =(E69-D69)/D69 | D37: =(F69-E69)/E69 | E37: =(G69-F69)/F69 | F37: =(H69-G69)/G69 | G37: =(I69-H69)/H69 | H37: =(J69-I69)/I69
A38: Production Growth | B38: =('Steel Supply Model'!D88-'Steel Supply Model'!C88)/'Steel Supply Model'!C88 | C38: =('Steel Supply Model'!E88-'Steel Supply Model'!D88)/'Steel Supply Model'!D88 | D38: =('Steel Supply Model'!F88-'Steel Supply Model'!E88)/'Steel Supply Model'!E88 | E38: =('Steel Supply Model'!G88-'Steel Supply Model'!F88)/'Steel Supply Model'!F88 | F38: =('Steel Supply Model'!H88-'Steel Supply Model'!G88)/'Steel Supply Model'!G88 | G38: =('Steel Supply Model'!I88-'Steel Supply Model'!H88)/'Steel Supply Model'!H88 | H38: =('Steel Supply Model'!J88-'Steel Supply Model'!I88)/'Steel Supply Model'!I88
A39: Inventory Days
A40: Collection Days
A41: Payment Days
A42: Change in NWC | B42: =D72 | C42: =E72 | D42: =F72 | E42: =G72 | F42: =H72 | G42: =I72 | H42: =J72
A45: Cash Locked in Working Capital
A46: Year | B46: Opening NWC | C46: Closing NWC | D46: Change in NWC
A47: FY27 | B47: =C71 | C47: =D71 | D47: =D72
A48: FY28 | B48: =D71 | C48: =E71 | D48: =E72
A49: FY29 | B49: =E71 | C49: =F71 | D49: =F72
A50: FY30 | B50: =F71 | C50: =G71 | D50: =G72
A51: FY31 | B51: =G71 | C51: =H71 | D51: =H72
A52: FY32 | B52: =H71 | C52: =I71 | D52: =I72
A53: FY33 | B53: =I71 | C53: =J71 | D53: =J72
A56: Scenario Analysis
A57: Year | B57: Base | C57: Bull | D57: Bear | E57: Stress
A58: FY27
A59: FY28
A60: FY29
A61: FY30
A62: FY31
A63: FY32
A64: FY33
A67: Workbook
A68: Line item | B68: Unit | C68: FY2026A | D68: FY2027E | E68: FY2028E | F68: FY2029E | G68: FY2030E | H68: FY2031E | I68: FY2032E | J68: FY2033E | K68: CAGR | L68: Audit Code
A69: Industry revenue | B69: Rs cr | C69: ='Revenue Forecast'!C$95 | D69: ='Revenue Forecast'!D$95 | E69: ='Revenue Forecast'!E$95 | F69: ='Revenue Forecast'!F$95 | G69: ='Revenue Forecast'!G$95 | H69: ='Revenue Forecast'!H$95 | I69: ='Revenue Forecast'!I$95 | J69: ='Revenue Forecast'!J$95 | K69: =IFERROR(IF(AND(ISNUMBER(C69),ISNUMBER(J69),C69>0),(J69/C69)^(1/7)-1,""),"")
A70: Net working capital | B70: days of revenue | C70: ='Model Assumptions'!D$25 | D70: ='Model Assumptions'!E$25 | E70: ='Model Assumptions'!F$25 | F70: ='Model Assumptions'!G$25 | G70: ='Model Assumptions'!H$25 | H70: ='Model Assumptions'!I$25 | I70: ='Model Assumptions'!J$25 | J70: ='Model Assumptions'!K$25
A71: Net working capital | B71: Rs cr | C71: =C69*C70/365 | D71: =D69*D70/365 | E71: =E69*E70/365 | F71: =F69*F70/365 | G71: =G69*G70/365 | H71: =H69*H70/365 | I71: =I69*I70/365 | J71: =J69*J70/365 | K71: =IFERROR(IF(AND(ISNUMBER(C71),ISNUMBER(J71),C71>0),(J71/C71)^(1/7)-1,""),"")
A72: Change in net working capital | B72: Rs cr | D72: =D71-C71 | E72: =E71-D71 | F72: =F71-E71 | G72: =G71-F71 | H72: =H71-G71 | I72: =I71-H71 | J72: =J71-I71
A73: NWC as % of revenue | B73: % | C73: =C71/C69 | D73: =D71/D69 | E73: =E71/E69 | F73: =F71/F69 | G73: =G71/G69 | H73: =H71/H69 | I73: =I71/I69 | J73: =J71/J69
A75: ACTION REQUIRED. Derive receivable, inventory and payable days from each company's balance sheet and replace driver D18 before this model is used to support a financing or transaction.

Sheet Cash Flow Model
A1: CASH FLOW MODEL
A2: Industry Financial Model | Indian Steel Industry | Horizon FY2027E-FY2033E | Base year FY2026A
A4: OBJECTIVE | H4: Active Scenario | J4: ='Control Panel'!$E$17
A5: Forecast the industry's operating cash flow, investing cash flow, financing cash flow, and Free Cash Flow (FCFF).
A7: Executive Summary
A8: KPI | B8: FY26A | C8: FY27E | D8: FY28E | E8: FY29E | F8: FY30E | G8: FY31E | H8: FY32E | I8: FY33E | J8: Audit Code
A9: EBITDA | B9: =C90 | C9: =D90 | D9: =E90 | E9: =F90 | F9: =G90 | G9: =H90 | H9: =I90 | I9: =J90
A10: Operating Cash Flow | B10: =C90-C96-C107 | C10: =D90-D96-D107 | D10: =E90-E96-E107 | E10: =F90-F96-F107 | F10: =G90-G96-G107 | G10: =H90-H96-H107 | H10: =I90-I96-I107 | I10: =J90-J96-J107
A11: Capex | B11: =$C$104 | C11: =$D$104 | D11: =$E$104 | E11: =$F$104 | F11: =$G$104 | G11: =$H$104 | H11: =$I$104 | I11: =$J$104
A12: Free Cash Flow | C12: =$D$108 | D12: =$E$108 | E12: =$F$108 | F12: =$G$108 | G12: =$H$108 | H12: =$I$108 | I12: =$J$108
A13: FCF Margin | C13: =D108/D91 | D13: =E108/E91 | E13: =F108/F91 | F13: =G108/G91 | G13: =H108/H91 | H13: =I108/I91 | I13: =J108/J91
A14: Cash Conversion | C14: =$D$109 | D14: =$E$109 | E14: =$F$109 | F14: =$G$109 | G14: =$H$109 | H14: =$I$109 | I14: =$J$109
A15: Cumulative FCF | C15: =D108 | D15: =C15+E108 | E15: =D15+F108 | F15: =E15+G108 | G15: =F15+H108 | H15: =G15+I108 | I15: =H15+J108
A18: Cash Flow Build-up
A19: Item | B19: FY26A | C19: FY27E | D19: FY28E | E19: FY29E | F19: FY30E | G19: FY31E | H19: FY32E | I19: FY33E | J19: Audit Code
A20: EBITDA | B20: =C90 | C20: =D90 | D20: =E90 | E20: =F90 | F20: =G90 | G20: =H90 | H20: =I90 | I20: =J90
A21: Less: Cash Taxes | B21: =-C96 | C21: =-D96 | D21: =-E96 | E21: =-F96 | F21: =-G96 | G21: =-H96 | H21: =-I96 | I21: =-J96
A22: Less: Change in Working Capital | B22: =-C107 | C22: =-D107 | D22: =-E107 | E22: =-F107 | F22: =-G107 | G22: =-H107 | H22: =-I107 | I22: =-J107
A23: Operating Cash Flow (OCF) | B23: =B22+B21+B20 | C23: =C22+C21+C20 | D23: =D22+D21+D20 | E23: =E22+E21+E20 | F23: =F22+F21+F20 | G23: =G22+G21+G20 | H23: =H22+H21+H20 | I23: =I22+I21+I20
A24: Less: Maintenance Capex | B24: =-C103 | C24: =-D103 | D24: =-E103 | E24: =-F103 | F24: =-G103 | G24: =-H103 | H24: =-I103 | I24: =-J103
A25: Less: Growth Capex | B25: =-C101 | C25: =-D101 | D25: =-E101 | E25: =-F101 | F25: =-G101 | G25: =-H101 | H25: =-I101 | I25: =-J101
A26: Free Cash Flow (FCFF) | B26: =B23+B24+B25 | C26: =C23+C24+C25 | D26: =D23+D24+D25 | E26: =E23+E24+E25 | F26: =F23+F24+F25 | G26: =G23+G24+G25 | H26: =H23+H24+H25 | I26: =I23+I24+I25
A29: Operating Cash Flow
A30: Item | B30: FY26A | C30: FY27E | D30: FY28E | E30: FY29E | F30: FY30E | G30: FY31E | H30: FY32E | I30: FY33E
A31: EBITDA | B31: =C90 | C31: =D90 | D31: =E90 | E31: =F90 | F31: =G90 | G31: =H90 | H31: =I90 | I31: =J90
A32: Cash Taxes | B32: =-C96 | C32: =-D96 | D32: =-E96 | E32: =-F96 | F32: =-G96 | G32: =-H96 | H32: =-I96 | I32: =-J96
A33: Working Capital Movement | B33: =-C107 | C33: =-D107 | D33: =-E107 | E33: =-F107 | F33: =-G107 | G33: =-H107 | H33: =-I107 | I33: =-J107
A34: Other Operating Cash Items | B34: 0 | C34: 0 | D34: 0 | E34: 0 | F34: 0 | G34: 0 | H34: 0 | I34: 0
A35: Operating Cash Flow | B35: =SUM(B31:B34) | C35: =SUM(C31:C34) | D35: =SUM(D31:D34) | E35: =SUM(E31:E34) | F35: =SUM(F31:F34) | G35: =SUM(G31:G34) | H35: =SUM(H31:H34) | I35: =SUM(I31:I34)
A38: Investing Cash Flow
A39: Item | B39: FY26A | C39: FY27E | D39: FY28E | E39: FY29E | F39: FY30E | G39: FY31E | H39: FY32E | I39: FY33E
A40: Maintenance Capex | B40: =-C103 | C40: =-D103 | D40: =-E103 | E40: =-F103 | F40: =-G103 | G40: =-H103 | H40: =-I103 | I40: =-J103
A41: Expansion Capex | B41: =-C101 | C41: =-D101 | D41: =-E101 | E41: =-F101 | F41: =-G101 | G41: =-H101 | H41: =-I101 | I41: =-J101
A42: Plant Upgrades | B42: 0 | C42: 0 | D42: 0 | E42: 0 | F42: 0 | G42: 0 | H42: 0 | I42: 0
A43: Other Investments | B43: 0 | C43: 0 | D43: 0 | E43: 0 | F43: 0 | G43: 0 | H43: 0 | I43: 0
A44: Total Investing Cash Flow | B44: =SUM(B40:B43) | C44: =SUM(C40:C43) | D44: =SUM(D40:D43) | E44: =SUM(E40:E43) | F44: =SUM(F40:F43) | G44: =SUM(G40:G43) | H44: =SUM(H40:H43) | I44: =SUM(I40:I43)
A47: Financing Cash Flow
A48: Item | B48: FY26A | C48: FY27E | D48: FY28E | E48: FY29E | F48: FY30E | G48: FY31E | H48: FY32E | I48: FY33E
A49: Debt Raised
A50: Debt Repaid | C50: ='Capital Allocation'!D79-'Capital Allocation'!D76 | D50: ='Capital Allocation'!E79-'Capital Allocation'!E76 | E50: ='Capital Allocation'!F79-'Capital Allocation'!F76 | F50: ='Capital Allocation'!G79-'Capital Allocation'!G76 | G50: ='Capital Allocation'!H79-'Capital Allocation'!H76 | H50: ='Capital Allocation'!I79-'Capital Allocation'!I76 | I50: ='Capital Allocation'!J79-'Capital Allocation'!J76
A51: Interest Paid | B51: =-'Capital Allocation'!C78 | C51: =-'Capital Allocation'!D78 | D51: =-'Capital Allocation'!E78 | E51: =-'Capital Allocation'!F78 | F51: =-'Capital Allocation'!G78 | G51: =-'Capital Allocation'!H78 | H51: =-'Capital Allocation'!I78 | I51: =-'Capital Allocation'!J78
A52: Dividends
A53: Share Buybacks
A54: Equity Raised
A55: Net Financing Cash Flow | B55: =SUM(B49:B54) | C55: =SUM(C49:C54) | D55: =SUM(D49:D54) | E55: =SUM(E49:E54) | F55: =SUM(F49:F54) | G55: =SUM(G49:G54) | H55: =SUM(H49:H54) | I55: =SUM(I49:I54)
A58: Free Cash Flow Bridge
A59: Driver | B59: FY26A | C59: FY27E | D59: FY28E | E59: FY29E | F59: FY30E | G59: FY31E | H59: FY32E | I59: FY33E
A60: Previous FCF | C60: =C108 | D60: =D108 | E60: =E108 | F60: =F108 | G60: =G108 | H60: =H108 | I60: =I108
A61: EBITDA Effect | C61: =D90-C90 | D61: =E90-D90 | E61: =F90-E90 | F61: =G90-F90 | G61: =H90-G90 | H61: =I90-H90 | I61: =J90-I90
A62: Working Capital Effect | C62: =-(D107-C107) | D62: =-(E107-D107) | E62: =-(F107-E107) | F62: =-(G107-F107) | G62: =-(H107-G107) | H62: =-(I107-H107) | I62: =-(J107-I107)
A63: Capex Effect | C63: =-(D104-C104) | D63: =-(E104-D104) | E63: =-(F104-E104) | F63: =-(G104-F104) | G63: =-(H104-G104) | H63: =-(I104-H104) | I63: =-(J104-I104)
A64: Tax Effect | C64: =-(D96-C96) | D64: =-(E96-D96) | E64: =-(F96-E96) | F64: =-(G96-F96) | G64: =-(H96-G96) | H64: =-(I96-H96) | I64: =-(J96-I96)
A65: Other | C65: 0 | D65: 0 | E65: 0 | F65: 0 | G65: 0 | H65: 0 | I65: 0
A66: FCFF | C66: =SUM(C60:C65) | D66: =SUM(D60:D65) | E66: =SUM(E60:E65) | F66: =SUM(F60:F65) | G66: =SUM(G60:G65) | H66: =SUM(H60:H65) | I66: =SUM(I60:I65)
A69: Cash Generation
A70: Item | B70: FY26A | C70: FY27E | D70: FY28E | E70: FY29E | F70: FY30E | G70: FY31E | H70: FY32E | I70: FY33E
A71: EBITDA | B71: =C90 | C71: =D90 | D71: =E90 | E71: =F90 | F71: =G90 | G71: =H90 | H71: =I90 | I71: =J90
A72: Operating Cash Flow | B72: =B35 | C72: =C35 | D72: =D35 | E72: =E35 | F72: =F35 | G72: =G35 | H72: =H35 | I72: =I35
A73: OCF / EBITDA | B73: =B72/B71 | C73: =C72/C71 | D73: =D72/D71 | E73: =E72/E71 | F73: =F72/F71 | G73: =G72/G71 | H73: =H72/H71 | I73: =I72/I71
A74: FCFF | B74: =C108 | C74: =D108 | D74: =E108 | E74: =F108 | F74: =G108 | G74: =H108 | H74: =I108 | I74: =J108
A77: Scenario Analysis
A78: Year FCFF | B78: Base | C78: Bull | D78: Bear | E78: Stress
A79: FY27
A80: FY28
A81: FY29
A82: FY30
A83: FY31
A84: FY32
A85: FY33
A88: Workbook
A89: Line item | B89: Unit | C89: FY2026A | D89: FY2027E | E89: FY2028E | F89: FY2029E | G89: FY2030E | H89: FY2031E | I89: FY2032E | J89: FY2033E | K89: Audit Code
A90: Industry EBITDA | B90: Rs cr | C90: ='EBITDA Model'!C$103 | D90: ='EBITDA Model'!D$103 | E90: ='EBITDA Model'!E$103 | F90: ='EBITDA Model'!F$103 | G90: ='EBITDA Model'!G$103 | H90: ='EBITDA Model'!H$103 | I90: ='EBITDA Model'!I$103 | J90: ='EBITDA Model'!J$103
A91: Industry revenue | B91: Rs cr | C91: ='Revenue Forecast'!C$95 | D91: ='Revenue Forecast'!D$95 | E91: ='Revenue Forecast'!E$95 | F91: ='Revenue Forecast'!F$95 | G91: ='Revenue Forecast'!G$95 | H91: ='Revenue Forecast'!H$95 | I91: ='Revenue Forecast'!I$95 | J91: ='Revenue Forecast'!J$95
A92: Depreciation and amortisation | B92: % of revenue | C92: ='Model Assumptions'!E$33 | D92: ='Model Assumptions'!E$33 | E92: ='Model Assumptions'!F$33 | F92: ='Model Assumptions'!G$33 | G92: ='Model Assumptions'!H$33 | H92: ='Model Assumptions'!I$33 | I92: ='Model Assumptions'!J$33 | J92: ='Model Assumptions'!K$33
A93: Depreciation and amortisation | B93: Rs cr | C93: =C91*C92 | D93: =D91*D92 | E93: =E91*E92 | F93: =F91*F92 | G93: =G91*G92 | H93: =H91*H92 | I93: =I91*I92 | J93: =J91*J92
A94: EBIT | B94: Rs cr | C94: =C90-C93 | D94: =D90-D93 | E94: =E90-E93 | F94: =F90-F93 | G94: =G90-G93 | H94: =H90-H93 | I94: =I90-I93 | J94: =J90-J93
A95: Effective tax rate | B95: % | C95: ='Model Assumptions'!D$22 | D95: ='Model Assumptions'!E$22 | E95: ='Model Assumptions'!F$22 | F95: ='Model Assumptions'!G$22 | G95: ='Model Assumptions'!H$22 | H95: ='Model Assumptions'!I$22 | I95: ='Model Assumptions'!J$22 | J95: ='Model Assumptions'!K$22
A96: Cash tax | B96: Rs cr | C96: =MAX(0,C94)*C95 | D96: =MAX(0,D94)*D95 | E96: =MAX(0,E94)*E95 | F96: =MAX(0,F94)*F95 | G96: =MAX(0,G94)*G95 | H96: =MAX(0,H94)*H95 | I96: =MAX(0,I94)*I95 | J96: =MAX(0,J94)*J95
A98: CAPITAL EXPENDITURE
A99: Capacity added | B99: Mtpa | C99: ='Capacity Forecast'!C$95 | D99: ='Capacity Forecast'!D$95 | E99: ='Capacity Forecast'!E$95 | F99: ='Capacity Forecast'!F$95 | G99: ='Capacity Forecast'!G$95 | H99: ='Capacity Forecast'!H$95 | I99: ='Capacity Forecast'!I$95 | J99: ='Capacity Forecast'!J$95
A100: Capex intensity | B100: Rs/t of capacity | C100: ='Model Assumptions'!D$23 | D100: ='Model Assumptions'!E$23 | E100: ='Model Assumptions'!F$23 | F100: ='Model Assumptions'!G$23 | G100: ='Model Assumptions'!H$23 | H100: ='Model Assumptions'!I$23 | I100: ='Model Assumptions'!J$23 | J100: ='Model Assumptions'!K$23
